{
  "type": "Feature",
  "properties": {
    "gn:admin1_code":"VLG",
    "gn:admin2_code":"VWV",
    "gn:admin3_code":"31.0",
    "gn:admin4_code":"31022.0",
    "gn:asciiname":"Veldhoek",
    "gn:country_code":"BE",
    "gn:dem":12,
    "gn:feature_class":"P",
    "gn:feature_code":"PPL",
    "gn:name":"Veldhoek",
    "gn:population":0,
    "gn:timezone":"Europe/Brussels",
    "iso:country":"BE",
    "wof:name":"Veldhoek",
    "wof:placetype":"locality"
},
  "geometry": {"coordinates":[3.20587,51.11051],"type":"Point"}
}