{
  "type": "Feature",
  "properties": {
    "gn:admin1_code":"WAL",
    "gn:admin2_code":"WLG",
    "gn:admin3_code":"63.0",
    "gn:admin4_code":"63087.0",
    "gn:asciiname":"Auel",
    "gn:country_code":"BE",
    "gn:dem":378,
    "gn:feature_class":"P",
    "gn:feature_code":"PPL",
    "gn:name":"Auel",
    "gn:population":0,
    "gn:timezone":"Europe/Brussels",
    "iso:country":"BE",
    "name:ceb_x_preferred":[
        "Auel"
    ],
    "name:deu_x_preferred":[
        "Auel"
    ],
    "name:epo_x_preferred":[
        "Auel"
    ],
    "name:eus_x_preferred":[
        "Auel"
    ],
    "name:fas_x_preferred":[
        "\u0627\u0648\u0644"
    ],
    "name:fra_x_preferred":[
        "Auel"
    ],
    "name:hun_x_preferred":[
        "Auel"
    ],
    "name:ita_x_preferred":[
        "Auel"
    ],
    "name:kaz_x_preferred":[
        "\u0410\u0443\u044d\u043b\u044c"
    ],
    "name:kir_x_preferred":[
        "\u0410\u0443\u044d\u043b\u044c"
    ],
    "name:msa_x_preferred":[
        "Auel"
    ],
    "name:nld_x_preferred":[
        "Auel"
    ],
    "name:pol_x_preferred":[
        "Auel"
    ],
    "name:por_x_preferred":[
        "Auel"
    ],
    "name:ron_x_preferred":[
        "Auel"
    ],
    "name:rus_x_preferred":[
        "\u0410\u0443\u044d\u043b\u044c"
    ],
    "name:spa_x_preferred":[
        "Auel"
    ],
    "name:srp_x_preferred":[
        "\u0410\u0443\u0435\u043b"
    ],
    "name:swe_x_preferred":[
        "Auel"
    ],
    "name:ukr_x_preferred":[
        "\u0410\u044e\u043b\u044c"
    ],
    "name:uzb_x_preferred":[
        "Auel"
    ],
    "name:vie_x_preferred":[
        "Auel"
    ],
    "name:vol_x_preferred":[
        "Auel"
    ],
    "name:war_x_preferred":[
        "Auel"
    ],
    "name:zho_x_preferred":[
        "\u5965\u5384\u5c14"
    ],
    "wof:name":"Auel",
    "wof:placetype":"locality"
},
  "geometry": {"coordinates":[6.17258,50.21141],"type":"Point"}
}