{
  "type": "Feature",
  "properties": {
    "gn:admin1_code":"WAL",
    "gn:admin2_code":"WLG",
    "gn:admin3_code":"63.0",
    "gn:admin4_code":"63087.0",
    "gn:asciiname":"Auel",
    "gn:country_code":"BE",
    "gn:dem":378,
    "gn:feature_class":"P",
    "gn:feature_code":"PPL",
    "gn:name":"Auel",
    "gn:population":0,
    "gn:timezone":"Europe/Brussels",
    "iso:country":"BE",
    "wof:name":"Auel",
    "wof:placetype":"locality"
},
  "geometry": {"coordinates":[6.17258,50.21141],"type":"Point"}
}