{
  "type": "Feature",
  "properties": {
    "gn:admin1_code":"VLG",
    "gn:admin2_code":"VBR",
    "gn:admin3_code":"24.0",
    "gn:admin4_code":"24137.0",
    "gn:asciiname":"Pepinusfort",
    "gn:country_code":"BE",
    "gn:dem":38,
    "gn:feature_class":"P",
    "gn:feature_code":"PPL",
    "gn:name":"Pepinusfort",
    "gn:population":0,
    "gn:timezone":"Europe/Brussels",
    "iso:country":"BE",
    "name:und_x_variant":[
        "Pepinisfort",
        "Pepinusfort"
    ],
    "wof:name":"Pepinusfort",
    "wof:placetype":"locality"
},
  "geometry": {"coordinates":[4.95907,50.85675],"type":"Point"}
}