{
  "type": "Feature",
  "properties": {
    "gn:admin1_code":"VLG",
    "gn:admin2_code":"VOV",
    "gn:admin3_code":"45.0",
    "gn:admin4_code":"45061.0",
    "gn:asciiname":"Kauborre",
    "gn:country_code":"BE",
    "gn:dem":76,
    "gn:feature_class":"P",
    "gn:feature_code":"PPL",
    "gn:name":"Kauborre",
    "gn:population":0,
    "gn:timezone":"Europe/Brussels",
    "iso:country":"BE",
    "wof:name":"Kauborre",
    "wof:placetype":"locality"
},
  "geometry": {"coordinates":[3.51667,50.85],"type":"Point"}
}