{
  "type": "Feature",
  "properties": {
    "gn:admin1_code":"WAL",
    "gn:admin2_code":"WNA",
    "gn:admin3_code":"91.0",
    "gn:admin4_code":"91114.0",
    "gn:asciiname":"Briquemont",
    "gn:country_code":"BE",
    "gn:dem":169,
    "gn:feature_class":"P",
    "gn:feature_code":"PPL",
    "gn:name":"Briquemont",
    "gn:population":0,
    "gn:timezone":"Europe/Brussels",
    "iso:country":"BE",
    "wof:name":"Briquemont",
    "wof:placetype":"locality"
},
  "geometry": {"coordinates":[5.14395,50.1808],"type":"Point"}
}