{
  "type": "Feature",
  "properties": {
    "gn:admin1_code":"WAL",
    "gn:admin2_code":"WLX",
    "gn:admin3_code":"81.0",
    "gn:admin4_code":"81003.0",
    "gn:asciiname":"Lischert",
    "gn:country_code":"BE",
    "gn:dem":341,
    "gn:feature_class":"P",
    "gn:feature_code":"PPL",
    "gn:name":"Lischert",
    "gn:population":0,
    "gn:timezone":"Europe/Brussels",
    "iso:country":"BE",
    "wof:name":"Lischert",
    "wof:placetype":"locality"
},
  "geometry": {"coordinates":[5.7565,49.72079],"type":"Point"}
}