{
  "type": "Feature",
  "properties": {
    "gn:admin1_code":"VLG",
    "gn:admin2_code":"VLI",
    "gn:admin3_code":"71.0",
    "gn:admin4_code":"71053.0",
    "gn:asciiname":"Neissem",
    "gn:country_code":"BE",
    "gn:dem":54,
    "gn:feature_class":"P",
    "gn:feature_code":"PPL",
    "gn:name":"Neissem",
    "gn:population":0,
    "gn:timezone":"Europe/Brussels",
    "iso:country":"BE",
    "name:und_x_variant":[
        "Nyssem",
        "Neissem"
    ],
    "wof:name":"Neissem",
    "wof:placetype":"locality"
},
  "geometry": {"coordinates":[5.14148,50.7891],"type":"Point"}
}