{
  "type": "Feature",
  "properties": {
    "gn:admin1_code":"WAL",
    "gn:admin2_code":"WLG",
    "gn:admin3_code":"63.0",
    "gn:admin4_code":"63040.0",
    "gn:asciiname":"Hirtz",
    "gn:country_code":"BE",
    "gn:dem":200,
    "gn:feature_class":"P",
    "gn:feature_code":"PPL",
    "gn:name":"Hirtz",
    "gn:population":0,
    "gn:timezone":"Europe/Brussels",
    "iso:country":"BE",
    "wof:name":"Hirtz",
    "wof:placetype":"locality"
},
  "geometry": {"coordinates":[5.99547,50.70537],"type":"Point"}
}