{
  "type": "Feature",
  "properties": {
    "gn:admin1_code":"WAL",
    "gn:admin2_code":"WLX",
    "gn:admin3_code":"84.0",
    "gn:admin4_code":"84043.0",
    "gn:asciiname":"Lohiepre",
    "gn:country_code":"BE",
    "gn:dem":410,
    "gn:feature_class":"P",
    "gn:feature_code":"PPL",
    "gn:name":"Lohi\u00e9pr\u00e9",
    "gn:population":0,
    "gn:timezone":"Europe/Brussels",
    "iso:country":"BE",
    "name:und_x_variant":[
        "Lohier-Pr\u00e9",
        "Lohi\u00e9pr\u00e9"
    ],
    "wof:name":"Lohiepre",
    "wof:placetype":"locality"
},
  "geometry": {"coordinates":[5.38333,49.86667],"type":"Point"}
}