{
  "type": "Feature",
  "properties": {
    "gn:admin1_code":"VLG",
    "gn:admin2_code":"VOV",
    "gn:admin3_code":"44.0",
    "gn:admin4_code":"44019.0",
    "gn:asciiname":"Vierhuizen",
    "gn:country_code":"BE",
    "gn:dem":6,
    "gn:feature_class":"P",
    "gn:feature_code":"PPL",
    "gn:name":"Vierhuizen",
    "gn:population":0,
    "gn:timezone":"Europe/Brussels",
    "iso:country":"BE",
    "wof:name":"Vierhuizen",
    "wof:placetype":"locality"
},
  "geometry": {"coordinates":[3.65572,51.16652],"type":"Point"}
}