{
  "type": "Feature",
  "properties": {
    "gn:gn_country":"BE",
    "gn:gn_fcode":"PPL",
    "gn:gn_pop":0,
    "iso:country":"BE",
    "name:bul_x_preferred":[
        "\u0412\u043b\u0435\u043a\u0435\u043c"
    ],
    "name:dut_x_preferred":[
        "Vlekkem"
    ],
    "name:eng_x_preferred":[
        "Vlekkem"
    ],
    "name:fre_x_preferred":[
        "Vlekkem"
    ],
    "name:ger_x_preferred":[
        "Vlekkem"
    ],
    "name:hun_x_preferred":[
        "Vlekkem"
    ],
    "name:swe_x_preferred":[
        "Vlekkem"
    ],
    "name:unk_x_variant":[
        "Vleckem"
    ],
    "qs_pg:aaroncc":"BE",
    "qs_pg:gn_country":"BE",
    "qs_pg:gn_fcode":"PPL",
    "qs_pg:gn_pop":0,
    "qs_pg:name":"Vlekkem",
    "qs_pg:name_adm0":"Belgique",
    "qs_pg:name_adm1":"Oost-Vlaanderen",
    "qs_pg:photos_9r":0,
    "qs_pg:photos_sr":0,
    "qs_pg:pop_sr":0,
    "qs_pg:qs_pg_placetype":"locality",
    "qs_pg:qs_pg_placetype_gp":"Town",
    "qs_pg:woe_adm0":23424757,
    "woe:adm0_id":23424757,
    "woe:name_adm0":"Belgique",
    "woe:name_adm1":"Oost-Vlaanderen",
    "woe:placetype":"Town",
    "wof:name":"Vlekkem",
    "wof:placetype":"locality"
},
  "geometry": {"coordinates":[3.93062,50.93589],"type":"Point"}
}