{
  "type": "Feature",
  "properties": {
    "gn:admin1_code":"VLG",
    "gn:admin2_code":"VOV",
    "gn:admin3_code":"44.0",
    "gn:admin4_code":"44021.0",
    "gn:asciiname":"Meire",
    "gn:country_code":"BE",
    "gn:dem":7,
    "gn:feature_class":"P",
    "gn:feature_code":"PPL",
    "gn:name":"Meire",
    "gn:population":0,
    "gn:timezone":"Europe/Brussels",
    "iso:country":"BE",
    "wof:name":"Meire",
    "wof:placetype":"locality"
},
  "geometry": {"coordinates":[3.63333,51.08333],"type":"Point"}
}