{
  "type": "Feature",
  "properties": {
    "gn:admin1_code":"VLG",
    "gn:admin2_code":"VOV",
    "gn:admin3_code":"42.0",
    "gn:admin4_code":"42003.0",
    "gn:asciiname":"Kerkstraat",
    "gn:country_code":"BE",
    "gn:dem":2,
    "gn:feature_class":"P",
    "gn:feature_code":"PPL",
    "gn:name":"Kerkstraat",
    "gn:population":0,
    "gn:timezone":"Europe/Brussels",
    "iso:country":"BE",
    "wof:name":"Kerkstraat",
    "wof:placetype":"locality"
},
  "geometry": {"coordinates":[3.95,51.06667],"type":"Point"}
}