{
  "type": "Feature",
  "properties": {
    "gn:admin1_code":"WAL",
    "gn:admin2_code":"WLX",
    "gn:admin3_code":"82.0",
    "gn:admin4_code":"82036.0",
    "gn:asciiname":"Lescheret",
    "gn:country_code":"BE",
    "gn:dem":457,
    "gn:feature_class":"P",
    "gn:feature_code":"PPL",
    "gn:name":"Lescheret",
    "gn:population":0,
    "gn:timezone":"Europe/Brussels",
    "iso:country":"BE",
    "name:und_x_variant":[
        "Lescherat",
        "Lescheret"
    ],
    "wof:name":"Lescheret",
    "wof:placetype":"locality"
},
  "geometry": {"coordinates":[5.56642,49.87644],"type":"Point"}
}