{
  "type": "Feature",
  "properties": {
    "gn:admin1_code":"VLG",
    "gn:admin2_code":"VLI",
    "gn:admin3_code":"71.0",
    "gn:admin4_code":"71070.0",
    "gn:asciiname":"De Stukken",
    "gn:country_code":"BE",
    "gn:dem":40,
    "gn:feature_class":"P",
    "gn:feature_code":"PPL",
    "gn:name":"De Stukken",
    "gn:population":0,
    "gn:timezone":"Europe/Brussels",
    "iso:country":"BE",
    "wof:name":"De Stukken",
    "wof:placetype":"locality"
},
  "geometry": {"coordinates":[5.3165,51.03283],"type":"Point"}
}