{
  "type": "Feature",
  "properties": {
    "gn:admin1_code":"WAL",
    "gn:admin2_code":"WLX",
    "gn:admin3_code":"84.0",
    "gn:admin4_code":"84043.0",
    "gn:asciiname":"Montplainchamps",
    "gn:country_code":"BE",
    "gn:dem":444,
    "gn:feature_class":"P",
    "gn:feature_code":"PPL",
    "gn:name":"Montplainchamps",
    "gn:population":0,
    "gn:timezone":"Europe/Brussels",
    "iso:country":"BE",
    "wof:name":"Montplainchamps",
    "wof:placetype":"locality"
},
  "geometry": {"coordinates":[5.41886,49.82039],"type":"Point"}
}