{
  "type": "Feature",
  "properties": {
    "gn:admin1_code":"VLG",
    "gn:admin2_code":"VOV",
    "gn:admin3_code":"44.0",
    "gn:admin4_code":"44052.0",
    "gn:asciiname":"Kalle",
    "gn:country_code":"BE",
    "gn:dem":48,
    "gn:feature_class":"P",
    "gn:feature_code":"PPL",
    "gn:name":"Kalle",
    "gn:population":0,
    "gn:timezone":"Europe/Brussels",
    "iso:country":"BE",
    "name:deu_x_preferred":[
        "Kalle"
    ],
    "name:fin_x_preferred":[
        "Kalle"
    ],
    "name:nld_x_preferred":[
        "Kalle"
    ],
    "name:swe_x_preferred":[
        "Karl"
    ],
    "wof:name":"Kalle",
    "wof:placetype":"locality"
},
  "geometry": {"coordinates":[3.78333,50.91667],"type":"Point"}
}