{
  "type": "Feature",
  "properties": {
    "gn:admin1_code":"WAL",
    "gn:admin2_code":"WLX",
    "gn:admin3_code":"82.0",
    "gn:admin4_code":"82003.0",
    "gn:asciiname":"Isle le Pre",
    "gn:country_code":"BE",
    "gn:dem":516,
    "gn:feature_class":"P",
    "gn:feature_code":"PPL",
    "gn:name":"Isle le Pr\u00e9",
    "gn:population":0,
    "gn:timezone":"Europe/Brussels",
    "iso:country":"BE",
    "wof:name":"Isle le Pre",
    "wof:placetype":"locality"
},
  "geometry": {"coordinates":[5.69314,49.98943],"type":"Point"}
}