{
  "type": "Feature",
  "properties": {
    "gn:admin1_code":"WAL",
    "gn:admin2_code":"WNA",
    "gn:admin3_code":"92.0",
    "gn:admin4_code":"92035.0",
    "gn:asciiname":"Les Boscailles",
    "gn:country_code":"BE",
    "gn:dem":183,
    "gn:feature_class":"P",
    "gn:feature_code":"PPL",
    "gn:name":"Les Boscailles",
    "gn:population":0,
    "gn:timezone":"Europe/Brussels",
    "iso:country":"BE",
    "wof:name":"Les Boscailles",
    "wof:placetype":"locality"
},
  "geometry": {"coordinates":[4.89501,50.54245],"type":"Point"}
}