{
  "type": "Feature",
  "properties": {
    "gn:admin1_code":"WAL",
    "gn:admin2_code":"WBR",
    "gn:admin3_code":"25.0",
    "gn:admin4_code":"25122.0",
    "gn:asciiname":"Geest-Gerompont-Petit-Rosiere",
    "gn:country_code":"BE",
    "gn:dem":130,
    "gn:feature_class":"P",
    "gn:feature_code":"PPL",
    "gn:name":"Geest-G\u00e9rompont-Petit-Rosi\u00e8re",
    "gn:population":0,
    "gn:timezone":"Europe/Brussels",
    "iso:country":"BE",
    "name:und_x_variant":[
        "Ramillies (Geest-G\u00e9rompont-Petit-Rosi\u00e8re)"
    ],
    "wof:name":"Geest-Gerompont-Petit-Rosiere",
    "wof:placetype":"locality"
},
  "geometry": {"coordinates":[4.8587,50.64043],"type":"Point"}
}