{
  "type": "Feature",
  "properties": {
    "gn:admin1_code":"VLG",
    "gn:admin2_code":"VAN",
    "gn:admin3_code":"13.0",
    "gn:admin4_code":"13003.0",
    "gn:asciiname":"Rijsberg",
    "gn:country_code":"BE",
    "gn:dem":31,
    "gn:feature_class":"P",
    "gn:feature_code":"PPL",
    "gn:name":"Rijsberg",
    "gn:population":0,
    "gn:timezone":"Europe/Brussels",
    "iso:country":"BE",
    "name:und_x_variant":[
        "Reisbergen",
        "Rijsberg"
    ],
    "wof:name":"Rijsberg",
    "wof:placetype":"locality"
},
  "geometry": {"coordinates":[5.17446,51.17978],"type":"Point"}
}