{
  "type": "Feature",
  "properties": {
    "gn:admin1_code":"VLG",
    "gn:admin2_code":"VOV",
    "gn:admin3_code":"46.0",
    "gn:admin4_code":"46020.0",
    "gn:asciiname":"Doorn",
    "gn:country_code":"BE",
    "gn:dem":5,
    "gn:feature_class":"P",
    "gn:feature_code":"PPL",
    "gn:name":"Doorn",
    "gn:population":0,
    "gn:timezone":"Europe/Brussels",
    "iso:country":"BE",
    "name:ara_x_preferred":[
        "\u062f\u0648\u0631\u0646"
    ],
    "name:ceb_x_preferred":[
        "Doorn"
    ],
    "name:epo_x_preferred":[
        "Doorn"
    ],
    "name:fra_x_preferred":[
        "Doorn"
    ],
    "name:fry_x_preferred":[
        "Doorn"
    ],
    "name:ind_x_preferred":[
        "Doorn"
    ],
    "name:ita_x_preferred":[
        "Doorn"
    ],
    "name:lim_x_preferred":[
        "Doorn"
    ],
    "name:msa_x_preferred":[
        "Doorn"
    ],
    "name:nld_x_preferred":[
        "Doorn"
    ],
    "name:nor_x_preferred":[
        "Doorn"
    ],
    "name:pol_x_preferred":[
        "Doorn"
    ],
    "name:ron_x_preferred":[
        "Doorn"
    ],
    "name:rus_x_preferred":[
        "\u0414\u043e\u0440\u043d"
    ],
    "name:spa_x_preferred":[
        "Doorn"
    ],
    "name:sqi_x_preferred":[
        "Doorn"
    ],
    "name:swe_x_preferred":[
        "Doorn"
    ],
    "name:tur_x_preferred":[
        "Doorn"
    ],
    "name:ukr_x_preferred":[
        "\u0414\u043e\u043e\u0440\u043d"
    ],
    "name:vol_x_preferred":[
        "Doorn"
    ],
    "wof:name":"Doorn",
    "wof:placetype":"locality"
},
  "geometry": {"coordinates":[4.13736,51.21133],"type":"Point"}
}