{
  "type": "Feature",
  "properties": {
    "gn:admin1_code":"VLG",
    "gn:admin2_code":"VWV",
    "gn:admin3_code":"37.0",
    "gn:admin4_code":"37012.0",
    "gn:asciiname":"Zuidwijk",
    "gn:country_code":"BE",
    "gn:dem":14,
    "gn:feature_class":"P",
    "gn:feature_code":"PPL",
    "gn:name":"Zuidwijk",
    "gn:population":0,
    "gn:timezone":"Europe/Brussels",
    "iso:country":"BE",
    "name:fra_x_preferred":[
        "Zuidwijk"
    ],
    "name:nld_x_preferred":[
        "Zuidwijk"
    ],
    "wof:name":"Zuidwijk",
    "wof:placetype":"locality"
},
  "geometry": {"coordinates":[3.41211,51.03422],"type":"Point"}
}