{
  "type": "Feature",
  "properties": {
    "gn:admin1_code":"WAL",
    "gn:admin2_code":"WNA",
    "gn:admin3_code":"91.0",
    "gn:admin4_code":"91114.0",
    "gn:asciiname":"Champs de la Fontaine",
    "gn:country_code":"BE",
    "gn:dem":206,
    "gn:feature_class":"P",
    "gn:feature_code":"PPL",
    "gn:name":"Champs de la Fontaine",
    "gn:population":0,
    "gn:timezone":"Europe/Brussels",
    "iso:country":"BE",
    "wof:name":"Champs de la Fontaine",
    "wof:placetype":"locality"
},
  "geometry": {"coordinates":[5.20781,50.2116],"type":"Point"}
}