{
  "type": "Feature",
  "properties": {
    "gn:admin1_code":"VLG",
    "gn:admin2_code":"VWV",
    "gn:admin3_code":"34.0",
    "gn:admin4_code":"34003.0",
    "gn:asciiname":"Raaptorf",
    "gn:country_code":"BE",
    "gn:dem":15,
    "gn:feature_class":"P",
    "gn:feature_code":"PPL",
    "gn:name":"Raaptorf",
    "gn:population":0,
    "gn:timezone":"Europe/Brussels",
    "iso:country":"BE",
    "wof:name":"Raaptorf",
    "wof:placetype":"locality"
},
  "geometry": {"coordinates":[3.43202,50.77202],"type":"Point"}
}