{
  "type": "Feature",
  "properties": {
    "gn:admin1_code":"VLG",
    "gn:admin2_code":"VAN",
    "gn:admin3_code":"11.0",
    "gn:admin4_code":"11013.0",
    "gn:asciiname":"Slijkhoek",
    "gn:country_code":"BE",
    "gn:dem":10,
    "gn:feature_class":"P",
    "gn:feature_code":"PPL",
    "gn:name":"Slijkhoek",
    "gn:population":0,
    "gn:timezone":"Europe/Brussels",
    "iso:country":"BE",
    "name:und_x_variant":[
        "Slykhoek",
        "Slijkhoek"
    ],
    "wof:name":"Slijkhoek",
    "wof:placetype":"locality"
},
  "geometry": {"coordinates":[4.41667,51.16667],"type":"Point"}
}