{
  "type": "Feature",
  "properties": {
    "gn:admin1_code":"WAL",
    "gn:admin2_code":"WHT",
    "gn:admin3_code":"57.0",
    "gn:admin4_code":"57081.0",
    "gn:asciiname":"Moulin",
    "gn:country_code":"BE",
    "gn:dem":50,
    "gn:feature_class":"P",
    "gn:feature_code":"PPL",
    "gn:name":"Moulin",
    "gn:population":0,
    "gn:timezone":"Europe/Brussels",
    "iso:country":"BE",
    "wof:name":"Moulin",
    "wof:placetype":"locality"
},
  "geometry": {"coordinates":[3.46667,50.65],"type":"Point"}
}