{
  "type": "Feature",
  "properties": {
    "gn:admin1_code":"WAL",
    "gn:admin2_code":"WLX",
    "gn:admin3_code":"84.0",
    "gn:admin4_code":"84016.0",
    "gn:asciiname":"Mont",
    "gn:country_code":"BE",
    "gn:dem":312,
    "gn:feature_class":"P",
    "gn:feature_code":"PPL",
    "gn:name":"Mont",
    "gn:population":0,
    "gn:timezone":"Europe/Brussels",
    "iso:country":"BE",
    "name:arg_x_preferred":[
        "Mont"
    ],
    "name:cat_x_preferred":[
        "Mont"
    ],
    "name:ceb_x_preferred":[
        "Mont"
    ],
    "name:deu_x_preferred":[
        "Mont"
    ],
    "name:epo_x_preferred":[
        "Mont"
    ],
    "name:est_x_preferred":[
        "Mont"
    ],
    "name:fra_x_preferred":[
        "Mont"
    ],
    "name:hun_x_preferred":[
        "Mont"
    ],
    "name:ita_x_preferred":[
        "Mont"
    ],
    "name:nds_x_preferred":[
        "Mont"
    ],
    "name:nld_x_preferred":[
        "Mont"
    ],
    "name:oci_x_preferred":[
        "Mont"
    ],
    "name:pms_x_preferred":[
        "Mont"
    ],
    "name:pol_x_preferred":[
        "Mont"
    ],
    "name:por_x_preferred":[
        "Mont"
    ],
    "name:rus_x_preferred":[
        "\u041c\u043e\u043d\u0442"
    ],
    "name:slk_x_preferred":[
        "Mont"
    ],
    "name:spa_x_preferred":[
        "Mont"
    ],
    "name:swe_x_preferred":[
        "Mont"
    ],
    "name:wln_x_preferred":[
        "Mont"
    ],
    "wof:name":"Mont",
    "wof:placetype":"locality"
},
  "geometry": {"coordinates":[5.057,49.99375],"type":"Point"}
}