{
  "type": "Feature",
  "properties": {
    "gn:admin1_code":"VLG",
    "gn:admin2_code":"VBR",
    "gn:admin3_code":"23.0",
    "gn:admin4_code":"23027.0",
    "gn:asciiname":"Rodenem",
    "gn:country_code":"BE",
    "gn:dem":71,
    "gn:feature_class":"P",
    "gn:feature_code":"PPL",
    "gn:name":"Rodenem",
    "gn:population":0,
    "gn:timezone":"Europe/Brussels",
    "iso:country":"BE",
    "wof:name":"Rodenem",
    "wof:placetype":"locality"
},
  "geometry": {"coordinates":[4.25025,50.7213],"type":"Point"}
}