{
  "type": "Feature",
  "properties": {
    "gn:admin1_code":"WAL",
    "gn:admin2_code":"WHT",
    "gn:admin3_code":"51.0",
    "gn:admin4_code":"51008.0",
    "gn:asciiname":"Bruyere",
    "gn:country_code":"BE",
    "gn:dem":70,
    "gn:feature_class":"P",
    "gn:feature_code":"PPL",
    "gn:name":"Bruy\u00e8re",
    "gn:population":0,
    "gn:timezone":"Europe/Brussels",
    "iso:country":"BE",
    "wof:name":"Bruyere",
    "wof:placetype":"locality"
},
  "geometry": {"coordinates":[3.70668,50.49852],"type":"Point"}
}