{
  "type": "Feature",
  "properties": {
    "gn:population":12815,
    "iso:country":"BE",
    "name:bre_x_preferred":[
        "Kraainem"
    ],
    "name:bul_x_preferred":[
        "\u041a\u0440\u0430\u0439\u043d\u0435\u043c"
    ],
    "name:cat_x_preferred":[
        "Kraainem"
    ],
    "name:ceb_x_preferred":[
        "Kraainem"
    ],
    "name:deu_x_preferred":[
        "Kraainem"
    ],
    "name:eng_x_preferred":[
        "Kraainem"
    ],
    "name:epo_x_preferred":[
        "Kraainem"
    ],
    "name:eus_x_preferred":[
        "Kraainem"
    ],
    "name:fas_x_preferred":[
        "\u06a9\u0631\u0646\u0645"
    ],
    "name:fra_x_preferred":[
        "Kraainem"
    ],
    "name:hun_x_preferred":[
        "Kraainem"
    ],
    "name:ita_x_preferred":[
        "Kraainem"
    ],
    "name:lit_x_preferred":[
        "Krainemas"
    ],
    "name:ltz_x_preferred":[
        "Kraainem"
    ],
    "name:nld_x_preferred":[
        "Kraainem"
    ],
    "name:nob_x_preferred":[
        "Kraainem"
    ],
    "name:nor_x_preferred":[
        "Kraainem"
    ],
    "name:oci_x_preferred":[
        "Kraainem"
    ],
    "name:pol_x_preferred":[
        "Kraainem"
    ],
    "name:por_x_preferred":[
        "Kraainem"
    ],
    "name:ron_x_preferred":[
        "Kraainem"
    ],
    "name:rus_x_preferred":[
        "\u041a\u0440\u0430\u0439\u043d\u0435\u043c"
    ],
    "name:slk_x_preferred":[
        "Kraainem"
    ],
    "name:spa_x_preferred":[
        "Kraainem"
    ],
    "name:swe_x_preferred":[
        "Kraainem"
    ],
    "name:tur_x_preferred":[
        "Kraainem"
    ],
    "name:und_x_variant":[
        "Crainhem"
    ],
    "name:vie_x_preferred":[
        "Kraainem"
    ],
    "name:vol_x_preferred":[
        "Kraainem"
    ],
    "name:war_x_preferred":[
        "Kraainem"
    ],
    "name:zho_x_preferred":[
        "\u514b\u8d56\u5185\u59c6"
    ],
    "qs:gn_fcode":"PPL",
    "qs:gn_local":0,
    "qs:gn_namadm1":"VLG",
    "qs:gn_name":"Kraainem",
    "qs:local_max":100,
    "qs:local_sum":157,
    "qs:localhoods":2,
    "qs:name":"Kraainem",
    "qs:name_adm0":"Belgique",
    "qs:name_adm1":"Vlaams Brabant",
    "qs:name_adm2":"Halle-Vilvoorde",
    "qs:name_lau":"Kraainem",
    "qs:name_local":"Kraainem",
    "qs:photo_max":54,
    "qs:photo_sum":100,
    "qs:placetype":"Suburb",
    "qs:quad_count":8,
    "qs:woe_adm0":23424757,
    "qs:woe_adm1":22525998,
    "qs:woe_adm2":12591768,
    "qs:woe_lau":20074658,
    "qs:woe_local":20074658,
    "qs:woe_ver":"7.10.0",
    "wd:wordcount":391,
    "wof:lang":[
        "dut"
    ],
    "wof:name":"Kraainem",
    "wof:placetype":"neighbourhood",
    "wof:population":12815
},
  "geometry": {"coordinates":[4.461987,50.86342],"type":"Point"}
}