{
  "type": "Feature",
  "properties": {
    "gn:country":"BE",
    "gn:fcode":"PPL",
    "gn:population":0,
    "iso:country":"BE",
    "name:eng_x_preferred":[
        "Samart"
    ],
    "name:fra_x_preferred":[
        "Samart"
    ],
    "name:gle_x_preferred":[
        "Samart"
    ],
    "name:hun_x_preferred":[
        "Samart"
    ],
    "name:nld_x_preferred":[
        "Samart"
    ],
    "name:wln_x_preferred":[
        "Sam\u00e5r"
    ],
    "qs_pg:aaroncc":"BE",
    "qs_pg:gn_country":"BE",
    "qs_pg:gn_fcode":"PPL",
    "qs_pg:gn_pop":0,
    "qs_pg:name":"Samart",
    "qs_pg:name_adm0":"Belgique",
    "qs_pg:name_adm1":"Namur",
    "qs_pg:photos_9k":1,
    "qs_pg:photos_9r":1,
    "qs_pg:photos_all":2,
    "qs_pg:photos_sr":0,
    "qs_pg:pop_sr":0,
    "qs_pg:qs_pg_placetype":"locality",
    "qs_pg:qs_pg_placetype_gp":"Town",
    "qs_pg:woe_adm0":23424757,
    "woe:adm0_id":23424757,
    "woe:name_adm0":"Belgique",
    "woe:name_adm1":"Namur",
    "woe:placetype":"Town",
    "wof:name":"Samart",
    "wof:placetype":"locality"
},
  "geometry": {"coordinates":[4.53379,50.17794],"type":"Point"}
}