{
  "type": "Feature",
  "properties": {
    "gn:admin1_code":"VLG",
    "gn:admin2_code":"VOV",
    "gn:admin3_code":"41.0",
    "gn:admin4_code":"41002.0",
    "gn:asciiname":"Sint-Job",
    "gn:country_code":"BE",
    "gn:dem":17,
    "gn:feature_class":"P",
    "gn:feature_code":"PPL",
    "gn:name":"Sint-Job",
    "gn:population":0,
    "gn:timezone":"Europe/Brussels",
    "iso:country":"BE",
    "name:und_x_variant":[
        "Saint-Job",
        "Sint-Job"
    ],
    "wof:name":"Sint-Job",
    "wof:placetype":"locality"
},
  "geometry": {"coordinates":[4.02939,50.93279],"type":"Point"}
}