{
  "type": "Feature",
  "properties": {
    "gn:gn_country":"BE",
    "gn:gn_fcode":"PPL",
    "gn:gn_pop":0,
    "iso:country":"BE",
    "name:cat_x_preferred":[
        "Coo"
    ],
    "name:dut_x_preferred":[
        "Coo"
    ],
    "name:eng_x_preferred":[
        "Coo"
    ],
    "name:fre_x_preferred":[
        "Coo"
    ],
    "name:ita_x_preferred":[
        "Coo"
    ],
    "name:ksh_x_preferred":[
        "Coo"
    ],
    "name:spa_x_preferred":[
        "Coo"
    ],
    "name:unk_x_variant":[
        "Coo"
    ],
    "qs_pg:aaroncc":"BE",
    "qs_pg:gn_country":"BE",
    "qs_pg:gn_fcode":"PPL",
    "qs_pg:gn_pop":0,
    "qs_pg:name":"Grand Coo",
    "qs_pg:name_adm0":"Belgique",
    "qs_pg:name_adm1":"Li\u00e8ge",
    "qs_pg:photos":318,
    "qs_pg:photos_1k":64,
    "qs_pg:photos_9k":1,
    "qs_pg:photos_9r":5,
    "qs_pg:photos_all":318,
    "qs_pg:photos_sr":5,
    "qs_pg:pop_sr":0,
    "qs_pg:qs_pg_placetype":"locality",
    "qs_pg:qs_pg_placetype_gp":"Town",
    "qs_pg:woe_adm0":23424757,
    "woe:adm0_id":23424757,
    "woe:name_adm0":"Belgique",
    "woe:name_adm1":"Li\u00e8ge",
    "woe:placetype":"Town",
    "wof:name":"Grand Coo",
    "wof:placetype":"locality"
},
  "geometry": {"coordinates":[5.8703,50.39391],"type":"Point"}
}