{
  "type": "Feature",
  "properties": {
    "gn:admin1_code":"WAL",
    "gn:admin2_code":"WHT",
    "gn:admin3_code":"55.0",
    "gn:admin4_code":"55010.0",
    "gn:asciiname":"Labliau",
    "gn:country_code":"BE",
    "gn:dem":61,
    "gn:feature_class":"P",
    "gn:feature_code":"PPL",
    "gn:name":"Labliau",
    "gn:population":0,
    "gn:timezone":"Europe/Brussels",
    "iso:country":"BE",
    "wof:name":"Labliau",
    "wof:placetype":"locality"
},
  "geometry": {"coordinates":[3.99025,50.66753],"type":"Point"}
}