{
  "type": "Feature",
  "properties": {
    "gn:admin1_code":"WAL",
    "gn:admin2_code":"WLX",
    "gn:admin3_code":"84.0",
    "gn:admin4_code":"84077.0",
    "gn:asciiname":"Chenet",
    "gn:country_code":"BE",
    "gn:dem":478,
    "gn:feature_class":"P",
    "gn:feature_code":"PPL",
    "gn:name":"Ch\u00eanet",
    "gn:population":0,
    "gn:timezone":"Europe/Brussels",
    "iso:country":"BE",
    "wof:name":"Chenet",
    "wof:placetype":"locality"
},
  "geometry": {"coordinates":[5.51679,49.95824],"type":"Point"}
}