{
  "type": "Feature",
  "properties": {
    "gn:admin1_code":"WAL",
    "gn:admin2_code":"WNA",
    "gn:admin3_code":"91.0",
    "gn:admin4_code":"91015.0",
    "gn:asciiname":"Monceau-en-Ardenne",
    "gn:country_code":"BE",
    "gn:dem":375,
    "gn:feature_class":"P",
    "gn:feature_code":"PPL",
    "gn:name":"Monceau-en-Ardenne",
    "gn:population":0,
    "gn:timezone":"Europe/Brussels",
    "iso:country":"BE",
    "name:und_x_variant":[
        "Bi\u00e8vre (Monceau-en-Ardenne)"
    ],
    "wof:name":"Monceau-en-Ardenne",
    "wof:placetype":"locality"
},
  "geometry": {"coordinates":[4.98767,49.90532],"type":"Point"}
}