{
  "type": "Feature",
  "properties": {
    "gn:country":"BE",
    "gn:fcode":"PPL",
    "gn:population":0,
    "iso:country":"BE",
    "name:eng_x_preferred":[
        "Malvoisin"
    ],
    "name:fra_x_preferred":[
        "Malvoisin"
    ],
    "name:hun_x_preferred":[
        "Malvoisin"
    ],
    "name:nld_x_preferred":[
        "Malvoisin"
    ],
    "name:und_x_variant":[
        "Gedinne (Malvoisin)"
    ],
    "name:wln_x_preferred":[
        "M\u00e5vjh\u00e9n"
    ],
    "qs_pg:aaroncc":"BE",
    "qs_pg:gn_country":"BE",
    "qs_pg:gn_fcode":"PPL",
    "qs_pg:gn_pop":0,
    "qs_pg:name":"Malvoisin",
    "qs_pg:name_adm0":"Belgique",
    "qs_pg:name_adm1":"Namur",
    "qs_pg:photos_9k":1,
    "qs_pg:photos_9r":1,
    "qs_pg:photos_all":1,
    "qs_pg:photos_sr":0,
    "qs_pg:pop_sr":0,
    "qs_pg:qs_pg_placetype":"locality",
    "qs_pg:qs_pg_placetype_gp":"Town",
    "qs_pg:woe_adm0":23424757,
    "woe:adm0_id":23424757,
    "woe:name_adm0":"Belgique",
    "woe:name_adm1":"Namur",
    "woe:placetype":"Town",
    "wof:name":"Malvoisin",
    "wof:placetype":"locality"
},
  "geometry": {"coordinates":[4.9623,50.01155],"type":"Point"}
}