{
  "type": "Feature",
  "properties": {
    "gn:admin1_code":"WAL",
    "gn:admin2_code":"WBR",
    "gn:admin3_code":"25.0",
    "gn:admin4_code":"25044.0",
    "gn:asciiname":"Monplaisir",
    "gn:country_code":"BE",
    "gn:dem":105,
    "gn:feature_class":"P",
    "gn:feature_code":"PPL",
    "gn:name":"Monplaisir",
    "gn:population":0,
    "gn:timezone":"Europe/Brussels",
    "iso:country":"BE",
    "name:deu_x_preferred":[
        "Monplaisir"
    ],
    "name:fra_x_preferred":[
        "Monplaisir"
    ],
    "name:und_x_variant":[
        "Mont Plaisir",
        "Monplaisir"
    ],
    "wof:name":"Monplaisir",
    "wof:placetype":"locality"
},
  "geometry": {"coordinates":[4.21304,50.62979],"type":"Point"}
}