{
  "type": "Feature",
  "properties": {
    "gn:admin1_code":"VLG",
    "gn:admin2_code":"VWV",
    "gn:admin3_code":"31.0",
    "gn:admin4_code":"31005.0",
    "gn:asciiname":"Klinkewal",
    "gn:country_code":"BE",
    "gn:dem":0,
    "gn:feature_class":"P",
    "gn:feature_code":"PPL",
    "gn:name":"Klinkewal",
    "gn:population":0,
    "gn:timezone":"Europe/Brussels",
    "iso:country":"BE",
    "wof:name":"Klinkewal",
    "wof:placetype":"locality"
},
  "geometry": {"coordinates":[3.23333,51.25],"type":"Point"}
}