{
  "type": "Feature",
  "properties": {
    "gn:admin1_code":"WAL",
    "gn:admin2_code":"WLX",
    "gn:admin3_code":"84.0",
    "gn:admin4_code":"84059.0",
    "gn:asciiname":"Beoli",
    "gn:country_code":"BE",
    "gn:dem":545,
    "gn:feature_class":"P",
    "gn:feature_code":"PPL",
    "gn:name":"B\u00e9oli",
    "gn:population":0,
    "gn:timezone":"Europe/Brussels",
    "iso:country":"BE",
    "wof:name":"Beoli",
    "wof:placetype":"locality"
},
  "geometry": {"coordinates":[5.36667,50.05],"type":"Point"}
}