{
  "type": "Feature",
  "properties": {
    "gn:admin1_code":"WAL",
    "gn:admin2_code":"WHT",
    "gn:admin3_code":"56.0",
    "gn:admin4_code":"56086.0",
    "gn:asciiname":"Petria",
    "gn:country_code":"BE",
    "gn:dem":211,
    "gn:feature_class":"P",
    "gn:feature_code":"PPL",
    "gn:name":"Petria",
    "gn:population":0,
    "gn:timezone":"Europe/Brussels",
    "iso:country":"BE",
    "wof:name":"Petria",
    "wof:placetype":"locality"
},
  "geometry": {"coordinates":[4.42843,50.34102],"type":"Point"}
}