{
  "type": "Feature",
  "properties": {
    "gn:admin1_code":"VLG",
    "gn:admin2_code":"VBR",
    "gn:admin3_code":"23.0",
    "gn:admin4_code":"23038.0",
    "gn:asciiname":"List",
    "gn:country_code":"BE",
    "gn:dem":18,
    "gn:feature_class":"P",
    "gn:feature_code":"PPL",
    "gn:name":"List",
    "gn:population":0,
    "gn:timezone":"Europe/Brussels",
    "iso:country":"BE",
    "wof:name":"List",
    "wof:placetype":"locality"
},
  "geometry": {"coordinates":[4.56453,50.92534000000001],"type":"Point"}
}