{
  "type": "Feature",
  "properties": {
    "gn:admin1_code":"WAL",
    "gn:admin2_code":"WLG",
    "gn:admin3_code":"62.0",
    "gn:admin4_code":"62026.0",
    "gn:asciiname":"Oneux",
    "gn:country_code":"BE",
    "gn:dem":208,
    "gn:feature_class":"P",
    "gn:feature_code":"PPL",
    "gn:name":"Oneux",
    "gn:population":0,
    "gn:timezone":"Europe/Brussels",
    "iso:country":"BE",
    "name:bug_x_preferred":[
        "Oneux"
    ],
    "name:cat_x_preferred":[
        "Oneux"
    ],
    "name:ceb_x_preferred":[
        "Oneux"
    ],
    "name:deu_x_preferred":[
        "Oneux"
    ],
    "name:eus_x_preferred":[
        "Oneux"
    ],
    "name:fra_x_preferred":[
        "Oneux"
    ],
    "name:hun_x_preferred":[
        "Oneux"
    ],
    "name:hye_x_preferred":[
        "\u0555\u0576\u0565"
    ],
    "name:ita_x_preferred":[
        "Oneux"
    ],
    "name:lat_x_preferred":[
        "Oneux"
    ],
    "name:mlg_x_preferred":[
        "Oneux"
    ],
    "name:msa_x_preferred":[
        "Oneux"
    ],
    "name:nld_x_preferred":[
        "Oneux"
    ],
    "name:oci_x_preferred":[
        "Oneux"
    ],
    "name:pcd_x_preferred":[
        "Oneux"
    ],
    "name:pms_x_preferred":[
        "Oneux"
    ],
    "name:pol_x_preferred":[
        "Oneux"
    ],
    "name:por_x_preferred":[
        "Oneux"
    ],
    "name:ron_x_preferred":[
        "Oneux"
    ],
    "name:slk_x_preferred":[
        "Oneux"
    ],
    "name:spa_x_preferred":[
        "Oneux"
    ],
    "name:swe_x_preferred":[
        "Oneux"
    ],
    "name:ukr_x_preferred":[
        "\u041e\u043d\u0435"
    ],
    "name:uzb_x_preferred":[
        "Oneux"
    ],
    "name:vie_x_preferred":[
        "Oneux"
    ],
    "name:vol_x_preferred":[
        "Oneux"
    ],
    "name:war_x_preferred":[
        "Oneux"
    ],
    "wof:name":"Oneux",
    "wof:placetype":"locality"
},
  "geometry": {"coordinates":[5.5982,50.4729],"type":"Point"}
}