{
  "type": "Feature",
  "properties": {
    "gn:admin1_code":"VLG",
    "gn:admin2_code":"VOV",
    "gn:admin3_code":"42.0",
    "gn:admin4_code":"42008.0",
    "gn:asciiname":"Driegoten",
    "gn:country_code":"BE",
    "gn:dem":2,
    "gn:feature_class":"P",
    "gn:feature_code":"PPL",
    "gn:name":"Driegoten",
    "gn:population":0,
    "gn:timezone":"Europe/Brussels",
    "iso:country":"BE",
    "name:und_x_variant":[
        "Drygoten",
        "Dreigoten",
        "Driegoten"
    ],
    "wof:name":"Driegoten",
    "wof:placetype":"locality"
},
  "geometry": {"coordinates":[4.15669,51.09495],"type":"Point"}
}