{
  "type": "Feature",
  "properties": {
    "gn:admin1_code":"WAL",
    "gn:admin2_code":"WHT",
    "gn:admin3_code":"55.0",
    "gn:admin4_code":"55050.0",
    "gn:asciiname":"Lavedelle",
    "gn:country_code":"BE",
    "gn:dem":100,
    "gn:feature_class":"P",
    "gn:feature_code":"PPL",
    "gn:name":"Lavedelle",
    "gn:population":0,
    "gn:timezone":"Europe/Brussels",
    "iso:country":"BE",
    "wof:name":"Lavedelle",
    "wof:placetype":"locality"
},
  "geometry": {"coordinates":[4.17811,50.55791],"type":"Point"}
}