{
  "type": "Feature",
  "properties": {
    "gn:admin1_code":"WAL",
    "gn:admin2_code":"WLG",
    "gn:admin3_code":"61.0",
    "gn:admin4_code":"61012.0",
    "gn:asciiname":"Odet",
    "gn:country_code":"BE",
    "gn:dem":299,
    "gn:feature_class":"P",
    "gn:feature_code":"PPL",
    "gn:name":"Odet",
    "gn:population":0,
    "gn:timezone":"Europe/Brussels",
    "iso:country":"BE",
    "name:bre_x_preferred":[
        "Oded"
    ],
    "name:ceb_x_preferred":[
        "Odet"
    ],
    "name:cym_x_preferred":[
        "Afon Oded"
    ],
    "name:deu_x_preferred":[
        "Odet"
    ],
    "name:ell_x_preferred":[
        "\u039f\u03bd\u03c4\u03ad"
    ],
    "name:eus_x_preferred":[
        "Odet"
    ],
    "name:fas_x_preferred":[
        "\u0627\u0648\u062f\u0647"
    ],
    "name:fra_x_preferred":[
        "Odet"
    ],
    "name:glv_x_preferred":[
        "Oded"
    ],
    "name:lat_x_preferred":[
        "Odera"
    ],
    "name:nld_x_preferred":[
        "Odet"
    ],
    "name:nno_x_preferred":[
        "Odet"
    ],
    "name:pol_x_preferred":[
        "Odet"
    ],
    "name:por_x_preferred":[
        "Rio Odet"
    ],
    "name:srp_x_preferred":[
        "\u041e\u0434\u0435"
    ],
    "name:tgk_x_preferred":[
        "\u041e\u0434\u0435\u0442"
    ],
    "name:zho_x_preferred":[
        "\u5967\u4ee3\u6cb3"
    ],
    "wof:name":"Odet",
    "wof:placetype":"locality"
},
  "geometry": {"coordinates":[5.30732,50.38647],"type":"Point"}
}