{
  "type": "Feature",
  "properties": {
    "gn:admin1_code":"WAL",
    "gn:admin2_code":"WHT",
    "gn:admin3_code":"56.0",
    "gn:admin4_code":"56078.0",
    "gn:asciiname":"Fostaille",
    "gn:country_code":"BE",
    "gn:dem":190,
    "gn:feature_class":"P",
    "gn:feature_code":"PPL",
    "gn:name":"Fostaille",
    "gn:population":0,
    "gn:timezone":"Europe/Brussels",
    "iso:country":"BE",
    "wof:name":"Fostaille",
    "wof:placetype":"locality"
},
  "geometry": {"coordinates":[4.31049,50.32943],"type":"Point"}
}