{
  "type": "Feature",
  "properties": {
    "gn:admin1_code":"VLG",
    "gn:admin2_code":"VOV",
    "gn:admin3_code":"44.0",
    "gn:admin4_code":"44019.0",
    "gn:asciiname":"Belzele",
    "gn:country_code":"BE",
    "gn:dem":5,
    "gn:feature_class":"P",
    "gn:feature_code":"PPL",
    "gn:name":"Belzele",
    "gn:population":0,
    "gn:timezone":"Europe/Brussels",
    "iso:country":"BE",
    "name:und_x_variant":[
        "Belzeele",
        "Belzele"
    ],
    "wof:name":"Belzele",
    "wof:placetype":"locality"
},
  "geometry": {"coordinates":[3.66882,51.1026],"type":"Point"}
}