{
  "type": "Feature",
  "properties": {
    "gn:admin1_code":"WAL",
    "gn:admin2_code":"WLX",
    "gn:admin3_code":"82.0",
    "gn:admin4_code":"82003.0",
    "gn:asciiname":"Marenwez",
    "gn:country_code":"BE",
    "gn:dem":506,
    "gn:feature_class":"P",
    "gn:feature_code":"PPL",
    "gn:name":"Marenwez",
    "gn:population":0,
    "gn:timezone":"Europe/Brussels",
    "iso:country":"BE",
    "wof:name":"Marenwez",
    "wof:placetype":"locality"
},
  "geometry": {"coordinates":[5.76667,49.98333],"type":"Point"}
}