{
  "type": "Feature",
  "properties": {
    "gn:admin1_code":"WAL",
    "gn:admin2_code":"WBR",
    "gn:admin3_code":"25.0",
    "gn:admin4_code":"25120.0",
    "gn:asciiname":"Libertange",
    "gn:country_code":"BE",
    "gn:dem":58,
    "gn:feature_class":"P",
    "gn:feature_code":"PPL",
    "gn:name":"Libertange",
    "gn:population":0,
    "gn:timezone":"Europe/Brussels",
    "iso:country":"BE",
    "wof:name":"Libertange",
    "wof:placetype":"locality"
},
  "geometry": {"coordinates":[4.98692,50.73191],"type":"Point"}
}