{
  "type": "Feature",
  "properties": {
    "gn:admin1_code":"WAL",
    "gn:admin2_code":"WLG",
    "gn:admin3_code":"63.0",
    "gn:admin4_code":"63049.0",
    "gn:asciiname":"Borgeuce",
    "gn:country_code":"BE",
    "gn:dem":422,
    "gn:feature_class":"P",
    "gn:feature_code":"PPL",
    "gn:name":"Borgeuc\u00e9",
    "gn:population":0,
    "gn:timezone":"Europe/Brussels",
    "iso:country":"BE",
    "wof:name":"Borgeuce",
    "wof:placetype":"locality"
},
  "geometry": {"coordinates":[6.03333,50.38333],"type":"Point"}
}