{
  "type": "Feature",
  "properties": {
    "gn:admin1_code":"WAL",
    "gn:admin2_code":"WHT",
    "gn:admin3_code":"57.0",
    "gn:admin4_code":"57072.0",
    "gn:asciiname":"La Glanerie",
    "gn:country_code":"BE",
    "gn:dem":38,
    "gn:feature_class":"P",
    "gn:feature_code":"PPL",
    "gn:name":"La Glanerie",
    "gn:population":0,
    "gn:timezone":"Europe/Brussels",
    "iso:country":"BE",
    "wof:name":"La Glanerie",
    "wof:placetype":"locality"
},
  "geometry": {"coordinates":[3.30094,50.52991],"type":"Point"}
}