{
  "type": "Feature",
  "properties": {
    "gn:admin1_code":"WAL",
    "gn:admin2_code":"WNA",
    "gn:admin3_code":"92.0",
    "gn:admin4_code":"92142.0",
    "gn:asciiname":"Malprouve",
    "gn:country_code":"BE",
    "gn:dem":154,
    "gn:feature_class":"P",
    "gn:feature_code":"PPL",
    "gn:name":"Malprouv\u00e9",
    "gn:population":0,
    "gn:timezone":"Europe/Brussels",
    "iso:country":"BE",
    "wof:name":"Malprouve",
    "wof:placetype":"locality"
},
  "geometry": {"coordinates":[4.7262,50.59481],"type":"Point"}
}