{
  "type": "Feature",
  "properties": {
    "gn:admin1_code":"WAL",
    "gn:admin2_code":"WLG",
    "gn:admin3_code":"63.0",
    "gn:admin4_code":"63038.0",
    "gn:asciiname":"Neufmarteau",
    "gn:country_code":"BE",
    "gn:dem":233,
    "gn:feature_class":"P",
    "gn:feature_code":"PPL",
    "gn:name":"Neufmarteau",
    "gn:population":0,
    "gn:timezone":"Europe/Brussels",
    "iso:country":"BE",
    "wof:name":"Neufmarteau",
    "wof:placetype":"locality"
},
  "geometry": {"coordinates":[5.89332,50.54137],"type":"Point"}
}