{
  "type": "Feature",
  "properties": {
    "gn:admin1_code":"WAL",
    "gn:admin2_code":"WLX",
    "gn:admin3_code":"83.0",
    "gn:admin4_code":"83034.0",
    "gn:asciiname":"Marengo",
    "gn:country_code":"BE",
    "gn:dem":289,
    "gn:feature_class":"P",
    "gn:feature_code":"PPL",
    "gn:name":"Marengo",
    "gn:population":0,
    "gn:timezone":"Europe/Brussels",
    "iso:country":"BE",
    "name:bre_x_preferred":[
        "Marengo"
    ],
    "name:cat_x_preferred":[
        "Marengo"
    ],
    "name:ceb_x_preferred":[
        "Marengo"
    ],
    "name:dan_x_preferred":[
        "Marengo"
    ],
    "name:deu_x_preferred":[
        "Marengo"
    ],
    "name:epo_x_preferred":[
        "Marengo"
    ],
    "name:fra_x_preferred":[
        "Marengo"
    ],
    "name:ita_x_preferred":[
        "Marengo"
    ],
    "name:kor_x_preferred":[
        "\ub9c8\ub81d\uace0"
    ],
    "name:nld_x_preferred":[
        "Marengo"
    ],
    "name:pol_x_preferred":[
        "Marengo"
    ],
    "name:por_x_preferred":[
        "Marengo"
    ],
    "name:rus_x_preferred":[
        "\u041c\u0430\u0440\u0435\u043d\u0433\u043e"
    ],
    "name:spa_x_preferred":[
        "Marengo"
    ],
    "name:srp_x_preferred":[
        "\u041c\u0430\u0440\u0435\u043d\u0433\u043e"
    ],
    "name:swe_x_preferred":[
        "Marengo"
    ],
    "name:ukr_x_preferred":[
        "\u041c\u0430\u0440\u0435\u043d\u0433\u043e"
    ],
    "name:vol_x_preferred":[
        "Marengo"
    ],
    "wof:name":"Marengo",
    "wof:placetype":"locality"
},
  "geometry": {"coordinates":[5.33333,50.18333],"type":"Point"}
}