{
  "type": "Feature",
  "properties": {
    "gn:admin1_code":"WAL",
    "gn:admin2_code":"WLG",
    "gn:admin3_code":"62.0",
    "gn:admin4_code":"62099.0",
    "gn:asciiname":"Maireux",
    "gn:country_code":"BE",
    "gn:dem":221,
    "gn:feature_class":"P",
    "gn:feature_code":"PPL",
    "gn:name":"Maireux",
    "gn:population":0,
    "gn:timezone":"Europe/Brussels",
    "iso:country":"BE",
    "name:und_x_variant":[
        "Maiseux",
        "Maireux"
    ],
    "wof:name":"Maireux",
    "wof:placetype":"locality"
},
  "geometry": {"coordinates":[5.73333,50.61667],"type":"Point"}
}