{
  "type": "Feature",
  "properties": {
    "gn:country":"BE",
    "gn:fcode":"PPL",
    "gn:population":0,
    "iso:country":"BE",
    "name:deu_x_preferred":[
        "Lompret"
    ],
    "name:eng_x_preferred":[
        "Lompret"
    ],
    "name:fas_x_preferred":[
        "\u0644\u0645\u067e\u0631\u062a"
    ],
    "name:fra_x_preferred":[
        "Lompret"
    ],
    "name:hun_x_preferred":[
        "Lompret"
    ],
    "name:nld_x_preferred":[
        "Lompret"
    ],
    "name:und_x_variant":[
        "Chimay (Lompret)"
    ],
    "name:wln_x_preferred":[
        "Lompr\u00e9-el-Fagne"
    ],
    "qs_pg:aaroncc":"BE",
    "qs_pg:gn_country":"BE",
    "qs_pg:gn_fcode":"PPL",
    "qs_pg:gn_pop":0,
    "qs_pg:name":"Lompret",
    "qs_pg:name_adm0":"Belgique",
    "qs_pg:name_adm1":"Hainaut",
    "qs_pg:photos_9r":0,
    "qs_pg:photos_sr":0,
    "qs_pg:pop_sr":0,
    "qs_pg:qs_pg_placetype":"locality",
    "qs_pg:qs_pg_placetype_gp":"Town",
    "qs_pg:woe_adm0":23424757,
    "woe:adm0_id":23424757,
    "woe:name_adm0":"Belgique",
    "woe:name_adm1":"Hainaut",
    "woe:placetype":"Town",
    "wof:name":"Lompret",
    "wof:placetype":"locality"
},
  "geometry": {"coordinates":[4.379,50.06441],"type":"Point"}
}