{
  "type": "Feature",
  "properties": {
    "gn:country":"BE",
    "gn:fcode":"PPL",
    "gn:population":0,
    "iso:country":"BE",
    "name:cat_x_preferred":[
        "Jemappes"
    ],
    "name:ceb_x_preferred":[
        "Jemappes"
    ],
    "name:deu_x_preferred":[
        "Jemappes"
    ],
    "name:eng_x_preferred":[
        "Jemappes"
    ],
    "name:fas_x_preferred":[
        "\u0698\u0648\u0645\u067e\u0647"
    ],
    "name:fra_x_preferred":[
        "Jemappes"
    ],
    "name:gle_x_preferred":[
        "Jemappes"
    ],
    "name:hun_x_preferred":[
        "Jemappes"
    ],
    "name:ita_x_preferred":[
        "Jemappes"
    ],
    "name:jpn_x_preferred":[
        "\u30b8\u30e3\u30de\u30c3\u30d7"
    ],
    "name:kor_x_preferred":[
        "\uc8fc\ub9c8\ud504"
    ],
    "name:lat_x_preferred":[
        "Gamapium"
    ],
    "name:nld_x_preferred":[
        "Jemappes"
    ],
    "name:nob_x_preferred":[
        "Jemappes"
    ],
    "name:pcd_x_preferred":[
        "Djumappes"
    ],
    "name:pol_x_preferred":[
        "Jemappes"
    ],
    "name:ron_x_preferred":[
        "Jemappes"
    ],
    "name:swe_x_preferred":[
        "Jemappes"
    ],
    "name:tur_x_preferred":[
        "Jemappes"
    ],
    "name:wln_x_preferred":[
        "Djumape"
    ],
    "name:zho_x_preferred":[
        "\u70ed\u9a6c\u666e"
    ],
    "qs_pg:aaroncc":"BE",
    "qs_pg:gn_country":"BE",
    "qs_pg:gn_fcode":"PPL",
    "qs_pg:gn_pop":0,
    "qs_pg:name":"Jemappes",
    "qs_pg:name_adm0":"Belgique",
    "qs_pg:name_adm1":"Hainaut",
    "qs_pg:photos_9k":1,
    "qs_pg:photos_9r":1,
    "qs_pg:photos_all":2,
    "qs_pg:photos_sr":0,
    "qs_pg:pop_sr":0,
    "qs_pg:qs_pg_placetype":"locality",
    "qs_pg:qs_pg_placetype_gp":"Town",
    "qs_pg:woe_adm0":23424757,
    "woe:adm0_id":23424757,
    "woe:name_adm0":"Belgique",
    "woe:name_adm1":"Hainaut",
    "woe:placetype":"Town",
    "wof:name":"Jemappes",
    "wof:placetype":"locality"
},
  "geometry": {"coordinates":[3.89096,50.44914],"type":"Point"}
}