{
  "type": "Feature",
  "properties": {
    "gn:admin1_code":"WAL",
    "gn:admin2_code":"WLX",
    "gn:admin3_code":"84.0",
    "gn:admin4_code":"84077.0",
    "gn:asciiname":"Siom",
    "gn:country_code":"BE",
    "gn:dem":428,
    "gn:feature_class":"P",
    "gn:feature_code":"PPL",
    "gn:name":"Siom",
    "gn:population":0,
    "gn:timezone":"Europe/Brussels",
    "iso:country":"BE",
    "wof:name":"Siom",
    "wof:placetype":"locality"
},
  "geometry": {"coordinates":[5.48333,50.01667],"type":"Point"}
}