{
  "type": "Feature",
  "properties": {
    "gn:admin1_code":"WAL",
    "gn:admin2_code":"WHT",
    "gn:admin3_code":"56.0",
    "gn:admin4_code":"56016.0",
    "gn:asciiname":"La Colotterie",
    "gn:country_code":"BE",
    "gn:dem":307,
    "gn:feature_class":"P",
    "gn:feature_code":"PPL",
    "gn:name":"La Colotterie",
    "gn:population":0,
    "gn:timezone":"Europe/Brussels",
    "iso:country":"BE",
    "name:und_x_variant":[
        "La Coletterie",
        "La Colotterie"
    ],
    "wof:name":"La Colotterie",
    "wof:placetype":"locality"
},
  "geometry": {"coordinates":[4.37295,50.01971],"type":"Point"}
}