{
  "type": "Feature",
  "properties": {
    "gn:gn_country":"BE",
    "gn:gn_fcode":"PPL",
    "gn:gn_pop":0,
    "iso:country":"BE",
    "name:dut_x_preferred":[
        "Rochehaut"
    ],
    "name:eng_x_preferred":[
        "Rochehaut"
    ],
    "name:epo_x_preferred":[
        "Rochehaut"
    ],
    "name:fre_x_preferred":[
        "Rochehaut"
    ],
    "name:ger_x_preferred":[
        "Rochehaut"
    ],
    "name:hun_x_preferred":[
        "Rochehaut"
    ],
    "name:wln_x_preferred":[
        "Rotch\u00f4"
    ],
    "qs_pg:aaroncc":"BE",
    "qs_pg:gn_country":"BE",
    "qs_pg:gn_fcode":"PPL",
    "qs_pg:gn_pop":0,
    "qs_pg:name":"Rochehaut",
    "qs_pg:name_adm0":"Belgique",
    "qs_pg:name_adm1":"Luxembourg",
    "qs_pg:photos":66,
    "qs_pg:photos_1k":13,
    "qs_pg:photos_9k":1,
    "qs_pg:photos_9r":2,
    "qs_pg:photos_all":66,
    "qs_pg:photos_sr":2,
    "qs_pg:pop_sr":0,
    "qs_pg:qs_pg_placetype":"locality",
    "qs_pg:qs_pg_placetype_gp":"Town",
    "qs_pg:woe_adm0":23424757,
    "woe:adm0_id":23424757,
    "woe:name_adm0":"Belgique",
    "woe:name_adm1":"Luxembourg",
    "woe:placetype":"Town",
    "wof:name":"Rochehaut",
    "wof:placetype":"locality"
},
  "geometry": {"coordinates":[5.00599,49.84041],"type":"Point"}
}