{
  "type": "Feature",
  "properties": {
    "gn:admin1_code":"WAL",
    "gn:admin2_code":"WHT",
    "gn:admin3_code":"51.0",
    "gn:admin4_code":"51019.0",
    "gn:asciiname":"Planque",
    "gn:country_code":"BE",
    "gn:dem":29,
    "gn:feature_class":"P",
    "gn:feature_code":"PPL",
    "gn:name":"Planque",
    "gn:population":0,
    "gn:timezone":"Europe/Brussels",
    "iso:country":"BE",
    "wof:name":"Planque",
    "wof:placetype":"locality"
},
  "geometry": {"coordinates":[3.76667,50.73333],"type":"Point"}
}