{
  "type": "Feature",
  "properties": {
    "gn:admin1_code":"WAL",
    "gn:admin2_code":"WLG",
    "gn:admin3_code":"63.0",
    "gn:admin4_code":"63079.0",
    "gn:asciiname":"Hodimont",
    "gn:country_code":"BE",
    "gn:dem":167,
    "gn:feature_class":"P",
    "gn:feature_code":"PPL",
    "gn:name":"Hodimont",
    "gn:population":0,
    "gn:timezone":"Europe/Brussels",
    "iso:country":"BE",
    "wof:name":"Hodimont",
    "wof:placetype":"locality"
},
  "geometry": {"coordinates":[5.85434,50.59446],"type":"Point"}
}