{
  "type": "Feature",
  "properties": {
    "iso:country":"BE",
    "qs_pg:aaroncc":"BE",
    "qs_pg:name":"Ribaucourt",
    "qs_pg:name_adm0":"Belgique",
    "qs_pg:name_adm1":"Vlaams Brabant",
    "qs_pg:photos":37,
    "qs_pg:photos_1k":7,
    "qs_pg:photos_9k":1,
    "qs_pg:photos_9r":2,
    "qs_pg:photos_all":37,
    "qs_pg:photos_sr":2,
    "qs_pg:pop_sr":0,
    "qs_pg:qs_pg_placetype":"locality",
    "qs_pg:qs_pg_placetype_gp":"Town",
    "qs_pg:woe_adm0":23424757,
    "woe:adm0_id":23424757,
    "woe:name_adm0":"Belgique",
    "woe:name_adm1":"Vlaams Brabant",
    "woe:placetype":"Town",
    "wof:name":"Ribaucourt",
    "wof:placetype":"locality"
},
  "geometry": {"coordinates":[4.531002,50.927667],"type":"Point"}
}