{
  "type": "Feature",
  "properties": {
    "gn:admin1_code":"VLG",
    "gn:admin2_code":"VWV",
    "gn:admin3_code":"32.0",
    "gn:admin4_code":"32011.0",
    "gn:asciiname":"Kruisstraat",
    "gn:country_code":"BE",
    "gn:dem":1,
    "gn:feature_class":"P",
    "gn:feature_code":"PPL",
    "gn:name":"Kruisstraat",
    "gn:population":0,
    "gn:timezone":"Europe/Brussels",
    "iso:country":"BE",
    "name:fra_x_preferred":[
        "Kruisstraat"
    ],
    "name:nld_x_preferred":[
        "Kruisstraat"
    ],
    "wof:name":"Kruisstraat",
    "wof:placetype":"locality"
},
  "geometry": {"coordinates":[2.95,51.03333],"type":"Point"}
}