{
  "type": "Feature",
  "properties": {
    "gn:admin1_code":"WAL",
    "gn:admin2_code":"WHT",
    "gn:admin3_code":"56.0",
    "gn:admin4_code":"56029.0",
    "gn:asciiname":"Badon",
    "gn:country_code":"BE",
    "gn:dem":226,
    "gn:feature_class":"P",
    "gn:feature_code":"PPL",
    "gn:name":"Badon",
    "gn:population":0,
    "gn:timezone":"Europe/Brussels",
    "iso:country":"BE",
    "wof:name":"Badon",
    "wof:placetype":"locality"
},
  "geometry": {"coordinates":[4.37852,50.19688],"type":"Point"}
}