{
  "type": "Feature",
  "properties": {
    "gn:admin1_code":"VLG",
    "gn:admin2_code":"VBR",
    "gn:admin3_code":"23.0",
    "gn:admin4_code":"23016.0",
    "gn:asciiname":"Goudveerdegem",
    "gn:country_code":"BE",
    "gn:dem":77,
    "gn:feature_class":"P",
    "gn:feature_code":"PPL",
    "gn:name":"Goudveerdegem",
    "gn:population":0,
    "gn:timezone":"Europe/Brussels",
    "iso:country":"BE",
    "name:und_x_variant":[
        "Goudveerdeghem",
        "Goudveerdegem"
    ],
    "wof:name":"Goudveerdegem",
    "wof:placetype":"locality"
},
  "geometry": {"coordinates":[4.17447,50.83727],"type":"Point"}
}