{
  "type": "Feature",
  "properties": {
    "gn:admin1_code":"WAL",
    "gn:admin2_code":"WLG",
    "gn:asciiname":"Snauwenberg",
    "gn:country_code":"BE",
    "gn:dem":138,
    "gn:feature_class":"P",
    "gn:feature_code":"PPL",
    "gn:name":"Snauwenberg",
    "gn:population":0,
    "gn:timezone":"Europe/Brussels",
    "iso:country":"BE",
    "wof:name":"Snauwenberg",
    "wof:placetype":"locality"
},
  "geometry": {"coordinates":[5.76667,50.76667],"type":"Point"}
}