{
  "type": "Feature",
  "properties": {
    "gn:admin1_code":"WAL",
    "gn:admin2_code":"WNA",
    "gn:admin3_code":"92.0",
    "gn:admin4_code":"92048.0",
    "gn:asciiname":"Bas-Sart",
    "gn:country_code":"BE",
    "gn:dem":140,
    "gn:feature_class":"P",
    "gn:feature_code":"PPL",
    "gn:name":"Bas-Sart",
    "gn:population":0,
    "gn:timezone":"Europe/Brussels",
    "iso:country":"BE",
    "wof:name":"Bas-Sart",
    "wof:placetype":"locality"
},
  "geometry": {"coordinates":[4.59395,50.37461],"type":"Point"}
}