{
  "type": "Feature",
  "properties": {
    "gn:admin1_code":"WAL",
    "gn:admin2_code":"WLX",
    "gn:admin3_code":"83.0",
    "gn:admin4_code":"83044.0",
    "gn:asciiname":"A Faihay",
    "gn:country_code":"BE",
    "gn:dem":321,
    "gn:feature_class":"P",
    "gn:feature_code":"PPL",
    "gn:name":"\u00c0 Faihay",
    "gn:population":0,
    "gn:timezone":"Europe/Brussels",
    "iso:country":"BE",
    "wof:name":"A Faihay",
    "wof:placetype":"locality"
},
  "geometry": {"coordinates":[5.50583,50.22127],"type":"Point"}
}