{
  "type": "Feature",
  "properties": {
    "gn:admin1_code":"WAL",
    "gn:admin2_code":"WLG",
    "gn:admin3_code":"64.0",
    "gn:admin4_code":"64056.0",
    "gn:asciiname":"Lens-sur-Geer",
    "gn:country_code":"BE",
    "gn:dem":98,
    "gn:feature_class":"P",
    "gn:feature_code":"PPL",
    "gn:name":"Lens-sur-Geer",
    "gn:population":0,
    "gn:timezone":"Europe/Brussels",
    "iso:country":"BE",
    "name:und_x_variant":[
        "Oreye (Lens-sur-Geer)"
    ],
    "wof:name":"Lens-sur-Geer",
    "wof:placetype":"locality"
},
  "geometry": {"coordinates":[5.35086,50.72162],"type":"Point"}
}