{
  "type": "Feature",
  "properties": {
    "gn:admin1_code":"WAL",
    "gn:admin2_code":"WLX",
    "gn:admin3_code":"82.0",
    "gn:admin4_code":"82003.0",
    "gn:asciiname":"Hemroulle",
    "gn:cc2":"BE",
    "gn:country_code":"BE",
    "gn:dem":479,
    "gn:feature_class":"P",
    "gn:feature_code":"PPL",
    "gn:name":"Hemroulle",
    "gn:population":0,
    "gn:timezone":"Europe/Brussels",
    "iso:country":"BE",
    "name:und_x_variant":[
        "Hemroule"
    ],
    "wof:name":"Hemroulle",
    "wof:placetype":"locality"
},
  "geometry": {"coordinates":[5.68723,50.02274],"type":"Point"}
}