{
  "type": "Feature",
  "properties": {
    "gn:gn_country":"BE",
    "gn:gn_fcode":"PPL",
    "gn:gn_pop":0,
    "iso:country":"BE",
    "name:bre_x_preferred":[
        "Krombeke"
    ],
    "name:eng_x_preferred":[
        "Krombeke"
    ],
    "name:fra_x_preferred":[
        "Krombeke"
    ],
    "name:hun_x_preferred":[
        "Krombeke"
    ],
    "name:nld_x_preferred":[
        "Krombeke"
    ],
    "name:unk_x_variant":[
        "Crombeke"
    ],
    "name:vls_x_preferred":[
        "Krombeke"
    ],
    "qs_pg:aaroncc":"BE",
    "qs_pg:gn_country":"BE",
    "qs_pg:gn_fcode":"PPL",
    "qs_pg:gn_pop":0,
    "qs_pg:name":"Krombeke",
    "qs_pg:name_adm0":"Belgique",
    "qs_pg:name_adm1":"West-Vlaanderen",
    "qs_pg:photos":46,
    "qs_pg:photos_1k":9,
    "qs_pg:photos_9k":1,
    "qs_pg:photos_9r":2,
    "qs_pg:photos_all":46,
    "qs_pg:photos_sr":2,
    "qs_pg:pop_sr":0,
    "qs_pg:qs_pg_placetype":"locality",
    "qs_pg:qs_pg_placetype_gp":"Town",
    "qs_pg:woe_adm0":23424757,
    "woe:adm0_id":23424757,
    "woe:name_adm0":"Belgique",
    "woe:name_adm1":"West-Vlaanderen",
    "woe:placetype":"Town",
    "wof:name":"Krombeke",
    "wof:placetype":"locality"
},
  "geometry": {"coordinates":[2.68826,50.91488],"type":"Point"}
}