{
  "type": "Feature",
  "properties": {
    "iso:country":"BE",
    "name:dut_x_preferred":[
        "Peuthy"
    ],
    "name:unk_x_variant":[
        "Peuthy"
    ],
    "qs:gn_adm0_cc":"BE",
    "qs:gn_local":2784604,
    "qs:gn_nam_loc":"vilvoorde",
    "qs:gn_namadm1":"VLG",
    "qs:local_max":1341,
    "qs:local_sum":1732,
    "qs:localhoods":2,
    "qs:name":"Peuthy",
    "qs:name_adm0":"Belgique",
    "qs:name_adm1":"Vlaams Brabant",
    "qs:name_adm2":"Halle-Vilvoorde",
    "qs:name_lau":"Vilvoorde",
    "qs:name_local":"Vilvoorde",
    "qs:photo_max":182,
    "qs:photo_sum":391,
    "qs:placetype":"Suburb",
    "qs:quad_count":30,
    "qs:woe_adm0":23424757,
    "qs:woe_adm1":22525998,
    "qs:woe_adm2":12591768,
    "qs:woe_lau":12602810,
    "qs:woe_local":978356,
    "qs:woe_ver":"7.10.0",
    "wof:lang":[
        "dut"
    ],
    "wof:name":"Peuthy",
    "wof:placetype":"neighbourhood"
},
  "geometry": {"coordinates":[4.469478,50.93569],"type":"Point"}
}