{
  "type": "Feature",
  "properties": {
    "gn:admin1_code":"VLG",
    "gn:admin2_code":"VOV",
    "gn:admin3_code":"44.0",
    "gn:admin4_code":"44012.0",
    "gn:asciiname":"Bommelhoek",
    "gn:country_code":"BE",
    "gn:dem":8,
    "gn:feature_class":"P",
    "gn:feature_code":"PPL",
    "gn:name":"Bommelhoek",
    "gn:population":0,
    "gn:timezone":"Europe/Brussels",
    "iso:country":"BE",
    "wof:name":"Bommelhoek",
    "wof:placetype":"locality"
},
  "geometry": {"coordinates":[3.63898,50.98898],"type":"Point"}
}