{
  "type": "Feature",
  "properties": {
    "iso:country":"BE",
    "name:nld_x_preferred":[
        "Zandvliet"
    ],
    "name:spa_x_preferred":[
        "Santvliet"
    ],
    "wof:name":"Zandvliet",
    "wof:placetype":"neighbourhood"
},
  "geometry": {"coordinates":[4.30618692816218,51.36053303415613],"type":"Point"}
}