{
  "type": "Feature",
  "properties": {
    "gn:admin1_code":"VLG",
    "gn:admin2_code":"VWV",
    "gn:admin3_code":"35.0",
    "gn:admin4_code":"35011.0",
    "gn:asciiname":"Middelkerke-Bad",
    "gn:country_code":"BE",
    "gn:dem":1,
    "gn:feature_class":"P",
    "gn:feature_code":"PPL",
    "gn:name":"Middelkerke-Bad",
    "gn:population":0,
    "gn:timezone":"Europe/Brussels",
    "iso:country":"BE",
    "wof:name":"Middelkerke-Bad",
    "wof:placetype":"locality"
},
  "geometry": {"coordinates":[2.81667,51.18333],"type":"Point"}
}