{
  "type": "Feature",
  "properties": {
    "gn:admin1_code":"VLG",
    "gn:admin2_code":"VAN",
    "gn:admin3_code":"11.0",
    "gn:admin4_code":"11009.0",
    "gn:asciiname":"Beekhoven",
    "gn:country_code":"BE",
    "gn:dem":19,
    "gn:feature_class":"P",
    "gn:feature_code":"PPL",
    "gn:name":"Beekhoven",
    "gn:population":0,
    "gn:timezone":"Europe/Brussels",
    "iso:country":"BE",
    "wof:name":"Beekhoven",
    "wof:placetype":"locality"
},
  "geometry": {"coordinates":[4.61667,51.35],"type":"Point"}
}