{
  "type": "Feature",
  "properties": {
    "gn:admin1_code":"WAL",
    "gn:admin2_code":"WLG",
    "gn:admin3_code":"63.0",
    "gn:admin4_code":"63057.0",
    "gn:asciiname":"La Bouteille",
    "gn:country_code":"BE",
    "gn:dem":274,
    "gn:feature_class":"P",
    "gn:feature_code":"PPL",
    "gn:name":"La Bouteille",
    "gn:population":0,
    "gn:timezone":"Europe/Brussels",
    "iso:country":"BE",
    "name:bug_x_preferred":[
        "La Bouteille"
    ],
    "name:cat_x_preferred":[
        "La Bouteille"
    ],
    "name:ceb_x_preferred":[
        "La Bouteille"
    ],
    "name:deu_x_preferred":[
        "La Bouteille"
    ],
    "name:eus_x_preferred":[
        "La Bouteille"
    ],
    "name:fra_x_preferred":[
        "La Bouteille"
    ],
    "name:hun_x_preferred":[
        "La Bouteille"
    ],
    "name:hye_x_preferred":[
        "\u053c\u0561 \u0532\u0578\u0582\u057f\u0565\u0575"
    ],
    "name:ind_x_preferred":[
        "La Bouteille"
    ],
    "name:ita_x_preferred":[
        "La Bouteille"
    ],
    "name:lat_x_preferred":[
        "La Bouteille"
    ],
    "name:ltz_x_preferred":[
        "La Bouteille"
    ],
    "name:mlg_x_preferred":[
        "La Bouteille"
    ],
    "name:msa_x_preferred":[
        "La Bouteille"
    ],
    "name:nld_x_preferred":[
        "La Bouteille"
    ],
    "name:oci_x_preferred":[
        "La Bouteille"
    ],
    "name:pms_x_preferred":[
        "La Bouteille"
    ],
    "name:pol_x_preferred":[
        "La Bouteille"
    ],
    "name:por_x_preferred":[
        "La Bouteille"
    ],
    "name:ron_x_preferred":[
        "La Bouteille"
    ],
    "name:rus_x_preferred":[
        "\u041b\u0430-\u0411\u0443\u0442\u0435\u0439"
    ],
    "name:slk_x_preferred":[
        "La Bouteille"
    ],
    "name:spa_x_preferred":[
        "La Bouteille"
    ],
    "name:sqi_x_preferred":[
        "La Bouteille"
    ],
    "name:srp_x_preferred":[
        "\u0411\u0443\u0442\u0435\u0458"
    ],
    "name:swe_x_preferred":[
        "La Bouteille"
    ],
    "name:ukr_x_preferred":[
        "\u041b\u0430-\u0411\u0443\u0442\u0435\u0439"
    ],
    "name:urd_x_preferred":[
        "\u0644\u0627 \u0628\u0648\u0679\u06cc\u06cc\u0644\u06cc"
    ],
    "name:uzb_x_preferred":[
        "La Bouteille"
    ],
    "name:vie_x_preferred":[
        "La Bouteille"
    ],
    "name:vol_x_preferred":[
        "La Bouteille"
    ],
    "name:war_x_preferred":[
        "La Bouteille"
    ],
    "name:zea_x_preferred":[
        "La Bouteille"
    ],
    "name:zho_x_preferred":[
        "\u62c9\u5e03\u6cf0\u8036"
    ],
    "wof:name":"La Bouteille",
    "wof:placetype":"locality"
},
  "geometry": {"coordinates":[5.75922,50.59894],"type":"Point"}
}