{
  "type": "Feature",
  "properties": {
    "gn:admin1_code":"WAL",
    "gn:admin2_code":"WLG",
    "gn:admin3_code":"63.0",
    "gn:admin4_code":"63057.0",
    "gn:asciiname":"La Bouteille",
    "gn:country_code":"BE",
    "gn:dem":274,
    "gn:feature_class":"P",
    "gn:feature_code":"PPL",
    "gn:name":"La Bouteille",
    "gn:population":0,
    "gn:timezone":"Europe/Brussels",
    "iso:country":"BE",
    "wof:name":"La Bouteille",
    "wof:placetype":"locality"
},
  "geometry": {"coordinates":[5.75922,50.59894],"type":"Point"}
}