{
  "type": "Feature",
  "properties": {
    "gn:admin1_code":"VLG",
    "gn:admin2_code":"VOV",
    "gn:admin3_code":"44.0",
    "gn:admin4_code":"44020.0",
    "gn:asciiname":"Vier Ekens",
    "gn:country_code":"BE",
    "gn:dem":26,
    "gn:feature_class":"P",
    "gn:feature_code":"PPL",
    "gn:name":"Vier Ekens",
    "gn:population":0,
    "gn:timezone":"Europe/Brussels",
    "iso:country":"BE",
    "name:und_x_variant":[
        "Vier-Eekens",
        "Vier Ekens"
    ],
    "wof:name":"Vier Ekens",
    "wof:placetype":"locality"
},
  "geometry": {"coordinates":[3.66667,50.93333],"type":"Point"}
}