{
  "type": "Feature",
  "properties": {
    "gn:gn_country":"BE",
    "gn:gn_fcode":"PPL",
    "gn:gn_pop":0,
    "iso:country":"BE",
    "name:dut_x_preferred":[
        "Bossuit"
    ],
    "name:eng_x_preferred":[
        "Bossuit"
    ],
    "name:est_x_preferred":[
        "Bossuit"
    ],
    "name:fre_x_preferred":[
        "Bossuit"
    ],
    "name:hun_x_preferred":[
        "Bossuit"
    ],
    "name:por_x_preferred":[
        "Bossuit"
    ],
    "name:unk_x_variant":[
        "Bossuyt"
    ],
    "name:vls_x_preferred":[
        "Bossuut"
    ],
    "qs_pg:aaroncc":"BE",
    "qs_pg:gn_country":"BE",
    "qs_pg:gn_fcode":"PPL",
    "qs_pg:gn_pop":0,
    "qs_pg:name":"Bossuit",
    "qs_pg:name_adm0":"Belgique",
    "qs_pg:name_adm1":"West-Vlaanderen",
    "qs_pg:photos_9k":1,
    "qs_pg:photos_9r":1,
    "qs_pg:photos_all":4,
    "qs_pg:photos_sr":0,
    "qs_pg:pop_sr":0,
    "qs_pg:qs_pg_placetype":"locality",
    "qs_pg:qs_pg_placetype_gp":"Town",
    "qs_pg:woe_adm0":23424757,
    "woe:adm0_id":23424757,
    "woe:name_adm0":"Belgique",
    "woe:name_adm1":"West-Vlaanderen",
    "woe:placetype":"Town",
    "wof:name":"Bossuit",
    "wof:placetype":"locality"
},
  "geometry": {"coordinates":[3.40822,50.74851],"type":"Point"}
}