{
  "type": "Feature",
  "properties": {
    "gn:admin1_code":"VLG",
    "gn:admin2_code":"VOV",
    "gn:admin3_code":"44.0",
    "gn:admin4_code":"44073.0",
    "gn:asciiname":"Pottersbrug",
    "gn:country_code":"BE",
    "gn:dem":5,
    "gn:feature_class":"P",
    "gn:feature_code":"PPL",
    "gn:name":"Pottersbrug",
    "gn:population":0,
    "gn:timezone":"Europe/Brussels",
    "iso:country":"BE",
    "wof:name":"Pottersbrug",
    "wof:placetype":"locality"
},
  "geometry": {"coordinates":[3.85812,51.16806],"type":"Point"}
}