{
  "type": "Feature",
  "properties": {
    "gn:admin1_code":"VLG",
    "gn:admin2_code":"VWV",
    "gn:admin3_code":"37.0",
    "gn:admin4_code":"37017.0",
    "gn:asciiname":"Kruishoek",
    "gn:country_code":"BE",
    "gn:dem":14,
    "gn:feature_class":"P",
    "gn:feature_code":"PPL",
    "gn:name":"Kruishoek",
    "gn:population":0,
    "gn:timezone":"Europe/Brussels",
    "iso:country":"BE",
    "wof:name":"Kruishoek",
    "wof:placetype":"locality"
},
  "geometry": {"coordinates":[3.31785,50.905],"type":"Point"}
}