{
  "type": "Feature",
  "properties": {
    "gn:admin1_code":"WAL",
    "gn:admin2_code":"WHT",
    "gn:admin3_code":"56.0",
    "gn:admin4_code":"56088.0",
    "gn:asciiname":"Rue d'en Haut",
    "gn:country_code":"BE",
    "gn:dem":222,
    "gn:feature_class":"P",
    "gn:feature_code":"PPL",
    "gn:name":"Rue d'en Haut",
    "gn:population":0,
    "gn:timezone":"Europe/Brussels",
    "iso:country":"BE",
    "wof:name":"Rue d'en Haut",
    "wof:placetype":"locality"
},
  "geometry": {"coordinates":[4.18987,50.19481],"type":"Point"}
}