{
  "type": "Feature",
  "properties": {
    "gn:admin1_code":"WAL",
    "gn:admin2_code":"WNA",
    "gn:admin3_code":"92.0",
    "gn:admin4_code":"92142.0",
    "gn:asciiname":"Raidit",
    "gn:country_code":"BE",
    "gn:dem":175,
    "gn:feature_class":"P",
    "gn:feature_code":"PPL",
    "gn:name":"Raidit",
    "gn:population":0,
    "gn:timezone":"Europe/Brussels",
    "iso:country":"BE",
    "wof:name":"Raidit",
    "wof:placetype":"locality"
},
  "geometry": {"coordinates":[4.74704,50.51621],"type":"Point"}
}