{
  "type": "Feature",
  "properties": {
    "gn:admin1_code":"WAL",
    "gn:admin2_code":"WLX",
    "gn:admin3_code":"85.0",
    "gn:admin4_code":"85047.0",
    "gn:asciiname":"Beauregard",
    "gn:country_code":"BE",
    "gn:dem":215,
    "gn:feature_class":"P",
    "gn:feature_code":"PPL",
    "gn:name":"Beauregard",
    "gn:population":0,
    "gn:timezone":"Europe/Brussels",
    "iso:country":"BE",
    "wof:name":"Beauregard",
    "wof:placetype":"locality"
},
  "geometry": {"coordinates":[5.49362,49.56787],"type":"Point"}
}