{
  "type": "Feature",
  "properties": {
    "gn:admin1_code":"WAL",
    "gn:admin2_code":"WLX",
    "gn:admin3_code":"85.0",
    "gn:admin4_code":"85039.0",
    "gn:asciiname":"Pres du Taureau",
    "gn:country_code":"BE",
    "gn:dem":332,
    "gn:feature_class":"P",
    "gn:feature_code":"PPL",
    "gn:name":"Pr\u00e9s du Taureau",
    "gn:population":0,
    "gn:timezone":"Europe/Brussels",
    "iso:country":"BE",
    "wof:name":"Pres du Taureau",
    "wof:placetype":"locality"
},
  "geometry": {"coordinates":[5.51209,49.69989],"type":"Point"}
}