{
  "type": "Feature",
  "properties": {
    "gn:admin1_code":"VLG",
    "gn:admin2_code":"VBR",
    "gn:admin3_code":"23.0",
    "gn:admin4_code":"23032.0",
    "gn:asciiname":"Nattendries",
    "gn:country_code":"BE",
    "gn:dem":41,
    "gn:feature_class":"P",
    "gn:feature_code":"PPL",
    "gn:name":"Nattendries",
    "gn:population":0,
    "gn:timezone":"Europe/Brussels",
    "iso:country":"BE",
    "wof:name":"Nattendries",
    "wof:placetype":"locality"
},
  "geometry": {"coordinates":[4.05,50.71667],"type":"Point"}
}