{
  "type": "Feature",
  "properties": {
    "gn:admin1_code":"VLG",
    "gn:admin2_code":"VOV",
    "gn:admin3_code":"41.0",
    "gn:admin4_code":"41018.0",
    "gn:asciiname":"Keringen",
    "gn:country_code":"BE",
    "gn:dem":29,
    "gn:feature_class":"P",
    "gn:feature_code":"PPL",
    "gn:name":"Keringen",
    "gn:population":0,
    "gn:timezone":"Europe/Brussels",
    "iso:country":"BE",
    "name:und_x_variant":[
        "Keiringen",
        "Keringen"
    ],
    "wof:name":"Keringen",
    "wof:placetype":"locality"
},
  "geometry": {"coordinates":[3.96075,50.78825],"type":"Point"}
}