{
  "type": "Feature",
  "properties": {
    "gn:admin1_code":"WAL",
    "gn:admin2_code":"WLX",
    "gn:admin3_code":"84.0",
    "gn:admin4_code":"84043.0",
    "gn:asciiname":"Tournay",
    "gn:country_code":"BE",
    "gn:dem":412,
    "gn:feature_class":"P",
    "gn:feature_code":"PPL",
    "gn:name":"Tournay",
    "gn:population":0,
    "gn:timezone":"Europe/Brussels",
    "iso:country":"BE",
    "name:cat_x_preferred":[
        "Tournay"
    ],
    "name:ceb_x_preferred":[
        "Tournay"
    ],
    "name:fra_x_preferred":[
        "Tournay"
    ],
    "name:nld_x_preferred":[
        "Tournay"
    ],
    "name:oci_x_preferred":[
        "Tournai"
    ],
    "name:swe_x_preferred":[
        "Tournay"
    ],
    "wof:name":"Tournay",
    "wof:placetype":"locality"
},
  "geometry": {"coordinates":[5.39829,49.85463],"type":"Point"}
}