{
  "type": "Feature",
  "properties": {
    "gn:admin1_code":"WAL",
    "gn:admin2_code":"WHT",
    "gn:admin3_code":"51.0",
    "gn:admin4_code":"51019.0",
    "gn:asciiname":"Lumenne",
    "gn:country_code":"BE",
    "gn:dem":104,
    "gn:feature_class":"P",
    "gn:feature_code":"PPL",
    "gn:name":"Lumenne",
    "gn:population":0,
    "gn:timezone":"Europe/Brussels",
    "iso:country":"BE",
    "wof:name":"Lumenne",
    "wof:placetype":"locality"
},
  "geometry": {"coordinates":[3.72226,50.76356],"type":"Point"}
}