{
  "type": "Feature",
  "properties": {
    "gn:admin1_code":"WAL",
    "gn:admin2_code":"WLG",
    "gn:admin3_code":"61.0",
    "gn:admin4_code":"61079.0",
    "gn:asciiname":"La Rock",
    "gn:country_code":"BE",
    "gn:dem":184,
    "gn:feature_class":"P",
    "gn:feature_code":"PPL",
    "gn:name":"La Rock",
    "gn:population":0,
    "gn:timezone":"Europe/Brussels",
    "iso:country":"BE",
    "wof:name":"La Rock",
    "wof:placetype":"locality"
},
  "geometry": {"coordinates":[5.51477,50.46541],"type":"Point"}
}