{
  "type": "Feature",
  "properties": {
    "gn:admin1_code":"WAL",
    "gn:admin2_code":"WLG",
    "gn:admin3_code":"64.0",
    "gn:admin4_code":"64021.0",
    "gn:asciiname":"Odeur",
    "gn:country_code":"BE",
    "gn:dem":131,
    "gn:feature_class":"P",
    "gn:feature_code":"PPL",
    "gn:name":"Odeur",
    "gn:population":0,
    "gn:timezone":"Europe/Brussels",
    "iso:country":"BE",
    "wof:name":"Odeur",
    "wof:placetype":"locality"
},
  "geometry": {"coordinates":[5.41578,50.70642],"type":"Point"}
}