{
  "type": "Feature",
  "properties": {
    "gn:admin1_code":"VLG",
    "gn:admin2_code":"VBR",
    "gn:admin3_code":"24.0",
    "gn:admin4_code":"24001.0",
    "gn:asciiname":"Schoonhoven",
    "gn:country_code":"BE",
    "gn:dem":24,
    "gn:feature_class":"P",
    "gn:feature_code":"PPL",
    "gn:name":"Schoonhoven",
    "gn:population":0,
    "gn:timezone":"Europe/Brussels",
    "iso:country":"BE",
    "name:ara_x_preferred":[
        "\u0633\u062e\u0648\u0646\u0647\u0648\u0641\u0646"
    ],
    "name:cat_x_preferred":[
        "Schoonhoven"
    ],
    "name:ceb_x_preferred":[
        "Schoonhoven"
    ],
    "name:dan_x_preferred":[
        "Schoonhoven"
    ],
    "name:deu_x_preferred":[
        "Schoonhoven"
    ],
    "name:eus_x_preferred":[
        "Schoonhoven"
    ],
    "name:fas_x_preferred":[
        "\u0627\u0633\u062e\u0648\u0646\u200c\u0647\u0648\u0641\u0646"
    ],
    "name:fra_x_preferred":[
        "Schoonhoven"
    ],
    "name:fry_x_preferred":[
        "Schoonhoven"
    ],
    "name:hye_x_preferred":[
        "\u0547\u056d\u0578\u0576\u0570\u0578\u057e\u0565\u0576"
    ],
    "name:ind_x_preferred":[
        "Schoonhoven"
    ],
    "name:ita_x_preferred":[
        "Schoonhoven"
    ],
    "name:jav_x_preferred":[
        "Schoonhoven"
    ],
    "name:lim_x_preferred":[
        "Schoonhoven"
    ],
    "name:mkd_x_preferred":[
        "\u0421\u0445\u043e\u043d\u0445\u043e\u0432\u0435\u043d"
    ],
    "name:msa_x_preferred":[
        "Schoonhoven"
    ],
    "name:nld_x_preferred":[
        "Schoonhoven"
    ],
    "name:pol_x_preferred":[
        "Schoonhoven"
    ],
    "name:por_x_preferred":[
        "Schoonhoven"
    ],
    "name:ron_x_preferred":[
        "Schoonhoven"
    ],
    "name:rus_x_preferred":[
        "\u0421\u0445\u043e\u043d\u0445\u043e\u0432\u0435\u043d"
    ],
    "name:spa_x_preferred":[
        "Schoonhoven"
    ],
    "name:sqi_x_preferred":[
        "Schoonhoven"
    ],
    "name:stq_x_preferred":[
        "Schoonhoven"
    ],
    "name:swe_x_preferred":[
        "Schoonhoven"
    ],
    "name:tur_x_preferred":[
        "Schoonhoven"
    ],
    "name:vie_x_preferred":[
        "Schoonhoven"
    ],
    "name:vol_x_preferred":[
        "Schoonhoven"
    ],
    "name:war_x_preferred":[
        "Schoonhoven"
    ],
    "name:zho_x_preferred":[
        "\u65af\u6d2a\u970d\u82ac"
    ],
    "wof:name":"Schoonhoven",
    "wof:placetype":"locality"
},
  "geometry": {"coordinates":[4.86249,50.97842],"type":"Point"}
}