{
  "type": "Feature",
  "properties": {
    "gn:admin1_code":"VLG",
    "gn:admin2_code":"VBR",
    "gn:admin3_code":"24.0",
    "gn:admin4_code":"24001.0",
    "gn:asciiname":"Schoonhoven",
    "gn:country_code":"BE",
    "gn:dem":24,
    "gn:feature_class":"P",
    "gn:feature_code":"PPL",
    "gn:name":"Schoonhoven",
    "gn:population":0,
    "gn:timezone":"Europe/Brussels",
    "iso:country":"BE",
    "wof:name":"Schoonhoven",
    "wof:placetype":"locality"
},
  "geometry": {"coordinates":[4.86249,50.97842],"type":"Point"}
}