{
  "type": "Feature",
  "properties": {
    "gn:admin1_code":"WAL",
    "gn:admin2_code":"WHT",
    "gn:admin3_code":"55.0",
    "gn:admin4_code":"55039.0",
    "gn:asciiname":"Marais",
    "gn:country_code":"BE",
    "gn:dem":67,
    "gn:feature_class":"P",
    "gn:feature_code":"PPL",
    "gn:name":"Marais",
    "gn:population":0,
    "gn:timezone":"Europe/Brussels",
    "iso:country":"BE",
    "wof:name":"Marais",
    "wof:placetype":"locality"
},
  "geometry": {"coordinates":[3.9361,50.64186],"type":"Point"}
}