{
  "type": "Feature",
  "properties": {
    "iso:country":"BE",
    "name:nld_x_preferred":[
        "Boesdaalveld"
    ],
    "qs:gn_adm0_cc":"BE",
    "qs:gn_local":2786700,
    "qs:gn_nam_loc":"St-Genesius-Rode, Vlaams-Brabant, BE",
    "qs:gn_namadm1":"VLG",
    "qs:local_max":276,
    "qs:local_sum":276,
    "qs:localhoods":1,
    "qs:name":"Boesdaalveld",
    "qs:name_adm0":"Belgique",
    "qs:name_adm1":"Vlaams Brabant",
    "qs:name_adm2":"Halle-Vilvoorde",
    "qs:name_lau":"St.-Genesius-Rode",
    "qs:name_local":"St.-Genesius-Rode",
    "qs:photo_max":68,
    "qs:photo_sum":276,
    "qs:placetype":"Suburb",
    "qs:quad_count":38,
    "qs:woe_adm0":23424757,
    "qs:woe_adm1":22525998,
    "qs:woe_adm2":12591768,
    "qs:woe_lau":12602682,
    "qs:woe_local":977173,
    "qs:woe_ver":"7.10.0",
    "wof:lang":[
        "dut"
    ],
    "wof:name":"Boesdaalveld",
    "wof:placetype":"neighbourhood"
},
  "geometry": {"coordinates":[4.352078,50.743347],"type":"Point"}
}