{
  "type": "Feature",
  "properties": {
    "gn:admin1_code":"VLG",
    "gn:admin2_code":"VWV",
    "gn:admin3_code":"34.0",
    "gn:admin4_code":"34022.0",
    "gn:asciiname":"Sterhoek",
    "gn:country_code":"BE",
    "gn:dem":36,
    "gn:feature_class":"P",
    "gn:feature_code":"PPL",
    "gn:name":"Sterhoek",
    "gn:population":0,
    "gn:timezone":"Europe/Brussels",
    "iso:country":"BE",
    "wof:name":"Sterhoek",
    "wof:placetype":"locality"
},
  "geometry": {"coordinates":[3.21667,50.76667],"type":"Point"}
}