{
  "type": "Feature",
  "properties": {
    "gn:admin1_code":"VLG",
    "gn:admin2_code":"VLI",
    "gn:admin3_code":"71.0",
    "gn:admin4_code":"71022.0",
    "gn:asciiname":"Melbeek",
    "gn:country_code":"BE",
    "gn:dem":54,
    "gn:feature_class":"P",
    "gn:feature_code":"PPL",
    "gn:name":"Melbeek",
    "gn:population":0,
    "gn:timezone":"Europe/Brussels",
    "iso:country":"BE",
    "wof:name":"Melbeek",
    "wof:placetype":"locality"
},
  "geometry": {"coordinates":[5.36557,50.89439],"type":"Point"}
}