{
  "type": "Feature",
  "properties": {
    "gn:admin1_code":"WAL",
    "gn:admin2_code":"WLX",
    "gn:admin3_code":"85.0",
    "gn:admin4_code":"85009.0",
    "gn:asciiname":"Mortinsart",
    "gn:country_code":"BE",
    "gn:dem":355,
    "gn:feature_class":"P",
    "gn:feature_code":"PPL",
    "gn:name":"Mortinsart",
    "gn:population":0,
    "gn:timezone":"Europe/Brussels",
    "iso:country":"BE",
    "wof:name":"Mortinsart",
    "wof:placetype":"locality"
},
  "geometry": {"coordinates":[5.58701,49.70558],"type":"Point"}
}