{
  "type": "Feature",
  "properties": {
    "gn:admin1_code":"WAL",
    "gn:admin2_code":"WHT",
    "gn:admin3_code":"51.0",
    "gn:admin4_code":"51065.0",
    "gn:asciiname":"Tuquet",
    "gn:country_code":"BE",
    "gn:dem":24,
    "gn:feature_class":"P",
    "gn:feature_code":"PPL",
    "gn:name":"Tuquet",
    "gn:population":0,
    "gn:timezone":"Europe/Brussels",
    "iso:country":"BE",
    "wof:name":"Tuquet",
    "wof:placetype":"locality"
},
  "geometry": {"coordinates":[3.53928,50.72826],"type":"Point"}
}