{
  "type": "Feature",
  "properties": {
    "gn:admin1_code":"VLG",
    "gn:admin2_code":"VBR",
    "gn:admin3_code":"24.0",
    "gn:admin4_code":"24066.0",
    "gn:asciiname":"Helstraat",
    "gn:country_code":"BE",
    "gn:dem":58,
    "gn:feature_class":"P",
    "gn:feature_code":"PPL",
    "gn:name":"Helstraat",
    "gn:population":0,
    "gn:timezone":"Europe/Brussels",
    "iso:country":"BE",
    "name:und_x_variant":[
        "Hel",
        "Helstraat"
    ],
    "wof:name":"Helstraat",
    "wof:placetype":"locality"
},
  "geometry": {"coordinates":[4.89569,50.86768],"type":"Point"}
}