{
  "type": "Feature",
  "properties": {
    "gn:country":"BE",
    "gn:fcode":"PPL",
    "gn:population":4235,
    "iso:country":"BE",
    "name:cat_x_preferred":[
        "Sint-Pieters-Voeren"
    ],
    "name:ceb_x_preferred":[
        "Sint-Pieters-Voeren"
    ],
    "name:deu_x_preferred":[
        "Sint-Pieters-Voeren"
    ],
    "name:eng_x_preferred":[
        "Sint-Pieters-Voeren"
    ],
    "name:fra_x_preferred":[
        "Fouron-Saint-Pierre"
    ],
    "name:fra_x_variant":[
        "Fourons (Fouron-Saint-Pierre)"
    ],
    "name:gle_x_preferred":[
        "Sint-Pieters-Voeren"
    ],
    "name:hun_x_preferred":[
        "Sint-Pieters-Voeren"
    ],
    "name:lim_x_preferred":[
        "S'n Pie\u00ebter"
    ],
    "name:nld_x_preferred":[
        "Sint-Pieters-Voeren"
    ],
    "name:nld_x_variant":[
        "Voeren (Sint-Pieters-Voeren)"
    ],
    "name:swe_x_preferred":[
        "Sint-Pieters-Voeren"
    ],
    "qs_pg:aaroncc":"BE",
    "qs_pg:gn_country":"BE",
    "qs_pg:gn_fcode":"PPL",
    "qs_pg:gn_pop":4235,
    "qs_pg:name":"Sint-Pieters-Voeren",
    "qs_pg:photos_9r":0,
    "qs_pg:photos_sr":0,
    "qs_pg:pop_sr":4,
    "qs_pg:qs_pg_placetype":"locality",
    "wof:name":"Sint-Pieters-Voeren",
    "wof:placetype":"locality",
    "wof:population":4235
},
  "geometry": {"coordinates":[5.82224,50.73863],"type":"Point"}
}