{
  "type": "Feature",
  "properties": {
    "gn:admin1_code":"WAL",
    "gn:admin2_code":"WHT",
    "gn:asciiname":"Zand",
    "gn:country_code":"BE",
    "gn:dem":17,
    "gn:feature_class":"P",
    "gn:feature_code":"PPL",
    "gn:name":"Zand",
    "gn:population":0,
    "gn:timezone":"Europe/Brussels",
    "iso:country":"BE",
    "name:cat_x_preferred":[
        "Zand"
    ],
    "name:ceb_x_preferred":[
        "Zand"
    ],
    "name:deu_x_preferred":[
        "Zand"
    ],
    "name:fra_x_preferred":[
        "Zand"
    ],
    "name:nld_x_preferred":[
        "Zand"
    ],
    "name:spa_x_preferred":[
        "Zand"
    ],
    "name:swe_x_preferred":[
        "Zand"
    ],
    "name:ukr_x_preferred":[
        "\u0417\u0430\u043d\u0434"
    ],
    "wof:name":"Zand",
    "wof:placetype":"locality"
},
  "geometry": {"coordinates":[4.96667,51.01667],"type":"Point"}
}