{
  "type": "Feature",
  "properties": {
    "gn:admin1_code":"VLG",
    "gn:admin2_code":"VAN",
    "gn:admin3_code":"12.0",
    "gn:admin4_code":"12040.0",
    "gn:asciiname":"Klein Willebroek",
    "gn:country_code":"BE",
    "gn:dem":5,
    "gn:feature_class":"P",
    "gn:feature_code":"PPL",
    "gn:name":"Klein Willebroek",
    "gn:population":0,
    "gn:timezone":"Europe/Brussels",
    "iso:country":"BE",
    "name:und_x_variant":[
        "Petit Willebroek",
        "Klein-Willebroeck",
        "Petit-Willebroeck",
        "Klein Willebroek"
    ],
    "wof:name":"Klein Willebroek",
    "wof:placetype":"locality"
},
  "geometry": {"coordinates":[4.36372,51.07988],"type":"Point"}
}