{
  "type": "Feature",
  "properties": {
    "gn:admin1_code":"WAL",
    "gn:admin2_code":"WBR",
    "gn:admin3_code":"25.0",
    "gn:admin4_code":"25005.0",
    "gn:asciiname":"Tilleul du Chene",
    "gn:country_code":"BE",
    "gn:dem":101,
    "gn:feature_class":"P",
    "gn:feature_code":"PPL",
    "gn:name":"Tilleul du Ch\u00eane",
    "gn:population":0,
    "gn:timezone":"Europe/Brussels",
    "iso:country":"BE",
    "wof:name":"Tilleul du Chene",
    "wof:placetype":"locality"
},
  "geometry": {"coordinates":[4.80074,50.77022],"type":"Point"}
}