{
  "type": "Feature",
  "properties": {
    "gn:country":"BE",
    "gn:fcode":"PPL",
    "gn:population":0,
    "iso:country":"BE",
    "name:ceb_x_preferred":[
        "Rijmenam"
    ],
    "name:eng_x_preferred":[
        "Rijmenam"
    ],
    "name:fra_x_preferred":[
        "Rijmenam"
    ],
    "name:hun_x_preferred":[
        "Rijmenam"
    ],
    "name:mkd_x_preferred":[
        "\u0420\u0435\u0458\u043c\u0435\u043d\u0430\u043c"
    ],
    "name:nld_x_preferred":[
        "Rijmenam"
    ],
    "name:swe_x_preferred":[
        "Rijmenam"
    ],
    "name:und_x_variant":[
        "Rymenam"
    ],
    "qs_pg:aaroncc":"BE",
    "qs_pg:gn_country":"BE",
    "qs_pg:gn_fcode":"PPL",
    "qs_pg:gn_pop":0,
    "qs_pg:name":"Rijmenam",
    "qs_pg:name_adm0":"Belgique",
    "qs_pg:name_adm1":"Antwerpen",
    "qs_pg:photos":207,
    "qs_pg:photos_1k":42,
    "qs_pg:photos_9k":1,
    "qs_pg:photos_9r":4,
    "qs_pg:photos_all":207,
    "qs_pg:photos_sr":4,
    "qs_pg:pop_sr":0,
    "qs_pg:qs_pg_placetype":"locality",
    "qs_pg:qs_pg_placetype_gp":"Town",
    "qs_pg:woe_adm0":23424757,
    "woe:adm0_id":23424757,
    "woe:name_adm0":"Belgique",
    "woe:name_adm1":"Antwerpen",
    "woe:placetype":"Town",
    "wof:name":"Rijmenam",
    "wof:placetype":"locality"
},
  "geometry": {"coordinates":[4.58405,51.0016],"type":"Point"}
}