{
  "type": "Feature",
  "properties": {
    "gn:gn_country":"BE",
    "gn:gn_fcode":"PPL",
    "gn:gn_pop":12252,
    "gn:population":12252,
    "iso:country":"BE",
    "name:baq_x_preferred":[
        "Machelen"
    ],
    "name:bar_x_preferred":[
        "Machelen"
    ],
    "name:bre_x_preferred":[
        "Machelen"
    ],
    "name:bul_x_preferred":[
        "\u041c\u0430\u0445\u0435\u043b\u0435\u043d"
    ],
    "name:cat_x_preferred":[
        "Machelen"
    ],
    "name:chi_x_preferred":[
        "\u9a6c\u8d6b\u4f26"
    ],
    "name:dut_x_preferred":[
        "Machelen"
    ],
    "name:eng_x_preferred":[
        "Machelen"
    ],
    "name:epo_x_preferred":[
        "Machelen"
    ],
    "name:fas_x_preferred":[
        "\u0645\u0634\u0648\u0644\u0627\u0646"
    ],
    "name:fre_x_preferred":[
        "Machelen"
    ],
    "name:ger_x_preferred":[
        "Machelen"
    ],
    "name:hun_x_preferred":[
        "Machelen"
    ],
    "name:ita_x_preferred":[
        "Machelen"
    ],
    "name:lit_x_preferred":[
        "Ma\u010delenas"
    ],
    "name:nob_x_preferred":[
        "Machelen"
    ],
    "name:oci_x_preferred":[
        "Machelen"
    ],
    "name:per_x_preferred":[
        "\u0645\u0634\u0648\u0644\u0627\u0646"
    ],
    "name:por_x_preferred":[
        "Machelen"
    ],
    "name:rum_x_preferred":[
        "Machelen"
    ],
    "name:slo_x_preferred":[
        "Machelen"
    ],
    "name:spa_x_preferred":[
        "Machelen"
    ],
    "name:swe_x_preferred":[
        "Machelen"
    ],
    "name:vie_x_preferred":[
        "Machelen"
    ],
    "name:vol_x_preferred":[
        "Machelen"
    ],
    "name:war_x_preferred":[
        "Machelen"
    ],
    "name:zho_x_preferred":[
        "\u9a6c\u8d6b\u4f26"
    ],
    "qs_pg:aaroncc":"BE",
    "qs_pg:gn_country":"BE",
    "qs_pg:gn_fcode":"PPL",
    "qs_pg:gn_pop":12252,
    "qs_pg:name":"Machelen",
    "qs_pg:name_adm0":"Belgique",
    "qs_pg:name_adm1":"Vlaams Brabant",
    "qs_pg:photos_9k":1,
    "qs_pg:photos_9r":1,
    "qs_pg:photos_all":2,
    "qs_pg:photos_sr":0,
    "qs_pg:pop_sr":6,
    "qs_pg:qs_pg_placetype":"locality",
    "qs_pg:qs_pg_placetype_gp":"Town",
    "qs_pg:woe_adm0":23424757,
    "woe:adm0_id":23424757,
    "woe:name_adm0":"Belgique",
    "woe:name_adm1":"Vlaams Brabant",
    "woe:placetype":"Town",
    "wof:name":"Machelen",
    "wof:placetype":"locality",
    "wof:population":12252
},
  "geometry": {"coordinates":[4.44174,50.91061],"type":"Point"}
}