{
  "type": "Feature",
  "properties": {
    "gn:admin1_code":"WAL",
    "gn:admin2_code":"WLG",
    "gn:admin3_code":"62.0",
    "gn:admin4_code":"62099.0",
    "gn:asciiname":"Tignee",
    "gn:country_code":"BE",
    "gn:dem":223,
    "gn:feature_class":"P",
    "gn:feature_code":"PPL",
    "gn:name":"Tign\u00e9e",
    "gn:population":0,
    "gn:timezone":"Europe/Brussels",
    "iso:country":"BE",
    "name:und_x_variant":[
        "Soumagne (Tign\u00e9e)"
    ],
    "wof:name":"Tignee",
    "wof:placetype":"locality"
},
  "geometry": {"coordinates":[5.70268,50.65142],"type":"Point"}
}