{
  "type": "Feature",
  "properties": {
    "gn:admin1_code":"WAL",
    "gn:admin2_code":"WLX",
    "gn:admin3_code":"84.0",
    "gn:admin4_code":"84035.0",
    "gn:asciiname":"Aux Tachenires",
    "gn:country_code":"BE",
    "gn:dem":436,
    "gn:feature_class":"P",
    "gn:feature_code":"PPL",
    "gn:name":"Aux Tachenires",
    "gn:population":0,
    "gn:timezone":"Europe/Brussels",
    "iso:country":"BE",
    "wof:name":"Aux Tachenires",
    "wof:placetype":"locality"
},
  "geometry": {"coordinates":[5.31476,49.97339],"type":"Point"}
}