{
  "type": "Feature",
  "properties": {
    "gn:admin1_code":"WAL",
    "gn:admin2_code":"WNA",
    "gn:admin3_code":"92.0",
    "gn:admin4_code":"92048.0",
    "gn:asciiname":"Gazelle",
    "gn:country_code":"BE",
    "gn:dem":197,
    "gn:feature_class":"P",
    "gn:feature_code":"PPL",
    "gn:name":"Gazelle",
    "gn:population":0,
    "gn:timezone":"Europe/Brussels",
    "iso:country":"BE",
    "wof:name":"Gazelle",
    "wof:placetype":"locality"
},
  "geometry": {"coordinates":[4.61667,50.36667],"type":"Point"}
}