{
  "type": "Feature",
  "properties": {
    "gn:admin1_code":"VLG",
    "gn:admin2_code":"VLI",
    "gn:admin3_code":"71.0",
    "gn:admin4_code":"71069.0",
    "gn:asciiname":"Zwartenhoek",
    "gn:country_code":"BE",
    "gn:dem":24,
    "gn:feature_class":"P",
    "gn:feature_code":"PPL",
    "gn:name":"Zwartenhoek",
    "gn:population":0,
    "gn:timezone":"Europe/Brussels",
    "iso:country":"BE",
    "name:und_x_variant":[
        "Zwarte Hoek",
        "Zwartenhoek"
    ],
    "wof:name":"Zwartenhoek",
    "wof:placetype":"locality"
},
  "geometry": {"coordinates":[5.11949,51.09335],"type":"Point"}
}