{
  "type": "Feature",
  "properties": {
    "gn:admin1_code":"WAL",
    "gn:admin2_code":"WLX",
    "gn:admin3_code":"82.0",
    "gn:admin4_code":"82014.0",
    "gn:asciiname":"Alhoumont",
    "gn:country_code":"BE",
    "gn:dem":445,
    "gn:feature_class":"P",
    "gn:feature_code":"PPL",
    "gn:name":"Alhoumont",
    "gn:population":0,
    "gn:timezone":"Europe/Brussels",
    "iso:country":"BE",
    "wof:name":"Alhoumont",
    "wof:placetype":"locality"
},
  "geometry": {"coordinates":[5.8171,50.11474000000001],"type":"Point"}
}