{
  "type": "Feature",
  "properties": {
    "gn:admin1_code":"WAL",
    "gn:admin2_code":"WLX",
    "gn:admin3_code":"85.0",
    "gn:admin4_code":"85011.0",
    "gn:asciiname":"Sainte-Cecile",
    "gn:country_code":"BE",
    "gn:dem":309,
    "gn:feature_class":"P",
    "gn:feature_code":"PPL",
    "gn:name":"Sainte-C\u00e9cile",
    "gn:population":0,
    "gn:timezone":"Europe/Brussels",
    "iso:country":"BE",
    "name:fas_x_preferred":[
        "\u0633\u0646 \u0633\u0633\u06cc\u0644"
    ],
    "name:fra_x_preferred":[
        "Sainte-C\u00e9cile"
    ],
    "name:nld_x_preferred":[
        "Sainte-C\u00e9cile"
    ],
    "name:urd_x_preferred":[
        "\u0633\u06cc\u0646-\u06a9\u06cc\u0644\u06d2"
    ],
    "wof:name":"Sainte-Cecile",
    "wof:placetype":"locality"
},
  "geometry": {"coordinates":[5.24237,49.72859],"type":"Point"}
}