{
  "type": "Feature",
  "properties": {
    "gn:admin1_code":"VLG",
    "gn:admin2_code":"VWV",
    "gn:asciiname":"Risquons Tout",
    "gn:country_code":"BE",
    "gn:dem":45,
    "gn:feature_class":"P",
    "gn:feature_code":"PPL",
    "gn:name":"Risquons Tout",
    "gn:population":0,
    "gn:timezone":"Europe/Brussels",
    "iso:country":"BE",
    "wof:name":"Risquons Tout",
    "wof:placetype":"locality"
},
  "geometry": {"coordinates":[3.18333,50.75],"type":"Point"}
}