{
  "type": "Feature",
  "properties": {
    "gn:admin1_code":"WAL",
    "gn:admin2_code":"WLX",
    "gn:admin3_code":"82.0",
    "gn:admin4_code":"82009.0",
    "gn:asciiname":"Sainlez",
    "gn:country_code":"BE",
    "gn:dem":493,
    "gn:feature_class":"P",
    "gn:feature_code":"PPL",
    "gn:name":"Sainlez",
    "gn:population":0,
    "gn:timezone":"Europe/Brussels",
    "iso:country":"BE",
    "wof:name":"Sainlez",
    "wof:placetype":"locality"
},
  "geometry": {"coordinates":[5.71207,49.92108],"type":"Point"}
}