{
  "type": "Feature",
  "properties": {
    "gn:country":"BE",
    "gn:fcode":"PPL",
    "gn:population":0,
    "iso:country":"BE",
    "name:eng_x_preferred":[
        "Opheers"
    ],
    "name:fra_x_preferred":[
        "Opheers"
    ],
    "name:gle_x_preferred":[
        "Opheers"
    ],
    "name:hun_x_preferred":[
        "Opheers"
    ],
    "name:nld_x_preferred":[
        "Opheers"
    ],
    "name:und_x_variant":[
        "Heers (Opheers)"
    ],
    "qs_pg:aaroncc":"BE",
    "qs_pg:gn_country":"BE",
    "qs_pg:gn_fcode":"PPL",
    "qs_pg:gn_pop":0,
    "qs_pg:name":"Opheers",
    "qs_pg:name_adm0":"Belgique",
    "qs_pg:name_adm1":"Limburg",
    "qs_pg:photos_9r":0,
    "qs_pg:photos_sr":0,
    "qs_pg:pop_sr":0,
    "qs_pg:qs_pg_placetype":"locality",
    "qs_pg:qs_pg_placetype_gp":"Town",
    "qs_pg:woe_adm0":23424757,
    "woe:adm0_id":23424757,
    "woe:name_adm0":"Belgique",
    "woe:name_adm1":"Limburg",
    "woe:placetype":"Town",
    "wof:name":"Opheers",
    "wof:placetype":"locality"
},
  "geometry": {"coordinates":[5.29807,50.73993],"type":"Point"}
}