{
  "type": "Feature",
  "properties": {
    "gn:admin1_code":"WAL",
    "gn:admin2_code":"WBR",
    "gn:admin3_code":"25.0",
    "gn:admin4_code":"25123.0",
    "gn:asciiname":"Stoquois",
    "gn:country_code":"BE",
    "gn:dem":78,
    "gn:feature_class":"P",
    "gn:feature_code":"PPL",
    "gn:name":"Stoquois",
    "gn:population":0,
    "gn:timezone":"Europe/Brussels",
    "iso:country":"BE",
    "wof:name":"Stoquois",
    "wof:placetype":"locality"
},
  "geometry": {"coordinates":[4.09363,50.66971],"type":"Point"}
}