{
  "type": "Feature",
  "properties": {
    "gn:admin1_code":"VLG",
    "gn:admin2_code":"VBR",
    "gn:admin3_code":"23.0",
    "gn:admin4_code":"23025.0",
    "gn:asciiname":"Beekkant",
    "gn:country_code":"BE",
    "gn:dem":28,
    "gn:feature_class":"P",
    "gn:feature_code":"PPL",
    "gn:name":"Beekkant",
    "gn:population":0,
    "gn:timezone":"Europe/Brussels",
    "iso:country":"BE",
    "wof:name":"Beekkant",
    "wof:placetype":"locality"
},
  "geometry": {"coordinates":[4.36667,50.93333],"type":"Point"}
}