{
  "type": "Feature",
  "properties": {
    "gn:admin1_code":"VLG",
    "gn:admin2_code":"VAN",
    "gn:admin3_code":"12.0",
    "gn:admin4_code":"12014.0",
    "gn:asciiname":"Lichten",
    "gn:country_code":"BE",
    "gn:dem":11,
    "gn:feature_class":"P",
    "gn:feature_code":"PPL",
    "gn:name":"Lichten",
    "gn:population":0,
    "gn:timezone":"Europe/Brussels",
    "iso:country":"BE",
    "wof:name":"Lichten",
    "wof:placetype":"locality"
},
  "geometry": {"coordinates":[4.76667,51.03333],"type":"Point"}
}