{
  "type": "Feature",
  "properties": {
    "gn:admin1_code":"VLG",
    "gn:admin2_code":"VOV",
    "gn:admin3_code":"45.0",
    "gn:admin4_code":"45017.0",
    "gn:asciiname":"Berken",
    "gn:country_code":"BE",
    "gn:dem":35,
    "gn:feature_class":"P",
    "gn:feature_code":"PPL",
    "gn:name":"Berken",
    "gn:population":0,
    "gn:timezone":"Europe/Brussels",
    "iso:country":"BE",
    "name:als_x_preferred":[
        "Berken"
    ],
    "name:ceb_x_preferred":[
        "Berken"
    ],
    "name:deu_x_preferred":[
        "Berken"
    ],
    "name:epo_x_preferred":[
        "Berken"
    ],
    "name:eus_x_preferred":[
        "Berken"
    ],
    "name:fra_x_preferred":[
        "Berken"
    ],
    "name:ita_x_preferred":[
        "Berken"
    ],
    "name:kaz_x_preferred":[
        "\u0411\u0435\u0440\u043a\u0435\u043d"
    ],
    "name:lmo_x_preferred":[
        "Berken"
    ],
    "name:msa_x_preferred":[
        "Berken"
    ],
    "name:nld_x_preferred":[
        "Berken"
    ],
    "name:nno_x_preferred":[
        "Berken"
    ],
    "name:rus_x_preferred":[
        "\u0411\u0435\u0440\u043a\u0435\u043d"
    ],
    "name:spa_x_preferred":[
        "Berken"
    ],
    "name:sqi_x_preferred":[
        "Berken"
    ],
    "name:swe_x_preferred":[
        "Berken"
    ],
    "name:vie_x_preferred":[
        "Berken"
    ],
    "name:vol_x_preferred":[
        "Berken"
    ],
    "name:war_x_preferred":[
        "Berken"
    ],
    "wof:name":"Berken",
    "wof:placetype":"locality"
},
  "geometry": {"coordinates":[3.49661,50.88819],"type":"Point"}
}