{
  "type": "Feature",
  "properties": {
    "gn:admin1_code":"WAL",
    "gn:admin2_code":"WBR",
    "gn:admin3_code":"25.0",
    "gn:admin4_code":"25048.0",
    "gn:asciiname":"Herbais",
    "gn:country_code":"BE",
    "gn:dem":82,
    "gn:feature_class":"P",
    "gn:feature_code":"PPL",
    "gn:name":"Herbais",
    "gn:population":0,
    "gn:timezone":"Europe/Brussels",
    "iso:country":"BE",
    "wof:name":"Herbais",
    "wof:placetype":"locality"
},
  "geometry": {"coordinates":[4.93009,50.71869],"type":"Point"}
}