{
  "type": "Feature",
  "properties": {
    "gn:admin1_code":"WAL",
    "gn:admin2_code":"WLX",
    "gn:admin3_code":"84.0",
    "gn:admin4_code":"84050.0",
    "gn:asciiname":"Le Fond de Chene",
    "gn:country_code":"BE",
    "gn:dem":355,
    "gn:feature_class":"P",
    "gn:feature_code":"PPL",
    "gn:name":"Le Fond de Ch\u00eane",
    "gn:population":0,
    "gn:timezone":"Europe/Brussels",
    "iso:country":"BE",
    "name:und_x_variant":[
        "Fond-de-Ch\u00eane",
        "Le Fond de Ch\u00eane"
    ],
    "wof:name":"Le Fond de Chene",
    "wof:placetype":"locality"
},
  "geometry": {"coordinates":[5.16667,49.98333],"type":"Point"}
}