{
  "type": "Feature",
  "properties": {
    "gn:admin1_code":"VLG",
    "gn:admin2_code":"VOV",
    "gn:admin3_code":"44.0",
    "gn:admin4_code":"44043.0",
    "gn:asciiname":"Terhand",
    "gn:country_code":"BE",
    "gn:dem":7,
    "gn:feature_class":"P",
    "gn:feature_code":"PPL",
    "gn:name":"Terhand",
    "gn:population":0,
    "gn:timezone":"Europe/Brussels",
    "iso:country":"BE",
    "wof:name":"Terhand",
    "wof:placetype":"locality"
},
  "geometry": {"coordinates":[3.75,51.01667],"type":"Point"}
}