{
  "type": "Feature",
  "properties": {
    "gn:gn_country":"BE",
    "gn:gn_fcode":"PPL",
    "gn:gn_pop":0,
    "iso:country":"BE",
    "name:ceb_x_preferred":[
        "Sint-Kruis-Winkel"
    ],
    "name:eng_x_preferred":[
        "Sint-Kruis-Winkel"
    ],
    "name:fra_x_preferred":[
        "Winkel-Sainte-Croix"
    ],
    "name:hun_x_preferred":[
        "Sint-Kruis-Winkel"
    ],
    "name:nld_x_preferred":[
        "Sint-Kruis-Winkel"
    ],
    "name:sco_x_preferred":[
        "Sint-Kruis-Winkel"
    ],
    "name:swe_x_preferred":[
        "Sint-Kruis-Winkel"
    ],
    "name:unk_x_variant":[
        "Winkel-Sainte-Croix"
    ],
    "qs_pg:aaroncc":"BE",
    "qs_pg:gn_country":"BE",
    "qs_pg:gn_fcode":"PPL",
    "qs_pg:gn_pop":0,
    "qs_pg:name":"St.-Kruis-Winkel",
    "qs_pg:name_adm0":"Belgique",
    "qs_pg:name_adm1":"Oost-Vlaanderen",
    "qs_pg:photos_9r":0,
    "qs_pg:photos_sr":0,
    "qs_pg:pop_sr":0,
    "qs_pg:qs_pg_placetype":"locality",
    "qs_pg:qs_pg_placetype_gp":"Town",
    "qs_pg:woe_adm0":23424757,
    "woe:adm0_id":23424757,
    "woe:name_adm0":"Belgique",
    "woe:name_adm1":"Oost-Vlaanderen",
    "woe:placetype":"Town",
    "wof:name":"St.-Kruis-Winkel",
    "wof:placetype":"locality"
},
  "geometry": {"coordinates":[3.81626,51.15578],"type":"Point"}
}