{
  "type": "Feature",
  "properties": {
    "gn:admin1_code":"WAL",
    "gn:admin2_code":"WHT",
    "gn:admin3_code":"55.0",
    "gn:admin4_code":"55039.0",
    "gn:asciiname":"Stoquoi",
    "gn:country_code":"BE",
    "gn:dem":47,
    "gn:feature_class":"P",
    "gn:feature_code":"PPL",
    "gn:name":"Stoquoi",
    "gn:population":0,
    "gn:timezone":"Europe/Brussels",
    "iso:country":"BE",
    "wof:name":"Stoquoi",
    "wof:placetype":"locality"
},
  "geometry": {"coordinates":[3.8914,50.67189000000001],"type":"Point"}
}