{
  "type": "Feature",
  "properties": {
    "gn:admin1_code":"WAL",
    "gn:admin2_code":"WLX",
    "gn:admin3_code":"83.0",
    "gn:admin4_code":"83031.0",
    "gn:asciiname":"Le Herou",
    "gn:country_code":"BE",
    "gn:dem":341,
    "gn:feature_class":"P",
    "gn:feature_code":"PPL",
    "gn:name":"Le H\u00e9rou",
    "gn:population":0,
    "gn:timezone":"Europe/Brussels",
    "iso:country":"BE",
    "name:und_x_variant":[
        "H\u00e9rou",
        "Le H\u00e9rou"
    ],
    "wof:name":"Le Herou",
    "wof:placetype":"locality"
},
  "geometry": {"coordinates":[5.65,50.15],"type":"Point"}
}