{
  "type": "Feature",
  "properties": {
    "gn:admin1_code":"VLG",
    "gn:admin2_code":"VOV",
    "gn:admin3_code":"46.0",
    "gn:admin4_code":"46024.0",
    "gn:asciiname":"Drie Schouwen",
    "gn:country_code":"BE",
    "gn:dem":8,
    "gn:feature_class":"P",
    "gn:feature_code":"PPL",
    "gn:name":"Drie Schouwen",
    "gn:population":0,
    "gn:timezone":"Europe/Brussels",
    "iso:country":"BE",
    "name:und_x_variant":[
        "Drie-Schauwen",
        "Drie Schouwen"
    ],
    "wof:name":"Drie Schouwen",
    "wof:placetype":"locality"
},
  "geometry": {"coordinates":[4.06574,51.22115],"type":"Point"}
}