{
  "type": "Feature",
  "properties": {
    "gn:admin1_code":"VLG",
    "gn:admin2_code":"VOV",
    "gn:admin3_code":"45.0",
    "gn:admin4_code":"45017.0",
    "gn:asciiname":"Baltenshoek",
    "gn:country_code":"BE",
    "gn:dem":25,
    "gn:feature_class":"P",
    "gn:feature_code":"PPL",
    "gn:name":"Baltenshoek",
    "gn:population":0,
    "gn:timezone":"Europe/Brussels",
    "iso:country":"BE",
    "wof:name":"Baltenshoek",
    "wof:placetype":"locality"
},
  "geometry": {"coordinates":[3.56667,50.88333],"type":"Point"}
}