{
  "type": "Feature",
  "properties": {
    "gn:admin1_code":"VLG",
    "gn:admin2_code":"VWV",
    "gn:admin3_code":"33.0",
    "gn:admin4_code":"33011.0",
    "gn:asciiname":"Diksmuidsepoort",
    "gn:country_code":"BE",
    "gn:dem":22,
    "gn:feature_class":"P",
    "gn:feature_code":"PPL",
    "gn:name":"Diksmuidsepoort",
    "gn:population":0,
    "gn:timezone":"Europe/Brussels",
    "iso:country":"BE",
    "wof:name":"Diksmuidsepoort",
    "wof:placetype":"locality"
},
  "geometry": {"coordinates":[2.88333,50.85],"type":"Point"}
}