{
  "type": "Feature",
  "properties": {
    "gn:admin1_code":"WAL",
    "gn:admin2_code":"WHT",
    "gn:admin3_code":"51.0",
    "gn:admin4_code":"51017.0",
    "gn:asciiname":"Wodecq",
    "gn:country_code":"BE",
    "gn:dem":33,
    "gn:feature_class":"P",
    "gn:feature_code":"PPL",
    "gn:name":"Wodecq",
    "gn:population":0,
    "gn:timezone":"Europe/Brussels",
    "iso:country":"BE",
    "wof:name":"Wodecq",
    "wof:placetype":"locality"
},
  "geometry": {"coordinates":[3.74649,50.71805],"type":"Point"}
}