{
  "type": "Feature",
  "properties": {
    "gn:admin1_code":"VLG",
    "gn:admin2_code":"VWV",
    "gn:admin3_code":"36.0",
    "gn:admin4_code":"36007.0",
    "gn:asciiname":"Zandberg",
    "gn:country_code":"BE",
    "gn:dem":15,
    "gn:feature_class":"P",
    "gn:feature_code":"PPL",
    "gn:name":"Zandberg",
    "gn:population":0,
    "gn:timezone":"Europe/Brussels",
    "iso:country":"BE",
    "name:ceb_x_preferred":[
        "Zandberg"
    ],
    "name:deu_x_preferred":[
        "Zandberg"
    ],
    "name:fra_x_preferred":[
        "Zandberg"
    ],
    "name:heb_x_preferred":[
        "\u05d6\u05e0\u05d3\u05d1\u05e8\u05d2"
    ],
    "name:kaz_x_preferred":[
        "\u0417\u0430\u043d\u0434\u0431\u0435\u0440\u0433"
    ],
    "name:kir_x_preferred":[
        "\u0417\u0430\u043d\u0434\u0431\u0435\u0440\u0433"
    ],
    "name:lav_x_preferred":[
        "Zandbergs"
    ],
    "name:lim_x_preferred":[
        "Zandjberg"
    ],
    "name:nds_x_preferred":[
        "Zandberg"
    ],
    "name:nld_x_preferred":[
        "Zandberg"
    ],
    "name:pol_x_preferred":[
        "Zandberg"
    ],
    "name:rus_x_preferred":[
        "\u0417\u0430\u043d\u0434\u0431\u0435\u0440\u0433"
    ],
    "wof:name":"Zandberg",
    "wof:placetype":"locality"
},
  "geometry": {"coordinates":[3.25064,50.93026],"type":"Point"}
}