{
  "type": "Feature",
  "properties": {
    "gn:admin1_code":"WAL",
    "gn:admin2_code":"WNA",
    "gn:admin3_code":"92.0",
    "gn:admin4_code":"92087.0",
    "gn:asciiname":"Rosinbois",
    "gn:country_code":"BE",
    "gn:dem":257,
    "gn:feature_class":"P",
    "gn:feature_code":"PPL",
    "gn:name":"Rosinbois",
    "gn:population":0,
    "gn:timezone":"Europe/Brussels",
    "iso:country":"BE",
    "wof:name":"Rosinbois",
    "wof:placetype":"locality"
},
  "geometry": {"coordinates":[4.61975,50.34979000000001],"type":"Point"}
}