{
  "type": "Feature",
  "properties": {
    "gn:admin1_code":"VLG",
    "gn:admin2_code":"VAN",
    "gn:admin3_code":"13.0",
    "gn:admin4_code":"13011.0",
    "gn:asciiname":"Oorlandseheide",
    "gn:country_code":"BE",
    "gn:dem":10,
    "gn:feature_class":"P",
    "gn:feature_code":"PPL",
    "gn:name":"Oorlandseheide",
    "gn:population":0,
    "gn:timezone":"Europe/Brussels",
    "iso:country":"BE",
    "name:und_x_variant":[
        "Oorlandsheide",
        "Oorlandscheheide",
        "Oorlandseheide"
    ],
    "wof:name":"Oorlandseheide",
    "wof:placetype":"locality"
},
  "geometry": {"coordinates":[4.79838,51.19447],"type":"Point"}
}