{
  "type": "Feature",
  "properties": {
    "gn:admin1_code":"VLG",
    "gn:admin2_code":"VAN",
    "gn:admin3_code":"13.0",
    "gn:admin4_code":"13008.0",
    "gn:asciiname":"Gasthuis Heide",
    "gn:country_code":"BE",
    "gn:dem":20,
    "gn:feature_class":"P",
    "gn:feature_code":"PPL",
    "gn:name":"Gasthuis Heide",
    "gn:population":0,
    "gn:timezone":"Europe/Brussels",
    "iso:country":"BE",
    "wof:name":"Gasthuis Heide",
    "wof:placetype":"locality"
},
  "geometry": {"coordinates":[5.01118,51.1295],"type":"Point"}
}