{
  "type": "Feature",
  "properties": {
    "gn:admin1_code":"WAL",
    "gn:admin2_code":"WLG",
    "gn:admin3_code":"61.0",
    "gn:admin4_code":"61019.0",
    "gn:asciiname":"Fagnoul",
    "gn:country_code":"BE",
    "gn:dem":310,
    "gn:feature_class":"P",
    "gn:feature_code":"PPL",
    "gn:name":"Fagnoul",
    "gn:population":0,
    "gn:timezone":"Europe/Brussels",
    "iso:country":"BE",
    "wof:name":"Fagnoul",
    "wof:placetype":"locality"
},
  "geometry": {"coordinates":[5.62665,50.3941],"type":"Point"}
}