{
  "type": "Feature",
  "properties": {
    "gn:admin1_code":"WAL",
    "gn:admin2_code":"WLX",
    "gn:admin3_code":"83.0",
    "gn:admin4_code":"83044.0",
    "gn:asciiname":"Marcouray",
    "gn:country_code":"BE",
    "gn:dem":303,
    "gn:feature_class":"P",
    "gn:feature_code":"PPL",
    "gn:name":"Marcouray",
    "gn:population":0,
    "gn:timezone":"Europe/Brussels",
    "iso:country":"BE",
    "wof:name":"Marcouray",
    "wof:placetype":"locality"
},
  "geometry": {"coordinates":[5.54764,50.21386],"type":"Point"}
}