{
  "type": "Feature",
  "properties": {
    "gn:admin1_code":"VLG",
    "gn:admin2_code":"VWV",
    "gn:admin3_code":"36.0",
    "gn:admin4_code":"36015.0",
    "gn:asciiname":"Spinnekens",
    "gn:country_code":"BE",
    "gn:dem":21,
    "gn:feature_class":"P",
    "gn:feature_code":"PPL",
    "gn:name":"Spinnekens",
    "gn:population":0,
    "gn:timezone":"Europe/Brussels",
    "iso:country":"BE",
    "wof:name":"Spinnekens",
    "wof:placetype":"locality"
},
  "geometry": {"coordinates":[3.15,50.96667],"type":"Point"}
}