{
  "type": "Feature",
  "properties": {
    "gn:admin1_code":"WAL",
    "gn:admin2_code":"WLX",
    "gn:admin3_code":"84.0",
    "gn:admin4_code":"84075.0",
    "gn:asciiname":"La Croisette",
    "gn:country_code":"BE",
    "gn:dem":246,
    "gn:feature_class":"P",
    "gn:feature_code":"PPL",
    "gn:name":"La Croisette",
    "gn:population":0,
    "gn:timezone":"Europe/Brussels",
    "iso:country":"BE",
    "wof:name":"La Croisette",
    "wof:placetype":"locality"
},
  "geometry": {"coordinates":[5.06667,50.08333],"type":"Point"}
}