{
  "type": "Feature",
  "properties": {
    "gn:admin1_code":"WAL",
    "gn:admin2_code":"WNA",
    "gn:admin3_code":"92.0",
    "gn:admin4_code":"92114.0",
    "gn:asciiname":"Ardenelle",
    "gn:country_code":"BE",
    "gn:dem":154,
    "gn:feature_class":"P",
    "gn:feature_code":"PPL",
    "gn:name":"Ardenelle",
    "gn:population":0,
    "gn:timezone":"Europe/Brussels",
    "iso:country":"BE",
    "wof:name":"Ardenelle",
    "wof:placetype":"locality"
},
  "geometry": {"coordinates":[4.62713,50.56023],"type":"Point"}
}