{
  "type": "Feature",
  "properties": {
    "gn:admin1_code":"WAL",
    "gn:admin2_code":"WHT",
    "gn:asciiname":"La Houlette",
    "gn:country_code":"BE",
    "gn:dem":98,
    "gn:feature_class":"P",
    "gn:feature_code":"PPL",
    "gn:name":"La Houlette",
    "gn:population":0,
    "gn:timezone":"Europe/Brussels",
    "iso:country":"BE",
    "wof:name":"La Houlette",
    "wof:placetype":"locality"
},
  "geometry": {"coordinates":[3.68235,50.31774],"type":"Point"}
}