{
  "type": "Feature",
  "properties": {
    "gn:admin1_code":"WAL",
    "gn:admin2_code":"WNA",
    "gn:admin3_code":"93.0",
    "gn:admin4_code":"93010.0",
    "gn:asciiname":"Pisselotte",
    "gn:country_code":"BE",
    "gn:dem":206,
    "gn:feature_class":"P",
    "gn:feature_code":"PPL",
    "gn:name":"Pisselotte",
    "gn:population":0,
    "gn:timezone":"Europe/Brussels",
    "iso:country":"BE",
    "wof:name":"Pisselotte",
    "wof:placetype":"locality"
},
  "geometry": {"coordinates":[4.41667,50.23333],"type":"Point"}
}