{
  "type": "Feature",
  "properties": {
    "gn:admin1_code":"WAL",
    "gn:admin2_code":"WNA",
    "gn:admin3_code":"92.0",
    "gn:admin4_code":"92087.0",
    "gn:asciiname":"Wagnee",
    "gn:country_code":"BE",
    "gn:dem":212,
    "gn:feature_class":"P",
    "gn:feature_code":"PPL",
    "gn:name":"Wagn\u00e9e",
    "gn:population":0,
    "gn:timezone":"Europe/Brussels",
    "iso:country":"BE",
    "wof:name":"Wagnee",
    "wof:placetype":"locality"
},
  "geometry": {"coordinates":[4.60766,50.31658],"type":"Point"}
}