{
  "type": "Feature",
  "properties": {
    "gn:admin1_code":"VLG",
    "gn:admin2_code":"VLI",
    "gn:admin3_code":"71.0",
    "gn:admin4_code":"71053.0",
    "gn:asciiname":"Schoorbroek",
    "gn:country_code":"BE",
    "gn:dem":64,
    "gn:feature_class":"P",
    "gn:feature_code":"PPL",
    "gn:name":"Schoorbroek",
    "gn:population":0,
    "gn:timezone":"Europe/Brussels",
    "iso:country":"BE",
    "wof:name":"Schoorbroek",
    "wof:placetype":"locality"
},
  "geometry": {"coordinates":[5.12707,50.78567],"type":"Point"}
}