{
  "type": "Feature",
  "properties": {
    "gn:admin1_code":"VLG",
    "gn:admin2_code":"VWV",
    "gn:admin3_code":"34.0",
    "gn:admin4_code":"34002.0",
    "gn:asciiname":"Scheidhoek",
    "gn:country_code":"BE",
    "gn:dem":38,
    "gn:feature_class":"P",
    "gn:feature_code":"PPL",
    "gn:name":"Scheidhoek",
    "gn:population":0,
    "gn:timezone":"Europe/Brussels",
    "iso:country":"BE",
    "wof:name":"Scheidhoek",
    "wof:placetype":"locality"
},
  "geometry": {"coordinates":[3.43412,50.8233],"type":"Point"}
}