{
  "type": "Feature",
  "properties": {
    "gn:admin1_code":"VLG",
    "gn:admin2_code":"VWV",
    "gn:admin3_code":"33.0",
    "gn:admin4_code":"33021.0",
    "gn:asciiname":"Lijssenthoek",
    "gn:country_code":"BE",
    "gn:dem":23,
    "gn:feature_class":"P",
    "gn:feature_code":"PPL",
    "gn:name":"Lijssenthoek",
    "gn:population":0,
    "gn:timezone":"Europe/Brussels",
    "iso:country":"BE",
    "wof:name":"Lijssenthoek",
    "wof:placetype":"locality"
},
  "geometry": {"coordinates":[2.70021,50.83052],"type":"Point"}
}