{
  "type": "Feature",
  "properties": {
    "gn:admin1_code":"WAL",
    "gn:admin2_code":"WNA",
    "gn:admin3_code":"91.0",
    "gn:admin4_code":"91059.0",
    "gn:asciiname":"Champion",
    "gn:country_code":"BE",
    "gn:dem":258,
    "gn:feature_class":"P",
    "gn:feature_code":"PPL",
    "gn:name":"Champion",
    "gn:population":0,
    "gn:timezone":"Europe/Brussels",
    "iso:country":"BE",
    "wof:name":"Champion",
    "wof:placetype":"locality"
},
  "geometry": {"coordinates":[5.11466,50.34908],"type":"Point"}
}