{
  "type": "Feature",
  "properties": {
    "gn:admin1_code":"WAL",
    "gn:admin2_code":"WNA",
    "gn:admin3_code":"91.0",
    "gn:admin4_code":"91059.0",
    "gn:asciiname":"Champion",
    "gn:country_code":"BE",
    "gn:dem":258,
    "gn:feature_class":"P",
    "gn:feature_code":"PPL",
    "gn:name":"Champion",
    "gn:population":0,
    "gn:timezone":"Europe/Brussels",
    "iso:country":"BE",
    "name:aze_x_preferred":[
        "\u00c7empion"
    ],
    "name:bul_x_preferred":[
        "\u0428\u0430\u043c\u043f\u0438\u043e\u043d"
    ],
    "name:che_x_preferred":[
        "\u0427\u0435\u043c\u043f\u0438\u043e\u043d"
    ],
    "name:deu_x_preferred":[
        "Champion"
    ],
    "name:epo_x_preferred":[
        "\u0108ampiono"
    ],
    "name:hye_x_preferred":[
        "\u0549\u0565\u0574\u057a\u056b\u0578\u0576"
    ],
    "name:ido_x_preferred":[
        "Championo"
    ],
    "name:ind_x_preferred":[
        "Juara"
    ],
    "name:kaz_x_preferred":[
        "\u0427\u0435\u043c\u043f\u0438\u043e\u043d"
    ],
    "name:kor_x_preferred":[
        "\ucc54\ud53c\uc5b8"
    ],
    "name:nld_x_preferred":[
        "Kampioen"
    ],
    "name:pol_x_preferred":[
        "Czempion"
    ],
    "name:por_x_preferred":[
        "Campe\u00e3o"
    ],
    "name:ron_x_preferred":[
        "Campion"
    ],
    "name:rus_x_preferred":[
        "\u0427\u0435\u043c\u043f\u0438\u043e\u043d"
    ],
    "name:spa_x_preferred":[
        "Campe\u00f3n"
    ],
    "name:ukr_x_preferred":[
        "\u0427\u0435\u043c\u043f\u0456\u043e\u043d"
    ],
    "name:uzb_x_preferred":[
        "Chempion"
    ],
    "name:xmf_x_preferred":[
        "\u10e9\u10d4\u10db\u10de\u10d8\u10dd\u10dc\u10d8"
    ],
    "wof:name":"Champion",
    "wof:placetype":"locality"
},
  "geometry": {"coordinates":[5.11466,50.34908],"type":"Point"}
}