{
  "type": "Feature",
  "properties": {
    "gn:admin1_code":"WAL",
    "gn:admin2_code":"WHT",
    "gn:admin3_code":"57.0",
    "gn:admin4_code":"57094.0",
    "gn:asciiname":"La Dime",
    "gn:country_code":"BE",
    "gn:dem":53,
    "gn:feature_class":"P",
    "gn:feature_code":"PPL",
    "gn:name":"La D\u00eeme",
    "gn:population":0,
    "gn:timezone":"Europe/Brussels",
    "iso:country":"BE",
    "wof:name":"La Dime",
    "wof:placetype":"locality"
},
  "geometry": {"coordinates":[3.58146,50.58548],"type":"Point"}
}