{
  "type": "Feature",
  "properties": {
    "gn:admin1_code":"VLG",
    "gn:admin2_code":"VOV",
    "gn:admin3_code":"44.0",
    "gn:admin4_code":"44019.0",
    "gn:asciiname":"Linde",
    "gn:country_code":"BE",
    "gn:dem":6,
    "gn:feature_class":"P",
    "gn:feature_code":"PPL",
    "gn:name":"Linde",
    "gn:population":0,
    "gn:timezone":"Europe/Brussels",
    "iso:country":"BE",
    "name:als_x_preferred":[
        "Linde"
    ],
    "name:ceb_x_preferred":[
        "Linde"
    ],
    "name:ces_x_preferred":[
        "Linde"
    ],
    "name:dan_x_preferred":[
        "Linde"
    ],
    "name:deu_x_preferred":[
        "Linde"
    ],
    "name:epo_x_preferred":[
        "Linde"
    ],
    "name:fra_x_preferred":[
        "Linde"
    ],
    "name:ita_x_preferred":[
        "Linde"
    ],
    "name:nld_x_preferred":[
        "Linde"
    ],
    "name:pol_x_preferred":[
        "Linde"
    ],
    "name:rus_x_preferred":[
        "\u041b\u0438\u043d\u0434\u0435"
    ],
    "name:spa_x_preferred":[
        "Linde"
    ],
    "name:swe_x_preferred":[
        "Linde"
    ],
    "name:ukr_x_preferred":[
        "\u041b\u0456\u043d\u0434\u0435"
    ],
    "name:vls_x_preferred":[
        "Linde"
    ],
    "wof:name":"Linde",
    "wof:placetype":"locality"
},
  "geometry": {"coordinates":[3.66065,51.12276],"type":"Point"}
}