{
  "type": "Feature",
  "properties": {
    "gn:admin1_code":"WAL",
    "gn:admin2_code":"WLG",
    "gn:admin3_code":"63.0",
    "gn:admin4_code":"63079.0",
    "gn:asciiname":"Jonckeu",
    "gn:country_code":"BE",
    "gn:dem":336,
    "gn:feature_class":"P",
    "gn:feature_code":"PPL",
    "gn:name":"Jonckeu",
    "gn:population":0,
    "gn:timezone":"Europe/Brussels",
    "iso:country":"BE",
    "wof:name":"Jonckeu",
    "wof:placetype":"locality"
},
  "geometry": {"coordinates":[5.86502,50.56143],"type":"Point"}
}