{
  "type": "Feature",
  "properties": {
    "gn:admin1_code":"WAL",
    "gn:admin2_code":"WNA",
    "gn:admin3_code":"91.0",
    "gn:admin4_code":"91143.0",
    "gn:asciiname":"Sugny",
    "gn:country_code":"BE",
    "gn:dem":357,
    "gn:feature_class":"P",
    "gn:feature_code":"PPL",
    "gn:name":"Sugny",
    "gn:population":0,
    "gn:timezone":"Europe/Brussels",
    "iso:country":"BE",
    "name:und_x_variant":[
        "Vresse-sur-Semois (Sugny)"
    ],
    "wof:name":"Sugny",
    "wof:placetype":"locality"
},
  "geometry": {"coordinates":[4.90222,49.81495],"type":"Point"}
}