{
  "type": "Feature",
  "properties": {
    "gn:admin1_code":"WAL",
    "gn:admin2_code":"WNA",
    "gn:admin3_code":"91.0",
    "gn:admin4_code":"91143.0",
    "gn:asciiname":"Sugny",
    "gn:country_code":"BE",
    "gn:dem":357,
    "gn:feature_class":"P",
    "gn:feature_code":"PPL",
    "gn:name":"Sugny",
    "gn:population":0,
    "gn:timezone":"Europe/Brussels",
    "iso:country":"BE",
    "name:bug_x_preferred":[
        "Sugny"
    ],
    "name:cat_x_preferred":[
        "Sugny"
    ],
    "name:ceb_x_preferred":[
        "Sugny"
    ],
    "name:deu_x_preferred":[
        "Sugny"
    ],
    "name:eus_x_preferred":[
        "Sugny"
    ],
    "name:fra_x_preferred":[
        "Sugny"
    ],
    "name:hun_x_preferred":[
        "Sugny"
    ],
    "name:hye_x_preferred":[
        "\u054d\u0578\u0582\u0576\u056b"
    ],
    "name:ita_x_preferred":[
        "Sugny"
    ],
    "name:lat_x_preferred":[
        "Sugny"
    ],
    "name:ltz_x_preferred":[
        "Sugny"
    ],
    "name:mlg_x_preferred":[
        "Sugny"
    ],
    "name:msa_x_preferred":[
        "Sugny"
    ],
    "name:nld_x_preferred":[
        "Sugny"
    ],
    "name:oci_x_preferred":[
        "Sugny"
    ],
    "name:pms_x_preferred":[
        "Sugny"
    ],
    "name:pol_x_preferred":[
        "Sugny"
    ],
    "name:por_x_preferred":[
        "Sugny"
    ],
    "name:ron_x_preferred":[
        "Sugny"
    ],
    "name:rus_x_preferred":[
        "\u0421\u044e\u043d\u044c\u0438"
    ],
    "name:slk_x_preferred":[
        "Sugny"
    ],
    "name:spa_x_preferred":[
        "Sugny"
    ],
    "name:sqi_x_preferred":[
        "Sugny"
    ],
    "name:swe_x_preferred":[
        "Sugny"
    ],
    "name:ukr_x_preferred":[
        "\u0421\u044e\u043d\u044c\u0457"
    ],
    "name:und_x_variant":[
        "Vresse-sur-Semois (Sugny)"
    ],
    "name:vie_x_preferred":[
        "Sugny"
    ],
    "name:vol_x_preferred":[
        "Sugny"
    ],
    "name:war_x_preferred":[
        "Sugny"
    ],
    "wof:name":"Sugny",
    "wof:placetype":"locality"
},
  "geometry": {"coordinates":[4.90222,49.81495],"type":"Point"}
}