{
  "type": "Feature",
  "properties": {
    "gn:admin1_code":"WAL",
    "gn:admin2_code":"WLX",
    "gn:admin3_code":"83.0",
    "gn:admin4_code":"83031.0",
    "gn:asciiname":"Nablery",
    "gn:country_code":"BE",
    "gn:dem":336,
    "gn:feature_class":"P",
    "gn:feature_code":"PPL",
    "gn:name":"Nablery",
    "gn:population":0,
    "gn:timezone":"Europe/Brussels",
    "iso:country":"BE",
    "wof:name":"Nablery",
    "wof:placetype":"locality"
},
  "geometry": {"coordinates":[5.58333,50.16667],"type":"Point"}
}