{
  "type": "Feature",
  "properties": {
    "gn:admin1_code":"VLG",
    "gn:admin2_code":"VAN",
    "gn:admin3_code":"11.0",
    "gn:admin4_code":"11025.0",
    "gn:asciiname":"Zeven Huizen",
    "gn:country_code":"BE",
    "gn:dem":15,
    "gn:feature_class":"P",
    "gn:feature_code":"PPL",
    "gn:name":"Zeven Huizen",
    "gn:population":0,
    "gn:timezone":"Europe/Brussels",
    "iso:country":"BE",
    "wof:name":"Zeven Huizen",
    "wof:placetype":"locality"
},
  "geometry": {"coordinates":[4.51667,51.13333],"type":"Point"}
}