{
  "type": "Feature",
  "properties": {
    "gn:admin1_code":"WAL",
    "gn:admin2_code":"WLG",
    "gn:admin3_code":"64.0",
    "gn:admin4_code":"64076.0",
    "gn:asciiname":"Niva",
    "gn:country_code":"BE",
    "gn:dem":159,
    "gn:feature_class":"P",
    "gn:feature_code":"PPL",
    "gn:name":"Niva",
    "gn:population":0,
    "gn:timezone":"Europe/Brussels",
    "iso:country":"BE",
    "wof:name":"Niva",
    "wof:placetype":"locality"
},
  "geometry": {"coordinates":[5.20869,50.63276],"type":"Point"}
}