{
  "type": "Feature",
  "properties": {
    "gn:admin1_code":"WAL",
    "gn:admin2_code":"WLX",
    "gn:admin3_code":"82.0",
    "gn:admin4_code":"82003.0",
    "gn:asciiname":"Arloncourt",
    "gn:country_code":"BE",
    "gn:dem":488,
    "gn:feature_class":"P",
    "gn:feature_code":"PPL",
    "gn:name":"Arloncourt",
    "gn:population":0,
    "gn:timezone":"Europe/Brussels",
    "iso:country":"BE",
    "name:und_x_variant":[
        "Ardencourt",
        "Arloncourt"
    ],
    "wof:name":"Arloncourt",
    "wof:placetype":"locality"
},
  "geometry": {"coordinates":[5.8039,50.02777],"type":"Point"}
}