{
  "type": "Feature",
  "properties": {
    "gn:admin1_code":"VLG",
    "gn:admin2_code":"VBR",
    "gn:admin3_code":"23.0",
    "gn:admin4_code":"23023.0",
    "gn:asciiname":"Stevelberg",
    "gn:country_code":"BE",
    "gn:dem":59,
    "gn:feature_class":"P",
    "gn:feature_code":"PPL",
    "gn:name":"Stevelberg",
    "gn:population":0,
    "gn:timezone":"Europe/Brussels",
    "iso:country":"BE",
    "name:und_x_variant":[
        "Steevelberg",
        "Stevelberg"
    ],
    "wof:name":"Stevelberg",
    "wof:placetype":"locality"
},
  "geometry": {"coordinates":[3.98333,50.73333],"type":"Point"}
}