{
  "type": "Feature",
  "properties": {
    "gn:gn_country":"BE",
    "gn:gn_fcode":"PPL",
    "gn:gn_pop":0,
    "iso:country":"BE",
    "name:dut_x_preferred":[
        "Saint-G\u00e9rard"
    ],
    "name:eng_x_preferred":[
        "Saint-G\u00e9rard"
    ],
    "name:fre_x_preferred":[
        "Saint-G\u00e9rard"
    ],
    "name:unk_x_variant":[
        "Saint-G\u00e9rard"
    ],
    "name:wln_x_preferred":[
        "Sint-Djur\u00e5d"
    ],
    "qs_pg:aaroncc":"BE",
    "qs_pg:gn_country":"BE",
    "qs_pg:gn_fcode":"PPL",
    "qs_pg:gn_pop":0,
    "qs_pg:name":"St.-G\u00e9rard",
    "qs_pg:name_adm0":"Belgique",
    "qs_pg:name_adm1":"Namur",
    "qs_pg:photos_9k":1,
    "qs_pg:photos_9r":1,
    "qs_pg:photos_all":2,
    "qs_pg:photos_sr":0,
    "qs_pg:pop_sr":0,
    "qs_pg:qs_pg_placetype":"locality",
    "qs_pg:qs_pg_placetype_gp":"Town",
    "qs_pg:woe_adm0":23424757,
    "woe:adm0_id":23424757,
    "woe:name_adm0":"Belgique",
    "woe:name_adm1":"Namur",
    "woe:placetype":"Town",
    "wof:name":"St.-G\u00e9rard",
    "wof:placetype":"locality"
},
  "geometry": {"coordinates":[4.74098,50.34645],"type":"Point"}
}