{
  "type": "Feature",
  "properties": {
    "gn:admin1_code":"VLG",
    "gn:admin2_code":"VAN",
    "gn:admin3_code":"11.0",
    "gn:admin4_code":"11053.0",
    "gn:asciiname":"De Wolfsheuvel",
    "gn:country_code":"BE",
    "gn:dem":17,
    "gn:feature_class":"P",
    "gn:feature_code":"PPL",
    "gn:name":"De Wolfsheuvel",
    "gn:population":0,
    "gn:timezone":"Europe/Brussels",
    "iso:country":"BE",
    "name:und_x_variant":[
        "Wolfsheuvel",
        "De Wolfsheuvel"
    ],
    "wof:name":"De Wolfsheuvel",
    "wof:placetype":"locality"
},
  "geometry": {"coordinates":[4.53794,51.40852],"type":"Point"}
}