{
  "type": "Feature",
  "properties": {
    "gn:admin1_code":"WAL",
    "gn:admin2_code":"WHT",
    "gn:admin3_code":"56.0",
    "gn:admin4_code":"56078.0",
    "gn:asciiname":"Malcampe",
    "gn:country_code":"BE",
    "gn:dem":183,
    "gn:feature_class":"P",
    "gn:feature_code":"PPL",
    "gn:name":"Malcamp\u00e9",
    "gn:population":0,
    "gn:timezone":"Europe/Brussels",
    "iso:country":"BE",
    "wof:name":"Malcampe",
    "wof:placetype":"locality"
},
  "geometry": {"coordinates":[4.33333,50.31667],"type":"Point"}
}