{
  "type": "Feature",
  "properties": {
    "gn:admin1_code":"VLG",
    "gn:admin2_code":"VOV",
    "gn:admin3_code":"45.0",
    "gn:admin4_code":"45060.0",
    "gn:asciiname":"Okerij",
    "gn:country_code":"BE",
    "gn:dem":98,
    "gn:feature_class":"P",
    "gn:feature_code":"PPL",
    "gn:name":"Okerij",
    "gn:population":0,
    "gn:timezone":"Europe/Brussels",
    "iso:country":"BE",
    "wof:name":"Okerij",
    "wof:placetype":"locality"
},
  "geometry": {"coordinates":[3.58333,50.76667],"type":"Point"}
}