{
  "type": "Feature",
  "properties": {
    "gn:admin1_code":"WAL",
    "gn:admin2_code":"WHT",
    "gn:admin3_code":"51.0",
    "gn:admin4_code":"51004.0",
    "gn:asciiname":"Stocq",
    "gn:country_code":"BE",
    "gn:dem":69,
    "gn:feature_class":"P",
    "gn:feature_code":"PPL",
    "gn:name":"Stocq",
    "gn:population":0,
    "gn:timezone":"Europe/Brussels",
    "iso:country":"BE",
    "wof:name":"Stocq",
    "wof:placetype":"locality"
},
  "geometry": {"coordinates":[3.74411,50.66959],"type":"Point"}
}