{
  "type": "Feature",
  "properties": {
    "iso:country":"BE",
    "name:dut_x_preferred":[
        "Wendelghem"
    ],
    "name:unk_x_variant":[
        "Wendelghem"
    ],
    "qs:gn_adm0_cc":"BE",
    "qs:gn_fcode":"PPL",
    "qs:gn_local":2797656,
    "qs:gn_nam_loc":"Gent, Gent, Gent, Oost-Vlaanderen, BE",
    "qs:gn_namadm1":"VLG",
    "qs:gn_name":"Wondelgem",
    "qs:local_max":6077,
    "qs:local_sum":36126,
    "qs:localhoods":17,
    "qs:name":"Wendelghem",
    "qs:name_adm0":"Belgique",
    "qs:name_adm1":"Oost-Vlaanderen",
    "qs:name_adm2":"Gent",
    "qs:name_lau":"Gent",
    "qs:name_local":"Gent",
    "qs:photo_max":161,
    "qs:photo_sum":546,
    "qs:placetype":"Suburb",
    "qs:quad_count":52,
    "qs:woe_adm0":23424757,
    "qs:woe_adm1":7153304,
    "qs:woe_adm2":12591774,
    "qs:woe_lau":12602289,
    "qs:woe_local":970013,
    "qs:woe_ver":"7.10.0",
    "wof:lang":[
        "dut"
    ],
    "wof:name":"Wendelghem",
    "wof:placetype":"neighbourhood"
},
  "geometry": {"coordinates":[3.725906,51.110773],"type":"Point"}
}