{
  "type": "Feature",
  "properties": {
    "gn:admin1_code":"WAL",
    "gn:admin2_code":"WHT",
    "gn:admin3_code":"51.0",
    "gn:admin4_code":"51065.0",
    "gn:asciiname":"Arc-Ainieres",
    "gn:country_code":"BE",
    "gn:dem":27,
    "gn:feature_class":"P",
    "gn:feature_code":"PPL",
    "gn:name":"Arc-Aini\u00e8res",
    "gn:population":0,
    "gn:timezone":"Europe/Brussels",
    "iso:country":"BE",
    "wof:name":"Arc-Ainieres",
    "wof:placetype":"locality"
},
  "geometry": {"coordinates":[3.55433,50.70151],"type":"Point"}
}