{
  "type": "Feature",
  "properties": {
    "gn:admin1_code":"WAL",
    "gn:admin2_code":"WBR",
    "gn:admin3_code":"25.0",
    "gn:admin4_code":"25119.0",
    "gn:asciiname":"Audrimont",
    "gn:country_code":"BE",
    "gn:dem":98,
    "gn:feature_class":"P",
    "gn:feature_code":"PPL",
    "gn:name":"Audrimont",
    "gn:population":0,
    "gn:timezone":"Europe/Brussels",
    "iso:country":"BE",
    "name:und_x_variant":[
        "Odrimont",
        "Audrimont"
    ],
    "wof:name":"Audrimont",
    "wof:placetype":"locality"
},
  "geometry": {"coordinates":[4.47744,50.69771],"type":"Point"}
}