{
  "type": "Feature",
  "properties": {
    "gn:admin1_code":"WAL",
    "gn:admin2_code":"WHT",
    "gn:admin3_code":"57.0",
    "gn:admin4_code":"57018.0",
    "gn:asciiname":"Delpre",
    "gn:country_code":"BE",
    "gn:dem":26,
    "gn:feature_class":"P",
    "gn:feature_code":"PPL",
    "gn:name":"Delpr\u00e9",
    "gn:population":0,
    "gn:timezone":"Europe/Brussels",
    "iso:country":"BE",
    "wof:name":"Delpre",
    "wof:placetype":"locality"
},
  "geometry": {"coordinates":[3.46667,50.68333],"type":"Point"}
}