{
  "type": "Feature",
  "properties": {
    "gn:admin1_code":"VLG",
    "gn:admin2_code":"VOV",
    "gn:admin3_code":"43.0",
    "gn:admin4_code":"43014.0",
    "gn:asciiname":"Boterhoek",
    "gn:country_code":"BE",
    "gn:dem":3,
    "gn:feature_class":"P",
    "gn:feature_code":"PPL",
    "gn:name":"Boterhoek",
    "gn:population":0,
    "gn:timezone":"Europe/Brussels",
    "iso:country":"BE",
    "wof:name":"Boterhoek",
    "wof:placetype":"locality"
},
  "geometry": {"coordinates":[3.51893,51.21941],"type":"Point"}
}