{
  "type": "Feature",
  "properties": {
    "gn:admin1_code":"VLG",
    "gn:admin2_code":"VOV",
    "gn:admin3_code":"44.0",
    "gn:admin4_code":"44052.0",
    "gn:asciiname":"Leegbracht",
    "gn:country_code":"BE",
    "gn:dem":55,
    "gn:feature_class":"P",
    "gn:feature_code":"PPL",
    "gn:name":"Leegbracht",
    "gn:population":0,
    "gn:timezone":"Europe/Brussels",
    "iso:country":"BE",
    "wof:name":"Leegbracht",
    "wof:placetype":"locality"
},
  "geometry": {"coordinates":[3.81852,50.92131],"type":"Point"}
}