{
  "type": "Feature",
  "properties": {
    "gn:admin1_code":"WAL",
    "gn:admin2_code":"WLX",
    "gn:admin3_code":"81.0",
    "gn:admin4_code":"81001.0",
    "gn:asciiname":"Schoppach",
    "gn:country_code":"BE",
    "gn:dem":379,
    "gn:feature_class":"P",
    "gn:feature_code":"PPL",
    "gn:name":"Schoppach",
    "gn:population":0,
    "gn:timezone":"Europe/Brussels",
    "iso:country":"BE",
    "wof:name":"Schoppach",
    "wof:placetype":"locality"
},
  "geometry": {"coordinates":[5.79125,49.6754],"type":"Point"}
}