{
  "type": "Feature",
  "properties": {
    "gn:admin1_code":"WAL",
    "gn:admin2_code":"WLX",
    "gn:admin3_code":"83.0",
    "gn:admin4_code":"83028.0",
    "gn:asciiname":"Fasol",
    "gn:country_code":"BE",
    "gn:dem":252,
    "gn:feature_class":"P",
    "gn:feature_code":"PPL",
    "gn:name":"Fasol",
    "gn:population":0,
    "gn:timezone":"Europe/Brussels",
    "iso:country":"BE",
    "wof:name":"Fasol",
    "wof:placetype":"locality"
},
  "geometry": {"coordinates":[5.43333,50.25],"type":"Point"}
}