{
  "type": "Feature",
  "properties": {
    "gn:admin1_code":"WAL",
    "gn:admin2_code":"WLG",
    "gn:admin3_code":"63.0",
    "gn:admin4_code":"63089.0",
    "gn:asciiname":"La Baraque",
    "gn:country_code":"BE",
    "gn:dem":332,
    "gn:feature_class":"P",
    "gn:feature_code":"PPL",
    "gn:name":"La Baraque",
    "gn:population":0,
    "gn:timezone":"Europe/Brussels",
    "iso:country":"BE",
    "name:und_x_variant":[
        "Baraque",
        "La Baraque"
    ],
    "wof:name":"La Baraque",
    "wof:placetype":"locality"
},
  "geometry": {"coordinates":[5.88333,50.65],"type":"Point"}
}