{
  "type": "Feature",
  "properties": {
    "gn:admin1_code":"WAL",
    "gn:admin2_code":"WNA",
    "gn:admin3_code":"91.0",
    "gn:admin4_code":"91034.0",
    "gn:asciiname":"Le Buc",
    "gn:country_code":"BE",
    "gn:dem":279,
    "gn:feature_class":"P",
    "gn:feature_code":"PPL",
    "gn:name":"Le Buc",
    "gn:population":0,
    "gn:timezone":"Europe/Brussels",
    "iso:country":"BE",
    "wof:name":"Le Buc",
    "wof:placetype":"locality"
},
  "geometry": {"coordinates":[4.94028,50.28436],"type":"Point"}
}