{
  "type": "Feature",
  "properties": {
    "gn:admin1_code":"WAL",
    "gn:admin2_code":"WHT",
    "gn:admin3_code":"56.0",
    "gn:admin4_code":"56005.0",
    "gn:asciiname":"Cuquegnies",
    "gn:country_code":"BE",
    "gn:dem":236,
    "gn:feature_class":"P",
    "gn:feature_code":"PPL",
    "gn:name":"Cuquegnies",
    "gn:population":0,
    "gn:timezone":"Europe/Brussels",
    "iso:country":"BE",
    "wof:name":"Cuquegnies",
    "wof:placetype":"locality"
},
  "geometry": {"coordinates":[4.26515,50.17794],"type":"Point"}
}