{
  "type": "Feature",
  "properties": {
    "gn:admin1_code":"VLG",
    "gn:admin2_code":"VBR",
    "gn:admin3_code":"24.0",
    "gn:admin4_code":"24054.0",
    "gn:asciiname":"Stuk",
    "gn:country_code":"BE",
    "gn:dem":58,
    "gn:feature_class":"P",
    "gn:feature_code":"PPL",
    "gn:name":"Stuk",
    "gn:population":0,
    "gn:timezone":"Europe/Brussels",
    "iso:country":"BE",
    "name:und_x_variant":[
        "Stuck",
        "Stuk"
    ],
    "wof:name":"Stuk",
    "wof:placetype":"locality"
},
  "geometry": {"coordinates":[5.03333,50.91667],"type":"Point"}
}