{
  "type": "Feature",
  "properties": {
    "gn:admin1_code":"WAL",
    "gn:admin2_code":"WNA",
    "gn:admin3_code":"93.0",
    "gn:admin4_code":"93014.0",
    "gn:asciiname":"Les Riesses",
    "gn:country_code":"BE",
    "gn:dem":367,
    "gn:feature_class":"P",
    "gn:feature_code":"PPL",
    "gn:name":"Les Riesses",
    "gn:population":0,
    "gn:timezone":"Europe/Brussels",
    "iso:country":"BE",
    "name:und_x_variant":[
        "La Riesse",
        "Les Riesses"
    ],
    "wof:name":"Les Riesses",
    "wof:placetype":"locality"
},
  "geometry": {"coordinates":[4.47504,49.96928],"type":"Point"}
}