{
  "type": "Feature",
  "properties": {
    "gn:admin1_code":"WAL",
    "gn:admin2_code":"WLX",
    "gn:admin3_code":"84.0",
    "gn:admin4_code":"84016.0",
    "gn:asciiname":"Chenne Lisse",
    "gn:country_code":"BE",
    "gn:dem":416,
    "gn:feature_class":"P",
    "gn:feature_code":"PPL",
    "gn:name":"Chenne Lisse",
    "gn:population":0,
    "gn:timezone":"Europe/Brussels",
    "iso:country":"BE",
    "name:und_x_variant":[
        "Tch\u00eane-Lisse",
        "Chenne Lisse"
    ],
    "wof:name":"Chenne Lisse",
    "wof:placetype":"locality"
},
  "geometry": {"coordinates":[5.06667,50.01667],"type":"Point"}
}