{
  "type": "Feature",
  "properties": {
    "gn:admin1_code":"VLG",
    "gn:admin2_code":"VLI",
    "gn:admin3_code":"73.0",
    "gn:admin4_code":"73098.0",
    "gn:asciiname":"Beurs",
    "gn:country_code":"BE",
    "gn:dem":55,
    "gn:feature_class":"P",
    "gn:feature_code":"PPL",
    "gn:name":"Beurs",
    "gn:population":0,
    "gn:timezone":"Europe/Brussels",
    "iso:country":"BE",
    "wof:name":"Beurs",
    "wof:placetype":"locality"
},
  "geometry": {"coordinates":[5.27342,50.84954000000001],"type":"Point"}
}