{
  "type": "Feature",
  "properties": {
    "gn:admin1_code":"WAL",
    "gn:admin2_code":"WLG",
    "gn:admin3_code":"63.0",
    "gn:admin4_code":"63004.0",
    "gn:asciiname":"Waronneux",
    "gn:country_code":"BE",
    "gn:dem":483,
    "gn:feature_class":"P",
    "gn:feature_code":"PPL",
    "gn:name":"Waronneux",
    "gn:population":0,
    "gn:timezone":"Europe/Brussels",
    "iso:country":"BE",
    "name:und_x_variant":[
        "Waronneux Inf\u00e9rieur",
        "War\u00f4neu",
        "Waronneux"
    ],
    "wof:name":"Waronneux",
    "wof:placetype":"locality"
},
  "geometry": {"coordinates":[6.04379,50.55987],"type":"Point"}
}