{
  "type": "Feature",
  "properties": {
    "gn:country":"BE",
    "gn:fcode":"PPL",
    "gn:population":0,
    "iso:country":"BE",
    "name:cat_x_preferred":[
        "Desni\u00e9"
    ],
    "name:deu_x_preferred":[
        "Desni\u00e9"
    ],
    "name:eng_x_preferred":[
        "Desni\u00e9"
    ],
    "name:fra_x_preferred":[
        "Desni\u00e9"
    ],
    "name:ltz_x_preferred":[
        "Desni\u00e9"
    ],
    "name:nld_x_preferred":[
        "Desni\u00e9"
    ],
    "qs_pg:aaroncc":"BE",
    "qs_pg:gn_country":"BE",
    "qs_pg:gn_fcode":"PPL",
    "qs_pg:gn_pop":0,
    "qs_pg:name":"Desni\u00e9",
    "qs_pg:name_adm0":"Belgique",
    "qs_pg:name_adm1":"Li\u00e8ge",
    "qs_pg:photos":17,
    "qs_pg:photos_1k":3,
    "qs_pg:photos_9k":1,
    "qs_pg:photos_9r":1,
    "qs_pg:photos_all":17,
    "qs_pg:photos_sr":1,
    "qs_pg:pop_sr":0,
    "qs_pg:qs_pg_placetype":"locality",
    "qs_pg:qs_pg_placetype_gp":"Town",
    "qs_pg:woe_adm0":23424757,
    "woe:adm0_id":23424757,
    "woe:name_adm0":"Belgique",
    "woe:name_adm1":"Li\u00e8ge",
    "woe:placetype":"Town",
    "wof:name":"Desni\u00e9",
    "wof:placetype":"locality"
},
  "geometry": {"coordinates":[5.81373,50.4628],"type":"Point"}
}