{
  "type": "Feature",
  "properties": {
    "gn:admin1_code":"WAL",
    "gn:admin2_code":"WLG",
    "gn:admin3_code":"63.0",
    "gn:admin4_code":"63045.0",
    "gn:asciiname":"Reharmont",
    "gn:country_code":"BE",
    "gn:dem":411,
    "gn:feature_class":"P",
    "gn:feature_code":"PPL",
    "gn:name":"Reharmont",
    "gn:population":0,
    "gn:timezone":"Europe/Brussels",
    "iso:country":"BE",
    "wof:name":"Reharmont",
    "wof:placetype":"locality"
},
  "geometry": {"coordinates":[5.822,50.34019],"type":"Point"}
}