{
  "type": "Feature",
  "properties": {
    "gn:admin1_code":"WAL",
    "gn:admin2_code":"WLX",
    "gn:admin3_code":"83.0",
    "gn:admin4_code":"83040.0",
    "gn:asciiname":"La Fange Botte",
    "gn:country_code":"BE",
    "gn:dem":331,
    "gn:feature_class":"P",
    "gn:feature_code":"PPL",
    "gn:name":"La Fange Bott\u00e9",
    "gn:population":0,
    "gn:timezone":"Europe/Brussels",
    "iso:country":"BE",
    "name:und_x_variant":[
        "A-la-Fange-Bott\u00e9",
        "La Fange Bott\u00e9"
    ],
    "wof:name":"La Fange Botte",
    "wof:placetype":"locality"
},
  "geometry": {"coordinates":[5.41972,50.16746],"type":"Point"}
}