{
  "type": "Feature",
  "properties": {
    "gn:admin1_code":"WAL",
    "gn:admin2_code":"WHT",
    "gn:admin3_code":"56.0",
    "gn:admin4_code":"56087.0",
    "gn:asciiname":"La Gade",
    "gn:country_code":"BE",
    "gn:dem":159,
    "gn:feature_class":"P",
    "gn:feature_code":"PPL",
    "gn:name":"La Gade",
    "gn:population":0,
    "gn:timezone":"Europe/Brussels",
    "iso:country":"BE",
    "name:und_x_variant":[
        "Gade",
        "La Gade"
    ],
    "wof:name":"La Gade",
    "wof:placetype":"locality"
},
  "geometry": {"coordinates":[4.23333,50.43333],"type":"Point"}
}