{
  "type": "Feature",
  "properties": {
    "gn:admin1_code":"VLG",
    "gn:admin2_code":"VWV",
    "gn:admin3_code":"31.0",
    "gn:admin4_code":"31040.0",
    "gn:asciiname":"Heidelberg",
    "gn:country_code":"BE",
    "gn:dem":8,
    "gn:feature_class":"P",
    "gn:feature_code":"PPL",
    "gn:name":"Heidelberg",
    "gn:population":0,
    "gn:timezone":"Europe/Brussels",
    "iso:country":"BE",
    "name:und_x_variant":[
        "Heydelberg",
        "Heidelberg"
    ],
    "wof:name":"Heidelberg",
    "wof:placetype":"locality"
},
  "geometry": {"coordinates":[3.16461,51.1488],"type":"Point"}
}