{
  "type": "Feature",
  "properties": {
    "gn:admin1_code":"WAL",
    "gn:admin2_code":"WLX",
    "gn:admin3_code":"84.0",
    "gn:admin4_code":"84059.0",
    "gn:asciiname":"Loie",
    "gn:country_code":"BE",
    "gn:dem":517,
    "gn:feature_class":"P",
    "gn:feature_code":"PPL",
    "gn:name":"Lo\u00efe",
    "gn:population":0,
    "gn:timezone":"Europe/Brussels",
    "iso:country":"BE",
    "name:und_x_variant":[
        "L\u2019A\u00f4ye",
        "Lo\u00efe"
    ],
    "wof:name":"Loie",
    "wof:placetype":"locality"
},
  "geometry": {"coordinates":[5.41667,50.01667],"type":"Point"}
}