{
  "type": "Feature",
  "properties": {
    "gn:admin1_code":"WAL",
    "gn:admin2_code":"WBR",
    "gn:admin3_code":"25.0",
    "gn:admin4_code":"25105.0",
    "gn:asciiname":"Niderand",
    "gn:country_code":"BE",
    "gn:dem":53,
    "gn:feature_class":"P",
    "gn:feature_code":"PPL",
    "gn:name":"Nid\u00e9rand",
    "gn:population":0,
    "gn:timezone":"Europe/Brussels",
    "iso:country":"BE",
    "name:und_x_variant":[
        "Nid\u00e9rant",
        "Niderhand",
        "Nederand",
        "Nid\u00e9rand"
    ],
    "wof:name":"Niderand",
    "wof:placetype":"locality"
},
  "geometry": {"coordinates":[4.23574,50.67944],"type":"Point"}
}