{
  "type": "Feature",
  "properties": {
    "gn:admin1_code":"WAL",
    "gn:admin2_code":"WHT",
    "gn:admin3_code":"52.0",
    "gn:admin4_code":"52021.0",
    "gn:asciiname":"Longpre",
    "gn:country_code":"BE",
    "gn:dem":144,
    "gn:feature_class":"P",
    "gn:feature_code":"PPL",
    "gn:name":"Longpr\u00e9",
    "gn:population":0,
    "gn:timezone":"Europe/Brussels",
    "iso:country":"BE",
    "wof:name":"Longpre",
    "wof:placetype":"locality"
},
  "geometry": {"coordinates":[4.54276,50.51315],"type":"Point"}
}