{
  "type": "Feature",
  "properties": {
    "gn:admin1_code":"VLG",
    "gn:admin2_code":"VAN",
    "gn:admin3_code":"13.0",
    "gn:admin4_code":"13040.0",
    "gn:asciiname":"Kemerke",
    "gn:country_code":"BE",
    "gn:dem":28,
    "gn:feature_class":"P",
    "gn:feature_code":"PPL",
    "gn:name":"Kemerke",
    "gn:population":0,
    "gn:timezone":"Europe/Brussels",
    "iso:country":"BE",
    "wof:name":"Kemerke",
    "wof:placetype":"locality"
},
  "geometry": {"coordinates":[4.96667,51.36667],"type":"Point"}
}