{
  "type": "Feature",
  "properties": {
    "gn:gn_country":"BE",
    "gn:gn_fcode":"PPL",
    "gn:gn_pop":0,
    "iso:country":"BE",
    "name:cat_x_preferred":[
        "M\u00e9nil"
    ],
    "name:ceb_x_preferred":[
        "M\u00e9nil"
    ],
    "name:deu_x_preferred":[
        "M\u00e9nil"
    ],
    "name:eus_x_preferred":[
        "M\u00e9nil"
    ],
    "name:fra_x_preferred":[
        "M\u00e9nil"
    ],
    "name:hun_x_preferred":[
        "M\u00e9nil"
    ],
    "name:ita_x_preferred":[
        "M\u00e9nil"
    ],
    "name:lat_x_preferred":[
        "M\u00e9nil"
    ],
    "name:msa_x_preferred":[
        "M\u00e9nil"
    ],
    "name:nld_x_preferred":[
        "M\u00e9nil"
    ],
    "name:oci_x_preferred":[
        "M\u00e9nil"
    ],
    "name:pms_x_preferred":[
        "M\u00e9nil"
    ],
    "name:pol_x_preferred":[
        "M\u00e9nil"
    ],
    "name:por_x_preferred":[
        "M\u00e9nil"
    ],
    "name:ron_x_preferred":[
        "M\u00e9nil"
    ],
    "name:slk_x_preferred":[
        "M\u00e9nil"
    ],
    "name:spa_x_preferred":[
        "M\u00e9nil"
    ],
    "name:swe_x_preferred":[
        "M\u00e9nil"
    ],
    "name:ukr_x_preferred":[
        "\u041c\u0435\u043d\u0456\u0439"
    ],
    "name:vie_x_preferred":[
        "M\u00e9nil"
    ],
    "name:vol_x_preferred":[
        "M\u00e9nil"
    ],
    "name:war_x_preferred":[
        "M\u00e9nil"
    ],
    "name:zho_x_preferred":[
        "\u6885\u5c3c\u52d2"
    ],
    "qs_pg:aaroncc":"BE",
    "qs_pg:gn_country":"BE",
    "qs_pg:gn_fcode":"PPL",
    "qs_pg:gn_pop":0,
    "qs_pg:name":"M\u00e9nil",
    "qs_pg:name_adm0":"Belgique",
    "qs_pg:name_adm1":"Luxembourg",
    "qs_pg:photos":4,
    "qs_pg:photos_1k":1,
    "qs_pg:photos_9k":1,
    "qs_pg:photos_9r":1,
    "qs_pg:photos_all":4,
    "qs_pg:photos_sr":1,
    "qs_pg:pop_sr":0,
    "qs_pg:qs_pg_placetype":"locality",
    "qs_pg:qs_pg_placetype_gp":"Town",
    "qs_pg:woe_adm0":23424757,
    "woe:adm0_id":23424757,
    "woe:name_adm0":"Belgique",
    "woe:name_adm1":"Luxembourg",
    "woe:placetype":"Town",
    "wof:name":"M\u00e9nil",
    "wof:placetype":"locality"
},
  "geometry": {"coordinates":[5.28014,49.71493],"type":"Point"}
}