{
  "type": "Feature",
  "properties": {
    "gn:admin1_code":"VLG",
    "gn:admin2_code":"VOV",
    "gn:admin3_code":"44.0",
    "gn:admin4_code":"44049.0",
    "gn:asciiname":"Hamme",
    "gn:country_code":"BE",
    "gn:dem":7,
    "gn:feature_class":"P",
    "gn:feature_code":"PPL",
    "gn:name":"Hamme",
    "gn:population":0,
    "gn:timezone":"Europe/Brussels",
    "iso:country":"BE",
    "name:afr_x_preferred":[
        "Hamme"
    ],
    "name:bre_x_preferred":[
        "Hamme"
    ],
    "name:bul_x_preferred":[
        "\u0425\u0430\u043c\u0435"
    ],
    "name:cat_x_preferred":[
        "Hamme"
    ],
    "name:ceb_x_preferred":[
        "Hamme"
    ],
    "name:deu_x_preferred":[
        "Hamme"
    ],
    "name:epo_x_preferred":[
        "Hamme"
    ],
    "name:est_x_preferred":[
        "Hamme"
    ],
    "name:eus_x_preferred":[
        "Hamme"
    ],
    "name:fas_x_preferred":[
        "\u0627\u0645"
    ],
    "name:fra_x_preferred":[
        "Hamme"
    ],
    "name:hun_x_preferred":[
        "Hamme"
    ],
    "name:ita_x_preferred":[
        "Hamme"
    ],
    "name:lit_x_preferred":[
        "Ham\u0117"
    ],
    "name:nld_x_preferred":[
        "Hamme"
    ],
    "name:nor_x_preferred":[
        "Hamme"
    ],
    "name:oci_x_preferred":[
        "Hamme"
    ],
    "name:pol_x_preferred":[
        "Hamme"
    ],
    "name:por_x_preferred":[
        "Hamme"
    ],
    "name:ron_x_preferred":[
        "Hamme"
    ],
    "name:sco_x_preferred":[
        "Hamme"
    ],
    "name:slk_x_preferred":[
        "Hamme"
    ],
    "name:spa_x_preferred":[
        "Hamme"
    ],
    "name:sqi_x_preferred":[
        "Ama"
    ],
    "name:swe_x_preferred":[
        "Hamme"
    ],
    "name:tur_x_preferred":[
        "Hamme"
    ],
    "name:vie_x_preferred":[
        "Hamme"
    ],
    "name:vol_x_preferred":[
        "Hamme"
    ],
    "name:war_x_preferred":[
        "Hamme"
    ],
    "wof:name":"Hamme",
    "wof:placetype":"locality"
},
  "geometry": {"coordinates":[3.5362,51.08858],"type":"Point"}
}