{
  "type": "Feature",
  "properties": {
    "gn:admin1_code":"WAL",
    "gn:admin2_code":"WHT",
    "gn:admin3_code":"56.0",
    "gn:admin4_code":"56051.0",
    "gn:asciiname":"Bout d'En Haut",
    "gn:country_code":"BE",
    "gn:dem":300,
    "gn:feature_class":"P",
    "gn:feature_code":"PPL",
    "gn:name":"Bout d'En Haut",
    "gn:population":0,
    "gn:timezone":"Europe/Brussels",
    "iso:country":"BE",
    "wof:name":"Bout d'En Haut",
    "wof:placetype":"locality"
},
  "geometry": {"coordinates":[4.24842,50.00584],"type":"Point"}
}