{
  "type": "Feature",
  "properties": {
    "gn:admin1_code":"WAL",
    "gn:admin2_code":"WBR",
    "gn:admin3_code":"25.0",
    "gn:admin4_code":"25084.0",
    "gn:asciiname":"Thorembais-les-Beguines",
    "gn:country_code":"BE",
    "gn:dem":128,
    "gn:feature_class":"P",
    "gn:feature_code":"PPL",
    "gn:name":"Thorembais-les-B\u00e9guines",
    "gn:population":0,
    "gn:timezone":"Europe/Brussels",
    "iso:country":"BE",
    "name:und_x_variant":[
        "Perwez (Thorembais-les-B\u00e9guines)"
    ],
    "wof:name":"Thorembais-les-Beguines",
    "wof:placetype":"locality"
},
  "geometry": {"coordinates":[4.81755,50.65819000000001],"type":"Point"}
}