{
  "type": "Feature",
  "properties": {
    "gn:admin1_code":"WAL",
    "gn:admin2_code":"WHT",
    "gn:admin3_code":"51.0",
    "gn:admin4_code":"51012.0",
    "gn:asciiname":"Sarrazin",
    "gn:country_code":"BE",
    "gn:dem":60,
    "gn:feature_class":"P",
    "gn:feature_code":"PPL",
    "gn:name":"Sarrazin",
    "gn:population":0,
    "gn:timezone":"Europe/Brussels",
    "iso:country":"BE",
    "name:deu_x_preferred":[
        "Sarrazin"
    ],
    "name:fra_x_preferred":[
        "Sarrazin"
    ],
    "name:nld_x_preferred":[
        "Sarrazin"
    ],
    "name:rus_x_preferred":[
        "\u0421\u0430\u0440\u0440\u0430\u0446\u0438\u043d"
    ],
    "wof:name":"Sarrazin",
    "wof:placetype":"locality"
},
  "geometry": {"coordinates":[3.88333,50.61667],"type":"Point"}
}