{
  "type": "Feature",
  "properties": {
    "gn:admin1_code":"WAL",
    "gn:admin2_code":"WBR",
    "gn:admin3_code":"25.0",
    "gn:admin4_code":"25105.0",
    "gn:asciiname":"Stehoux",
    "gn:country_code":"BE",
    "gn:dem":96,
    "gn:feature_class":"P",
    "gn:feature_code":"PPL",
    "gn:name":"St\u00e9houx",
    "gn:population":0,
    "gn:timezone":"Europe/Brussels",
    "iso:country":"BE",
    "wof:name":"Stehoux",
    "wof:placetype":"locality"
},
  "geometry": {"coordinates":[4.20648,50.67375],"type":"Point"}
}