{
  "type": "Feature",
  "properties": {
    "gn:country":"BE",
    "gn:fcode":"PPL",
    "gn:population":0,
    "iso:country":"BE",
    "name:cat_x_preferred":[
        "Weyler"
    ],
    "name:eng_x_preferred":[
        "Weyler"
    ],
    "name:est_x_preferred":[
        "Weyler"
    ],
    "name:fra_x_preferred":[
        "Weyler"
    ],
    "name:ltz_x_preferred":[
        "Weyler"
    ],
    "name:ltz_x_variant":[
        "Weller"
    ],
    "name:nld_x_preferred":[
        "Weyler"
    ],
    "name:wln_x_preferred":[
        "Weyler"
    ],
    "name:zho_x_preferred":[
        "\u97e6\u83b1\u5c14"
    ],
    "qs_pg:aaroncc":"BE",
    "qs_pg:gn_country":"BE",
    "qs_pg:gn_fcode":"PPL",
    "qs_pg:gn_pop":0,
    "qs_pg:name":"Weyler",
    "qs_pg:name_adm0":"Belgique",
    "qs_pg:name_adm1":"Luxembourg",
    "qs_pg:photos_9k":1,
    "qs_pg:photos_9r":1,
    "qs_pg:photos_all":4,
    "qs_pg:photos_sr":0,
    "qs_pg:pop_sr":0,
    "qs_pg:qs_pg_placetype":"locality",
    "qs_pg:qs_pg_placetype_gp":"Town",
    "qs_pg:woe_adm0":23424757,
    "woe:adm0_id":23424757,
    "woe:name_adm0":"Belgique",
    "woe:name_adm1":"Luxembourg",
    "woe:placetype":"Town",
    "wof:name":"Weyler",
    "wof:placetype":"locality"
},
  "geometry": {"coordinates":[5.82384,49.65681],"type":"Point"}
}