{
  "type": "Feature",
  "properties": {
    "gn:admin1_code":"VLG",
    "gn:admin2_code":"VOV",
    "gn:admin3_code":"44.0",
    "gn:admin4_code":"44073.0",
    "gn:asciiname":"Penen",
    "gn:country_code":"BE",
    "gn:dem":9,
    "gn:feature_class":"P",
    "gn:feature_code":"PPL",
    "gn:name":"Penen",
    "gn:population":0,
    "gn:timezone":"Europe/Brussels",
    "iso:country":"BE",
    "name:und_x_variant":[
        "Peenen",
        "Penen"
    ],
    "wof:name":"Penen",
    "wof:placetype":"locality"
},
  "geometry": {"coordinates":[3.89471,51.17624],"type":"Point"}
}