{
  "type": "Feature",
  "properties": {
    "gn:admin1_code":"WAL",
    "gn:admin2_code":"WLX",
    "gn:admin3_code":"82.0",
    "gn:admin4_code":"82037.0",
    "gn:asciiname":"Rettigny",
    "gn:country_code":"BE",
    "gn:dem":394,
    "gn:feature_class":"P",
    "gn:feature_code":"PPL",
    "gn:name":"Rettigny",
    "gn:population":0,
    "gn:timezone":"Europe/Brussels",
    "iso:country":"BE",
    "wof:name":"Rettigny",
    "wof:placetype":"locality"
},
  "geometry": {"coordinates":[5.88017,50.16744],"type":"Point"}
}