{
  "type": "Feature",
  "properties": {
    "gn:admin1_code":"WAL",
    "gn:admin2_code":"WNA",
    "gn:admin3_code":"91.0",
    "gn:admin4_code":"91059.0",
    "gn:asciiname":"Grande Frume",
    "gn:country_code":"BE",
    "gn:dem":264,
    "gn:feature_class":"P",
    "gn:feature_code":"PPL",
    "gn:name":"Grande Frume",
    "gn:population":0,
    "gn:timezone":"Europe/Brussels",
    "iso:country":"BE",
    "wof:name":"Grande Frume",
    "wof:placetype":"locality"
},
  "geometry": {"coordinates":[5.13333,50.31667],"type":"Point"}
}