{
  "type": "Feature",
  "properties": {
    "gn:admin1_code":"WAL",
    "gn:admin2_code":"WLG",
    "gn:admin3_code":"62.0",
    "gn:admin4_code":"62119.0",
    "gn:asciiname":"Rabosee",
    "gn:country_code":"BE",
    "gn:dem":170,
    "gn:feature_class":"P",
    "gn:feature_code":"PPL",
    "gn:name":"Rabos\u00e9e",
    "gn:population":0,
    "gn:timezone":"Europe/Brussels",
    "iso:country":"BE",
    "name:und_x_variant":[
        "Raboz\u00e9e",
        "Rabez\u00e9e",
        "Rabos\u00e9e"
    ],
    "wof:name":"Rabosee",
    "wof:placetype":"locality"
},
  "geometry": {"coordinates":[5.67416,50.66871],"type":"Point"}
}