{
  "type": "Feature",
  "properties": {
    "gn:admin1_code":"VLG",
    "gn:admin2_code":"VBR",
    "gn:admin3_code":"24.0",
    "gn:admin4_code":"24059.0",
    "gn:asciiname":"Eliksem",
    "gn:country_code":"BE",
    "gn:dem":48,
    "gn:feature_class":"P",
    "gn:feature_code":"PPL",
    "gn:name":"Eliksem",
    "gn:population":0,
    "gn:timezone":"Europe/Brussels",
    "iso:country":"BE",
    "name:fra_x_preferred":[
        "Eliksem"
    ],
    "name:nld_x_preferred":[
        "Eliksem"
    ],
    "name:und_x_variant":[
        "Elixem"
    ],
    "wof:name":"Eliksem",
    "wof:placetype":"locality"
},
  "geometry": {"coordinates":[5.01044,50.78408],"type":"Point"}
}