{
  "type": "Feature",
  "properties": {
    "gn:admin1_code":"WAL",
    "gn:admin2_code":"WHT",
    "gn:admin3_code":"51.0",
    "gn:admin4_code":"51065.0",
    "gn:asciiname":"Bas Forest",
    "gn:country_code":"BE",
    "gn:dem":37,
    "gn:feature_class":"P",
    "gn:feature_code":"PPL",
    "gn:name":"Bas Forest",
    "gn:population":0,
    "gn:timezone":"Europe/Brussels",
    "iso:country":"BE",
    "wof:name":"Bas Forest",
    "wof:placetype":"locality"
},
  "geometry": {"coordinates":[3.55,50.66667],"type":"Point"}
}