{
  "type": "Feature",
  "properties": {
    "gn:admin1_code":"WAL",
    "gn:admin2_code":"WLG",
    "gn:admin3_code":"63.0",
    "gn:admin4_code":"63076.0",
    "gn:asciiname":"Banoyard",
    "gn:country_code":"BE",
    "gn:dem":352,
    "gn:feature_class":"P",
    "gn:feature_code":"PPL",
    "gn:name":"Banoyard",
    "gn:population":0,
    "gn:timezone":"Europe/Brussels",
    "iso:country":"BE",
    "name:und_x_variant":[
        "Les Cours",
        "Banoyard"
    ],
    "wof:name":"Banoyard",
    "wof:placetype":"locality"
},
  "geometry": {"coordinates":[5.79775,50.47098],"type":"Point"}
}