{
  "type": "Feature",
  "properties": {
    "gn:admin1_code":"WAL",
    "gn:admin2_code":"WLG",
    "gn:admin3_code":"63.0",
    "gn:admin4_code":"63023.0",
    "gn:asciiname":"Stockem",
    "gn:country_code":"BE",
    "gn:dem":279,
    "gn:feature_class":"P",
    "gn:feature_code":"PPL",
    "gn:name":"Stockem",
    "gn:population":0,
    "gn:timezone":"Europe/Brussels",
    "iso:country":"BE",
    "name:cat_x_preferred":[
        "Stockem"
    ],
    "name:ceb_x_preferred":[
        "Stockem"
    ],
    "name:fra_x_preferred":[
        "Stockem"
    ],
    "name:ltz_x_preferred":[
        "Stackem"
    ],
    "name:msa_x_preferred":[
        "Stockem"
    ],
    "name:nld_x_preferred":[
        "Stockem"
    ],
    "name:pol_x_preferred":[
        "Stockem"
    ],
    "name:swe_x_preferred":[
        "Stockem"
    ],
    "wof:name":"Stockem",
    "wof:placetype":"locality"
},
  "geometry": {"coordinates":[6.02961,50.63155],"type":"Point"}
}