{
  "type": "Feature",
  "properties": {
    "gn:gn_country":"BE",
    "gn:gn_fcode":"PPL",
    "gn:gn_pop":0,
    "iso:country":"BE",
    "name:afr_x_preferred":[
        "Meeuwen-Gruitrode"
    ],
    "name:bre_x_preferred":[
        "Meeuwen-Gruitrode"
    ],
    "name:bul_x_preferred":[
        "\u041c\u0435\u0443\u0435\u043d-\u0413\u0440\u043e\u0439\u0442\u0440\u043e\u0434\u0435"
    ],
    "name:cat_x_preferred":[
        "Meeuwen-Gruitrode"
    ],
    "name:ceb_x_preferred":[
        "Meeuwen-Gruitrode"
    ],
    "name:dan_x_preferred":[
        "Meeuwen-Gruitrode"
    ],
    "name:deu_x_preferred":[
        "Meeuwen-Gruitrode"
    ],
    "name:eng_x_preferred":[
        "Meeuwen-Gruitrode"
    ],
    "name:epo_x_preferred":[
        "Meeuwen-Gruitrode"
    ],
    "name:eus_x_preferred":[
        "Meeuwen-Gruitrode"
    ],
    "name:fas_x_preferred":[
        "\u0645\u0626\u0648\u0627\u0646-\u06af\u0631\u0648\u0626\u06cc\u062a\u0631\u0648\u062f"
    ],
    "name:fra_x_preferred":[
        "Meeuwen-Gruitrode"
    ],
    "name:hun_x_preferred":[
        "Meeuwen-Gruitrode"
    ],
    "name:ita_x_preferred":[
        "Meeuwen-Gruitrode"
    ],
    "name:lim_x_preferred":[
        "Mi\u00ebve-Roj"
    ],
    "name:ltz_x_preferred":[
        "Meeuwen-Gruitrode"
    ],
    "name:nld_x_preferred":[
        "Meeuwen-Gruitrode"
    ],
    "name:nob_x_preferred":[
        "Meeuwen-Gruitrode"
    ],
    "name:oci_x_preferred":[
        "Meeuwen-Gruitrode"
    ],
    "name:pol_x_preferred":[
        "Meeuwen-Gruitrode"
    ],
    "name:por_x_preferred":[
        "Meeuwen-Gruitrode"
    ],
    "name:ron_x_preferred":[
        "Meeuwen-Gruitrode"
    ],
    "name:slk_x_preferred":[
        "Meeuwen-Gruitrode"
    ],
    "name:spa_x_preferred":[
        "Meeuwen-Gruitrode"
    ],
    "name:swe_x_preferred":[
        "Meeuwen-Gruitrode"
    ],
    "name:tha_x_preferred":[
        "\u0e40\u0e21\u0e27\u0e40\u0e27\u0e34\u0e19-\u0e40\u0e04\u0e23\u0e22\u0e42\u0e15\u0e23\u0e40\u0e14\u0e2d"
    ],
    "name:vie_x_preferred":[
        "Meeuwen-Gruitrode"
    ],
    "name:vol_x_preferred":[
        "Meeuwen-Gruitrode"
    ],
    "name:war_x_preferred":[
        "Meeuwen-Gruitrode"
    ],
    "name:zho_x_preferred":[
        "\u6885\u5384\u6587\uff0d\u8d6b\u96f7\u7279\u7f57\u5fb7"
    ],
    "qs_pg:aaroncc":"BE",
    "qs_pg:gn_country":"BE",
    "qs_pg:gn_fcode":"PPL",
    "qs_pg:gn_pop":0,
    "qs_pg:name":"Meeuwen-gruitrode",
    "qs_pg:name_adm0":"Belgique",
    "qs_pg:name_adm1":"Limburg",
    "qs_pg:photos_9k":1,
    "qs_pg:photos_9r":1,
    "qs_pg:photos_all":1,
    "qs_pg:photos_sr":0,
    "qs_pg:pop_sr":0,
    "qs_pg:qs_pg_placetype":"locality",
    "qs_pg:qs_pg_placetype_gp":"Town",
    "qs_pg:woe_adm0":23424757,
    "woe:adm0_id":23424757,
    "woe:name_adm0":"Belgique",
    "woe:name_adm1":"Limburg",
    "woe:placetype":"Town",
    "wof:name":"Meeuwen-gruitrode",
    "wof:placetype":"locality"
},
  "geometry": {"coordinates":[5.5505,51.09468],"type":"Point"}
}