{
  "type": "Feature",
  "properties": {
    "gn:admin1_code":"WAL",
    "gn:admin2_code":"WLG",
    "gn:admin3_code":"63.0",
    "gn:admin4_code":"63046.0",
    "gn:asciiname":"Membach",
    "gn:country_code":"BE",
    "gn:dem":244,
    "gn:feature_class":"P",
    "gn:feature_code":"PPL",
    "gn:name":"Membach",
    "gn:population":0,
    "gn:timezone":"Europe/Brussels",
    "iso:country":"BE",
    "name:und_x_variant":[
        "Baelen (Membach)"
    ],
    "wof:name":"Membach",
    "wof:placetype":"locality"
},
  "geometry": {"coordinates":[5.99506,50.61908],"type":"Point"}
}