{
  "type": "Feature",
  "properties": {
    "gn:admin1_code":"BRU",
    "gn:admin2_code":"BRU",
    "gn:admin3_code":"21.0",
    "gn:admin4_code":"21004.0",
    "gn:asciiname":"European district",
    "gn:country_code":"BE",
    "gn:dem":70,
    "gn:feature_class":"P",
    "gn:feature_code":"PPL",
    "gn:name":"European district",
    "gn:population":0,
    "gn:timezone":"Europe/Brussels",
    "iso:country":"BE",
    "wof:name":"European district",
    "wof:placetype":"locality"
},
  "geometry": {"coordinates":[4.37235,50.8432],"type":"Point"}
}