{
  "type": "Feature",
  "properties": {
    "gn:admin1_code":"WAL",
    "gn:admin2_code":"WLX",
    "gn:admin3_code":"82.0",
    "gn:admin4_code":"82038.0",
    "gn:asciiname":"Tonny",
    "gn:country_code":"BE",
    "gn:dem":390,
    "gn:feature_class":"P",
    "gn:feature_code":"PPL",
    "gn:name":"Tonny",
    "gn:population":0,
    "gn:timezone":"Europe/Brussels",
    "iso:country":"BE",
    "name:ind_x_preferred":[
        "Tonny"
    ],
    "name:nor_x_preferred":[
        "Tonny"
    ],
    "name:swe_x_preferred":[
        "Tonny"
    ],
    "wof:name":"Tonny",
    "wof:placetype":"locality"
},
  "geometry": {"coordinates":[5.51012,50.02625],"type":"Point"}
}