{
  "type": "Feature",
  "properties": {
    "gn:admin1_code":"WAL",
    "gn:admin2_code":"WHT",
    "gn:admin3_code":"51.0",
    "gn:admin4_code":"51004.0",
    "gn:asciiname":"Croquy",
    "gn:country_code":"BE",
    "gn:dem":50,
    "gn:feature_class":"P",
    "gn:feature_code":"PPL",
    "gn:name":"Croquy",
    "gn:population":0,
    "gn:timezone":"Europe/Brussels",
    "iso:country":"BE",
    "wof:name":"Croquy",
    "wof:placetype":"locality"
},
  "geometry": {"coordinates":[3.88333,50.63333],"type":"Point"}
}