{
  "type": "Feature",
  "properties": {
    "gn:admin1_code":"WAL",
    "gn:admin2_code":"WLG",
    "gn:admin3_code":"61.0",
    "gn:admin4_code":"61012.0",
    "gn:asciiname":"Saint-Fontaine",
    "gn:country_code":"BE",
    "gn:dem":224,
    "gn:feature_class":"P",
    "gn:feature_code":"PPL",
    "gn:name":"Saint-Fontaine",
    "gn:population":0,
    "gn:timezone":"Europe/Brussels",
    "iso:country":"BE",
    "name:und_x_variant":[
        "Sainte-Fontaine",
        "Saint-Fontaine"
    ],
    "wof:name":"Saint-Fontaine",
    "wof:placetype":"locality"
},
  "geometry": {"coordinates":[5.24245,50.41211],"type":"Point"}
}