{
  "type": "Feature",
  "properties": {
    "gn:admin1_code":"WAL",
    "gn:admin2_code":"WLX",
    "gn:admin3_code":"82.0",
    "gn:admin4_code":"82038.0",
    "gn:asciiname":"Houmont",
    "gn:country_code":"BE",
    "gn:dem":469,
    "gn:feature_class":"P",
    "gn:feature_code":"PPL",
    "gn:name":"Houmont",
    "gn:population":0,
    "gn:timezone":"Europe/Brussels",
    "iso:country":"BE",
    "wof:name":"Houmont",
    "wof:placetype":"locality"
},
  "geometry": {"coordinates":[5.58526,49.99609],"type":"Point"}
}