{
  "type": "Feature",
  "properties": {
    "gn:admin1_code":"WAL",
    "gn:admin2_code":"WLG",
    "gn:admin3_code":"62.0",
    "gn:admin4_code":"62120.0",
    "gn:asciiname":"Boulboulle",
    "gn:country_code":"BE",
    "gn:dem":178,
    "gn:feature_class":"P",
    "gn:feature_code":"PPL",
    "gn:name":"Boulboulle",
    "gn:population":0,
    "gn:timezone":"Europe/Brussels",
    "iso:country":"BE",
    "wof:name":"Boulboulle",
    "wof:placetype":"locality"
},
  "geometry": {"coordinates":[5.45,50.61667],"type":"Point"}
}