{
  "type": "Feature",
  "properties": {
    "gn:country":"BE",
    "gn:fcode":"PPL",
    "gn:population":0,
    "iso:country":"BE",
    "name:eng_x_preferred":[
        "Pont-de-Loup"
    ],
    "name:fra_x_preferred":[
        "Pont-de-Loup"
    ],
    "name:hun_x_preferred":[
        "Pont-de-Loup"
    ],
    "name:nld_x_preferred":[
        "Pont-de-Loup"
    ],
    "name:und_x_variant":[
        "Aiseau-Presles (Pont-de-Loup)"
    ],
    "name:wln_x_preferred":[
        "Pondl\u00f4"
    ],
    "qs_pg:aaroncc":"BE",
    "qs_pg:gn_country":"BE",
    "qs_pg:gn_fcode":"PPL",
    "qs_pg:gn_pop":0,
    "qs_pg:name":"Pont-de-Loup",
    "qs_pg:name_adm0":"Belgique",
    "qs_pg:name_adm1":"Hainaut",
    "qs_pg:photos_9k":1,
    "qs_pg:photos_9r":1,
    "qs_pg:photos_all":2,
    "qs_pg:photos_sr":0,
    "qs_pg:pop_sr":0,
    "qs_pg:qs_pg_placetype":"locality",
    "qs_pg:qs_pg_placetype_gp":"Town",
    "qs_pg:woe_adm0":23424757,
    "woe:adm0_id":23424757,
    "woe:name_adm0":"Belgique",
    "woe:name_adm1":"Hainaut",
    "woe:placetype":"Town",
    "wof:name":"Pont-de-Loup",
    "wof:placetype":"locality"
},
  "geometry": {"coordinates":[4.54594,50.41656],"type":"Point"}
}