{
  "type": "Feature",
  "properties": {
    "gn:admin1_code":"WAL",
    "gn:admin2_code":"WHT",
    "gn:admin3_code":"53.0",
    "gn:admin4_code":"53084.0",
    "gn:asciiname":"Warchaix",
    "gn:country_code":"BE",
    "gn:dem":79,
    "gn:feature_class":"P",
    "gn:feature_code":"PPL",
    "gn:name":"Warchaix",
    "gn:population":0,
    "gn:timezone":"Europe/Brussels",
    "iso:country":"BE",
    "wof:name":"Warchaix",
    "wof:placetype":"locality"
},
  "geometry": {"coordinates":[3.96667,50.38333],"type":"Point"}
}