{
  "type": "Feature",
  "properties": {
    "gn:admin1_code":"WAL",
    "gn:admin2_code":"WHT",
    "gn:admin3_code":"51.0",
    "gn:admin4_code":"51019.0",
    "gn:asciiname":"Pourri",
    "gn:country_code":"BE",
    "gn:dem":63,
    "gn:feature_class":"P",
    "gn:feature_code":"PPL",
    "gn:name":"Pourri",
    "gn:population":0,
    "gn:timezone":"Europe/Brussels",
    "iso:country":"BE",
    "name:und_x_variant":[
        "Le Pourri",
        "Pourri"
    ],
    "wof:name":"Pourri",
    "wof:placetype":"locality"
},
  "geometry": {"coordinates":[3.71708,50.73794],"type":"Point"}
}