{
  "type": "Feature",
  "properties": {
    "gn:admin1_code":"VLG",
    "gn:admin2_code":"VAN",
    "gn:admin3_code":"13.0",
    "gn:admin4_code":"13036.0",
    "gn:asciiname":"Pomfort",
    "gn:country_code":"BE",
    "gn:dem":23,
    "gn:feature_class":"P",
    "gn:feature_code":"PPL",
    "gn:name":"Pomfort",
    "gn:population":0,
    "gn:timezone":"Europe/Brussels",
    "iso:country":"BE",
    "name:und_x_variant":[
        "Pontfort",
        "Ponfort",
        "Pomfort"
    ],
    "wof:name":"Pomfort",
    "wof:placetype":"locality"
},
  "geometry": {"coordinates":[5.05152,51.26233],"type":"Point"}
}