{
  "type": "Feature",
  "properties": {
    "gn:country":"BE",
    "gn:fcode":"PPL",
    "gn:population":0,
    "iso:country":"BE",
    "name:cat_x_preferred":[
        "Remersdaal"
    ],
    "name:deu_x_preferred":[
        "Remersdaal"
    ],
    "name:eng_x_preferred":[
        "Remersdaal"
    ],
    "name:fra_x_preferred":[
        "R\u00e9mersdael"
    ],
    "name:hun_x_preferred":[
        "Remersdaal"
    ],
    "name:lim_x_preferred":[
        "Rimmezjdel"
    ],
    "name:nld_x_preferred":[
        "Remersdaal"
    ],
    "name:und_x_variant":[
        "Voeren (Remersdaal)"
    ],
    "qs_pg:aaroncc":"BE",
    "qs_pg:gn_country":"BE",
    "qs_pg:gn_fcode":"PPL",
    "qs_pg:gn_pop":0,
    "qs_pg:name":"Remersdaal",
    "qs_pg:name_adm0":"Belgique",
    "qs_pg:name_adm1":"Limburg",
    "qs_pg:photos":775,
    "qs_pg:photos_1k":157,
    "qs_pg:photos_9k":3,
    "qs_pg:photos_9r":6,
    "qs_pg:photos_all":775,
    "qs_pg:photos_sr":9,
    "qs_pg:pop_sr":0,
    "qs_pg:qs_pg_placetype":"locality",
    "qs_pg:qs_pg_placetype_gp":"Town",
    "qs_pg:woe_adm0":23424757,
    "woe:adm0_id":23424757,
    "woe:name_adm0":"Belgique",
    "woe:name_adm1":"Limburg",
    "woe:placetype":"Town",
    "wof:name":"Remersdaal",
    "wof:placetype":"locality"
},
  "geometry": {"coordinates":[5.88065,50.7314],"type":"Point"}
}