{
  "type": "Feature",
  "properties": {
    "gn:admin1_code":"WAL",
    "gn:admin2_code":"WLX",
    "gn:admin3_code":"81.0",
    "gn:admin4_code":"81015.0",
    "gn:asciiname":"Longeau",
    "gn:country_code":"BE",
    "gn:dem":272,
    "gn:feature_class":"P",
    "gn:feature_code":"PPL",
    "gn:name":"Longeau",
    "gn:population":0,
    "gn:timezone":"Europe/Brussels",
    "iso:country":"BE",
    "wof:name":"Longeau",
    "wof:placetype":"locality"
},
  "geometry": {"coordinates":[5.83261,49.57734],"type":"Point"}
}