{
  "type": "Feature",
  "properties": {
    "iso:country":"BE",
    "name:dut_x_variant":[
        "Vrijheidwijk"
    ],
    "wof:name":"Quartier des Libertes",
    "wof:placetype":"neighbourhood"
},
  "geometry": {"coordinates":[4.36558179447257,50.84888393508137],"type":"Point"}
}