{
  "type": "Feature",
  "properties": {
    "gn:gn_country":"BE",
    "gn:gn_fcode":"PPL",
    "gn:gn_pop":0,
    "iso:country":"BE",
    "name:bre_x_preferred":[
        "Kaaskerke"
    ],
    "name:bul_x_preferred":[
        "\u041a\u0430\u0441\u043a\u0435\u0440\u043a\u0435"
    ],
    "name:eng_x_preferred":[
        "Kaaskerke"
    ],
    "name:fra_x_preferred":[
        "Kaaskerke"
    ],
    "name:hun_x_preferred":[
        "Kaaskerke"
    ],
    "name:nld_x_preferred":[
        "Kaaskerke"
    ],
    "name:por_x_preferred":[
        "Kaaskerke"
    ],
    "name:swe_x_preferred":[
        "Kaaskerke"
    ],
    "name:unk_x_variant":[
        "Caeskerke"
    ],
    "name:vls_x_preferred":[
        "Koaskerke"
    ],
    "qs_pg:aaroncc":"BE",
    "qs_pg:gn_country":"BE",
    "qs_pg:gn_fcode":"PPL",
    "qs_pg:gn_pop":0,
    "qs_pg:name":"Kaaskerke",
    "qs_pg:name_adm0":"Belgique",
    "qs_pg:name_adm1":"West-Vlaanderen",
    "qs_pg:photos_9k":1,
    "qs_pg:photos_9r":1,
    "qs_pg:photos_all":1,
    "qs_pg:photos_sr":0,
    "qs_pg:pop_sr":0,
    "qs_pg:qs_pg_placetype":"locality",
    "qs_pg:qs_pg_placetype_gp":"Town",
    "qs_pg:woe_adm0":23424757,
    "woe:adm0_id":23424757,
    "woe:name_adm0":"Belgique",
    "woe:name_adm1":"West-Vlaanderen",
    "woe:placetype":"Town",
    "wof:name":"Kaaskerke",
    "wof:placetype":"locality"
},
  "geometry": {"coordinates":[2.83872,51.03544],"type":"Point"}
}