{
  "type": "Feature",
  "properties": {
    "gn:admin1_code":"VLG",
    "gn:admin2_code":"VWV",
    "gn:admin3_code":"36.0",
    "gn:admin4_code":"36011.0",
    "gn:asciiname":"Vijfwege",
    "gn:country_code":"BE",
    "gn:dem":22,
    "gn:feature_class":"P",
    "gn:feature_code":"PPL",
    "gn:name":"Vijfwege",
    "gn:population":0,
    "gn:timezone":"Europe/Brussels",
    "iso:country":"BE",
    "name:und_x_variant":[
        "Vijfwegen",
        "Wijtwege",
        "Vyfwege",
        "Vijfwege"
    ],
    "wof:name":"Vijfwege",
    "wof:placetype":"locality"
},
  "geometry": {"coordinates":[3.13131,51.03475],"type":"Point"}
}