{
  "type": "Feature",
  "properties": {
    "gn:gn_country":"BE",
    "gn:gn_fcode":"PPL",
    "gn:gn_pop":0,
    "iso:country":"BE",
    "name:dut_x_preferred":[
        "Neerwinden"
    ],
    "name:eng_x_preferred":[
        "Neerwinden"
    ],
    "name:fre_x_preferred":[
        "Neerwinden"
    ],
    "name:ger_x_preferred":[
        "Neerwinden"
    ],
    "name:hun_x_preferred":[
        "Neerwinden"
    ],
    "name:jpn_x_preferred":[
        "\u30cd\u30fc\u30eb\u30a6\u30a3\u30f3\u30c7\u30f3"
    ],
    "name:lit_x_preferred":[
        "Neerwinden m\u016b\u0161is"
    ],
    "name:pol_x_preferred":[
        "Neerwinden"
    ],
    "name:swe_x_preferred":[
        "Neerwinden"
    ],
    "qs_pg:aaroncc":"BE",
    "qs_pg:gn_country":"BE",
    "qs_pg:gn_fcode":"PPL",
    "qs_pg:gn_pop":0,
    "qs_pg:name":"Neerwinden",
    "qs_pg:name_adm0":"Belgique",
    "qs_pg:name_adm1":"Vlaams Brabant",
    "qs_pg:photos_9r":0,
    "qs_pg:photos_sr":0,
    "qs_pg:pop_sr":0,
    "qs_pg:qs_pg_placetype":"locality",
    "qs_pg:qs_pg_placetype_gp":"Town",
    "qs_pg:woe_adm0":23424757,
    "woe:adm0_id":23424757,
    "woe:name_adm0":"Belgique",
    "woe:name_adm1":"Vlaams Brabant",
    "woe:placetype":"Town",
    "wof:name":"Neerwinden",
    "wof:placetype":"locality"
},
  "geometry": {"coordinates":[5.04021,50.76756],"type":"Point"}
}