{
  "type": "Feature",
  "properties": {
    "gn:admin1_code":"WAL",
    "gn:admin2_code":"WHT",
    "gn:admin3_code":"55.0",
    "gn:admin4_code":"55004.0",
    "gn:asciiname":"Warichaix",
    "gn:country_code":"BE",
    "gn:dem":87,
    "gn:feature_class":"P",
    "gn:feature_code":"PPL",
    "gn:name":"Warichaix",
    "gn:population":0,
    "gn:timezone":"Europe/Brussels",
    "iso:country":"BE",
    "wof:name":"Warichaix",
    "wof:placetype":"locality"
},
  "geometry": {"coordinates":[4.18817,50.65576],"type":"Point"}
}