{
  "type": "Feature",
  "properties": {
    "gn:admin1_code":"VLG",
    "gn:admin2_code":"VOV",
    "gn:admin3_code":"44.0",
    "gn:admin4_code":"44029.0",
    "gn:asciiname":"Langedonk",
    "gn:country_code":"BE",
    "gn:dem":9,
    "gn:feature_class":"P",
    "gn:feature_code":"PPL",
    "gn:name":"Langedonk",
    "gn:population":0,
    "gn:timezone":"Europe/Brussels",
    "iso:country":"BE",
    "wof:name":"Langedonk",
    "wof:placetype":"locality"
},
  "geometry": {"coordinates":[3.40509,51.12717],"type":"Point"}
}