{
  "type": "Feature",
  "properties": {
    "gn:admin1_code":"VLG",
    "gn:admin2_code":"VLI",
    "gn:admin3_code":"72.0",
    "gn:admin4_code":"72018.0",
    "gn:asciiname":"Raam",
    "gn:country_code":"BE",
    "gn:dem":31,
    "gn:feature_class":"P",
    "gn:feature_code":"PPL",
    "gn:name":"Raam",
    "gn:population":0,
    "gn:timezone":"Europe/Brussels",
    "iso:country":"BE",
    "wof:name":"Raam",
    "wof:placetype":"locality"
},
  "geometry": {"coordinates":[5.75819,51.1348],"type":"Point"}
}