{
  "type": "Feature",
  "properties": {
    "gn:admin1_code":"VLG",
    "gn:admin2_code":"VAN",
    "gn:admin3_code":"12.0",
    "gn:admin4_code":"12014.0",
    "gn:asciiname":"Goor",
    "gn:country_code":"BE",
    "gn:dem":12,
    "gn:feature_class":"P",
    "gn:feature_code":"PPL",
    "gn:name":"Goor",
    "gn:population":0,
    "gn:timezone":"Europe/Brussels",
    "iso:country":"BE",
    "name:ceb_x_preferred":[
        "Goor"
    ],
    "name:fas_x_preferred":[
        "\u062e\u0648\u0631"
    ],
    "name:fra_x_preferred":[
        "Goor"
    ],
    "name:ita_x_preferred":[
        "Goor"
    ],
    "name:lat_x_preferred":[
        "Gora"
    ],
    "name:nld_x_preferred":[
        "Goor"
    ],
    "name:rus_x_preferred":[
        "\u0413\u043e\u043e\u0440"
    ],
    "wof:name":"Goor",
    "wof:placetype":"locality"
},
  "geometry": {"coordinates":[4.7253,51.04583],"type":"Point"}
}