{
  "type": "Feature",
  "properties": {
    "gn:admin1_code":"WAL",
    "gn:admin2_code":"WNA",
    "gn:admin3_code":"91.0",
    "gn:admin4_code":"91030.0",
    "gn:asciiname":"Emptinnal",
    "gn:country_code":"BE",
    "gn:dem":235,
    "gn:feature_class":"P",
    "gn:feature_code":"PPL",
    "gn:name":"Emptinnal",
    "gn:population":0,
    "gn:timezone":"Europe/Brussels",
    "iso:country":"BE",
    "name:fra_x_preferred":[
        "Emptinale"
    ],
    "name:fra_x_variant":[
        "Emptinal",
        "Emptinnal"
    ],
    "wof:name":"Emptinnal",
    "wof:placetype":"locality"
},
  "geometry": {"coordinates":[5.10255,50.31883],"type":"Point"}
}