{
  "type": "Feature",
  "properties": {
    "gn:country":"BE",
    "gn:fcode":"PPL",
    "gn:population":0,
    "iso:country":"BE",
    "name:eng_x_preferred":[
        "Grasheide"
    ],
    "name:nld_x_preferred":[
        "Grasheide"
    ],
    "qs_pg:aaroncc":"BE",
    "qs_pg:gn_country":"BE",
    "qs_pg:gn_fcode":"PPL",
    "qs_pg:gn_pop":0,
    "qs_pg:name":"Grasheide",
    "qs_pg:name_adm0":"Belgique",
    "qs_pg:name_adm1":"Antwerpen",
    "qs_pg:photos_9r":0,
    "qs_pg:photos_sr":0,
    "qs_pg:pop_sr":0,
    "qs_pg:qs_pg_placetype":"locality",
    "qs_pg:qs_pg_placetype_gp":"Town",
    "qs_pg:woe_adm0":23424757,
    "woe:adm0_id":23424757,
    "woe:name_adm0":"Belgique",
    "woe:name_adm1":"Antwerpen",
    "woe:placetype":"Town",
    "wof:name":"Grasheide",
    "wof:placetype":"locality"
},
  "geometry": {"coordinates":[4.66029,51.02815],"type":"Point"}
}