{
  "type": "Feature",
  "properties": {
    "gn:admin1_code":"VLG",
    "gn:admin2_code":"VOV",
    "gn:admin3_code":"44.0",
    "gn:admin4_code":"44034.0",
    "gn:asciiname":"Vierweegse",
    "gn:country_code":"BE",
    "gn:dem":3,
    "gn:feature_class":"P",
    "gn:feature_code":"PPL",
    "gn:name":"Vierweegse",
    "gn:population":0,
    "gn:timezone":"Europe/Brussels",
    "iso:country":"BE",
    "wof:name":"Vierweegse",
    "wof:placetype":"locality"
},
  "geometry": {"coordinates":[3.83333,51.11667],"type":"Point"}
}