{
  "type": "Feature",
  "properties": {
    "gn:admin1_code":"VLG",
    "gn:admin2_code":"VOV",
    "gn:admin3_code":"43.0",
    "gn:admin4_code":"43005.0",
    "gn:asciiname":"Vrouwenstraat",
    "gn:country_code":"BE",
    "gn:dem":3,
    "gn:feature_class":"P",
    "gn:feature_code":"PPL",
    "gn:name":"Vrouwenstraat",
    "gn:population":0,
    "gn:timezone":"Europe/Brussels",
    "iso:country":"BE",
    "name:und_x_variant":[
        "Vrouwenstraet",
        "Vrouwenstraat"
    ],
    "wof:name":"Vrouwenstraat",
    "wof:placetype":"locality"
},
  "geometry": {"coordinates":[3.53655,51.20456],"type":"Point"}
}