{
  "type": "Feature",
  "properties": {
    "gn:admin1_code":"VLG",
    "gn:admin2_code":"VWV",
    "gn:admin3_code":"32.0",
    "gn:admin4_code":"32003.0",
    "gn:asciiname":"Stuivekenskerke",
    "gn:country_code":"BE",
    "gn:dem":0,
    "gn:feature_class":"P",
    "gn:feature_code":"PPL",
    "gn:name":"Stuivekenskerke",
    "gn:population":0,
    "gn:timezone":"Europe/Brussels",
    "iso:country":"BE",
    "name:bre_x_preferred":[
        "Stuivekenskerke"
    ],
    "name:ceb_x_preferred":[
        "Stuivekenskerke"
    ],
    "name:fra_x_preferred":[
        "Stuivekenskerke"
    ],
    "name:nld_x_preferred":[
        "Stuivekenskerke"
    ],
    "name:por_x_preferred":[
        "Stuivekenskerke"
    ],
    "name:swe_x_preferred":[
        "Stuivekenskerke"
    ],
    "name:und_x_variant":[
        "Stuyvekenskerke",
        "Stuivekenskerke"
    ],
    "name:vls_x_preferred":[
        "Stuvetjeskerke"
    ],
    "wof:name":"Stuivekenskerke",
    "wof:placetype":"locality"
},
  "geometry": {"coordinates":[2.82511,51.07679],"type":"Point"}
}