{
  "type": "Feature",
  "properties": {
    "gn:admin1_code":"VLG",
    "gn:admin2_code":"VWV",
    "gn:admin3_code":"38.0",
    "gn:admin4_code":"38025.0",
    "gn:asciiname":"Knolle Hoek",
    "gn:country_code":"BE",
    "gn:dem":1,
    "gn:feature_class":"P",
    "gn:feature_code":"PPL",
    "gn:name":"Knolle Hoek",
    "gn:population":0,
    "gn:timezone":"Europe/Brussels",
    "iso:country":"BE",
    "wof:name":"Knolle Hoek",
    "wof:placetype":"locality"
},
  "geometry": {"coordinates":[2.72223,51.03997],"type":"Point"}
}