{
  "type": "Feature",
  "properties": {
    "gn:admin1_code":"WAL",
    "gn:admin2_code":"WHT",
    "gn:admin3_code":"57.0",
    "gn:admin4_code":"57094.0",
    "gn:asciiname":"Le Chene",
    "gn:country_code":"BE",
    "gn:dem":65,
    "gn:feature_class":"P",
    "gn:feature_code":"PPL",
    "gn:name":"Le Ch\u00eane",
    "gn:population":0,
    "gn:timezone":"Europe/Brussels",
    "iso:country":"BE",
    "wof:name":"Le Chene",
    "wof:placetype":"locality"
},
  "geometry": {"coordinates":[3.61667,50.63333],"type":"Point"}
}