{
  "type": "Feature",
  "properties": {
    "gn:admin1_code":"VLG",
    "gn:admin2_code":"VOV",
    "gn:admin3_code":"44.0",
    "gn:admin4_code":"44013.0",
    "gn:asciiname":"Peerdeken",
    "gn:country_code":"BE",
    "gn:dem":5,
    "gn:feature_class":"P",
    "gn:feature_code":"PPL",
    "gn:name":"Peerdeken",
    "gn:population":0,
    "gn:timezone":"Europe/Brussels",
    "iso:country":"BE",
    "wof:name":"Peerdeken",
    "wof:placetype":"locality"
},
  "geometry": {"coordinates":[3.83638,51.07583],"type":"Point"}
}