{
  "type": "Feature",
  "properties": {
    "gn:admin1_code":"WAL",
    "gn:admin2_code":"WHT",
    "gn:admin3_code":"51.0",
    "gn:admin4_code":"51019.0",
    "gn:asciiname":"Esquenne",
    "gn:country_code":"BE",
    "gn:dem":75,
    "gn:feature_class":"P",
    "gn:feature_code":"PPL",
    "gn:name":"Esquenne",
    "gn:population":0,
    "gn:timezone":"Europe/Brussels",
    "iso:country":"BE",
    "wof:name":"Esquenne",
    "wof:placetype":"locality"
},
  "geometry": {"coordinates":[3.76628,50.75446],"type":"Point"}
}