{
  "type": "Feature",
  "properties": {
    "gn:admin1_code":"VLG",
    "gn:admin2_code":"VWV",
    "gn:admin3_code":"34.0",
    "gn:admin4_code":"34013.0",
    "gn:asciiname":"Sint-Pietersknok",
    "gn:country_code":"BE",
    "gn:dem":18,
    "gn:feature_class":"P",
    "gn:feature_code":"PPL",
    "gn:name":"Sint-Pietersknok",
    "gn:population":0,
    "gn:timezone":"Europe/Brussels",
    "iso:country":"BE",
    "wof:name":"Sint-Pietersknok",
    "wof:placetype":"locality"
},
  "geometry": {"coordinates":[3.30899,50.89893],"type":"Point"}
}