{
  "type": "Feature",
  "properties": {
    "gn:admin1_code":"WAL",
    "gn:admin2_code":"WLG",
    "gn:admin3_code":"63.0",
    "gn:admin4_code":"63048.0",
    "gn:asciiname":"Donnerkaul",
    "gn:country_code":"BE",
    "gn:dem":237,
    "gn:feature_class":"P",
    "gn:feature_code":"PPL",
    "gn:name":"Donnerkaul",
    "gn:population":0,
    "gn:timezone":"Europe/Brussels",
    "iso:country":"BE",
    "wof:name":"Donnerkaul",
    "wof:placetype":"locality"
},
  "geometry": {"coordinates":[5.99743,50.68838],"type":"Point"}
}