{
  "type": "Feature",
  "properties": {
    "gn:admin1_code":"WAL",
    "gn:admin2_code":"WLX",
    "gn:admin3_code":"85.0",
    "gn:admin4_code":"85011.0",
    "gn:asciiname":"Azy",
    "gn:country_code":"BE",
    "gn:dem":305,
    "gn:feature_class":"P",
    "gn:feature_code":"PPL",
    "gn:name":"Azy",
    "gn:population":0,
    "gn:timezone":"Europe/Brussels",
    "iso:country":"BE",
    "name:cat_x_preferred":[
        "Azy"
    ],
    "name:ceb_x_preferred":[
        "Azy"
    ],
    "name:deu_x_preferred":[
        "Azy"
    ],
    "name:eus_x_preferred":[
        "Azy"
    ],
    "name:fra_x_preferred":[
        "Azy"
    ],
    "name:hun_x_preferred":[
        "Azy"
    ],
    "name:ita_x_preferred":[
        "Azy"
    ],
    "name:lat_x_preferred":[
        "Azy"
    ],
    "name:msa_x_preferred":[
        "Azy"
    ],
    "name:nld_x_preferred":[
        "Azy"
    ],
    "name:oci_x_preferred":[
        "Azy"
    ],
    "name:pms_x_preferred":[
        "Azy"
    ],
    "name:pol_x_preferred":[
        "Azy"
    ],
    "name:por_x_preferred":[
        "Azy"
    ],
    "name:ron_x_preferred":[
        "Azy"
    ],
    "name:rus_x_preferred":[
        "\u0410\u0437\u0438"
    ],
    "name:slk_x_preferred":[
        "Azy"
    ],
    "name:spa_x_preferred":[
        "Azy"
    ],
    "name:sqi_x_preferred":[
        "Azy"
    ],
    "name:srp_x_preferred":[
        "\u0410\u0437\u0438"
    ],
    "name:swe_x_preferred":[
        "Azy"
    ],
    "name:ukr_x_preferred":[
        "\u0410\u0437\u0456"
    ],
    "name:und_x_variant":[
        "Asy"
    ],
    "name:uzb_x_preferred":[
        "Azy"
    ],
    "name:vie_x_preferred":[
        "Azy"
    ],
    "name:vol_x_preferred":[
        "Azy"
    ],
    "name:war_x_preferred":[
        "Azy"
    ],
    "wof:name":"Azy",
    "wof:placetype":"locality"
},
  "geometry": {"coordinates":[5.27881,49.72124],"type":"Point"}
}