{
  "type": "Feature",
  "properties": {
    "gn:admin1_code":"WAL",
    "gn:admin2_code":"WLX",
    "gn:admin3_code":"85.0",
    "gn:admin4_code":"85011.0",
    "gn:asciiname":"Azy",
    "gn:country_code":"BE",
    "gn:dem":305,
    "gn:feature_class":"P",
    "gn:feature_code":"PPL",
    "gn:name":"Azy",
    "gn:population":0,
    "gn:timezone":"Europe/Brussels",
    "iso:country":"BE",
    "name:und_x_variant":[
        "Asy",
        "Azy"
    ],
    "wof:name":"Azy",
    "wof:placetype":"locality"
},
  "geometry": {"coordinates":[5.27881,49.72124],"type":"Point"}
}