{
  "type": "Feature",
  "properties": {
    "gn:admin1_code":"VLG",
    "gn:admin2_code":"VLI",
    "gn:admin3_code":"73.0",
    "gn:admin4_code":"73040.0",
    "gn:asciiname":"Hoogveld",
    "gn:country_code":"BE",
    "gn:dem":97,
    "gn:feature_class":"P",
    "gn:feature_code":"PPL",
    "gn:name":"Hoogveld",
    "gn:population":0,
    "gn:timezone":"Europe/Brussels",
    "iso:country":"BE",
    "wof:name":"Hoogveld",
    "wof:placetype":"locality"
},
  "geometry": {"coordinates":[5.43695,50.833],"type":"Point"}
}