{
  "type": "Feature",
  "properties": {
    "gn:admin1_code":"VLG",
    "gn:admin2_code":"VOV",
    "gn:admin3_code":"44.0",
    "gn:admin4_code":"44020.0",
    "gn:asciiname":"Wassen",
    "gn:country_code":"BE",
    "gn:dem":28,
    "gn:feature_class":"P",
    "gn:feature_code":"PPL",
    "gn:name":"Wassen",
    "gn:population":0,
    "gn:timezone":"Europe/Brussels",
    "iso:country":"BE",
    "wof:name":"Wassen",
    "wof:placetype":"locality"
},
  "geometry": {"coordinates":[3.70662,50.94408],"type":"Point"}
}