{
  "type": "Feature",
  "properties": {
    "gn:admin1_code":"WAL",
    "gn:admin2_code":"WLX",
    "gn:admin3_code":"85.0",
    "gn:admin4_code":"85045.0",
    "gn:asciiname":"Bakese",
    "gn:country_code":"BE",
    "gn:dem":245,
    "gn:feature_class":"P",
    "gn:feature_code":"PPL",
    "gn:name":"Bak\u00e8se",
    "gn:population":0,
    "gn:timezone":"Europe/Brussels",
    "iso:country":"BE",
    "wof:name":"Bakese",
    "wof:placetype":"locality"
},
  "geometry": {"coordinates":[5.61868,49.58881],"type":"Point"}
}