{
  "type": "Feature",
  "properties": {
    "gn:admin1_code":"WAL",
    "gn:admin2_code":"WLX",
    "gn:admin3_code":"83.0",
    "gn:admin4_code":"83040.0",
    "gn:asciiname":"Chavanne",
    "gn:country_code":"BE",
    "gn:dem":253,
    "gn:feature_class":"P",
    "gn:feature_code":"PPL",
    "gn:name":"Chavanne",
    "gn:population":0,
    "gn:timezone":"Europe/Brussels",
    "iso:country":"BE",
    "name:bug_x_preferred":[
        "Chavanne"
    ],
    "name:cat_x_preferred":[
        "Chavanne"
    ],
    "name:ceb_x_preferred":[
        "Chavanne"
    ],
    "name:deu_x_preferred":[
        "Chavanne"
    ],
    "name:eus_x_preferred":[
        "Chavanne"
    ],
    "name:fra_x_preferred":[
        "Chavanne"
    ],
    "name:hun_x_preferred":[
        "Chavanne"
    ],
    "name:ita_x_preferred":[
        "Chavanne"
    ],
    "name:lat_x_preferred":[
        "Chavanne"
    ],
    "name:ltz_x_preferred":[
        "Chavanne"
    ],
    "name:msa_x_preferred":[
        "Chavanne"
    ],
    "name:nld_x_preferred":[
        "Chavanne"
    ],
    "name:oci_x_preferred":[
        "Chavanne"
    ],
    "name:pms_x_preferred":[
        "Chavanne"
    ],
    "name:pol_x_preferred":[
        "Chavanne"
    ],
    "name:por_x_preferred":[
        "Chavanne"
    ],
    "name:rus_x_preferred":[
        "\u0428\u0430\u0432\u0430\u043d"
    ],
    "name:slk_x_preferred":[
        "Chavanne"
    ],
    "name:spa_x_preferred":[
        "Chavanne"
    ],
    "name:srp_x_preferred":[
        "\u0428\u0430\u0432\u0430\u043d"
    ],
    "name:swe_x_preferred":[
        "Chavanne"
    ],
    "name:ukr_x_preferred":[
        "\u0428\u0430\u0432\u0430\u043d\u043d"
    ],
    "name:uzb_x_preferred":[
        "Chavanne"
    ],
    "name:vie_x_preferred":[
        "Chavanne"
    ],
    "name:vol_x_preferred":[
        "Chavanne"
    ],
    "name:war_x_preferred":[
        "Chavanne"
    ],
    "wof:name":"Chavanne",
    "wof:placetype":"locality"
},
  "geometry": {"coordinates":[5.35194,50.17525],"type":"Point"}
}