{
  "type": "Feature",
  "properties": {
    "gn:admin1_code":"WAL",
    "gn:admin2_code":"WLG",
    "gn:admin3_code":"61.0",
    "gn:admin4_code":"61028.0",
    "gn:asciiname":"Envoz",
    "gn:country_code":"BE",
    "gn:dem":162,
    "gn:feature_class":"P",
    "gn:feature_code":"PPL",
    "gn:name":"Envoz",
    "gn:population":0,
    "gn:timezone":"Europe/Brussels",
    "iso:country":"BE",
    "name:und_x_variant":[
        "Envaux",
        "Envoz"
    ],
    "wof:name":"Envoz",
    "wof:placetype":"locality"
},
  "geometry": {"coordinates":[5.14536,50.53428],"type":"Point"}
}