{
  "type": "Feature",
  "properties": {
    "gn:gn_country":"BE",
    "gn:gn_fcode":"PPL",
    "gn:gn_pop":0,
    "iso:country":"BE",
    "name:eng_x_preferred":[
        "Seilles"
    ],
    "name:est_x_preferred":[
        "Seilles"
    ],
    "name:fra_x_preferred":[
        "Seilles"
    ],
    "name:nld_x_preferred":[
        "Seilles"
    ],
    "name:slv_x_preferred":[
        "Seilles"
    ],
    "name:unk_x_variant":[
        "Andenne (Seilles)"
    ],
    "name:wln_x_preferred":[
        "Seye"
    ],
    "qs_pg:aaroncc":"BE",
    "qs_pg:gn_country":"BE",
    "qs_pg:gn_fcode":"PPL",
    "qs_pg:gn_pop":0,
    "qs_pg:name":"Seilles",
    "qs_pg:name_adm0":"Belgique",
    "qs_pg:name_adm1":"Namur",
    "qs_pg:photos_9k":1,
    "qs_pg:photos_9r":1,
    "qs_pg:photos_all":16,
    "qs_pg:photos_sr":0,
    "qs_pg:pop_sr":0,
    "qs_pg:qs_pg_placetype":"locality",
    "qs_pg:qs_pg_placetype_gp":"Town",
    "qs_pg:woe_adm0":23424757,
    "woe:adm0_id":23424757,
    "woe:name_adm0":"Belgique",
    "woe:name_adm1":"Namur",
    "woe:placetype":"Town",
    "wof:name":"Seilles",
    "wof:placetype":"locality"
},
  "geometry": {"coordinates":[5.09268,50.50065],"type":"Point"}
}