{
  "type": "Feature",
  "properties": {
    "gn:admin1_code":"WAL",
    "gn:admin2_code":"WHT",
    "gn:admin3_code":"55.0",
    "gn:admin4_code":"55023.0",
    "gn:asciiname":"Chapelle Saint-Pierre",
    "gn:country_code":"BE",
    "gn:dem":19,
    "gn:feature_class":"P",
    "gn:feature_code":"PPL",
    "gn:name":"Chapelle Saint-Pierre",
    "gn:population":0,
    "gn:timezone":"Europe/Brussels",
    "iso:country":"BE",
    "wof:name":"Chapelle Saint-Pierre",
    "wof:placetype":"locality"
},
  "geometry": {"coordinates":[3.88422,50.73561],"type":"Point"}
}