{
  "type": "Feature",
  "properties": {
    "gn:admin1_code":"VLG",
    "gn:admin2_code":"VAN",
    "gn:admin3_code":"13.0",
    "gn:admin4_code":"13013.0",
    "gn:asciiname":"Venusberg",
    "gn:country_code":"BE",
    "gn:dem":18,
    "gn:feature_class":"P",
    "gn:feature_code":"PPL",
    "gn:name":"Venusberg",
    "gn:population":0,
    "gn:timezone":"Europe/Brussels",
    "iso:country":"BE",
    "wof:name":"Venusberg",
    "wof:placetype":"locality"
},
  "geometry": {"coordinates":[4.84892,51.03197],"type":"Point"}
}