{
  "type": "Feature",
  "properties": {
    "gn:admin1_code":"VLG",
    "gn:admin2_code":"VAN",
    "gn:admin3_code":"13.0",
    "gn:admin4_code":"13013.0",
    "gn:asciiname":"Venusberg",
    "gn:country_code":"BE",
    "gn:dem":18,
    "gn:feature_class":"P",
    "gn:feature_code":"PPL",
    "gn:name":"Venusberg",
    "gn:population":0,
    "gn:timezone":"Europe/Brussels",
    "iso:country":"BE",
    "name:bak_x_preferred":[
        "\u0412\u0435\u043d\u0443\u0441\u0431\u0435\u0440\u0433"
    ],
    "name:ceb_x_preferred":[
        "Venusberg"
    ],
    "name:deu_x_preferred":[
        "Venusberg"
    ],
    "name:est_x_preferred":[
        "Venusberg"
    ],
    "name:fra_x_preferred":[
        "Venusberg"
    ],
    "name:ita_x_preferred":[
        "Venusberg"
    ],
    "name:nld_x_preferred":[
        "Venusberg"
    ],
    "name:swe_x_preferred":[
        "Venusberg"
    ],
    "wof:name":"Venusberg",
    "wof:placetype":"locality"
},
  "geometry": {"coordinates":[4.84892,51.03197],"type":"Point"}
}