{
  "type": "Feature",
  "properties": {
    "gn:country":"BE",
    "gn:fcode":"PPL",
    "gn:population":0,
    "iso:country":"BE",
    "name:cat_x_preferred":[
        "Haine-Saint-Paul"
    ],
    "name:eng_x_preferred":[
        "Haine-Saint-Paul"
    ],
    "name:fra_x_preferred":[
        "Haine-Saint-Paul"
    ],
    "name:gle_x_preferred":[
        "Haine-Saint-Paul"
    ],
    "name:hun_x_preferred":[
        "Haine-Saint-Paul"
    ],
    "name:nld_x_preferred":[
        "Haine-Saint-Paul"
    ],
    "name:wln_x_preferred":[
        "Inne-Sint-P\u00e5"
    ],
    "qs_pg:aaroncc":"BE",
    "qs_pg:gn_country":"BE",
    "qs_pg:gn_fcode":"PPL",
    "qs_pg:gn_pop":0,
    "qs_pg:name":"Haine-St.-Paul",
    "qs_pg:name_adm0":"Belgique",
    "qs_pg:name_adm1":"Hainaut",
    "qs_pg:photos_9r":0,
    "qs_pg:photos_sr":0,
    "qs_pg:pop_sr":0,
    "qs_pg:qs_pg_placetype":"locality",
    "qs_pg:qs_pg_placetype_gp":"Town",
    "qs_pg:woe_adm0":23424757,
    "woe:adm0_id":23424757,
    "woe:name_adm0":"Belgique",
    "woe:name_adm1":"Hainaut",
    "woe:placetype":"Town",
    "wof:name":"Haine-St.-Paul",
    "wof:placetype":"locality"
},
  "geometry": {"coordinates":[4.1767,50.46186],"type":"Point"}
}