{
  "type": "Feature",
  "properties": {
    "gn:admin1_code":"WAL",
    "gn:admin2_code":"WBR",
    "gn:admin3_code":"25.0",
    "gn:admin4_code":"25023.0",
    "gn:asciiname":"Faux",
    "gn:country_code":"BE",
    "gn:dem":82,
    "gn:feature_class":"P",
    "gn:feature_code":"PPL",
    "gn:name":"Faux",
    "gn:population":0,
    "gn:timezone":"Europe/Brussels",
    "iso:country":"BE",
    "name:ceb_x_preferred":[
        "Faux"
    ],
    "name:deu_x_preferred":[
        "Faux"
    ],
    "name:fra_x_preferred":[
        "Faux"
    ],
    "name:ita_x_preferred":[
        "Faux"
    ],
    "name:nds_x_preferred":[
        "Faux"
    ],
    "name:nld_x_preferred":[
        "Faux"
    ],
    "name:pms_x_preferred":[
        "Faux"
    ],
    "name:pol_x_preferred":[
        "Faux"
    ],
    "name:por_x_preferred":[
        "Faux"
    ],
    "name:slk_x_preferred":[
        "Faux"
    ],
    "name:spa_x_preferred":[
        "Faux"
    ],
    "name:sqi_x_preferred":[
        "Faux"
    ],
    "name:swe_x_preferred":[
        "Faux"
    ],
    "wof:name":"Faux",
    "wof:placetype":"locality"
},
  "geometry": {"coordinates":[4.54671,50.62088],"type":"Point"}
}