{
  "type": "Feature",
  "properties": {
    "gn:admin1_code":"WAL",
    "gn:admin2_code":"WLG",
    "gn:admin3_code":"64.0",
    "gn:admin4_code":"64034.0",
    "gn:asciiname":"Le Perroquet",
    "gn:country_code":"BE",
    "gn:dem":139,
    "gn:feature_class":"P",
    "gn:feature_code":"PPL",
    "gn:name":"Le Perroquet",
    "gn:population":0,
    "gn:timezone":"Europe/Brussels",
    "iso:country":"BE",
    "wof:name":"Le Perroquet",
    "wof:placetype":"locality"
},
  "geometry": {"coordinates":[5.08333,50.65],"type":"Point"}
}