{
  "type": "Feature",
  "properties": {
    "gn:admin1_code":"VLG",
    "gn:admin2_code":"VLI",
    "gn:admin3_code":"72.0",
    "gn:admin4_code":"72040.0",
    "gn:asciiname":"Plokrooi",
    "gn:country_code":"BE",
    "gn:dem":73,
    "gn:feature_class":"P",
    "gn:feature_code":"PPL",
    "gn:name":"Plokrooi",
    "gn:population":0,
    "gn:timezone":"Europe/Brussels",
    "iso:country":"BE",
    "name:und_x_variant":[
        "Plockroy",
        "Plokroi",
        "Plockroij",
        "Plokrooi"
    ],
    "wof:name":"Plokrooi",
    "wof:placetype":"locality"
},
  "geometry": {"coordinates":[5.52627,51.07523],"type":"Point"}
}