{
  "type": "Feature",
  "properties": {
    "gn:admin1_code":"VLG",
    "gn:admin2_code":"VOV",
    "gn:admin3_code":"45.0",
    "gn:admin4_code":"45017.0",
    "gn:asciiname":"Vaddenhoek",
    "gn:country_code":"BE",
    "gn:dem":34,
    "gn:feature_class":"P",
    "gn:feature_code":"PPL",
    "gn:name":"Vaddenhoek",
    "gn:population":0,
    "gn:timezone":"Europe/Brussels",
    "iso:country":"BE",
    "wof:name":"Vaddenhoek",
    "wof:placetype":"locality"
},
  "geometry": {"coordinates":[3.55535,50.88482],"type":"Point"}
}