{
  "type": "Feature",
  "properties": {
    "gn:admin1_code":"VLG",
    "gn:admin2_code":"VWV",
    "gn:admin3_code":"32.0",
    "gn:admin4_code":"32011.0",
    "gn:asciiname":"Ruidenberg",
    "gn:country_code":"BE",
    "gn:dem":33,
    "gn:feature_class":"P",
    "gn:feature_code":"PPL",
    "gn:name":"Ruidenberg",
    "gn:population":0,
    "gn:timezone":"Europe/Brussels",
    "iso:country":"BE",
    "wof:name":"Ruidenberg",
    "wof:placetype":"locality"
},
  "geometry": {"coordinates":[3.01006,51.06838],"type":"Point"}
}