{
  "type": "Feature",
  "properties": {
    "gn:admin1_code":"VLG",
    "gn:admin2_code":"VWV",
    "gn:admin3_code":"33.0",
    "gn:admin4_code":"33037.0",
    "gn:asciiname":"Reutel",
    "gn:cc2":"BE",
    "gn:country_code":"BE",
    "gn:dem":49,
    "gn:feature_class":"P",
    "gn:feature_code":"PPL",
    "gn:name":"Reutel",
    "gn:population":0,
    "gn:timezone":"Europe/Brussels",
    "iso:country":"BE",
    "name:und_x_variant":[
        "Reutelhoek"
    ],
    "wof:name":"Reutel",
    "wof:placetype":"locality"
},
  "geometry": {"coordinates":[3.0039,50.84985],"type":"Point"}
}