{
  "type": "Feature",
  "properties": {
    "gn:admin1_code":"WAL",
    "gn:admin2_code":"WHT",
    "gn:admin3_code":"57.0",
    "gn:admin4_code":"57081.0",
    "gn:asciiname":"Chaos",
    "gn:country_code":"BE",
    "gn:dem":27,
    "gn:feature_class":"P",
    "gn:feature_code":"PPL",
    "gn:name":"Chaos",
    "gn:population":0,
    "gn:timezone":"Europe/Brussels",
    "iso:country":"BE",
    "name:ara_x_preferred":[
        "\u0643\u0627\u0648\u0633"
    ],
    "name:ceb_x_preferred":[
        "Chaos"
    ],
    "name:ces_x_preferred":[
        "Chaos"
    ],
    "name:deu_x_preferred":[
        "Chaos"
    ],
    "name:ell_x_preferred":[
        "\u03a7\u03ac\u03bf\u03c2"
    ],
    "name:fas_x_preferred":[
        "\u0622\u0634\u0648\u0628"
    ],
    "name:fin_x_preferred":[
        "Chaos"
    ],
    "name:fra_x_preferred":[
        "Chaos"
    ],
    "name:glg_x_preferred":[
        "Chaos"
    ],
    "name:heb_x_preferred":[
        "\u05db\u05d0\u05d5\u05e1"
    ],
    "name:hye_x_preferred":[
        "\u0554\u0561\u0578\u057d"
    ],
    "name:ita_x_preferred":[
        "Chaos"
    ],
    "name:jpn_x_preferred":[
        "\u30ab\u30aa\u30b9"
    ],
    "name:kor_x_preferred":[
        "\uce74\uc624\uc2a4"
    ],
    "name:nld_x_preferred":[
        "Chaos"
    ],
    "name:pol_x_preferred":[
        "Chaos"
    ],
    "name:rus_x_preferred":[
        "Chaos"
    ],
    "name:sco_x_preferred":[
        "Chaos"
    ],
    "name:slk_x_preferred":[
        "Chaos"
    ],
    "name:spa_x_preferred":[
        "Chaos"
    ],
    "wof:name":"Chaos",
    "wof:placetype":"locality"
},
  "geometry": {"coordinates":[3.25079,50.65078],"type":"Point"}
}