{
  "type": "Feature",
  "properties": {
    "gn:admin1_code":"VLG",
    "gn:admin2_code":"VWV",
    "gn:asciiname":"Malcense",
    "gn:country_code":"BE",
    "gn:dem":50,
    "gn:feature_class":"P",
    "gn:feature_code":"PPL",
    "gn:name":"Malcense",
    "gn:population":0,
    "gn:timezone":"Europe/Brussels",
    "iso:country":"BE",
    "wof:name":"Malcense",
    "wof:placetype":"locality"
},
  "geometry": {"coordinates":[3.25,50.73333],"type":"Point"}
}