{
  "type": "Feature",
  "properties": {
    "gn:admin1_code":"WAL",
    "gn:admin2_code":"WLX",
    "gn:admin3_code":"83.0",
    "gn:admin4_code":"83049.0",
    "gn:asciiname":"Tultay Ramont",
    "gn:country_code":"BE",
    "gn:dem":387,
    "gn:feature_class":"P",
    "gn:feature_code":"PPL",
    "gn:name":"Tultay Ramont",
    "gn:population":0,
    "gn:timezone":"Europe/Brussels",
    "iso:country":"BE",
    "name:und_x_variant":[
        "Ramont",
        "Tultay Ramont"
    ],
    "wof:name":"Tultay Ramont",
    "wof:placetype":"locality"
},
  "geometry": {"coordinates":[5.50778,50.09066],"type":"Point"}
}