{
  "type": "Feature",
  "properties": {
    "gn:admin1_code":"VLG",
    "gn:admin2_code":"VOV",
    "gn:admin3_code":"45.0",
    "gn:admin4_code":"45059.0",
    "gn:asciiname":"Den Hul",
    "gn:country_code":"BE",
    "gn:dem":103,
    "gn:feature_class":"P",
    "gn:feature_code":"PPL",
    "gn:name":"Den Hul",
    "gn:population":0,
    "gn:timezone":"Europe/Brussels",
    "iso:country":"BE",
    "name:und_x_variant":[
        "Hul",
        "Den Hul"
    ],
    "wof:name":"Den Hul",
    "wof:placetype":"locality"
},
  "geometry": {"coordinates":[3.71968,50.79807],"type":"Point"}
}