{
  "type": "Feature",
  "properties": {
    "gn:admin1_code":"WAL",
    "gn:admin2_code":"WLG",
    "gn:admin3_code":"63.0",
    "gn:admin4_code":"63087.0",
    "gn:asciiname":"Gruefflingen",
    "gn:country_code":"BE",
    "gn:dem":476,
    "gn:feature_class":"P",
    "gn:feature_code":"PPL",
    "gn:name":"Gr\u00fcfflingen",
    "gn:population":0,
    "gn:timezone":"Europe/Brussels",
    "iso:country":"BE",
    "name:und_x_variant":[
        "Grufflange",
        "Gruflange",
        "Gr\u00fcfflingen"
    ],
    "wof:name":"Gruefflingen",
    "wof:placetype":"locality"
},
  "geometry": {"coordinates":[6.08889,50.22444],"type":"Point"}
}