{
  "type": "Feature",
  "properties": {
    "iso:country":"BE",
    "name:ceb_x_preferred":[
        "Weelde Military"
    ],
    "name:eng_x_preferred":[
        "Weelde Air Base"
    ],
    "name:eng_x_variant":[
        "EBWE"
    ],
    "name:fas_x_preferred":[
        "\u067e\u0627\u06cc\u06af\u0627\u0647 \u0647\u0648\u0627\u06cc\u06cc \u0648\u06cc\u0644\u062f\u0647"
    ],
    "name:fra_x_preferred":[
        "Base a\u00e9rienne de Weelde"
    ],
    "name:jpn_x_preferred":[
        "\u30a6\u30a7\u30fc\u30eb\u30c7\u7a7a\u8ecd\u57fa\u5730"
    ],
    "name:msa_x_preferred":[
        "Pengkalan Udara Weelde"
    ],
    "name:nld_x_preferred":[
        "Vliegveld Weelde"
    ],
    "name:swe_x_preferred":[
        "Weelde Military"
    ],
    "name:tgk_x_preferred":[
        "\u041f\u043e\u0439\u0433\u043e\u04b3\u0438 \u04b3\u0430\u0432\u043e\u0438\u0438 \u0412\u0438\u043b\u0434\u0435"
    ],
    "name:tgk_x_variant":[
        "\u041f\u043e\u0439\u0433\u043e\u04b3\u0438 \u04b3\u0430\u0432\u043e\u04e3 \u0432\u0438\u043b\u0434\u04b3"
    ],
    "name:zho_x_preferred":[
        "\u97e6\u5c14\u5fb7\u7a7a\u519b\u57fa\u5730"
    ],
    "oa:elevation_ft":"105",
    "oa:type":"small_airport",
    "wd:wordcount":113,
    "woe:hierarchy":{
        "country_id":23424757,
        "county_id":12591772,
        "localadmin_id":12602509,
        "planet_id":1,
        "state_id":7153308
    },
    "wof:name":"Weelde Airport",
    "wof:placetype":"campus"
},
  "geometry": {"coordinates":[4.964747,51.396461],"type":"Point"}
}