{
  "type": "Feature",
  "properties": {
    "gn:gn_country":"BE",
    "gn:gn_fcode":"PPL",
    "gn:gn_pop":0,
    "iso:country":"BE",
    "name:deu_x_preferred":[
        "Goyet"
    ],
    "name:eng_x_preferred":[
        "Goyet"
    ],
    "name:fra_x_preferred":[
        "Goyet"
    ],
    "name:nld_x_preferred":[
        "Goyet"
    ],
    "name:por_x_preferred":[
        "Goyet"
    ],
    "qs_pg:aaroncc":"BE",
    "qs_pg:gn_country":"BE",
    "qs_pg:gn_fcode":"PPL",
    "qs_pg:gn_pop":0,
    "qs_pg:name":"Goyet",
    "qs_pg:name_adm0":"Belgique",
    "qs_pg:name_adm1":"Namur",
    "qs_pg:photos":13,
    "qs_pg:photos_1k":3,
    "qs_pg:photos_9k":1,
    "qs_pg:photos_9r":1,
    "qs_pg:photos_all":13,
    "qs_pg:photos_sr":1,
    "qs_pg:pop_sr":0,
    "qs_pg:qs_pg_placetype":"locality",
    "qs_pg:qs_pg_placetype_gp":"Town",
    "qs_pg:woe_adm0":23424757,
    "woe:adm0_id":23424757,
    "woe:name_adm0":"Belgique",
    "woe:name_adm1":"Namur",
    "woe:placetype":"Town",
    "wof:name":"Goyet",
    "wof:placetype":"locality"
},
  "geometry": {"coordinates":[4.66667,50.48333],"type":"Point"}
}