{
  "type": "Feature",
  "properties": {
    "gn:admin1_code":"VLG",
    "gn:admin2_code":"VLI",
    "gn:admin3_code":"72.0",
    "gn:admin4_code":"72030.0",
    "gn:asciiname":"Houterstraat",
    "gn:country_code":"BE",
    "gn:dem":64,
    "gn:feature_class":"P",
    "gn:feature_code":"PPL",
    "gn:name":"Houterstraat",
    "gn:population":0,
    "gn:timezone":"Europe/Brussels",
    "iso:country":"BE",
    "name:und_x_variant":[
        "Houtestraat",
        "Houterstraat"
    ],
    "wof:name":"Houterstraat",
    "wof:placetype":"locality"
},
  "geometry": {"coordinates":[5.41197,51.11885],"type":"Point"}
}