{
  "type": "Feature",
  "properties": {
    "gn:admin1_code":"WAL",
    "gn:admin2_code":"WNA",
    "gn:admin3_code":"91.0",
    "gn:admin4_code":"91142.0",
    "gn:asciiname":"Blaimont",
    "gn:country_code":"BE",
    "gn:dem":236,
    "gn:feature_class":"P",
    "gn:feature_code":"PPL",
    "gn:name":"Blaimont",
    "gn:population":0,
    "gn:timezone":"Europe/Brussels",
    "iso:country":"BE",
    "name:und_x_variant":[
        "Hasti\u00e8re (Blaimont)"
    ],
    "wof:name":"Blaimont",
    "wof:placetype":"locality"
},
  "geometry": {"coordinates":[4.84231,50.19231],"type":"Point"}
}