{
  "type": "Feature",
  "properties": {
    "gn:admin1_code":"VLG",
    "gn:admin2_code":"VBR",
    "gn:admin3_code":"24.0",
    "gn:admin4_code":"24011.0",
    "gn:asciiname":"Merrbeek",
    "gn:country_code":"BE",
    "gn:dem":48,
    "gn:feature_class":"P",
    "gn:feature_code":"PPL",
    "gn:name":"Merrbeek",
    "gn:population":0,
    "gn:timezone":"Europe/Brussels",
    "iso:country":"BE",
    "name:und_x_variant":[
        "Merrebeek",
        "Merbeek",
        "Merrbeek"
    ],
    "wof:name":"Merrbeek",
    "wof:placetype":"locality"
},
  "geometry": {"coordinates":[4.76099,50.8396],"type":"Point"}
}