{
  "type": "Feature",
  "properties": {
    "gn:admin1_code":"WAL",
    "gn:admin2_code":"WLX",
    "gn:admin3_code":"83.0",
    "gn:admin4_code":"83055.0",
    "gn:asciiname":"Mont Derrieux",
    "gn:country_code":"BE",
    "gn:dem":409,
    "gn:feature_class":"P",
    "gn:feature_code":"PPL",
    "gn:name":"Mont Derrieux",
    "gn:population":0,
    "gn:timezone":"Europe/Brussels",
    "iso:country":"BE",
    "name:und_x_variant":[
        "Maison Derrieux",
        "Mont Derrieux"
    ],
    "wof:name":"Mont Derrieux",
    "wof:placetype":"locality"
},
  "geometry": {"coordinates":[5.65,50.31667],"type":"Point"}
}