{
  "type": "Feature",
  "properties": {
    "gn:admin1_code":"VLG",
    "gn:admin2_code":"VWV",
    "gn:admin3_code":"34.0",
    "gn:admin4_code":"34002.0",
    "gn:asciiname":"Bergstraat",
    "gn:country_code":"BE",
    "gn:dem":36,
    "gn:feature_class":"P",
    "gn:feature_code":"PPL",
    "gn:name":"Bergstraat",
    "gn:population":0,
    "gn:timezone":"Europe/Brussels",
    "iso:country":"BE",
    "name:und_x_variant":[
        "Bergstraet",
        "Bergstraat"
    ],
    "wof:name":"Bergstraat",
    "wof:placetype":"locality"
},
  "geometry": {"coordinates":[3.46667,50.83333],"type":"Point"}
}