{
  "type": "Feature",
  "properties": {
    "gn:admin1_code":"WAL",
    "gn:admin2_code":"WHT",
    "gn:admin3_code":"57.0",
    "gn:admin4_code":"57072.0",
    "gn:asciiname":"Petit Rumes",
    "gn:country_code":"BE",
    "gn:dem":45,
    "gn:feature_class":"P",
    "gn:feature_code":"PPL",
    "gn:name":"Petit Rumes",
    "gn:population":0,
    "gn:timezone":"Europe/Brussels",
    "iso:country":"BE",
    "wof:name":"Petit Rumes",
    "wof:placetype":"locality"
},
  "geometry": {"coordinates":[3.33874,50.53995],"type":"Point"}
}