{
  "type": "Feature",
  "properties": {
    "gn:admin1_code":"WAL",
    "gn:admin2_code":"WHT",
    "gn:admin3_code":"57.0",
    "gn:admin4_code":"57018.0",
    "gn:asciiname":"Farinette",
    "gn:country_code":"BE",
    "gn:dem":27,
    "gn:feature_class":"P",
    "gn:feature_code":"PPL",
    "gn:name":"Farinette",
    "gn:population":0,
    "gn:timezone":"Europe/Brussels",
    "iso:country":"BE",
    "wof:name":"Farinette",
    "wof:placetype":"locality"
},
  "geometry": {"coordinates":[3.43359,50.67751],"type":"Point"}
}