{
  "type": "Feature",
  "properties": {
    "gn:admin1_code":"VLG",
    "gn:admin2_code":"VOV",
    "gn:admin3_code":"44.0",
    "gn:admin4_code":"44029.0",
    "gn:asciiname":"Konijn",
    "gn:country_code":"BE",
    "gn:dem":13,
    "gn:feature_class":"P",
    "gn:feature_code":"PPL",
    "gn:name":"Konijn",
    "gn:population":0,
    "gn:timezone":"Europe/Brussels",
    "iso:country":"BE",
    "wof:name":"Konijn",
    "wof:placetype":"locality"
},
  "geometry": {"coordinates":[3.50545,51.13137],"type":"Point"}
}