{
  "type": "Feature",
  "properties": {
    "gn:admin1_code":"VLG",
    "gn:admin2_code":"VAN",
    "gn:admin3_code":"12.0",
    "gn:admin4_code":"12030.0",
    "gn:asciiname":"Moerhoek",
    "gn:country_code":"BE",
    "gn:dem":0,
    "gn:feature_class":"P",
    "gn:feature_code":"PPL",
    "gn:name":"Moerhoek",
    "gn:population":0,
    "gn:timezone":"Europe/Brussels",
    "iso:country":"BE",
    "wof:name":"Moerhoek",
    "wof:placetype":"locality"
},
  "geometry": {"coordinates":[4.33333,51.08333],"type":"Point"}
}