{
  "type": "Feature",
  "properties": {
    "gn:admin1_code":"VLG",
    "gn:admin2_code":"VOV",
    "gn:admin3_code":"44.0",
    "gn:admin4_code":"44072.0",
    "gn:asciiname":"Kere",
    "gn:country_code":"BE",
    "gn:dem":6,
    "gn:feature_class":"P",
    "gn:feature_code":"PPL",
    "gn:name":"Kere",
    "gn:population":0,
    "gn:timezone":"Europe/Brussels",
    "iso:country":"BE",
    "name:und_x_variant":[
        "Keere",
        "Kere"
    ],
    "wof:name":"Kere",
    "wof:placetype":"locality"
},
  "geometry": {"coordinates":[3.58333,51.15],"type":"Point"}
}