{
  "type": "Feature",
  "properties": {
    "gn:gn_country":"BE",
    "gn:gn_fcode":"PPL",
    "gn:gn_pop":0,
    "iso:country":"BE",
    "name:deu_x_preferred":[
        "Kategorie:Melsbroek"
    ],
    "name:eng_x_preferred":[
        "Melsbroek"
    ],
    "name:fra_x_preferred":[
        "Melsbroek"
    ],
    "name:jpn_x_preferred":[
        "\u30e1\u30eb\u30b9\u30d6\u30ed\u30fc\u30af"
    ],
    "name:nld_x_preferred":[
        "Melsbroek"
    ],
    "name:unk_x_variant":[
        "Melsbroeck"
    ],
    "qs_pg:aaroncc":"BE",
    "qs_pg:gn_country":"BE",
    "qs_pg:gn_fcode":"PPL",
    "qs_pg:gn_pop":0,
    "qs_pg:name":"Melsbroek",
    "qs_pg:name_adm0":"Belgique",
    "qs_pg:name_adm1":"Vlaams Brabant",
    "qs_pg:photos":307,
    "qs_pg:photos_1k":62,
    "qs_pg:photos_9k":1,
    "qs_pg:photos_9r":5,
    "qs_pg:photos_all":307,
    "qs_pg:photos_sr":5,
    "qs_pg:pop_sr":0,
    "qs_pg:qs_pg_placetype":"locality",
    "qs_pg:qs_pg_placetype_gp":"Town",
    "qs_pg:woe_adm0":23424757,
    "woe:adm0_id":23424757,
    "woe:name_adm0":"Belgique",
    "woe:name_adm1":"Vlaams Brabant",
    "woe:placetype":"Town",
    "wof:name":"Melsbroek",
    "wof:placetype":"locality"
},
  "geometry": {"coordinates":[4.47985,50.91559],"type":"Point"}
}