{
  "type": "Feature",
  "properties": {
    "gn:admin1_code":"WAL",
    "gn:admin2_code":"WLG",
    "gn:admin3_code":"62.0",
    "gn:admin4_code":"62100.0",
    "gn:asciiname":"Menage",
    "gn:country_code":"BE",
    "gn:dem":210,
    "gn:feature_class":"P",
    "gn:feature_code":"PPL",
    "gn:name":"M\u00e9nage",
    "gn:population":0,
    "gn:timezone":"Europe/Brussels",
    "iso:country":"BE",
    "wof:name":"Menage",
    "wof:placetype":"locality"
},
  "geometry": {"coordinates":[5.60867,50.5118],"type":"Point"}
}