{
  "type": "Feature",
  "properties": {
    "gn:admin1_code":"VLG",
    "gn:admin2_code":"VOV",
    "gn:admin3_code":"43.0",
    "gn:admin4_code":"43002.0",
    "gn:asciiname":"Nieuwburg",
    "gn:country_code":"BE",
    "gn:dem":2,
    "gn:feature_class":"P",
    "gn:feature_code":"PPL",
    "gn:name":"Nieuwburg",
    "gn:population":0,
    "gn:timezone":"Europe/Brussels",
    "iso:country":"BE",
    "wof:name":"Nieuwburg",
    "wof:placetype":"locality"
},
  "geometry": {"coordinates":[3.72146,51.21187000000001],"type":"Point"}
}