{
  "type": "Feature",
  "properties": {
    "gn:admin1_code":"VLG",
    "gn:admin2_code":"VOV",
    "gn:admin3_code":"45.0",
    "gn:admin4_code":"45059.0",
    "gn:asciiname":"Molenhoek",
    "gn:country_code":"BE",
    "gn:dem":46,
    "gn:feature_class":"P",
    "gn:feature_code":"PPL",
    "gn:name":"Molenhoek",
    "gn:population":0,
    "gn:timezone":"Europe/Brussels",
    "iso:country":"BE",
    "wof:name":"Molenhoek",
    "wof:placetype":"locality"
},
  "geometry": {"coordinates":[3.76976,50.81261],"type":"Point"}
}