{
  "type": "Feature",
  "properties": {
    "gn:country":"BE",
    "gn:fcode":"PPL",
    "gn:population":0,
    "iso:country":"BE",
    "name:cat_x_preferred":[
        "Mons-lez-Li\u00e8ge"
    ],
    "name:ceb_x_preferred":[
        "Mons-lez-Li\u00e8ge"
    ],
    "name:eng_x_preferred":[
        "Mons-lez-Li\u00e8ge"
    ],
    "name:fra_x_preferred":[
        "Mons-lez-Li\u00e8ge"
    ],
    "name:gle_x_preferred":[
        "Mons-lez-Li\u00e8ge"
    ],
    "name:nld_x_preferred":[
        "Mons-lez-Li\u00e8ge"
    ],
    "name:swe_x_preferred":[
        "Mons-lez-Li\u00e8ge"
    ],
    "name:und_x_variant":[
        "Fl\u00e9malle (Mons-lez-Li\u00e8ge)"
    ],
    "name:zho_x_preferred":[
        "\u8499\u65af\u83b1\u5217\u65e5"
    ],
    "qs_pg:aaroncc":"BE",
    "qs_pg:gn_country":"BE",
    "qs_pg:gn_fcode":"PPL",
    "qs_pg:gn_pop":0,
    "qs_pg:name":"Mons-lez-Liege",
    "qs_pg:name_adm0":"Belgique",
    "qs_pg:name_adm1":"Li\u00e8ge",
    "qs_pg:photos":138,
    "qs_pg:photos_1k":28,
    "qs_pg:photos_9k":1,
    "qs_pg:photos_9r":3,
    "qs_pg:photos_all":138,
    "qs_pg:photos_sr":3,
    "qs_pg:pop_sr":0,
    "qs_pg:qs_pg_placetype":"locality",
    "qs_pg:qs_pg_placetype_gp":"Town",
    "qs_pg:woe_adm0":23424757,
    "woe:adm0_id":23424757,
    "woe:name_adm0":"Belgique",
    "woe:name_adm1":"Li\u00e8ge",
    "woe:placetype":"Town",
    "wof:name":"Mons-lez-Liege",
    "wof:placetype":"locality"
},
  "geometry": {"coordinates":[5.45626,50.62306],"type":"Point"}
}