{
  "type": "Feature",
  "properties": {
    "gn:admin1_code":"WAL",
    "gn:admin2_code":"WLG",
    "gn:admin3_code":"62.0",
    "gn:admin4_code":"62120.0",
    "gn:asciiname":"Oneux",
    "gn:country_code":"BE",
    "gn:dem":108,
    "gn:feature_class":"P",
    "gn:feature_code":"PPL",
    "gn:name":"Oneux",
    "gn:population":0,
    "gn:timezone":"Europe/Brussels",
    "iso:country":"BE",
    "name:und_x_variant":[
        "Les Oneux",
        "Oneux"
    ],
    "wof:name":"Oneux",
    "wof:placetype":"locality"
},
  "geometry": {"coordinates":[5.45802,50.60335],"type":"Point"}
}