{
  "type": "Feature",
  "properties": {
    "gn:admin1_code":"WAL",
    "gn:admin2_code":"WHT",
    "gn:admin3_code":"51.0",
    "gn:admin4_code":"51065.0",
    "gn:asciiname":"Pire",
    "gn:country_code":"BE",
    "gn:dem":48,
    "gn:feature_class":"P",
    "gn:feature_code":"PPL",
    "gn:name":"Pire",
    "gn:population":0,
    "gn:timezone":"Europe/Brussels",
    "iso:country":"BE",
    "name:bos_x_preferred":[
        "Pire"
    ],
    "name:ceb_x_preferred":[
        "Pire"
    ],
    "name:fra_x_preferred":[
        "Pire"
    ],
    "name:hrv_x_preferred":[
        "Pire"
    ],
    "name:ita_x_preferred":[
        "Pire"
    ],
    "name:por_x_preferred":[
        "Pire"
    ],
    "name:swe_x_preferred":[
        "Pire"
    ],
    "name:tur_x_preferred":[
        "Pire"
    ],
    "wof:name":"Pire",
    "wof:placetype":"locality"
},
  "geometry": {"coordinates":[3.56667,50.65],"type":"Point"}
}