{
  "type": "Feature",
  "properties": {
    "gn:admin1_code":"WAL",
    "gn:admin2_code":"WLG",
    "gn:admin3_code":"63.0",
    "gn:admin4_code":"63045.0",
    "gn:asciiname":"Jevigne",
    "gn:country_code":"BE",
    "gn:dem":425,
    "gn:feature_class":"P",
    "gn:feature_code":"PPL",
    "gn:name":"J\u00e9vigne",
    "gn:population":0,
    "gn:timezone":"Europe/Brussels",
    "iso:country":"BE",
    "wof:name":"Jevigne",
    "wof:placetype":"locality"
},
  "geometry": {"coordinates":[5.76753,50.29493],"type":"Point"}
}