{
  "type": "Feature",
  "properties": {
    "gn:admin1_code":"WAL",
    "gn:admin2_code":"WHT",
    "gn:admin3_code":"57.0",
    "gn:admin4_code":"57094.0",
    "gn:asciiname":"Andricourt",
    "gn:country_code":"BE",
    "gn:dem":42,
    "gn:feature_class":"P",
    "gn:feature_code":"PPL",
    "gn:name":"Andricourt",
    "gn:population":0,
    "gn:timezone":"Europe/Brussels",
    "iso:country":"BE",
    "wof:name":"Andricourt",
    "wof:placetype":"locality"
},
  "geometry": {"coordinates":[3.68411,50.60716],"type":"Point"}
}