{
  "type": "Feature",
  "properties": {
    "gn:admin1_code":"VLG",
    "gn:admin2_code":"VLI",
    "gn:admin3_code":"72.0",
    "gn:admin4_code":"72003.0",
    "gn:asciiname":"Neerkrijel",
    "gn:country_code":"BE",
    "gn:dem":38,
    "gn:feature_class":"P",
    "gn:feature_code":"PPL",
    "gn:name":"Neerkrijel",
    "gn:population":0,
    "gn:timezone":"Europe/Brussels",
    "iso:country":"BE",
    "name:und_x_variant":[
        "Neerkreyel",
        "Neerkreijel",
        "Neerkreiel",
        "Neerkrijel"
    ],
    "wof:name":"Neerkrijel",
    "wof:placetype":"locality"
},
  "geometry": {"coordinates":[5.59831,51.18462],"type":"Point"}
}