{
  "type": "Feature",
  "properties": {
    "gn:admin1_code":"WAL",
    "gn:admin2_code":"WLX",
    "gn:admin3_code":"84.0",
    "gn:admin4_code":"84059.0",
    "gn:asciiname":"Au Cheny du Mont",
    "gn:country_code":"BE",
    "gn:dem":436,
    "gn:feature_class":"P",
    "gn:feature_code":"PPL",
    "gn:name":"Au Cheny du Mont",
    "gn:population":0,
    "gn:timezone":"Europe/Brussels",
    "iso:country":"BE",
    "wof:name":"Au Cheny du Mont",
    "wof:placetype":"locality"
},
  "geometry": {"coordinates":[5.29685,50.03948],"type":"Point"}
}