{
  "type": "Feature",
  "properties": {
    "gn:admin1_code":"WAL",
    "gn:admin2_code":"WNA",
    "gn:admin3_code":"91.0",
    "gn:admin4_code":"91013.0",
    "gn:asciiname":"Gifromont",
    "gn:country_code":"BE",
    "gn:dem":247,
    "gn:feature_class":"P",
    "gn:feature_code":"PPL",
    "gn:name":"Gifromont",
    "gn:population":0,
    "gn:timezone":"Europe/Brussels",
    "iso:country":"BE",
    "wof:name":"Gifromont",
    "wof:placetype":"locality"
},
  "geometry": {"coordinates":[5.03333,50.08333],"type":"Point"}
}