{
  "type": "Feature",
  "properties": {
    "iso:country":"BE",
    "name:cat_x_preferred":[
        "M\u00e9ry"
    ],
    "name:ceb_x_preferred":[
        "M\u00e9ry"
    ],
    "name:deu_x_preferred":[
        "M\u00e9ry"
    ],
    "name:eus_x_preferred":[
        "M\u00e9ry"
    ],
    "name:fra_x_colloquial":[
        "Mery"
    ],
    "name:fra_x_preferred":[
        "M\u00e9ry"
    ],
    "name:hun_x_preferred":[
        "M\u00e9ry"
    ],
    "name:ita_x_preferred":[
        "M\u00e9ry"
    ],
    "name:lat_x_preferred":[
        "M\u00e9ry"
    ],
    "name:lat_x_variant":[
        "Meris"
    ],
    "name:lmo_x_preferred":[
        "M\u00e9ry"
    ],
    "name:msa_x_preferred":[
        "M\u00e9ry"
    ],
    "name:nld_x_preferred":[
        "M\u00e9ry"
    ],
    "name:oci_x_preferred":[
        "M\u00e9ry"
    ],
    "name:pms_x_preferred":[
        "M\u00e9ry"
    ],
    "name:pol_x_preferred":[
        "M\u00e9ry"
    ],
    "name:por_x_preferred":[
        "M\u00e9ry"
    ],
    "name:ron_x_preferred":[
        "M\u00e9ry"
    ],
    "name:slk_x_preferred":[
        "M\u00e9ry"
    ],
    "name:spa_x_preferred":[
        "M\u00e9ry"
    ],
    "name:swe_x_preferred":[
        "M\u00e9ry"
    ],
    "name:ukr_x_preferred":[
        "\u041c\u0435\u0440\u0456"
    ],
    "name:unk_x_variant":[
        "M\u00e9ry"
    ],
    "name:uzb_x_preferred":[
        "M\u00e9ry"
    ],
    "name:vie_x_preferred":[
        "M\u00e9ry"
    ],
    "name:vol_x_preferred":[
        "M\u00e9ry"
    ],
    "name:war_x_preferred":[
        "M\u00e9ry"
    ],
    "qs:gn_adm0_cc":"BE",
    "qs:gn_fcode":"PPL",
    "qs:gn_local":2798637,
    "qs:gn_nam_loc":"Esneux, Li\u00e8ge, Li\u00e8ge, BE",
    "qs:gn_namadm1":"WAL",
    "qs:gn_name":"M\u00e9ry",
    "qs:local_max":113,
    "qs:local_sum":113,
    "qs:localhoods":1,
    "qs:name":"M\u00e9ry",
    "qs:name_adm0":"Belgique",
    "qs:name_adm1":"Li\u00e8ge",
    "qs:name_adm2":"Li\u00e8ge",
    "qs:name_lau":"Esneux",
    "qs:name_local":"Esneux",
    "qs:photo_max":19,
    "qs:photo_sum":113,
    "qs:placetype":"Suburb",
    "qs:quad_count":27,
    "qs:woe_adm0":23424757,
    "qs:woe_adm1":7153300,
    "qs:woe_adm2":12591793,
    "qs:woe_lau":12602502,
    "qs:woe_local":12602502,
    "qs:woe_ver":"7.10.0",
    "wof:lang":[
        "fre"
    ],
    "wof:name":"M\u00e9ry",
    "wof:placetype":"neighbourhood"
},
  "geometry": {"coordinates":[5.573787,50.54351],"type":"Point"}
}