{
  "type": "Feature",
  "properties": {
    "gn:admin1_code":"WAL",
    "gn:admin2_code":"WLG",
    "gn:admin3_code":"64.0",
    "gn:admin4_code":"64034.0",
    "gn:asciiname":"Petit-Hallet",
    "gn:country_code":"BE",
    "gn:dem":100,
    "gn:feature_class":"P",
    "gn:feature_code":"PPL",
    "gn:name":"Petit-Hallet",
    "gn:population":0,
    "gn:timezone":"Europe/Brussels",
    "iso:country":"BE",
    "wof:name":"Petit-Hallet",
    "wof:placetype":"locality"
},
  "geometry": {"coordinates":[5.0199,50.68762],"type":"Point"}
}