{
  "type": "Feature",
  "properties": {
    "gn:admin1_code":"WAL",
    "gn:admin2_code":"WLG",
    "gn:admin3_code":"61.0",
    "gn:admin4_code":"61003.0",
    "gn:asciiname":"Ombret",
    "gn:country_code":"BE",
    "gn:dem":72,
    "gn:feature_class":"P",
    "gn:feature_code":"PPL",
    "gn:name":"Ombret",
    "gn:population":0,
    "gn:timezone":"Europe/Brussels",
    "iso:country":"BE",
    "name:und_x_variant":[
        "Amay (Ombret)"
    ],
    "wof:name":"Ombret",
    "wof:placetype":"locality"
},
  "geometry": {"coordinates":[5.33378,50.54224],"type":"Point"}
}