{
  "type": "Feature",
  "properties": {
    "gn:admin1_code":"WAL",
    "gn:admin2_code":"WLG",
    "gn:admin3_code":"62.0",
    "gn:admin4_code":"62122.0",
    "gn:asciiname":"Sous l'Abbaye",
    "gn:country_code":"BE",
    "gn:dem":261,
    "gn:feature_class":"P",
    "gn:feature_code":"PPL",
    "gn:name":"Sous l'Abbaye",
    "gn:population":0,
    "gn:timezone":"Europe/Brussels",
    "iso:country":"BE",
    "wof:name":"Sous l'Abbaye",
    "wof:placetype":"locality"
},
  "geometry": {"coordinates":[5.65569,50.56286],"type":"Point"}
}