{
  "type": "Feature",
  "properties": {
    "gn:admin1_code":"WAL",
    "gn:admin2_code":"WHT",
    "gn:admin3_code":"52.0",
    "gn:admin4_code":"52011.0",
    "gn:asciiname":"Trieu des Agneaux",
    "gn:country_code":"BE",
    "gn:dem":133,
    "gn:feature_class":"P",
    "gn:feature_code":"PPL",
    "gn:name":"Trieu des Agneaux",
    "gn:population":0,
    "gn:timezone":"Europe/Brussels",
    "iso:country":"BE",
    "name:und_x_variant":[
        "Trieu",
        "Trieu des Agneaux"
    ],
    "wof:name":"Trieu des Agneaux",
    "wof:placetype":"locality"
},
  "geometry": {"coordinates":[4.38333,50.45],"type":"Point"}
}