{
  "type": "Feature",
  "properties": {
    "gn:gn_country":"BE",
    "gn:gn_fcode":"PPL",
    "gn:gn_pop":0,
    "iso:country":"BE",
    "name:eng_x_preferred":[
        "Spontin"
    ],
    "name:est_x_preferred":[
        "Spontin"
    ],
    "name:fra_x_preferred":[
        "Spontin"
    ],
    "name:ltz_x_preferred":[
        "Spontin"
    ],
    "name:nld_x_preferred":[
        "Spontin"
    ],
    "name:ron_x_preferred":[
        "Spontin"
    ],
    "name:unk_x_variant":[
        "Yvoir (Spontin)"
    ],
    "name:wln_x_preferred":[
        "Spontin"
    ],
    "qs_pg:aaroncc":"BE",
    "qs_pg:gn_country":"BE",
    "qs_pg:gn_fcode":"PPL",
    "qs_pg:gn_pop":0,
    "qs_pg:name":"Spontin",
    "qs_pg:name_adm0":"Belgique",
    "qs_pg:name_adm1":"Namur",
    "qs_pg:photos":357,
    "qs_pg:photos_1k":72,
    "qs_pg:photos_9k":2,
    "qs_pg:photos_9r":5,
    "qs_pg:photos_all":357,
    "qs_pg:photos_sr":6,
    "qs_pg:pop_sr":0,
    "qs_pg:qs_pg_placetype":"locality",
    "qs_pg:qs_pg_placetype_gp":"Town",
    "qs_pg:woe_adm0":23424757,
    "woe:adm0_id":23424757,
    "woe:name_adm0":"Belgique",
    "woe:name_adm1":"Namur",
    "woe:placetype":"Town",
    "wof:name":"Spontin",
    "wof:placetype":"locality"
},
  "geometry": {"coordinates":[5.0059,50.32256],"type":"Point"}
}