{
  "type": "Feature",
  "properties": {
    "gn:country":"BE",
    "gn:fcode":"PPL",
    "gn:population":0,
    "iso:country":"BE",
    "name:bul_x_preferred":[
        "\u041f\u043e\u043b\u0438\u043d\u043a\u0445\u043e\u0432\u0435"
    ],
    "name:cat_x_preferred":[
        "Pollinkhove"
    ],
    "name:ceb_x_preferred":[
        "Pollinkhove"
    ],
    "name:eng_x_preferred":[
        "Pollinkhove"
    ],
    "name:fra_x_preferred":[
        "Pollinkhove"
    ],
    "name:gle_x_preferred":[
        "Pollinkhove"
    ],
    "name:hun_x_preferred":[
        "Pollinkhove"
    ],
    "name:nld_x_preferred":[
        "Pollinkhove"
    ],
    "name:por_x_preferred":[
        "Pollinkhove"
    ],
    "name:swe_x_preferred":[
        "Pollinkhove"
    ],
    "name:und_x_variant":[
        "Pollinchove"
    ],
    "name:vls_x_preferred":[
        "Pollienkove"
    ],
    "name:zho_x_preferred":[
        "\u6ce2\u6797\u514b\u970d\u5f17"
    ],
    "qs_pg:aaroncc":"BE",
    "qs_pg:gn_country":"BE",
    "qs_pg:gn_fcode":"PPL",
    "qs_pg:gn_pop":0,
    "qs_pg:name":"Pollinkhove",
    "qs_pg:name_adm0":"Belgique",
    "qs_pg:name_adm1":"West-Vlaanderen",
    "qs_pg:photos":31,
    "qs_pg:photos_1k":6,
    "qs_pg:photos_9k":1,
    "qs_pg:photos_9r":2,
    "qs_pg:photos_all":31,
    "qs_pg:photos_sr":2,
    "qs_pg:pop_sr":0,
    "qs_pg:qs_pg_placetype":"locality",
    "qs_pg:qs_pg_placetype_gp":"Town",
    "qs_pg:woe_adm0":23424757,
    "woe:adm0_id":23424757,
    "woe:name_adm0":"Belgique",
    "woe:name_adm1":"West-Vlaanderen",
    "woe:placetype":"Town",
    "wof:name":"Pollinkhove",
    "wof:placetype":"locality"
},
  "geometry": {"coordinates":[2.7326,50.97118],"type":"Point"}
}