{
  "type": "Feature",
  "properties": {
    "gn:admin1_code":"VLG",
    "gn:admin2_code":"VOV",
    "gn:admin3_code":"43.0",
    "gn:admin4_code":"43010.0",
    "gn:asciiname":"Oosthoek",
    "gn:country_code":"BE",
    "gn:dem":2,
    "gn:feature_class":"P",
    "gn:feature_code":"PPL",
    "gn:name":"Oosthoek",
    "gn:population":0,
    "gn:timezone":"Europe/Brussels",
    "iso:country":"BE",
    "wof:name":"Oosthoek",
    "wof:placetype":"locality"
},
  "geometry": {"coordinates":[3.47475,51.2429],"type":"Point"}
}