{
  "type": "Feature",
  "properties": {
    "gn:country":"BE",
    "gn:fcode":"PPL",
    "gn:population":0,
    "iso:country":"BE",
    "name:eng_x_preferred":[
        "Beffe"
    ],
    "name:fra_x_preferred":[
        "Beffe"
    ],
    "name:gle_x_preferred":[
        "Beffe"
    ],
    "name:hun_x_preferred":[
        "Beffe"
    ],
    "name:ita_x_preferred":[
        "Beffe"
    ],
    "name:jpn_x_preferred":[
        "\u30d9\u30c3\u30d5\u30a7"
    ],
    "name:nld_x_preferred":[
        "Beffe"
    ],
    "name:wln_x_preferred":[
        "B\u00eafe"
    ],
    "qs_pg:aaroncc":"BE",
    "qs_pg:gn_country":"BE",
    "qs_pg:gn_fcode":"PPL",
    "qs_pg:gn_pop":0,
    "qs_pg:name":"Beffe",
    "qs_pg:name_adm0":"Belgique",
    "qs_pg:name_adm1":"Luxembourg",
    "qs_pg:photos":18,
    "qs_pg:photos_1k":4,
    "qs_pg:photos_9k":1,
    "qs_pg:photos_9r":1,
    "qs_pg:photos_all":18,
    "qs_pg:photos_sr":1,
    "qs_pg:pop_sr":0,
    "qs_pg:qs_pg_placetype":"locality",
    "qs_pg:qs_pg_placetype_gp":"Town",
    "qs_pg:woe_adm0":23424757,
    "woe:adm0_id":23424757,
    "woe:name_adm0":"Belgique",
    "woe:name_adm1":"Luxembourg",
    "woe:placetype":"Town",
    "wof:name":"Beffe",
    "wof:placetype":"locality"
},
  "geometry": {"coordinates":[5.5226,50.24649],"type":"Point"}
}