{
  "type": "Feature",
  "properties": {
    "gn:admin1_code":"VLG",
    "gn:admin2_code":"VAN",
    "gn:admin3_code":"12.0",
    "gn:admin4_code":"12005.0",
    "gn:asciiname":"Harent",
    "gn:country_code":"BE",
    "gn:dem":5,
    "gn:feature_class":"P",
    "gn:feature_code":"PPL",
    "gn:name":"Harent",
    "gn:population":0,
    "gn:timezone":"Europe/Brussels",
    "iso:country":"BE",
    "name:und_x_variant":[
        "Haarent",
        "Haerent",
        "Harent"
    ],
    "wof:name":"Harent",
    "wof:placetype":"locality"
},
  "geometry": {"coordinates":[4.57261,51.02333],"type":"Point"}
}