{
  "type": "Feature",
  "properties": {
    "gn:admin1_code":"WAL",
    "gn:admin2_code":"WLG",
    "gn:admin3_code":"61.0",
    "gn:admin4_code":"61048.0",
    "gn:asciiname":"Himbe",
    "gn:country_code":"BE",
    "gn:dem":271,
    "gn:feature_class":"P",
    "gn:feature_code":"PPL",
    "gn:name":"Himbe",
    "gn:population":0,
    "gn:timezone":"Europe/Brussels",
    "iso:country":"BE",
    "wof:name":"Himbe",
    "wof:placetype":"locality"
},
  "geometry": {"coordinates":[5.46732,50.41963],"type":"Point"}
}