{
  "type": "Feature",
  "properties": {
    "gn:admin1_code":"VLG",
    "gn:admin2_code":"VLI",
    "gn:admin3_code":"71.0",
    "gn:admin4_code":"71004.0",
    "gn:asciiname":"Brelaar",
    "gn:country_code":"BE",
    "gn:dem":24,
    "gn:feature_class":"P",
    "gn:feature_code":"PPL",
    "gn:name":"Brelaar",
    "gn:population":0,
    "gn:timezone":"Europe/Brussels",
    "iso:country":"BE",
    "name:und_x_variant":[
        "Breelaer",
        "Brelaar"
    ],
    "wof:name":"Brelaar",
    "wof:placetype":"locality"
},
  "geometry": {"coordinates":[5.14078,51.04113],"type":"Point"}
}