{
  "type": "Feature",
  "properties": {
    "gn:admin1_code":"VLG",
    "gn:admin2_code":"VBR",
    "gn:admin3_code":"23.0",
    "gn:admin4_code":"23024.0",
    "gn:asciiname":"Groten Haardinge",
    "gn:country_code":"BE",
    "gn:dem":39,
    "gn:feature_class":"P",
    "gn:feature_code":"PPL",
    "gn:name":"Groten Haardinge",
    "gn:population":0,
    "gn:timezone":"Europe/Brussels",
    "iso:country":"BE",
    "name:und_x_variant":[
        "Grooten-Haarding",
        "Grote Haarding",
        "Groten Haardinge"
    ],
    "wof:name":"Groten Haardinge",
    "wof:placetype":"locality"
},
  "geometry": {"coordinates":[4.06667,50.78333],"type":"Point"}
}