{
  "type": "Feature",
  "properties": {
    "gn:admin1_code":"VLG",
    "gn:admin2_code":"VLI",
    "gn:admin3_code":"72.0",
    "gn:admin4_code":"72037.0",
    "gn:asciiname":"Robbert",
    "gn:country_code":"BE",
    "gn:dem":35,
    "gn:feature_class":"P",
    "gn:feature_code":"PPL",
    "gn:name":"Robbert",
    "gn:population":0,
    "gn:timezone":"Europe/Brussels",
    "iso:country":"BE",
    "name:deu_x_preferred":[
        "Robbert"
    ],
    "name:nds_x_preferred":[
        "Robbert"
    ],
    "wof:name":"Robbert",
    "wof:placetype":"locality"
},
  "geometry": {"coordinates":[5.55,51.25],"type":"Point"}
}