{
  "type": "Feature",
  "properties": {
    "gn:country":"BE",
    "gn:fcode":"PPL",
    "gn:population":0,
    "iso:country":"BE",
    "name:ara_x_preferred":[
        "\u0644\u0648\u062f\u064a\u0644\u064a\u0646\u0633\u0627\u0631\u062a"
    ],
    "name:bul_x_preferred":[
        "\u041b\u043e\u0434\u0435\u043b\u0438\u043d\u0441\u0430\u0440\u0442"
    ],
    "name:ceb_x_preferred":[
        "Lodelinsart"
    ],
    "name:eng_x_preferred":[
        "Lodelinsart"
    ],
    "name:fas_x_preferred":[
        "\u0644\u0648\u062f\u0647\u200c\u0644\u06cc\u0646\u0633\u0627\u0631\u062a"
    ],
    "name:fra_x_preferred":[
        "Lodelinsart"
    ],
    "name:gle_x_preferred":[
        "Lodelinsart"
    ],
    "name:hun_x_preferred":[
        "Lodelinsart"
    ],
    "name:ita_x_preferred":[
        "Lodelinsart"
    ],
    "name:nld_x_preferred":[
        "Lodelinsart"
    ],
    "name:pcd_x_preferred":[
        "Lodelinsart"
    ],
    "name:swe_x_preferred":[
        "Lodelinsart"
    ],
    "name:und_x_variant":[
        "Charleroi (Lodelinsart)"
    ],
    "name:wln_x_preferred":[
        "Lodlins\u00e5t"
    ],
    "qs_pg:aaroncc":"BE",
    "qs_pg:gn_country":"BE",
    "qs_pg:gn_fcode":"PPL",
    "qs_pg:gn_pop":0,
    "qs_pg:name":"Lodelinsart",
    "qs_pg:name_adm0":"Belgique",
    "qs_pg:name_adm1":"Hainaut",
    "qs_pg:photos_9k":1,
    "qs_pg:photos_9r":1,
    "qs_pg:photos_all":1,
    "qs_pg:photos_sr":0,
    "qs_pg:pop_sr":0,
    "qs_pg:qs_pg_placetype":"locality",
    "qs_pg:qs_pg_placetype_gp":"Town",
    "qs_pg:woe_adm0":23424757,
    "woe:adm0_id":23424757,
    "woe:name_adm0":"Belgique",
    "woe:name_adm1":"Hainaut",
    "woe:placetype":"Town",
    "wof:name":"Lodelinsart",
    "wof:placetype":"locality"
},
  "geometry": {"coordinates":[4.44886,50.43138],"type":"Point"}
}