{
  "type": "Feature",
  "properties": {
    "gn:gn_country":"BE",
    "gn:gn_fcode":"PPL",
    "gn:gn_pop":0,
    "iso:country":"BE",
    "name:bul_x_preferred":[
        "\u041b\u043e\u0434\u0435\u043b\u0438\u043d\u0441\u0430\u0440\u0442"
    ],
    "name:dut_x_preferred":[
        "Lodelinsart"
    ],
    "name:eng_x_preferred":[
        "Lodelinsart"
    ],
    "name:fre_x_preferred":[
        "Lodelinsart"
    ],
    "name:hun_x_preferred":[
        "Lodelinsart"
    ],
    "name:swe_x_preferred":[
        "Lodelinsart"
    ],
    "name:unk_x_variant":[
        "Charleroi (Lodelinsart)"
    ],
    "name:wln_x_preferred":[
        "Lodlins\u00e5t"
    ],
    "qs_pg:aaroncc":"BE",
    "qs_pg:gn_country":"BE",
    "qs_pg:gn_fcode":"PPL",
    "qs_pg:gn_pop":0,
    "qs_pg:name":"Lodelinsart",
    "qs_pg:name_adm0":"Belgique",
    "qs_pg:name_adm1":"Hainaut",
    "qs_pg:photos_9k":1,
    "qs_pg:photos_9r":1,
    "qs_pg:photos_all":1,
    "qs_pg:photos_sr":0,
    "qs_pg:pop_sr":0,
    "qs_pg:qs_pg_placetype":"locality",
    "qs_pg:qs_pg_placetype_gp":"Town",
    "qs_pg:woe_adm0":23424757,
    "woe:adm0_id":23424757,
    "woe:name_adm0":"Belgique",
    "woe:name_adm1":"Hainaut",
    "woe:placetype":"Town",
    "wof:name":"Lodelinsart",
    "wof:placetype":"locality"
},
  "geometry": {"coordinates":[4.44886,50.43138],"type":"Point"}
}