{
  "type": "Feature",
  "properties": {
    "gn:admin1_code":"WAL",
    "gn:admin2_code":"WNA",
    "gn:admin3_code":"93.0",
    "gn:admin4_code":"93022.0",
    "gn:asciiname":"Ry Massart",
    "gn:country_code":"BE",
    "gn:dem":269,
    "gn:feature_class":"P",
    "gn:feature_code":"PPL",
    "gn:name":"Ry Massart",
    "gn:population":0,
    "gn:timezone":"Europe/Brussels",
    "iso:country":"BE",
    "wof:name":"Ry Massart",
    "wof:placetype":"locality"
},
  "geometry": {"coordinates":[4.58333,50.28333],"type":"Point"}
}