{
  "type": "Feature",
  "properties": {
    "gn:admin1_code":"WAL",
    "gn:admin2_code":"WHT",
    "gn:admin3_code":"55.0",
    "gn:admin4_code":"55023.0",
    "gn:asciiname":"Glacenee",
    "gn:country_code":"BE",
    "gn:dem":32,
    "gn:feature_class":"P",
    "gn:feature_code":"PPL",
    "gn:name":"Glacen\u00e9e",
    "gn:population":0,
    "gn:timezone":"Europe/Brussels",
    "iso:country":"BE",
    "name:und_x_variant":[
        "Glacen\u00e9",
        "Glacen\u00e9e"
    ],
    "wof:name":"Glacenee",
    "wof:placetype":"locality"
},
  "geometry": {"coordinates":[3.86367,50.72227],"type":"Point"}
}