{
  "type": "Feature",
  "properties": {
    "gn:country":"BE",
    "gn:fcode":"PPL",
    "gn:population":0,
    "iso:country":"BE",
    "name:eng_x_preferred":[
        "Attenrode-Wever"
    ],
    "name:fra_x_preferred":[
        "Attenrode-Wever"
    ],
    "name:gle_x_preferred":[
        "Attenrode-Wever"
    ],
    "name:hun_x_preferred":[
        "Attenrode-Wever"
    ],
    "name:nld_x_preferred":[
        "Attenrode"
    ],
    "qs_pg:aaroncc":"BE",
    "qs_pg:gn_country":"BE",
    "qs_pg:gn_fcode":"PPL",
    "qs_pg:gn_pop":0,
    "qs_pg:name":"Attenrode",
    "qs_pg:name_adm0":"Belgique",
    "qs_pg:name_adm1":"Vlaams Brabant",
    "qs_pg:photos_9r":0,
    "qs_pg:photos_sr":0,
    "qs_pg:pop_sr":0,
    "qs_pg:qs_pg_placetype":"locality",
    "qs_pg:qs_pg_placetype_gp":"Town",
    "qs_pg:woe_adm0":23424757,
    "woe:adm0_id":23424757,
    "woe:name_adm0":"Belgique",
    "woe:name_adm1":"Vlaams Brabant",
    "woe:placetype":"Town",
    "wof:name":"Attenrode",
    "wof:placetype":"locality"
},
  "geometry": {"coordinates":[4.92438,50.87782],"type":"Point"}
}