{
  "type": "Feature",
  "properties": {
    "gn:admin1_code":"VLG",
    "gn:admin2_code":"VOV",
    "gn:admin3_code":"41.0",
    "gn:admin4_code":"41018.0",
    "gn:asciiname":"Vrijheid",
    "gn:country_code":"BE",
    "gn:dem":34,
    "gn:feature_class":"P",
    "gn:feature_code":"PPL",
    "gn:name":"Vrijheid",
    "gn:population":0,
    "gn:timezone":"Europe/Brussels",
    "iso:country":"BE",
    "wof:name":"Vrijheid",
    "wof:placetype":"locality"
},
  "geometry": {"coordinates":[3.87972,50.82021],"type":"Point"}
}