{
  "type": "Feature",
  "properties": {
    "gn:admin1_code":"WAL",
    "gn:admin2_code":"WHT",
    "gn:admin3_code":"55.0",
    "gn:admin4_code":"55022.0",
    "gn:asciiname":"Lait Beurre",
    "gn:country_code":"BE",
    "gn:dem":113,
    "gn:feature_class":"P",
    "gn:feature_code":"PPL",
    "gn:name":"Lait Beurr\u00e9",
    "gn:population":0,
    "gn:timezone":"Europe/Brussels",
    "iso:country":"BE",
    "wof:name":"Lait Beurre",
    "wof:placetype":"locality"
},
  "geometry": {"coordinates":[4.15823,50.46654],"type":"Point"}
}