{
  "type": "Feature",
  "properties": {
    "gn:admin1_code":"VLG",
    "gn:admin2_code":"VWV",
    "gn:admin3_code":"32.0",
    "gn:admin4_code":"32003.0",
    "gn:asciiname":"Vijversmolenhoek",
    "gn:country_code":"BE",
    "gn:dem":4,
    "gn:feature_class":"P",
    "gn:feature_code":"PPL",
    "gn:name":"Vijversmolenhoek",
    "gn:population":0,
    "gn:timezone":"Europe/Brussels",
    "iso:country":"BE",
    "name:und_x_variant":[
        "Vyversmolenhoek",
        "Vijversmolenhoek"
    ],
    "wof:name":"Vijversmolenhoek",
    "wof:placetype":"locality"
},
  "geometry": {"coordinates":[2.92459,51.09422],"type":"Point"}
}