{
  "type": "Feature",
  "properties": {
    "gn:admin1_code":"VLG",
    "gn:admin2_code":"VBR",
    "gn:admin3_code":"23.0",
    "gn:admin4_code":"23062.0",
    "gn:asciiname":"Zavelenborre",
    "gn:country_code":"BE",
    "gn:dem":69,
    "gn:feature_class":"P",
    "gn:feature_code":"PPL",
    "gn:name":"Zavelenborre",
    "gn:population":0,
    "gn:timezone":"Europe/Brussels",
    "iso:country":"BE",
    "wof:name":"Zavelenborre",
    "wof:placetype":"locality"
},
  "geometry": {"coordinates":[4.5056,50.77099000000001],"type":"Point"}
}