{
  "type": "Feature",
  "properties": {
    "gn:admin1_code":"WAL",
    "gn:admin2_code":"WLX",
    "gn:admin3_code":"82.0",
    "gn:admin4_code":"82003.0",
    "gn:asciiname":"Marvie",
    "gn:country_code":"BE",
    "gn:dem":487,
    "gn:feature_class":"P",
    "gn:feature_code":"PPL",
    "gn:name":"Marvie",
    "gn:population":0,
    "gn:timezone":"Europe/Brussels",
    "iso:country":"BE",
    "wof:name":"Marvie",
    "wof:placetype":"locality"
},
  "geometry": {"coordinates":[5.74602,49.98512],"type":"Point"}
}