{
  "type": "Feature",
  "properties": {
    "gn:admin1_code":"VLG",
    "gn:admin2_code":"VBR",
    "gn:admin3_code":"23.0",
    "gn:admin4_code":"23016.0",
    "gn:asciiname":"Spanuit",
    "gn:country_code":"BE",
    "gn:dem":70,
    "gn:feature_class":"P",
    "gn:feature_code":"PPL",
    "gn:name":"Spanuit",
    "gn:population":0,
    "gn:timezone":"Europe/Brussels",
    "iso:country":"BE",
    "wof:name":"Spanuit",
    "wof:placetype":"locality"
},
  "geometry": {"coordinates":[4.21475,50.84048],"type":"Point"}
}