{
  "type": "Feature",
  "properties": {
    "gn:admin1_code":"WAL",
    "gn:admin2_code":"WNA",
    "gn:admin3_code":"92.0",
    "gn:admin4_code":"92097.0",
    "gn:asciiname":"Bois d'Ohey",
    "gn:country_code":"BE",
    "gn:dem":272,
    "gn:feature_class":"P",
    "gn:feature_code":"PPL",
    "gn:name":"Bois d'Ohey",
    "gn:population":0,
    "gn:timezone":"Europe/Brussels",
    "iso:country":"BE",
    "wof:name":"Bois d'Ohey",
    "wof:placetype":"locality"
},
  "geometry": {"coordinates":[5.11705,50.44568],"type":"Point"}
}