{
  "type": "Feature",
  "properties": {
    "gn:admin1_code":"WAL",
    "gn:admin2_code":"WNA",
    "gn:admin3_code":"92.0",
    "gn:admin4_code":"92097.0",
    "gn:asciiname":"Sur le Try",
    "gn:country_code":"BE",
    "gn:dem":264,
    "gn:feature_class":"P",
    "gn:feature_code":"PPL",
    "gn:name":"Sur le Try",
    "gn:population":0,
    "gn:timezone":"Europe/Brussels",
    "iso:country":"BE",
    "wof:name":"Sur le Try",
    "wof:placetype":"locality"
},
  "geometry": {"coordinates":[5.13128,50.43793],"type":"Point"}
}