{
  "type": "Feature",
  "properties": {
    "gn:admin1_code":"WAL",
    "gn:admin2_code":"WHT",
    "gn:admin3_code":"51.0",
    "gn:admin4_code":"51009.0",
    "gn:asciiname":"Pommeroeul",
    "gn:country_code":"BE",
    "gn:dem":27,
    "gn:feature_class":"P",
    "gn:feature_code":"PPL",
    "gn:name":"Pommeroeul",
    "gn:population":0,
    "gn:timezone":"Europe/Brussels",
    "iso:country":"BE",
    "wof:name":"Pommeroeul",
    "wof:placetype":"locality"
},
  "geometry": {"coordinates":[3.71252,50.46188],"type":"Point"}
}