{
  "type": "Feature",
  "properties": {
    "gn:admin1_code":"WAL",
    "gn:admin2_code":"WHT",
    "gn:admin3_code":"52.0",
    "gn:admin4_code":"52063.0",
    "gn:asciiname":"Brule",
    "gn:country_code":"BE",
    "gn:dem":111,
    "gn:feature_class":"P",
    "gn:feature_code":"PPL",
    "gn:name":"Br\u00fbl\u00e9",
    "gn:population":0,
    "gn:timezone":"Europe/Brussels",
    "iso:country":"BE",
    "name:ceb_x_preferred":[
        "Brule"
    ],
    "name:deu_x_preferred":[
        "Brule"
    ],
    "name:fra_x_preferred":[
        "Brule"
    ],
    "name:ita_x_preferred":[
        "Brule"
    ],
    "name:nld_x_preferred":[
        "Brule"
    ],
    "name:pol_x_preferred":[
        "Brule"
    ],
    "name:por_x_preferred":[
        "Brule"
    ],
    "name:rus_x_preferred":[
        "\u0411\u0440\u044e\u043b\u0435"
    ],
    "name:srp_x_preferred":[
        "\u0411\u0440\u0443\u043b"
    ],
    "name:ukr_x_preferred":[
        "\u0411\u0440\u044e\u043b"
    ],
    "wof:name":"Brule",
    "wof:placetype":"locality"
},
  "geometry": {"coordinates":[4.25,50.56667],"type":"Point"}
}