{
  "type": "Feature",
  "properties": {
    "iso:country":"BE",
    "qs_pg:aaroncc":"BE",
    "qs_pg:name":"St.-Pieters-Dyk",
    "qs_pg:name_adm0":"Belgique",
    "qs_pg:name_adm1":"West-Vlaanderen",
    "qs_pg:photos":60,
    "qs_pg:photos_1k":12,
    "qs_pg:photos_9k":1,
    "qs_pg:photos_9r":2,
    "qs_pg:photos_all":60,
    "qs_pg:photos_sr":2,
    "qs_pg:pop_sr":0,
    "qs_pg:qs_pg_placetype":"neighbourhood",
    "qs_pg:qs_pg_placetype_gp":"Suburb",
    "qs_pg:woe_adm0":23424757,
    "woe:adm0_id":23424757,
    "woe:name_adm0":"Belgique",
    "woe:name_adm1":"West-Vlaanderen",
    "woe:placetype":"Suburb",
    "wof:name":"St.-Pieters-Dyk",
    "wof:placetype":"neighbourhood"
},
  "geometry": {"coordinates":[3.201591,51.223053],"type":"Point"}
}