{
  "type": "Feature",
  "properties": {
    "gn:admin1_code":"WAL",
    "gn:admin2_code":"WLG",
    "gn:admin3_code":"62.0",
    "gn:admin4_code":"62027.0",
    "gn:asciiname":"Afnay",
    "gn:country_code":"BE",
    "gn:dem":154,
    "gn:feature_class":"P",
    "gn:feature_code":"PPL",
    "gn:name":"Afnay",
    "gn:population":0,
    "gn:timezone":"Europe/Brussels",
    "iso:country":"BE",
    "name:und_x_variant":[
        "Affnay",
        "Afnai",
        "Afnay"
    ],
    "wof:name":"Afnay",
    "wof:placetype":"locality"
},
  "geometry": {"coordinates":[5.77297,50.72616],"type":"Point"}
}