{
  "type": "Feature",
  "properties": {
    "gn:admin1_code":"WAL",
    "gn:admin2_code":"WNA",
    "gn:admin3_code":"91.0",
    "gn:admin4_code":"91030.0",
    "gn:asciiname":"Halloy",
    "gn:country_code":"BE",
    "gn:dem":226,
    "gn:feature_class":"P",
    "gn:feature_code":"PPL",
    "gn:name":"Halloy",
    "gn:population":0,
    "gn:timezone":"Europe/Brussels",
    "iso:country":"BE",
    "wof:name":"Halloy",
    "wof:placetype":"locality"
},
  "geometry": {"coordinates":[5.07111,50.30991],"type":"Point"}
}