{
  "type": "Feature",
  "properties": {
    "gn:admin1_code":"WAL",
    "gn:admin2_code":"WNA",
    "gn:admin3_code":"91.0",
    "gn:admin4_code":"91030.0",
    "gn:asciiname":"Halloy",
    "gn:country_code":"BE",
    "gn:dem":226,
    "gn:feature_class":"P",
    "gn:feature_code":"PPL",
    "gn:name":"Halloy",
    "gn:population":0,
    "gn:timezone":"Europe/Brussels",
    "iso:country":"BE",
    "name:bre_x_preferred":[
        "Halloy"
    ],
    "name:ceb_x_preferred":[
        "Halloy"
    ],
    "name:ces_x_preferred":[
        "Halloy"
    ],
    "name:deu_x_preferred":[
        "Halloy"
    ],
    "name:fra_x_preferred":[
        "Halloy"
    ],
    "name:ita_x_preferred":[
        "Halloy"
    ],
    "name:nds_x_preferred":[
        "Halloy"
    ],
    "name:nld_x_preferred":[
        "Halloy"
    ],
    "name:pms_x_preferred":[
        "Halloy"
    ],
    "name:pol_x_preferred":[
        "Halloy"
    ],
    "name:por_x_preferred":[
        "Halloy"
    ],
    "name:slk_x_preferred":[
        "Halloy"
    ],
    "name:spa_x_preferred":[
        "Halloy"
    ],
    "name:swe_x_preferred":[
        "Halloy"
    ],
    "name:ukr_x_preferred":[
        "\u0410\u043b\u043b\u0443\u0430"
    ],
    "wof:name":"Halloy",
    "wof:placetype":"locality"
},
  "geometry": {"coordinates":[5.07111,50.30991],"type":"Point"}
}