{
  "type": "Feature",
  "properties": {
    "gn:admin1_code":"VLG",
    "gn:admin2_code":"VLI",
    "gn:admin3_code":"72.0",
    "gn:admin4_code":"72003.0",
    "gn:asciiname":"Goolder",
    "gn:country_code":"BE",
    "gn:dem":44,
    "gn:feature_class":"P",
    "gn:feature_code":"PPL",
    "gn:name":"Goolder",
    "gn:population":0,
    "gn:timezone":"Europe/Brussels",
    "iso:country":"BE",
    "name:und_x_variant":[
        "Golderhees",
        "Goolder"
    ],
    "wof:name":"Goolder",
    "wof:placetype":"locality"
},
  "geometry": {"coordinates":[5.55077,51.16942],"type":"Point"}
}