{
  "type": "Feature",
  "properties": {
    "gn:admin1_code":"WAL",
    "gn:admin2_code":"WNA",
    "gn:admin3_code":"92.0",
    "gn:admin4_code":"92094.0",
    "gn:asciiname":"Vigneroul",
    "gn:country_code":"BE",
    "gn:dem":83,
    "gn:feature_class":"P",
    "gn:feature_code":"PPL",
    "gn:name":"Vigneroul",
    "gn:population":0,
    "gn:timezone":"Europe/Brussels",
    "iso:country":"BE",
    "wof:name":"Vigneroul",
    "wof:placetype":"locality"
},
  "geometry": {"coordinates":[4.86667,50.45],"type":"Point"}
}