{
  "type": "Feature",
  "properties": {
    "gn:admin1_code":"VLG",
    "gn:admin2_code":"VWV",
    "gn:admin3_code":"31.0",
    "gn:admin4_code":"31033.0",
    "gn:asciiname":"Vijfhuishoek",
    "gn:country_code":"BE",
    "gn:dem":11,
    "gn:feature_class":"P",
    "gn:feature_code":"PPL",
    "gn:name":"Vijfhuishoek",
    "gn:population":0,
    "gn:timezone":"Europe/Brussels",
    "iso:country":"BE",
    "name:und_x_variant":[
        "Vyfhuyshoek",
        "Vijfhuishoek"
    ],
    "wof:name":"Vijfhuishoek",
    "wof:placetype":"locality"
},
  "geometry": {"coordinates":[3.07445,51.04398],"type":"Point"}
}