{
  "type": "Feature",
  "properties": {
    "gn:admin1_code":"WAL",
    "gn:admin2_code":"WHT",
    "gn:admin3_code":"56.0",
    "gn:admin4_code":"56022.0",
    "gn:asciiname":"Bersillies-l'Abbaye",
    "gn:country_code":"BE",
    "gn:dem":145,
    "gn:feature_class":"P",
    "gn:feature_code":"PPL",
    "gn:name":"Bersillies-l'Abbaye",
    "gn:population":0,
    "gn:timezone":"Europe/Brussels",
    "iso:country":"BE",
    "name:und_x_variant":[
        "Erquelinnes (Bersillies-l'Abbaye)"
    ],
    "wof:name":"Bersillies-l'Abbaye",
    "wof:placetype":"locality"
},
  "geometry": {"coordinates":[4.14845,50.26186],"type":"Point"}
}