{
  "type": "Feature",
  "properties": {
    "gn:admin1_code":"WAL",
    "gn:admin2_code":"WHT",
    "gn:admin3_code":"57.0",
    "gn:admin4_code":"57081.0",
    "gn:asciiname":"La Cavee",
    "gn:country_code":"BE",
    "gn:dem":57,
    "gn:feature_class":"P",
    "gn:feature_code":"PPL",
    "gn:name":"La Cav\u00e9e",
    "gn:population":0,
    "gn:timezone":"Europe/Brussels",
    "iso:country":"BE",
    "wof:name":"La Cavee",
    "wof:placetype":"locality"
},
  "geometry": {"coordinates":[3.54424,50.58409],"type":"Point"}
}