{
  "type": "Feature",
  "properties": {
    "gn:admin1_code":"VLG",
    "gn:admin2_code":"VOV",
    "gn:admin3_code":"44.0",
    "gn:admin4_code":"44045.0",
    "gn:asciiname":"Terwest",
    "gn:country_code":"BE",
    "gn:dem":4,
    "gn:feature_class":"P",
    "gn:feature_code":"PPL",
    "gn:name":"Terwest",
    "gn:population":0,
    "gn:timezone":"Europe/Brussels",
    "iso:country":"BE",
    "wof:name":"Terwest",
    "wof:placetype":"locality"
},
  "geometry": {"coordinates":[3.92479,51.17409],"type":"Point"}
}