{
  "type": "Feature",
  "properties": {
    "gn:admin1_code":"WAL",
    "gn:admin2_code":"WLG",
    "gn:admin3_code":"61.0",
    "gn:admin4_code":"61068.0",
    "gn:asciiname":"Halbosart",
    "gn:country_code":"BE",
    "gn:dem":193,
    "gn:feature_class":"P",
    "gn:feature_code":"PPL",
    "gn:name":"Halbosart",
    "gn:population":0,
    "gn:timezone":"Europe/Brussels",
    "iso:country":"BE",
    "name:und_x_variant":[
        "Halbesart",
        "Halbpsart",
        "Halbosart"
    ],
    "wof:name":"Halbosart",
    "wof:placetype":"locality"
},
  "geometry": {"coordinates":[5.2658,50.55653],"type":"Point"}
}