{
  "type": "Feature",
  "properties": {
    "gn:admin1_code":"VLG",
    "gn:admin2_code":"VBR",
    "gn:admin3_code":"23.0",
    "gn:admin4_code":"23105.0",
    "gn:asciiname":"Essene",
    "gn:country_code":"BE",
    "gn:dem":41,
    "gn:feature_class":"P",
    "gn:feature_code":"PPL",
    "gn:name":"Essene",
    "gn:population":0,
    "gn:timezone":"Europe/Brussels",
    "iso:country":"BE",
    "name:und_x_variant":[
        "Esschene",
        "Essene"
    ],
    "wof:name":"Essene",
    "wof:placetype":"locality"
},
  "geometry": {"coordinates":[4.13743,50.90163],"type":"Point"}
}