{
  "type": "Feature",
  "properties": {
    "gn:admin1_code":"WAL",
    "gn:admin2_code":"WLG",
    "gn:admin3_code":"63.0",
    "gn:admin4_code":"63075.0",
    "gn:asciiname":"La Levee",
    "gn:country_code":"BE",
    "gn:dem":299,
    "gn:feature_class":"P",
    "gn:feature_code":"PPL",
    "gn:name":"La Lev\u00e9e",
    "gn:population":0,
    "gn:timezone":"Europe/Brussels",
    "iso:country":"BE",
    "wof:name":"La Levee",
    "wof:placetype":"locality"
},
  "geometry": {"coordinates":[5.76667,50.38333],"type":"Point"}
}