{
  "type": "Feature",
  "properties": {
    "gn:admin1_code":"VLG",
    "gn:admin2_code":"VAN",
    "gn:admin3_code":"11.0",
    "gn:admin4_code":"11002.0",
    "gn:asciiname":"Bund",
    "gn:country_code":"BE",
    "gn:dem":3,
    "gn:feature_class":"P",
    "gn:feature_code":"PPL",
    "gn:name":"Bund",
    "gn:population":0,
    "gn:timezone":"Europe/Brussels",
    "iso:country":"BE",
    "name:deu_x_preferred":[
        "Bund"
    ],
    "name:fin_x_preferred":[
        "Bund"
    ],
    "name:fra_x_preferred":[
        "Bund"
    ],
    "name:ita_x_preferred":[
        "Bund"
    ],
    "name:jpn_x_preferred":[
        "\u30d6\u30f3\u30c8"
    ],
    "name:lit_x_preferred":[
        "Bundas"
    ],
    "name:nld_x_historical":[
        "Bunt"
    ],
    "name:nld_x_preferred":[
        "Bunt"
    ],
    "name:nld_x_variant":[
        "Bund"
    ],
    "name:nor_x_preferred":[
        "Bund"
    ],
    "name:pol_x_preferred":[
        "Bund"
    ],
    "name:por_x_preferred":[
        "Bund"
    ],
    "name:rus_x_preferred":[
        "\u0411\u0443\u043d\u0434"
    ],
    "name:slk_x_preferred":[
        "Zv\u00e4z"
    ],
    "name:spa_x_preferred":[
        "Bund"
    ],
    "name:swe_x_preferred":[
        "Bund"
    ],
    "wof:name":"Bund",
    "wof:placetype":"locality"
},
  "geometry": {"coordinates":[4.4291,51.28487],"type":"Point"}
}