{
  "type": "Feature",
  "properties": {
    "gn:admin1_code":"VLG",
    "gn:admin2_code":"VBR",
    "gn:admin3_code":"23.0",
    "gn:admin4_code":"23003.0",
    "gn:asciiname":"Solheide",
    "gn:country_code":"BE",
    "gn:dem":43,
    "gn:feature_class":"P",
    "gn:feature_code":"PPL",
    "gn:name":"Solheide",
    "gn:population":0,
    "gn:timezone":"Europe/Brussels",
    "iso:country":"BE",
    "wof:name":"Solheide",
    "wof:placetype":"locality"
},
  "geometry": {"coordinates":[4.29543,50.73473],"type":"Point"}
}