{
  "type": "Feature",
  "properties": {
    "gn:admin1_code":"VLG",
    "gn:admin2_code":"VWV",
    "gn:admin3_code":"33.0",
    "gn:admin4_code":"33037.0",
    "gn:asciiname":"Poezelhoek",
    "gn:country_code":"BE",
    "gn:dem":35,
    "gn:feature_class":"P",
    "gn:feature_code":"PPL",
    "gn:name":"Poezelhoek",
    "gn:population":0,
    "gn:timezone":"Europe/Brussels",
    "iso:country":"BE",
    "wof:name":"Poezelhoek",
    "wof:placetype":"locality"
},
  "geometry": {"coordinates":[3.00322,50.84242],"type":"Point"}
}