{
  "type": "Feature",
  "properties": {
    "gn:admin1_code":"VLG",
    "gn:admin2_code":"VAN",
    "gn:admin3_code":"13.0",
    "gn:admin4_code":"13014.0",
    "gn:asciiname":"Vijfhuizen",
    "gn:country_code":"BE",
    "gn:dem":12,
    "gn:feature_class":"P",
    "gn:feature_code":"PPL",
    "gn:name":"Vijfhuizen",
    "gn:population":0,
    "gn:timezone":"Europe/Brussels",
    "iso:country":"BE",
    "name:ceb_x_preferred":[
        "Vijfhuizen"
    ],
    "name:fas_x_preferred":[
        "\u0641\u06cc\u0641\u200c\u0647\u0627\u06cc\u0632\u0646"
    ],
    "name:fra_x_preferred":[
        "Vijfhuizen"
    ],
    "name:ita_x_preferred":[
        "Vijfhuizen"
    ],
    "name:nld_x_preferred":[
        "Vijfhuizen"
    ],
    "name:sqi_x_preferred":[
        "Vijfhuizen"
    ],
    "wof:name":"Vijfhuizen",
    "wof:placetype":"locality"
},
  "geometry": {"coordinates":[4.76875,51.43774000000001],"type":"Point"}
}