{
  "type": "Feature",
  "properties": {
    "gn:admin1_code":"VLG",
    "gn:admin2_code":"VAN",
    "gn:admin3_code":"11.0",
    "gn:admin4_code":"11022.0",
    "gn:asciiname":"Kleine Horendonk",
    "gn:country_code":"BE",
    "gn:dem":13,
    "gn:feature_class":"P",
    "gn:feature_code":"PPL",
    "gn:name":"Kleine Horendonk",
    "gn:population":0,
    "gn:timezone":"Europe/Brussels",
    "iso:country":"BE",
    "name:und_x_variant":[
        "Kleinen Horendonck Heide",
        "Kleinen Horendonk",
        "Kleine Horendonk"
    ],
    "wof:name":"Kleine Horendonk",
    "wof:placetype":"locality"
},
  "geometry": {"coordinates":[4.51667,51.45],"type":"Point"}
}