{
  "type": "Feature",
  "properties": {
    "gn:admin1_code":"WAL",
    "gn:admin2_code":"WLX",
    "gn:admin3_code":"83.0",
    "gn:admin4_code":"83049.0",
    "gn:asciiname":"Noir Bras",
    "gn:country_code":"BE",
    "gn:dem":452,
    "gn:feature_class":"P",
    "gn:feature_code":"PPL",
    "gn:name":"Noir Bras",
    "gn:population":0,
    "gn:timezone":"Europe/Brussels",
    "iso:country":"BE",
    "wof:name":"Noir Bras",
    "wof:placetype":"locality"
},
  "geometry": {"coordinates":[5.4801,50.10184],"type":"Point"}
}