{
  "type": "Feature",
  "properties": {
    "gn:admin1_code":"WAL",
    "gn:admin2_code":"WLX",
    "gn:admin3_code":"84.0",
    "gn:admin4_code":"84016.0",
    "gn:asciiname":"Selassin",
    "gn:country_code":"BE",
    "gn:dem":346,
    "gn:feature_class":"P",
    "gn:feature_code":"PPL",
    "gn:name":"Selassin",
    "gn:population":0,
    "gn:timezone":"Europe/Brussels",
    "iso:country":"BE",
    "wof:name":"Selassin",
    "wof:placetype":"locality"
},
  "geometry": {"coordinates":[5.0423,49.99641],"type":"Point"}
}