{
  "type": "Feature",
  "properties": {
    "gn:admin1_code":"VLG",
    "gn:admin2_code":"VLI",
    "gn:admin3_code":"71.0",
    "gn:admin4_code":"71016.0",
    "gn:asciiname":"Genkerhei",
    "gn:country_code":"BE",
    "gn:dem":55,
    "gn:feature_class":"P",
    "gn:feature_code":"PPL",
    "gn:name":"Genkerhei",
    "gn:population":0,
    "gn:timezone":"Europe/Brussels",
    "iso:country":"BE",
    "name:und_x_variant":[
        "Genckerhei",
        "Genkerhei"
    ],
    "wof:name":"Genkerhei",
    "wof:placetype":"locality"
},
  "geometry": {"coordinates":[5.45,50.96667],"type":"Point"}
}