{
  "type": "Feature",
  "properties": {
    "iso:country":"BE",
    "name:nld_x_preferred":[
        "Hoogboom"
    ],
    "qs:gn_adm0_cc":"BE",
    "qs:gn_fcode":"PPL",
    "qs:gn_local":2794730,
    "qs:gn_nam_loc":"Kapellen, Kapellen, Antwerpen, Antwerpen, BE",
    "qs:gn_namadm1":"VLG",
    "qs:gn_name":"Hoogboom",
    "qs:local_max":415,
    "qs:local_sum":415,
    "qs:localhoods":1,
    "qs:name":"Hoogboom",
    "qs:name_adm0":"Belgique",
    "qs:name_adm1":"Antwerpen",
    "qs:name_adm2":"Antwerpen",
    "qs:name_lau":"Kapellen",
    "qs:name_local":"Kapellen",
    "qs:photo_max":89,
    "qs:photo_sum":415,
    "qs:placetype":"Suburb",
    "qs:quad_count":35,
    "qs:woe_adm0":23424757,
    "qs:woe_adm1":7153308,
    "qs:woe_adm2":12591760,
    "qs:woe_lau":12602748,
    "qs:woe_local":971867,
    "qs:woe_ver":"7.10.0",
    "wof:lang":[
        "dut"
    ],
    "wof:name":"Hoogboom",
    "wof:placetype":"neighbourhood"
},
  "geometry": {"coordinates":[4.432257,51.308704],"type":"Point"}
}