{
  "type": "Feature",
  "properties": {
    "gn:admin1_code":"WAL",
    "gn:admin2_code":"WLX",
    "gn:admin3_code":"82.0",
    "gn:admin4_code":"82037.0",
    "gn:asciiname":"Chimonti",
    "gn:country_code":"BE",
    "gn:dem":500,
    "gn:feature_class":"P",
    "gn:feature_code":"PPLL",
    "gn:name":"Ch\u00eemonti",
    "gn:population":0,
    "gn:timezone":"Europe/Brussels",
    "iso:country":"BE",
    "wof:name":"Chimonti",
    "wof:placetype":"locality"
},
  "geometry": {"coordinates":[5.93267,50.19925],"type":"Point"}
}