{
  "type": "Feature",
  "properties": {
    "gn:country":"BE",
    "gn:fcode":"PPL",
    "gn:population":0,
    "iso:country":"BE",
    "name:ceb_x_preferred":[
        "Grivegn\u00e9e"
    ],
    "name:fra_x_preferred":[
        "Grivegn\u00e9e"
    ],
    "name:lim_x_preferred":[
        "Grivegn\u00e9e"
    ],
    "name:ltz_x_preferred":[
        "Grivegn\u00e9e"
    ],
    "name:nld_x_preferred":[
        "Grivegn\u00e9e"
    ],
    "name:swe_x_preferred":[
        "Grivegn\u00e9e"
    ],
    "name:und_x_variant":[
        "Li\u00e8ge (Grivegn\u00e9e)"
    ],
    "name:wln_x_preferred":[
        "Grimgn\u00eaye"
    ],
    "qs_pg:aaroncc":"BE",
    "qs_pg:gn_country":"BE",
    "qs_pg:gn_fcode":"PPL",
    "qs_pg:gn_pop":0,
    "qs_pg:name":"Grivegn\u00e9e",
    "qs_pg:name_adm0":"Belgique",
    "qs_pg:name_adm1":"Li\u00e8ge",
    "qs_pg:photos":32,
    "qs_pg:photos_1k":6,
    "qs_pg:photos_9k":1,
    "qs_pg:photos_9r":2,
    "qs_pg:photos_all":32,
    "qs_pg:photos_sr":2,
    "qs_pg:pop_sr":0,
    "qs_pg:qs_pg_placetype":"neighbourhood",
    "qs_pg:qs_pg_placetype_gp":"Suburb",
    "qs_pg:woe_adm0":23424757,
    "woe:adm0_id":23424757,
    "woe:name_adm0":"Belgique",
    "woe:name_adm1":"Li\u00e8ge",
    "woe:placetype":"Suburb",
    "wof:name":"Grivegn\u00e9e",
    "wof:placetype":"neighbourhood"
},
  "geometry": {"coordinates":[5.61101,50.62148],"type":"Point"}
}