{
  "type": "Feature",
  "properties": {
    "gn:admin1_code":"VLG",
    "gn:admin2_code":"VWV",
    "gn:admin3_code":"37.0",
    "gn:admin4_code":"37007.0",
    "gn:asciiname":"Paanders",
    "gn:country_code":"BE",
    "gn:dem":32,
    "gn:feature_class":"P",
    "gn:feature_code":"PPL",
    "gn:name":"Paanders",
    "gn:population":0,
    "gn:timezone":"Europe/Brussels",
    "iso:country":"BE",
    "wof:name":"Paanders",
    "wof:placetype":"locality"
},
  "geometry": {"coordinates":[3.31659,50.94007],"type":"Point"}
}