{
  "type": "Feature",
  "properties": {
    "gn:admin1_code":"VLG",
    "gn:admin2_code":"VOV",
    "gn:admin3_code":"45.0",
    "gn:admin4_code":"45017.0",
    "gn:asciiname":"Marolle",
    "gn:country_code":"BE",
    "gn:dem":16,
    "gn:feature_class":"P",
    "gn:feature_code":"PPL",
    "gn:name":"Marolle",
    "gn:population":0,
    "gn:timezone":"Europe/Brussels",
    "iso:country":"BE",
    "name:und_x_variant":[
        "De Marolle",
        "Marolle"
    ],
    "wof:name":"Marolle",
    "wof:placetype":"locality"
},
  "geometry": {"coordinates":[3.53829,50.93422],"type":"Point"}
}