{
  "type": "Feature",
  "properties": {
    "gn:admin1_code":"VLG",
    "gn:admin2_code":"VOV",
    "gn:admin3_code":"41.0",
    "gn:admin4_code":"41027.0",
    "gn:asciiname":"Destelberg",
    "gn:country_code":"BE",
    "gn:dem":57,
    "gn:feature_class":"P",
    "gn:feature_code":"PPL",
    "gn:name":"Destelberg",
    "gn:population":0,
    "gn:timezone":"Europe/Brussels",
    "iso:country":"BE",
    "wof:name":"Destelberg",
    "wof:placetype":"locality"
},
  "geometry": {"coordinates":[3.93333,50.85],"type":"Point"}
}