{
  "type": "Feature",
  "properties": {
    "gn:admin1_code":"VLG",
    "gn:admin2_code":"VLI",
    "gn:admin3_code":"71.0",
    "gn:admin4_code":"71045.0",
    "gn:asciiname":"Breestraat",
    "gn:country_code":"BE",
    "gn:dem":46,
    "gn:feature_class":"P",
    "gn:feature_code":"PPL",
    "gn:name":"Breestraat",
    "gn:population":0,
    "gn:timezone":"Europe/Brussels",
    "iso:country":"BE",
    "wof:name":"Breestraat",
    "wof:placetype":"locality"
},
  "geometry": {"coordinates":[5.25,50.88333],"type":"Point"}
}