{
  "type": "Feature",
  "properties": {
    "gn:admin1_code":"WAL",
    "gn:admin2_code":"WLG",
    "gn:admin3_code":"61.0",
    "gn:admin4_code":"61039.0",
    "gn:asciiname":"Jamagne",
    "gn:country_code":"BE",
    "gn:dem":206,
    "gn:feature_class":"P",
    "gn:feature_code":"PPL",
    "gn:name":"Jamagne",
    "gn:population":0,
    "gn:timezone":"Europe/Brussels",
    "iso:country":"BE",
    "wof:name":"Jamagne",
    "wof:placetype":"locality"
},
  "geometry": {"coordinates":[5.23122,50.45171],"type":"Point"}
}