{
  "type": "Feature",
  "properties": {
    "gn:admin1_code":"WAL",
    "gn:admin2_code":"WLG",
    "gn:admin3_code":"63.0",
    "gn:admin4_code":"63075.0",
    "gn:asciiname":"Monceau",
    "gn:country_code":"BE",
    "gn:dem":267,
    "gn:feature_class":"P",
    "gn:feature_code":"PPL",
    "gn:name":"Monceau",
    "gn:population":0,
    "gn:timezone":"Europe/Brussels",
    "iso:country":"BE",
    "wof:name":"Monceau",
    "wof:placetype":"locality"
},
  "geometry": {"coordinates":[5.82219,50.39208],"type":"Point"}
}