{
  "type": "Feature",
  "properties": {
    "gn:country":"BE",
    "gn:fcode":"PPL",
    "gn:population":0,
    "iso:country":"BE",
    "name:deu_x_preferred":[
        "Forri\u00e8res"
    ],
    "name:eng_x_preferred":[
        "Forri\u00e8res"
    ],
    "name:fra_x_preferred":[
        "Forri\u00e8res"
    ],
    "name:gle_x_preferred":[
        "Forri\u00e8res"
    ],
    "name:hun_x_preferred":[
        "Forri\u00e8res"
    ],
    "name:ltz_x_preferred":[
        "Forri\u00e8res"
    ],
    "name:nld_x_preferred":[
        "Forri\u00e8res"
    ],
    "name:slv_x_preferred":[
        "Forri\u00e8res"
    ],
    "name:wln_x_preferred":[
        "Forire"
    ],
    "qs_pg:aaroncc":"BE",
    "qs_pg:gn_country":"BE",
    "qs_pg:gn_fcode":"PPL",
    "qs_pg:gn_pop":0,
    "qs_pg:name":"Forri\u00e8res",
    "qs_pg:name_adm0":"Belgique",
    "qs_pg:name_adm1":"Luxembourg",
    "qs_pg:photos_9k":1,
    "qs_pg:photos_9r":1,
    "qs_pg:photos_all":4,
    "qs_pg:photos_sr":0,
    "qs_pg:pop_sr":0,
    "qs_pg:qs_pg_placetype":"locality",
    "qs_pg:qs_pg_placetype_gp":"Town",
    "qs_pg:woe_adm0":23424757,
    "woe:adm0_id":23424757,
    "woe:name_adm0":"Belgique",
    "woe:name_adm1":"Luxembourg",
    "woe:placetype":"Town",
    "wof:name":"Forri\u00e8res",
    "wof:placetype":"locality"
},
  "geometry": {"coordinates":[5.28268,50.13132],"type":"Point"}
}