{
  "type": "Feature",
  "properties": {
    "gn:admin1_code":"WAL",
    "gn:admin2_code":"WLX",
    "gn:admin3_code":"82.0",
    "gn:admin4_code":"82014.0",
    "gn:asciiname":"Chevroumont",
    "gn:country_code":"BE",
    "gn:dem":407,
    "gn:feature_class":"P",
    "gn:feature_code":"PPL",
    "gn:name":"Chevroumont",
    "gn:population":0,
    "gn:timezone":"Europe/Brussels",
    "iso:country":"BE",
    "wof:name":"Chevroumont",
    "wof:placetype":"locality"
},
  "geometry": {"coordinates":[5.73572,50.16656],"type":"Point"}
}