{
  "type": "Feature",
  "properties": {
    "gn:admin1_code":"VLG",
    "gn:admin2_code":"VOV",
    "gn:admin3_code":"41.0",
    "gn:admin4_code":"41002.0",
    "gn:asciiname":"Klaarhaag",
    "gn:country_code":"BE",
    "gn:dem":29,
    "gn:feature_class":"P",
    "gn:feature_code":"PPL",
    "gn:name":"Klaarhaag",
    "gn:population":0,
    "gn:timezone":"Europe/Brussels",
    "iso:country":"BE",
    "name:und_x_variant":[
        "Klairhage",
        "Klaarhaag"
    ],
    "wof:name":"Klaarhaag",
    "wof:placetype":"locality"
},
  "geometry": {"coordinates":[4.11942,50.94443],"type":"Point"}
}