{
  "type": "Feature",
  "properties": {
    "gn:admin1_code":"WAL",
    "gn:admin2_code":"WNA",
    "gn:admin3_code":"91.0",
    "gn:admin4_code":"91120.0",
    "gn:asciiname":"Sinsin",
    "gn:country_code":"BE",
    "gn:dem":223,
    "gn:feature_class":"P",
    "gn:feature_code":"PPL",
    "gn:name":"Sinsin",
    "gn:population":0,
    "gn:timezone":"Europe/Brussels",
    "iso:country":"BE",
    "name:und_x_variant":[
        "Somme-Leuze (Sinsin)"
    ],
    "wof:name":"Sinsin",
    "wof:placetype":"locality"
},
  "geometry": {"coordinates":[5.25464,50.27502],"type":"Point"}
}