{
  "type": "Feature",
  "properties": {
    "gn:admin1_code":"VLG",
    "gn:admin2_code":"VWV",
    "gn:admin3_code":"35.0",
    "gn:admin4_code":"35011.0",
    "gn:asciiname":"Slijpebrug",
    "gn:country_code":"BE",
    "gn:dem":1,
    "gn:feature_class":"P",
    "gn:feature_code":"PPL",
    "gn:name":"Slijpebrug",
    "gn:population":0,
    "gn:timezone":"Europe/Brussels",
    "iso:country":"BE",
    "name:und_x_variant":[
        "Slypebrug",
        "Slijpebrug"
    ],
    "wof:name":"Slijpebrug",
    "wof:placetype":"locality"
},
  "geometry": {"coordinates":[2.83125,51.16433],"type":"Point"}
}