{
  "type": "Feature",
  "properties": {
    "gn:admin1_code":"WAL",
    "gn:admin2_code":"WNA",
    "gn:admin3_code":"91.0",
    "gn:admin4_code":"91013.0",
    "gn:asciiname":"Thanville",
    "gn:country_code":"BE",
    "gn:dem":246,
    "gn:feature_class":"P",
    "gn:feature_code":"PPL",
    "gn:name":"Thanville",
    "gn:population":0,
    "gn:timezone":"Europe/Brussels",
    "iso:country":"BE",
    "wof:name":"Thanville",
    "wof:placetype":"locality"
},
  "geometry": {"coordinates":[4.98281,50.08165],"type":"Point"}
}