{
  "type": "Feature",
  "properties": {
    "gn:admin1_code":"WAL",
    "gn:admin2_code":"WLG",
    "gn:admin3_code":"63.0",
    "gn:admin4_code":"63023.0",
    "gn:asciiname":"Oe",
    "gn:country_code":"BE",
    "gn:dem":295,
    "gn:feature_class":"P",
    "gn:feature_code":"PPL",
    "gn:name":"Oe",
    "gn:population":0,
    "gn:timezone":"Europe/Brussels",
    "iso:country":"BE",
    "wof:name":"Oe",
    "wof:placetype":"locality"
},
  "geometry": {"coordinates":[6.03333,50.61667],"type":"Point"}
}