{
  "type": "Feature",
  "properties": {
    "gn:admin1_code":"WAL",
    "gn:admin2_code":"WNA",
    "gn:admin3_code":"92.0",
    "gn:admin4_code":"92035.0",
    "gn:asciiname":"Matignee",
    "gn:country_code":"BE",
    "gn:dem":160,
    "gn:feature_class":"P",
    "gn:feature_code":"PPL",
    "gn:name":"Matign\u00e9e",
    "gn:population":0,
    "gn:timezone":"Europe/Brussels",
    "iso:country":"BE",
    "wof:name":"Matignee",
    "wof:placetype":"locality"
},
  "geometry": {"coordinates":[4.83282,50.55805],"type":"Point"}
}