{
  "type": "Feature",
  "properties": {
    "gn:admin1_code":"WAL",
    "gn:admin2_code":"WHT",
    "gn:admin3_code":"56.0",
    "gn:admin4_code":"56078.0",
    "gn:asciiname":"Les Waibes",
    "gn:country_code":"BE",
    "gn:dem":150,
    "gn:feature_class":"P",
    "gn:feature_code":"PPL",
    "gn:name":"Les Waibes",
    "gn:population":0,
    "gn:timezone":"Europe/Brussels",
    "iso:country":"BE",
    "name:und_x_variant":[
        "Waibes",
        "Les Waibes"
    ],
    "wof:name":"Les Waibes",
    "wof:placetype":"locality"
},
  "geometry": {"coordinates":[4.28922,50.34502],"type":"Point"}
}