{
  "type": "Feature",
  "properties": {
    "gn:gn_country":"BE",
    "gn:gn_fcode":"PPL",
    "gn:gn_pop":0,
    "iso:country":"BE",
    "name:dut_x_preferred":[
        "Relegem"
    ],
    "name:eng_x_preferred":[
        "Relegem"
    ],
    "name:fre_x_preferred":[
        "Releghem"
    ],
    "name:hun_x_preferred":[
        "Relegem"
    ],
    "name:spa_x_preferred":[
        "Relegem"
    ],
    "name:unk_x_variant":[
        "Releghem"
    ],
    "qs_pg:aaroncc":"BE",
    "qs_pg:gn_country":"BE",
    "qs_pg:gn_fcode":"PPL",
    "qs_pg:gn_pop":0,
    "qs_pg:name":"Relegem",
    "qs_pg:name_adm0":"Belgique",
    "qs_pg:name_adm1":"Vlaams Brabant",
    "qs_pg:photos":16,
    "qs_pg:photos_1k":3,
    "qs_pg:photos_9k":1,
    "qs_pg:photos_9r":1,
    "qs_pg:photos_all":16,
    "qs_pg:photos_sr":1,
    "qs_pg:pop_sr":0,
    "qs_pg:qs_pg_placetype":"locality",
    "qs_pg:qs_pg_placetype_gp":"Town",
    "qs_pg:woe_adm0":23424757,
    "woe:adm0_id":23424757,
    "woe:name_adm0":"Belgique",
    "woe:name_adm1":"Vlaams Brabant",
    "woe:placetype":"Town",
    "wof:name":"Relegem",
    "wof:placetype":"locality"
},
  "geometry": {"coordinates":[4.27694,50.89908],"type":"Point"}
}