{
  "type": "Feature",
  "properties": {
    "gn:admin1_code":"WAL",
    "gn:admin2_code":"WLX",
    "gn:admin3_code":"83.0",
    "gn:admin4_code":"83034.0",
    "gn:asciiname":"Tintenard",
    "gn:country_code":"BE",
    "gn:dem":185,
    "gn:feature_class":"P",
    "gn:feature_code":"PPL",
    "gn:name":"Tintenard",
    "gn:population":0,
    "gn:timezone":"Europe/Brussels",
    "iso:country":"BE",
    "wof:name":"Tintenard",
    "wof:placetype":"locality"
},
  "geometry": {"coordinates":[5.34638,50.25507],"type":"Point"}
}