{
  "type": "Feature",
  "properties": {
    "gn:country":"BE",
    "gn:fcode":"PPL",
    "gn:population":0,
    "iso:country":"BE",
    "name:ceb_x_preferred":[
        "Vaux"
    ],
    "name:deu_x_preferred":[
        "Vaux"
    ],
    "name:epo_x_preferred":[
        "Vaux"
    ],
    "name:fra_x_preferred":[
        "Vaux"
    ],
    "name:hye_x_preferred":[
        "\u054e\u0578"
    ],
    "name:ita_x_preferred":[
        "Vaux"
    ],
    "name:jpn_x_preferred":[
        "\u30f4\u30a9\u30fc"
    ],
    "name:nds_x_preferred":[
        "Vaux"
    ],
    "name:nld_x_preferred":[
        "Vaux"
    ],
    "name:oci_x_preferred":[
        "Vaux"
    ],
    "name:pms_x_preferred":[
        "Vaux"
    ],
    "name:pol_x_preferred":[
        "Vaux"
    ],
    "name:por_x_preferred":[
        "Vaux"
    ],
    "name:slk_x_preferred":[
        "Vaux"
    ],
    "name:spa_x_preferred":[
        "Vaux"
    ],
    "name:swe_x_preferred":[
        "Vaux"
    ],
    "qs_pg:aaroncc":"BE",
    "qs_pg:gn_country":"BE",
    "qs_pg:gn_fcode":"PPL",
    "qs_pg:gn_pop":0,
    "qs_pg:name":"Vaux",
    "qs_pg:name_adm0":"Belgique",
    "qs_pg:name_adm1":"Luxembourg",
    "qs_pg:photos_9r":0,
    "qs_pg:photos_sr":0,
    "qs_pg:pop_sr":0,
    "qs_pg:qs_pg_placetype":"locality",
    "qs_pg:qs_pg_placetype_gp":"Town",
    "qs_pg:woe_adm0":23424757,
    "woe:adm0_id":23424757,
    "woe:name_adm0":"Belgique",
    "woe:name_adm1":"Luxembourg",
    "woe:placetype":"Town",
    "wof:name":"Vaux",
    "wof:placetype":"locality"
},
  "geometry": {"coordinates":[5.85286,50.1745],"type":"Point"}
}