{
  "type": "Feature",
  "properties": {
    "gn:admin1_code":"VLG",
    "gn:admin2_code":"VAN",
    "gn:admin3_code":"11.0",
    "gn:admin4_code":"11022.0",
    "gn:asciiname":"Zwartenheuvel",
    "gn:country_code":"BE",
    "gn:dem":20,
    "gn:feature_class":"P",
    "gn:feature_code":"PPL",
    "gn:name":"Zwartenheuvel",
    "gn:population":0,
    "gn:timezone":"Europe/Brussels",
    "iso:country":"BE",
    "wof:name":"Zwartenheuvel",
    "wof:placetype":"locality"
},
  "geometry": {"coordinates":[4.4529,51.38882],"type":"Point"}
}