{
  "type": "Feature",
  "properties": {
    "gn:admin1_code":"WAL",
    "gn:admin2_code":"WNA",
    "gn:admin3_code":"93.0",
    "gn:admin4_code":"93010.0",
    "gn:asciiname":"Battefer",
    "gn:country_code":"BE",
    "gn:dem":174,
    "gn:feature_class":"P",
    "gn:feature_code":"PPL",
    "gn:name":"Battefer",
    "gn:population":0,
    "gn:timezone":"Europe/Brussels",
    "iso:country":"BE",
    "wof:name":"Battefer",
    "wof:placetype":"locality"
},
  "geometry": {"coordinates":[4.42206,50.23303],"type":"Point"}
}