{
  "type": "Feature",
  "properties": {
    "gn:admin1_code":"VLG",
    "gn:admin2_code":"VOV",
    "gn:admin3_code":"42.0",
    "gn:admin4_code":"42003.0",
    "gn:asciiname":"Sluis",
    "gn:country_code":"BE",
    "gn:dem":2,
    "gn:feature_class":"P",
    "gn:feature_code":"PPL",
    "gn:name":"Sluis",
    "gn:population":0,
    "gn:timezone":"Europe/Brussels",
    "iso:country":"BE",
    "name:afr_x_preferred":[
        "Sluis"
    ],
    "name:ara_x_preferred":[
        "\u0633\u0644\u0627\u0648\u0633"
    ],
    "name:bre_x_preferred":[
        "Sluis"
    ],
    "name:bul_x_preferred":[
        "\u0421\u043b\u043e\u0439\u0441"
    ],
    "name:cat_x_preferred":[
        "Sluis"
    ],
    "name:ceb_x_preferred":[
        "Gemeente Sluis"
    ],
    "name:dan_x_preferred":[
        "Sluis"
    ],
    "name:deu_x_preferred":[
        "Sluis"
    ],
    "name:epo_x_preferred":[
        "Sluis"
    ],
    "name:eus_x_preferred":[
        "Sluis"
    ],
    "name:fas_x_preferred":[
        "\u0627\u0633\u0644\u0627\u06cc\u0633"
    ],
    "name:fin_x_preferred":[
        "Sluis"
    ],
    "name:fra_x_preferred":[
        "L'\u00c9cluse"
    ],
    "name:fry_x_preferred":[
        "Sl\u00fbs"
    ],
    "name:gle_x_preferred":[
        "Sluis"
    ],
    "name:glg_x_preferred":[
        "Sluis"
    ],
    "name:hye_x_preferred":[
        "\u054d\u056c\u0561\u0578\u0582\u057d"
    ],
    "name:ind_x_preferred":[
        "Sluis"
    ],
    "name:ita_x_preferred":[
        "Sluis"
    ],
    "name:jpn_x_preferred":[
        "\u30b9\u30ed\u30a4\u30b9"
    ],
    "name:lim_x_preferred":[
        "Sluis"
    ],
    "name:ltz_x_preferred":[
        "Sluis"
    ],
    "name:msa_x_preferred":[
        "Sluis"
    ],
    "name:nld_x_preferred":[
        "Sluis"
    ],
    "name:nor_x_preferred":[
        "Sluis"
    ],
    "name:pol_x_preferred":[
        "Sluis"
    ],
    "name:por_x_preferred":[
        "Sluis"
    ],
    "name:ron_x_preferred":[
        "Sluis"
    ],
    "name:rus_x_preferred":[
        "\u0421\u043b\u0451\u0439\u0441"
    ],
    "name:spa_x_preferred":[
        "Esclusa"
    ],
    "name:sqi_x_preferred":[
        "Sluis"
    ],
    "name:stq_x_preferred":[
        "Sluis"
    ],
    "name:swe_x_preferred":[
        "Sluis"
    ],
    "name:tur_x_preferred":[
        "Sluis"
    ],
    "name:vie_x_preferred":[
        "Sluis"
    ],
    "name:vls_x_preferred":[
        "Sluus"
    ],
    "name:vol_x_preferred":[
        "Sluis"
    ],
    "name:war_x_preferred":[
        "Sluis"
    ],
    "name:zea_x_preferred":[
        "Sluus"
    ],
    "name:zho_x_preferred":[
        "\u65af\u52d2\u4f0a\u65af"
    ],
    "wof:name":"Sluis",
    "wof:placetype":"locality"
},
  "geometry": {"coordinates":[3.98596,51.01961],"type":"Point"}
}