{
  "type": "Feature",
  "properties": {
    "gn:admin1_code":"VLG",
    "gn:admin2_code":"VLI",
    "gn:admin3_code":"73.0",
    "gn:admin4_code":"73042.0",
    "gn:asciiname":"Lanakerheide",
    "gn:country_code":"BE",
    "gn:dem":68,
    "gn:feature_class":"P",
    "gn:feature_code":"PPL",
    "gn:name":"Lanakerheide",
    "gn:population":0,
    "gn:timezone":"Europe/Brussels",
    "iso:country":"BE",
    "name:und_x_variant":[
        "Lanaeker Heide",
        "Lanakerheide"
    ],
    "wof:name":"Lanakerheide",
    "wof:placetype":"locality"
},
  "geometry": {"coordinates":[5.62837,50.89621],"type":"Point"}
}