{
  "type": "Feature",
  "properties": {
    "gn:admin1_code":"WAL",
    "gn:admin2_code":"WLG",
    "gn:admin3_code":"62.0",
    "gn:admin4_code":"62027.0",
    "gn:asciiname":"Mortroux",
    "gn:country_code":"BE",
    "gn:dem":114,
    "gn:feature_class":"P",
    "gn:feature_code":"PPL",
    "gn:name":"Mortroux",
    "gn:population":0,
    "gn:timezone":"Europe/Brussels",
    "iso:country":"BE",
    "name:cat_x_preferred":[
        "Mortroux"
    ],
    "name:fra_x_preferred":[
        "Mortroux"
    ],
    "name:lim_x_preferred":[
        "Mortroux"
    ],
    "name:ltz_x_preferred":[
        "Mortroux"
    ],
    "name:nld_x_preferred":[
        "Mortroux"
    ],
    "name:und_x_variant":[
        "Dalhem (Mortroux)"
    ],
    "wof:name":"Mortroux",
    "wof:placetype":"locality"
},
  "geometry": {"coordinates":[5.75289,50.7116],"type":"Point"}
}