{
  "type": "Feature",
  "properties": {
    "gn:admin1_code":"WAL",
    "gn:admin2_code":"WHT",
    "gn:admin3_code":"51.0",
    "gn:admin4_code":"51019.0",
    "gn:asciiname":"Bois",
    "gn:country_code":"BE",
    "gn:dem":101,
    "gn:feature_class":"P",
    "gn:feature_code":"PPL",
    "gn:name":"Bois",
    "gn:population":0,
    "gn:timezone":"Europe/Brussels",
    "iso:country":"BE",
    "name:ara_x_preferred":[
        "\u0628\u0648\u0627"
    ],
    "name:ben_x_preferred":[
        "\u09ac\u09cb\u0987\u09b8"
    ],
    "name:ceb_x_preferred":[
        "Bois"
    ],
    "name:deu_x_preferred":[
        "Bois"
    ],
    "name:ell_x_preferred":[
        "\u039c\u03c0\u03cc\u03b9\u03c2"
    ],
    "name:fas_x_preferred":[
        "\u0628\u0648\u06cc\u0633"
    ],
    "name:fra_x_preferred":[
        "Bois"
    ],
    "name:glg_x_preferred":[
        "Bois"
    ],
    "name:heb_x_preferred":[
        "\u05d1\u05d5\u05d0\u05d4"
    ],
    "name:hin_x_preferred":[
        "\u092c\u094b\u0907\u0938"
    ],
    "name:hun_x_preferred":[
        "Bois"
    ],
    "name:ind_x_preferred":[
        "Bois"
    ],
    "name:ita_x_preferred":[
        "Bois"
    ],
    "name:jpn_x_preferred":[
        "\u30dc\u30a2\u5ddd"
    ],
    "name:kor_x_preferred":[
        "\ubcf4\uc774\uc2a4"
    ],
    "name:nld_x_preferred":[
        "Bois"
    ],
    "name:oci_x_preferred":[
        "Bois"
    ],
    "name:pol_x_preferred":[
        "Bois"
    ],
    "name:por_x_preferred":[
        "Bois"
    ],
    "name:ron_x_preferred":[
        "Bois"
    ],
    "name:rus_x_preferred":[
        "\u0411\u0443\u0430"
    ],
    "name:spa_x_preferred":[
        "Bois"
    ],
    "name:swe_x_preferred":[
        "Bois"
    ],
    "name:tur_x_preferred":[
        "Bois"
    ],
    "name:ukr_x_preferred":[
        "\u0411\u043e\u0456\u0441"
    ],
    "name:urd_x_preferred":[
        "\u0628\u0648\u0627\u0626\u0633"
    ],
    "name:vie_x_preferred":[
        "S\u00f4ng Bois"
    ],
    "name:zho_cn_x_preferred":[
        "\u535a\u4f0a\u65af\u6cb3"
    ],
    "name:zho_tw_x_preferred":[
        "\u5e03\u74e6\u6cb3"
    ],
    "wof:name":"Bois",
    "wof:placetype":"locality"
},
  "geometry": {"coordinates":[3.73333,50.76667],"type":"Point"}
}