{
  "type": "Feature",
  "properties": {
    "gn:admin1_code":"WAL",
    "gn:admin2_code":"WHT",
    "gn:admin3_code":"51.0",
    "gn:admin4_code":"51019.0",
    "gn:asciiname":"Bois",
    "gn:country_code":"BE",
    "gn:dem":101,
    "gn:feature_class":"P",
    "gn:feature_code":"PPL",
    "gn:name":"Bois",
    "gn:population":0,
    "gn:timezone":"Europe/Brussels",
    "iso:country":"BE",
    "name:ceb_x_preferred":[
        "Bois"
    ],
    "name:deu_x_preferred":[
        "Bois"
    ],
    "name:fra_x_preferred":[
        "Bois"
    ],
    "name:glg_x_preferred":[
        "Bois"
    ],
    "name:ita_x_preferred":[
        "Bois"
    ],
    "name:nld_x_preferred":[
        "Bois"
    ],
    "name:oci_x_preferred":[
        "Bois"
    ],
    "name:pol_x_preferred":[
        "Bois"
    ],
    "name:ron_x_preferred":[
        "Bois"
    ],
    "name:rus_x_preferred":[
        "\u0411\u0443\u0430"
    ],
    "name:swe_x_preferred":[
        "Bois"
    ],
    "wof:name":"Bois",
    "wof:placetype":"locality"
},
  "geometry": {"coordinates":[3.73333,50.76667],"type":"Point"}
}