{
  "type": "Feature",
  "properties": {
    "gn:admin1_code":"VLG",
    "gn:admin2_code":"VWV",
    "gn:admin3_code":"36.0",
    "gn:admin4_code":"36010.0",
    "gn:asciiname":"Slijpshoek",
    "gn:country_code":"BE",
    "gn:dem":19,
    "gn:feature_class":"P",
    "gn:feature_code":"PPL",
    "gn:name":"Slijpshoek",
    "gn:population":0,
    "gn:timezone":"Europe/Brussels",
    "iso:country":"BE",
    "name:und_x_variant":[
        "Slypshoek",
        "Slijphoek",
        "Slijpshoek"
    ],
    "wof:name":"Slijpshoek",
    "wof:placetype":"locality"
},
  "geometry": {"coordinates":[3.09847,50.86902],"type":"Point"}
}