{
  "type": "Feature",
  "properties": {
    "gn:admin1_code":"VLG",
    "gn:admin2_code":"VBR",
    "gn:admin3_code":"24.0",
    "gn:admin4_code":"24135.0",
    "gn:asciiname":"Bensberg",
    "gn:country_code":"BE",
    "gn:dem":55,
    "gn:feature_class":"P",
    "gn:feature_code":"PPL",
    "gn:name":"Bensberg",
    "gn:population":0,
    "gn:timezone":"Europe/Brussels",
    "iso:country":"BE",
    "wof:name":"Bensberg",
    "wof:placetype":"locality"
},
  "geometry": {"coordinates":[4.85996,50.91401],"type":"Point"}
}