{
  "type": "Feature",
  "properties": {
    "gn:admin1_code":"WAL",
    "gn:admin2_code":"WNA",
    "gn:admin3_code":"91.0",
    "gn:admin4_code":"91143.0",
    "gn:asciiname":"Peront",
    "gn:country_code":"BE",
    "gn:dem":361,
    "gn:feature_class":"P",
    "gn:feature_code":"PPL",
    "gn:name":"Peront",
    "gn:population":0,
    "gn:timezone":"Europe/Brussels",
    "iso:country":"BE",
    "name:und_x_variant":[
        "Poront",
        "Peront"
    ],
    "wof:name":"Peront",
    "wof:placetype":"locality"
},
  "geometry": {"coordinates":[4.91667,49.81667],"type":"Point"}
}