{
  "type": "Feature",
  "properties": {
    "gn:country":"BE",
    "gn:fcode":"PPL",
    "gn:population":0,
    "iso:country":"BE",
    "name:eng_x_preferred":[
        "Oteppe"
    ],
    "name:fra_x_preferred":[
        "Oteppe"
    ],
    "name:gle_x_preferred":[
        "Oteppe"
    ],
    "name:hun_x_preferred":[
        "Oteppe"
    ],
    "name:nld_x_preferred":[
        "Oteppe"
    ],
    "name:und_x_variant":[
        "Burdinne (Oteppe)"
    ],
    "name:wln_x_preferred":[
        "\u00d4tepe"
    ],
    "qs_pg:aaroncc":"BE",
    "qs_pg:gn_country":"BE",
    "qs_pg:gn_fcode":"PPL",
    "qs_pg:gn_pop":0,
    "qs_pg:name":"Oteppe",
    "qs_pg:name_adm0":"Belgique",
    "qs_pg:name_adm1":"Li\u00e8ge",
    "qs_pg:photos":125,
    "qs_pg:photos_1k":25,
    "qs_pg:photos_9k":1,
    "qs_pg:photos_9r":3,
    "qs_pg:photos_all":125,
    "qs_pg:photos_sr":3,
    "qs_pg:pop_sr":0,
    "qs_pg:qs_pg_placetype":"locality",
    "qs_pg:qs_pg_placetype_gp":"Town",
    "qs_pg:woe_adm0":23424757,
    "woe:adm0_id":23424757,
    "woe:name_adm0":"Belgique",
    "woe:name_adm1":"Li\u00e8ge",
    "woe:placetype":"Town",
    "wof:name":"Oteppe",
    "wof:placetype":"locality"
},
  "geometry": {"coordinates":[5.12632,50.58008],"type":"Point"}
}