{
  "type": "Feature",
  "properties": {
    "gn:admin1_code":"VLG",
    "gn:admin2_code":"VLI",
    "gn:admin3_code":"73.0",
    "gn:admin4_code":"73098.0",
    "gn:asciiname":"Vrolingen",
    "gn:country_code":"BE",
    "gn:dem":50,
    "gn:feature_class":"P",
    "gn:feature_code":"PPL",
    "gn:name":"Vrolingen",
    "gn:population":0,
    "gn:timezone":"Europe/Brussels",
    "iso:country":"BE",
    "wof:name":"Vrolingen",
    "wof:placetype":"locality"
},
  "geometry": {"coordinates":[5.35549,50.83467],"type":"Point"}
}