{
  "type": "Feature",
  "properties": {
    "gn:admin1_code":"VLG",
    "gn:admin2_code":"VAN",
    "gn:admin3_code":"12.0",
    "gn:admin4_code":"12030.0",
    "gn:asciiname":"Puursheide",
    "gn:country_code":"BE",
    "gn:dem":3,
    "gn:feature_class":"P",
    "gn:feature_code":"PPL",
    "gn:name":"Puursheide",
    "gn:population":0,
    "gn:timezone":"Europe/Brussels",
    "iso:country":"BE",
    "name:und_x_variant":[
        "Puers-heide",
        "Puursheide"
    ],
    "wof:name":"Puursheide",
    "wof:placetype":"locality"
},
  "geometry": {"coordinates":[4.27902,51.06954],"type":"Point"}
}