{
  "type": "Feature",
  "properties": {
    "gn:admin1_code":"WAL",
    "gn:admin2_code":"WHT",
    "gn:admin3_code":"52.0",
    "gn:admin4_code":"52075.0",
    "gn:asciiname":"Pont a Migneloux",
    "gn:country_code":"BE",
    "gn:dem":142,
    "gn:feature_class":"P",
    "gn:feature_code":"PPL",
    "gn:name":"Pont \u00e0 Migneloux",
    "gn:population":0,
    "gn:timezone":"Europe/Brussels",
    "iso:country":"BE",
    "wof:name":"Pont a Migneloux",
    "wof:placetype":"locality"
},
  "geometry": {"coordinates":[4.46216,50.5002],"type":"Point"}
}