{
  "type": "Feature",
  "properties": {
    "gn:admin1_code":"WAL",
    "gn:admin2_code":"WLG",
    "gn:admin3_code":"63.0",
    "gn:admin4_code":"63023.0",
    "gn:asciiname":"Langes",
    "gn:country_code":"BE",
    "gn:dem":357,
    "gn:feature_class":"P",
    "gn:feature_code":"PPL",
    "gn:name":"Langes",
    "gn:population":0,
    "gn:timezone":"Europe/Brussels",
    "iso:country":"BE",
    "name:und_x_variant":[
        "Langestal",
        "Langes"
    ],
    "wof:name":"Langes",
    "wof:placetype":"locality"
},
  "geometry": {"coordinates":[6.06091,50.62318],"type":"Point"}
}