{
  "type": "Feature",
  "properties": {
    "gn:admin1_code":"VLG",
    "gn:admin2_code":"VBR",
    "gn:admin3_code":"24.0",
    "gn:admin4_code":"24055.0",
    "gn:asciiname":"Balkestraat",
    "gn:country_code":"BE",
    "gn:dem":16,
    "gn:feature_class":"P",
    "gn:feature_code":"PPL",
    "gn:name":"Balkestraat",
    "gn:population":0,
    "gn:timezone":"Europe/Brussels",
    "iso:country":"BE",
    "name:und_x_variant":[
        "Balkerstraat",
        "Balkestraat"
    ],
    "wof:name":"Balkestraat",
    "wof:placetype":"locality"
},
  "geometry": {"coordinates":[4.58915,50.92674],"type":"Point"}
}