{
  "type": "Feature",
  "properties": {
    "gn:country":"BE",
    "gn:fcode":"PPL",
    "gn:population":2236,
    "iso:country":"BE",
    "name:bre_x_preferred":[
        "Tinlot"
    ],
    "name:bul_x_preferred":[
        "\u0422\u0435\u043d\u043b\u043e"
    ],
    "name:cat_x_preferred":[
        "Tinlot"
    ],
    "name:ceb_x_preferred":[
        "Tinlot"
    ],
    "name:deu_x_preferred":[
        "Tinlot"
    ],
    "name:eng_x_preferred":[
        "Tinlot"
    ],
    "name:epo_x_preferred":[
        "Tinlot"
    ],
    "name:est_x_preferred":[
        "Tinlot vald"
    ],
    "name:est_x_variant":[
        "Tinlot' vald"
    ],
    "name:eus_x_preferred":[
        "Tinlot"
    ],
    "name:fas_x_preferred":[
        "\u062a\u0646\u0644\u0648"
    ],
    "name:fra_x_preferred":[
        "Tinlot"
    ],
    "name:hun_x_preferred":[
        "Tinlot"
    ],
    "name:ita_x_preferred":[
        "Tinlot"
    ],
    "name:lim_x_preferred":[
        "Tinlot"
    ],
    "name:ltz_x_preferred":[
        "Tinlot"
    ],
    "name:nld_x_preferred":[
        "Tinlot"
    ],
    "name:nob_x_preferred":[
        "Tinlot"
    ],
    "name:oci_x_preferred":[
        "Tinlot"
    ],
    "name:pol_x_preferred":[
        "Tinlot"
    ],
    "name:por_x_preferred":[
        "Tinlot"
    ],
    "name:ron_x_preferred":[
        "Tinlot"
    ],
    "name:rus_x_preferred":[
        "\u0422\u0435\u043d\u043b\u043e"
    ],
    "name:rus_x_variant":[
        "\u0422\u0438\u043d\u043b\u043e"
    ],
    "name:slk_x_preferred":[
        "Tinlot"
    ],
    "name:spa_x_preferred":[
        "Tinlot"
    ],
    "name:vie_x_preferred":[
        "Tinlot"
    ],
    "name:vol_x_preferred":[
        "Tinlot"
    ],
    "name:war_x_preferred":[
        "Tinlot"
    ],
    "name:zho_x_preferred":[
        "\u5766\u6d1b"
    ],
    "qs_pg:aaroncc":"BE",
    "qs_pg:gn_country":"BE",
    "qs_pg:gn_fcode":"PPL",
    "qs_pg:gn_pop":2236,
    "qs_pg:name":"Tinlot",
    "qs_pg:name_adm0":"Belgique",
    "qs_pg:name_adm1":"Li\u00e8ge",
    "qs_pg:photos_9k":1,
    "qs_pg:photos_9r":1,
    "qs_pg:photos_all":1,
    "qs_pg:photos_sr":0,
    "qs_pg:pop_sr":4,
    "qs_pg:qs_pg_placetype":"locality",
    "qs_pg:qs_pg_placetype_gp":"Town",
    "qs_pg:woe_adm0":23424757,
    "woe:adm0_id":23424757,
    "woe:name_adm0":"Belgique",
    "woe:name_adm1":"Li\u00e8ge",
    "woe:placetype":"Town",
    "wof:name":"Tinlot",
    "wof:placetype":"locality",
    "wof:population":2236
},
  "geometry": {"coordinates":[5.37755,50.47493],"type":"Point"}
}