{
  "type": "Feature",
  "properties": {
    "gn:admin1_code":"WAL",
    "gn:admin2_code":"WNA",
    "gn:admin3_code":"91.0",
    "gn:admin4_code":"91143.0",
    "gn:asciiname":"Les Quatre Bornes",
    "gn:country_code":"BE",
    "gn:dem":371,
    "gn:feature_class":"P",
    "gn:feature_code":"PPL",
    "gn:name":"Les Quatre Bornes",
    "gn:population":0,
    "gn:timezone":"Europe/Brussels",
    "iso:country":"BE",
    "name:und_x_variant":[
        "Les 4 Bornes",
        "Les Quatre Bornes"
    ],
    "wof:name":"Les Quatre Bornes",
    "wof:placetype":"locality"
},
  "geometry": {"coordinates":[4.89815,49.83831],"type":"Point"}
}