{
  "type": "Feature",
  "properties": {
    "gn:admin1_code":"VLG",
    "gn:admin2_code":"VOV",
    "gn:admin3_code":"44.0",
    "gn:admin4_code":"44072.0",
    "gn:asciiname":"Schaaperve",
    "gn:country_code":"BE",
    "gn:dem":5,
    "gn:feature_class":"P",
    "gn:feature_code":"PPL",
    "gn:name":"Schaaperve",
    "gn:population":0,
    "gn:timezone":"Europe/Brussels",
    "iso:country":"BE",
    "name:und_x_variant":[
        "Schaperye",
        "Schaaperve"
    ],
    "wof:name":"Schaaperve",
    "wof:placetype":"locality"
},
  "geometry": {"coordinates":[3.58333,51.16667],"type":"Point"}
}