{
  "type": "Feature",
  "properties": {
    "gn:admin1_code":"WAL",
    "gn:admin2_code":"WLX",
    "gn:admin3_code":"83.0",
    "gn:admin4_code":"83012.0",
    "gn:asciiname":"Hermanne",
    "gn:country_code":"BE",
    "gn:dem":270,
    "gn:feature_class":"P",
    "gn:feature_code":"PPL",
    "gn:name":"Hermanne",
    "gn:population":0,
    "gn:timezone":"Europe/Brussels",
    "iso:country":"BE",
    "wof:name":"Hermanne",
    "wof:placetype":"locality"
},
  "geometry": {"coordinates":[5.48666,50.40978],"type":"Point"}
}