{
  "type": "Feature",
  "properties": {
    "gn:admin1_code":"VLG",
    "gn:admin2_code":"VAN",
    "gn:admin3_code":"13.0",
    "gn:admin4_code":"13025.0",
    "gn:asciiname":"Stokt",
    "gn:country_code":"BE",
    "gn:dem":25,
    "gn:feature_class":"P",
    "gn:feature_code":"PPL",
    "gn:name":"Stokt",
    "gn:population":0,
    "gn:timezone":"Europe/Brussels",
    "iso:country":"BE",
    "wof:name":"Stokt",
    "wof:placetype":"locality"
},
  "geometry": {"coordinates":[5.0591,51.18927],"type":"Point"}
}