{
  "type": "Feature",
  "properties": {
    "gn:admin1_code":"WAL",
    "gn:admin2_code":"WLG",
    "gn:admin3_code":"63.0",
    "gn:admin4_code":"63067.0",
    "gn:asciiname":"Breitfeld",
    "gn:country_code":"BE",
    "gn:dem":432,
    "gn:feature_class":"P",
    "gn:feature_code":"PPL",
    "gn:name":"Breitfeld",
    "gn:population":0,
    "gn:timezone":"Europe/Brussels",
    "iso:country":"BE",
    "wof:name":"Breitfeld",
    "wof:placetype":"locality"
},
  "geometry": {"coordinates":[6.15389,50.26417],"type":"Point"}
}