{
  "type": "Feature",
  "properties": {
    "gn:admin1_code":"VLG",
    "gn:admin2_code":"VAN",
    "gn:admin3_code":"11.0",
    "gn:admin4_code":"11053.0",
    "gn:asciiname":"Blekenberg",
    "gn:country_code":"BE",
    "gn:dem":25,
    "gn:feature_class":"P",
    "gn:feature_code":"PPL",
    "gn:name":"Blekenberg",
    "gn:population":0,
    "gn:timezone":"Europe/Brussels",
    "iso:country":"BE",
    "name:und_x_variant":[
        "Bleekenberg",
        "Blekenberg"
    ],
    "wof:name":"Blekenberg",
    "wof:placetype":"locality"
},
  "geometry": {"coordinates":[4.54693,51.38305],"type":"Point"}
}