{
  "type": "Feature",
  "properties": {
    "gn:admin1_code":"WAL",
    "gn:admin2_code":"WNA",
    "gn:admin3_code":"92.0",
    "gn:admin4_code":"92006.0",
    "gn:asciiname":"Trieu d'Avillon",
    "gn:country_code":"BE",
    "gn:dem":279,
    "gn:feature_class":"P",
    "gn:feature_code":"PPL",
    "gn:name":"Trieu d'Avillon",
    "gn:population":0,
    "gn:timezone":"Europe/Brussels",
    "iso:country":"BE",
    "name:und_x_variant":[
        "Trieu-d'Avillon-Fays",
        "Trieu d'Avillon"
    ],
    "wof:name":"Trieu d'Avillon",
    "wof:placetype":"locality"
},
  "geometry": {"coordinates":[4.99758,50.39331],"type":"Point"}
}