{
  "type": "Feature",
  "properties": {
    "gn:admin1_code":"WAL",
    "gn:admin2_code":"WHT",
    "gn:admin3_code":"55.0",
    "gn:admin4_code":"55039.0",
    "gn:asciiname":"Beauregard",
    "gn:country_code":"BE",
    "gn:dem":64,
    "gn:feature_class":"P",
    "gn:feature_code":"PPL",
    "gn:name":"Beauregard",
    "gn:population":0,
    "gn:timezone":"Europe/Brussels",
    "iso:country":"BE",
    "wof:name":"Beauregard",
    "wof:placetype":"locality"
},
  "geometry": {"coordinates":[3.90287,50.65195],"type":"Point"}
}