{
  "type": "Feature",
  "properties": {
    "gn:admin1_code":"WAL",
    "gn:admin2_code":"WHT",
    "gn:admin3_code":"55.0",
    "gn:admin4_code":"55039.0",
    "gn:asciiname":"Beauregard",
    "gn:country_code":"BE",
    "gn:dem":64,
    "gn:feature_class":"P",
    "gn:feature_code":"PPL",
    "gn:name":"Beauregard",
    "gn:population":0,
    "gn:timezone":"Europe/Brussels",
    "iso:country":"BE",
    "name:ceb_x_preferred":[
        "Beauregard"
    ],
    "name:deu_x_preferred":[
        "Beauregard"
    ],
    "name:fas_x_preferred":[
        "\u0628\u0648\u0631\u06af\u0627\u0631\u062f"
    ],
    "name:fra_x_preferred":[
        "Beauregard"
    ],
    "name:hun_x_preferred":[
        "Beauregard"
    ],
    "name:ita_x_preferred":[
        "Beauregard"
    ],
    "name:kor_x_preferred":[
        "\ubcf4\ub974\uac00\ub974"
    ],
    "name:nds_x_preferred":[
        "Beauregard"
    ],
    "name:nld_x_preferred":[
        "Beauregard"
    ],
    "name:pol_x_preferred":[
        "Beauregard"
    ],
    "name:por_x_preferred":[
        "Beauregard"
    ],
    "name:ron_x_preferred":[
        "Beauregard"
    ],
    "name:rus_x_preferred":[
        "\u0411\u043e\u0440\u0435\u0433\u0430\u0440"
    ],
    "name:slk_x_preferred":[
        "Beauregard"
    ],
    "name:spa_x_preferred":[
        "Beauregard"
    ],
    "name:srp_x_preferred":[
        "\u0411\u043e\u0440\u0435\u0433\u0430\u0440\u0434"
    ],
    "name:swe_x_preferred":[
        "Beauregard"
    ],
    "name:ukr_x_preferred":[
        "\u0411\u043e\u0440\u0435\u0433\u0430\u0440"
    ],
    "wof:name":"Beauregard",
    "wof:placetype":"locality"
},
  "geometry": {"coordinates":[3.90287,50.65195],"type":"Point"}
}