{
  "type": "Feature",
  "properties": {
    "gn:gn_country":"BE",
    "gn:gn_fcode":"PPL",
    "gn:gn_pop":0,
    "iso:country":"BE",
    "name:dut_x_preferred":[
        "Rocherath"
    ],
    "name:eng_x_preferred":[
        "Rocherath"
    ],
    "name:fre_x_preferred":[
        "Rocherath"
    ],
    "name:ger_x_preferred":[
        "Rocherath-Krinkelt"
    ],
    "name:jpn_x_preferred":[
        "\u30ed\u30c1\u30a7\u30e9\u30b9"
    ],
    "name:ltz_x_preferred":[
        "Rocherath"
    ],
    "name:unk_x_variant":[
        "Bullange (Rocherath)"
    ],
    "qs_pg:aaroncc":"BE",
    "qs_pg:gn_country":"BE",
    "qs_pg:gn_fcode":"PPL",
    "qs_pg:gn_pop":0,
    "qs_pg:name":"Rocherath",
    "qs_pg:name_adm0":"Belgique",
    "qs_pg:name_adm1":"Li\u00e8ge",
    "qs_pg:photos":13,
    "qs_pg:photos_1k":3,
    "qs_pg:photos_9k":1,
    "qs_pg:photos_9r":1,
    "qs_pg:photos_all":13,
    "qs_pg:photos_sr":1,
    "qs_pg:pop_sr":0,
    "qs_pg:qs_pg_placetype":"locality",
    "qs_pg:qs_pg_placetype_gp":"Town",
    "qs_pg:woe_adm0":23424757,
    "woe:adm0_id":23424757,
    "woe:name_adm0":"Belgique",
    "woe:name_adm1":"Li\u00e8ge",
    "woe:placetype":"Town",
    "wof:name":"Rocherath",
    "wof:placetype":"locality"
},
  "geometry": {"coordinates":[6.30049,50.43706],"type":"Point"}
}