{
  "type": "Feature",
  "properties": {
    "gn:admin1_code":"WAL",
    "gn:admin2_code":"WHT",
    "gn:admin3_code":"55.0",
    "gn:admin4_code":"55004.0",
    "gn:asciiname":"Barriere d'Ecaussinnes",
    "gn:country_code":"BE",
    "gn:dem":106,
    "gn:feature_class":"P",
    "gn:feature_code":"PPL",
    "gn:name":"Barri\u00e8re d\u2019\u00c9caussinnes",
    "gn:population":0,
    "gn:timezone":"Europe/Brussels",
    "iso:country":"BE",
    "name:und_x_variant":[
        "Barri\u00e8re d\u2019\u00c9caussines",
        "Barri\u00e8re d\u2019\u00c9caussinnes"
    ],
    "wof:name":"Barriere d'Ecaussinnes",
    "wof:placetype":"locality"
},
  "geometry": {"coordinates":[4.13507,50.59142],"type":"Point"}
}