{
  "type": "Feature",
  "properties": {
    "gn:admin1_code":"WAL",
    "gn:admin2_code":"WNA",
    "gn:admin3_code":"92.0",
    "gn:admin4_code":"92140.0",
    "gn:asciiname":"Ordin",
    "gn:country_code":"BE",
    "gn:dem":105,
    "gn:feature_class":"P",
    "gn:feature_code":"PPL",
    "gn:name":"Ordin",
    "gn:population":0,
    "gn:timezone":"Europe/Brussels",
    "iso:country":"BE",
    "wof:name":"Ordin",
    "wof:placetype":"locality"
},
  "geometry": {"coordinates":[4.70615,50.4688],"type":"Point"}
}