{
  "type": "Feature",
  "properties": {
    "gn:admin1_code":"VLG",
    "gn:admin2_code":"VLI",
    "gn:admin3_code":"71.0",
    "gn:admin4_code":"71016.0",
    "gn:asciiname":"Vlasberg",
    "gn:country_code":"BE",
    "gn:dem":83,
    "gn:feature_class":"P",
    "gn:feature_code":"PPL",
    "gn:name":"Vlasberg",
    "gn:population":0,
    "gn:timezone":"Europe/Brussels",
    "iso:country":"BE",
    "wof:name":"Vlasberg",
    "wof:placetype":"locality"
},
  "geometry": {"coordinates":[5.43333,50.98333],"type":"Point"}
}