{
  "type": "Feature",
  "properties": {
    "gn:admin1_code":"VLG",
    "gn:admin2_code":"VOV",
    "gn:admin3_code":"41.0",
    "gn:admin4_code":"41018.0",
    "gn:asciiname":"Waterloze",
    "gn:country_code":"BE",
    "gn:dem":54,
    "gn:feature_class":"P",
    "gn:feature_code":"PPL",
    "gn:name":"Waterloze",
    "gn:population":0,
    "gn:timezone":"Europe/Brussels",
    "iso:country":"BE",
    "name:und_x_variant":[
        "Waterlooze",
        "Waterloos",
        "Waterloze"
    ],
    "wof:name":"Waterloze",
    "wof:placetype":"locality"
},
  "geometry": {"coordinates":[3.90124,50.82899999999999],"type":"Point"}
}