{
  "type": "Feature",
  "properties": {
    "gn:admin1_code":"WAL",
    "gn:admin2_code":"WNA",
    "gn:admin3_code":"92.0",
    "gn:admin4_code":"92141.0",
    "gn:asciiname":"Mehagnoul",
    "gn:country_code":"BE",
    "gn:dem":162,
    "gn:feature_class":"P",
    "gn:feature_code":"PPL",
    "gn:name":"Mehagnoul",
    "gn:population":0,
    "gn:timezone":"Europe/Brussels",
    "iso:country":"BE",
    "wof:name":"Mehagnoul",
    "wof:placetype":"locality"
},
  "geometry": {"coordinates":[4.82425,50.55244],"type":"Point"}
}