{
  "type": "Feature",
  "properties": {
    "gn:admin1_code":"WAL",
    "gn:admin2_code":"WBR",
    "gn:admin3_code":"25.0",
    "gn:admin4_code":"25110.0",
    "gn:asciiname":"Vert Coucou",
    "gn:country_code":"BE",
    "gn:dem":115,
    "gn:feature_class":"P",
    "gn:feature_code":"PPL",
    "gn:name":"Vert Coucou",
    "gn:population":0,
    "gn:timezone":"Europe/Brussels",
    "iso:country":"BE",
    "wof:name":"Vert Coucou",
    "wof:placetype":"locality"
},
  "geometry": {"coordinates":[4.41865,50.69825],"type":"Point"}
}