{
  "type": "Feature",
  "properties": {
    "gn:admin1_code":"VLG",
    "gn:admin2_code":"VOV",
    "gn:admin3_code":"44.0",
    "gn:admin4_code":"44040.0",
    "gn:asciiname":"Rotsenheirweg",
    "gn:country_code":"BE",
    "gn:dem":10,
    "gn:feature_class":"P",
    "gn:feature_code":"PPL",
    "gn:name":"Rotsenheirweg",
    "gn:population":0,
    "gn:timezone":"Europe/Brussels",
    "iso:country":"BE",
    "name:und_x_variant":[
        "Rodschenheirweg",
        "Rotsenheirweg"
    ],
    "wof:name":"Rotsenheirweg",
    "wof:placetype":"locality"
},
  "geometry": {"coordinates":[3.78333,51.01667],"type":"Point"}
}