{
  "type": "Feature",
  "properties": {
    "gn:admin1_code":"VLG",
    "gn:admin2_code":"VOV",
    "gn:asciiname":"Rode Sluis",
    "gn:country_code":"BE",
    "gn:dem":2,
    "gn:feature_class":"P",
    "gn:feature_code":"PPL",
    "gn:name":"Rode Sluis",
    "gn:population":0,
    "gn:timezone":"Europe/Brussels",
    "iso:country":"BE",
    "wof:name":"Rode Sluis",
    "wof:placetype":"locality"
},
  "geometry": {"coordinates":[3.91558,51.2169],"type":"Point"}
}