{
  "type": "Feature",
  "properties": {
    "gn:admin1_code":"WAL",
    "gn:admin2_code":"WLX",
    "gn:admin3_code":"82.0",
    "gn:admin4_code":"82038.0",
    "gn:asciiname":"Fosset",
    "gn:country_code":"BE",
    "gn:dem":395,
    "gn:feature_class":"P",
    "gn:feature_code":"PPL",
    "gn:name":"Fosset",
    "gn:population":0,
    "gn:timezone":"Europe/Brussels",
    "iso:country":"BE",
    "name:deu_x_preferred":[
        "Fosset"
    ],
    "name:nld_x_preferred":[
        "Fosset"
    ],
    "wof:name":"Fosset",
    "wof:placetype":"locality"
},
  "geometry": {"coordinates":[5.55827,50.02977],"type":"Point"}
}