{
  "type": "Feature",
  "properties": {
    "gn:admin1_code":"VLG",
    "gn:admin2_code":"VLI",
    "gn:admin3_code":"71.0",
    "gn:admin4_code":"71004.0",
    "gn:asciiname":"Klitsberg",
    "gn:country_code":"BE",
    "gn:dem":42,
    "gn:feature_class":"P",
    "gn:feature_code":"PPL",
    "gn:name":"Klitsberg",
    "gn:population":0,
    "gn:timezone":"Europe/Brussels",
    "iso:country":"BE",
    "wof:name":"Klitsberg",
    "wof:placetype":"locality"
},
  "geometry": {"coordinates":[5.16083,51.03859],"type":"Point"}
}