{
  "type": "Feature",
  "properties": {
    "gn:admin1_code":"WAL",
    "gn:admin2_code":"WHT",
    "gn:admin3_code":"57.0",
    "gn:admin4_code":"57062.0",
    "gn:asciiname":"La Carne",
    "gn:country_code":"BE",
    "gn:dem":32,
    "gn:feature_class":"P",
    "gn:feature_code":"PPL",
    "gn:name":"La Carne",
    "gn:population":0,
    "gn:timezone":"Europe/Brussels",
    "iso:country":"BE",
    "name:und_x_variant":[
        "Le Carne",
        "La Carne"
    ],
    "wof:name":"La Carne",
    "wof:placetype":"locality"
},
  "geometry": {"coordinates":[3.37779,50.68293],"type":"Point"}
}