{
  "type": "Feature",
  "properties": {
    "gn:admin1_code":"WAL",
    "gn:admin2_code":"WLG",
    "gn:admin3_code":"62.0",
    "gn:admin4_code":"62120.0",
    "gn:asciiname":"Hoc",
    "gn:country_code":"BE",
    "gn:dem":219,
    "gn:feature_class":"P",
    "gn:feature_code":"PPL",
    "gn:name":"Hoc",
    "gn:population":0,
    "gn:timezone":"Europe/Brussels",
    "iso:country":"BE",
    "name:bar_x_preferred":[
        "Hoc"
    ],
    "name:deu_x_preferred":[
        "Hoc"
    ],
    "name:und_x_variant":[
        "En Hoc",
        "Le Hoc"
    ],
    "wof:name":"Hoc",
    "wof:placetype":"locality"
},
  "geometry": {"coordinates":[5.45,50.56667],"type":"Point"}
}