{
  "type": "Feature",
  "properties": {
    "gn:admin1_code":"WAL",
    "gn:admin2_code":"WLX",
    "gn:admin3_code":"85.0",
    "gn:admin4_code":"85011.0",
    "gn:asciiname":"Le Prieure",
    "gn:country_code":"BE",
    "gn:dem":230,
    "gn:feature_class":"P",
    "gn:feature_code":"PPL",
    "gn:name":"Le Prieur\u00e9",
    "gn:population":0,
    "gn:timezone":"Europe/Brussels",
    "iso:country":"BE",
    "wof:name":"Le Prieure",
    "wof:placetype":"locality"
},
  "geometry": {"coordinates":[5.18333,49.71667],"type":"Point"}
}