{
  "type": "Feature",
  "properties": {
    "gn:gn_country":"BE",
    "gn:gn_fcode":"PPL",
    "gn:gn_pop":27297,
    "gn:population":27297,
    "iso:country":"BE",
    "name:ara_x_preferred":[
        "\u0623\u0646"
    ],
    "name:bre_x_preferred":[
        "Ans"
    ],
    "name:bul_x_preferred":[
        "\u0410\u043d\u0441"
    ],
    "name:cat_x_preferred":[
        "Ans"
    ],
    "name:ceb_x_preferred":[
        "Ans"
    ],
    "name:dan_x_preferred":[
        "Ans"
    ],
    "name:deu_x_preferred":[
        "Ans"
    ],
    "name:eng_x_preferred":[
        "Ans"
    ],
    "name:epo_x_preferred":[
        "Ans"
    ],
    "name:eus_x_preferred":[
        "Ans"
    ],
    "name:fas_x_preferred":[
        "\u0622\u0646"
    ],
    "name:fra_x_preferred":[
        "Ans"
    ],
    "name:hun_x_preferred":[
        "Ans"
    ],
    "name:ita_x_preferred":[
        "Ans"
    ],
    "name:jpn_x_preferred":[
        "\u30a2\u30f3\u30b9"
    ],
    "name:lat_x_preferred":[
        "Ans"
    ],
    "name:lav_x_preferred":[
        "Ansa"
    ],
    "name:lim_x_preferred":[
        "Ans"
    ],
    "name:ltz_x_preferred":[
        "Ans"
    ],
    "name:mkd_x_preferred":[
        "\u0410\u043d\u0441"
    ],
    "name:nld_x_preferred":[
        "Ans"
    ],
    "name:nob_x_preferred":[
        "Ans"
    ],
    "name:oci_x_preferred":[
        "Ans"
    ],
    "name:pol_x_preferred":[
        "Ans"
    ],
    "name:por_x_preferred":[
        "Ans"
    ],
    "name:ron_x_preferred":[
        "Ans"
    ],
    "name:rus_x_preferred":[
        "\u0410\u043d\u0441"
    ],
    "name:slk_x_preferred":[
        "Ans"
    ],
    "name:spa_x_preferred":[
        "Ans"
    ],
    "name:swe_x_preferred":[
        "Ans"
    ],
    "name:vie_x_preferred":[
        "Ans"
    ],
    "name:vol_x_preferred":[
        "Ans"
    ],
    "name:war_x_preferred":[
        "Ans"
    ],
    "name:wln_x_preferred":[
        "Anse"
    ],
    "name:zho_x_preferred":[
        "\u6602\u65af"
    ],
    "qs_pg:aaroncc":"BE",
    "qs_pg:gn_country":"BE",
    "qs_pg:gn_fcode":"PPL",
    "qs_pg:gn_pop":27297,
    "qs_pg:name":"Ans",
    "qs_pg:name_adm0":"Belgique",
    "qs_pg:name_adm1":"Li\u00e8ge",
    "qs_pg:photos":124,
    "qs_pg:photos_1k":25,
    "qs_pg:photos_9k":7,
    "qs_pg:photos_9r":7,
    "qs_pg:photos_all":1492,
    "qs_pg:photos_sr":3,
    "qs_pg:pop_sr":7,
    "qs_pg:qs_pg_placetype":"locality",
    "qs_pg:qs_pg_placetype_gp":"Town",
    "qs_pg:woe_adm0":23424757,
    "woe:adm0_id":23424757,
    "woe:name_adm0":"Belgique",
    "woe:name_adm1":"Li\u00e8ge",
    "woe:placetype":"Town",
    "wof:name":"Ans",
    "wof:placetype":"locality",
    "wof:population":27297
},
  "geometry": {"coordinates":[5.52029,50.6623],"type":"Point"}
}