{
  "type": "Feature",
  "properties": {
    "gn:admin1_code":"WAL",
    "gn:admin2_code":"WLX",
    "gn:admin3_code":"84.0",
    "gn:admin4_code":"84035.0",
    "gn:asciiname":"Devant la Het",
    "gn:country_code":"BE",
    "gn:dem":498,
    "gn:feature_class":"P",
    "gn:feature_code":"PPL",
    "gn:name":"Devant la Het",
    "gn:population":0,
    "gn:timezone":"Europe/Brussels",
    "iso:country":"BE",
    "name:und_x_variant":[
        "Devant la Heid",
        "Devant la Het"
    ],
    "wof:name":"Devant la Het",
    "wof:placetype":"locality"
},
  "geometry": {"coordinates":[5.28333,49.95],"type":"Point"}
}