{
  "type": "Feature",
  "properties": {
    "gn:admin1_code":"VLG",
    "gn:admin2_code":"VWV",
    "gn:admin3_code":"37.0",
    "gn:admin4_code":"37017.0",
    "gn:asciiname":"Kokeldries",
    "gn:country_code":"BE",
    "gn:dem":11,
    "gn:feature_class":"P",
    "gn:feature_code":"PPL",
    "gn:name":"Kokeldries",
    "gn:population":0,
    "gn:timezone":"Europe/Brussels",
    "iso:country":"BE",
    "name:und_x_variant":[
        "Kokeldriesch",
        "Kokeldries"
    ],
    "wof:name":"Kokeldries",
    "wof:placetype":"locality"
},
  "geometry": {"coordinates":[3.36667,50.91667],"type":"Point"}
}