{
  "type": "Feature",
  "properties": {
    "gn:admin1_code":"VLG",
    "gn:admin2_code":"VWV",
    "gn:admin3_code":"36.0",
    "gn:admin4_code":"36011.0",
    "gn:asciiname":"Heihoek",
    "gn:country_code":"BE",
    "gn:dem":43,
    "gn:feature_class":"P",
    "gn:feature_code":"PPL",
    "gn:name":"Heihoek",
    "gn:population":0,
    "gn:timezone":"Europe/Brussels",
    "iso:country":"BE",
    "wof:name":"Heihoek",
    "wof:placetype":"locality"
},
  "geometry": {"coordinates":[3.15442,51.00411],"type":"Point"}
}