{
  "type": "Feature",
  "properties": {
    "gn:admin1_code":"WAL",
    "gn:asciiname":"Ruinsette",
    "gn:country_code":"BE",
    "gn:dem":139,
    "gn:feature_class":"P",
    "gn:feature_code":"PPL",
    "gn:name":"Ruinsette",
    "gn:population":0,
    "gn:timezone":"Europe/Brussels",
    "iso:country":"BE",
    "wof:name":"Ruinsette",
    "wof:placetype":"locality"
},
  "geometry": {"coordinates":[3.83333,50.35],"type":"Point"}
}