{
  "type": "Feature",
  "properties": {
    "gn:admin1_code":"VLG",
    "gn:admin2_code":"VOV",
    "gn:admin3_code":"44.0",
    "gn:admin4_code":"44043.0",
    "gn:asciiname":"Makegem",
    "gn:country_code":"BE",
    "gn:dem":35,
    "gn:feature_class":"P",
    "gn:feature_code":"PPL",
    "gn:name":"Makegem",
    "gn:population":0,
    "gn:timezone":"Europe/Brussels",
    "iso:country":"BE",
    "wof:name":"Makegem",
    "wof:placetype":"locality"
},
  "geometry": {"coordinates":[3.71558,50.94018],"type":"Point"}
}