{
  "type": "Feature",
  "properties": {
    "gn:admin1_code":"WAL",
    "gn:admin2_code":"WLG",
    "gn:admin3_code":"62.0",
    "gn:admin4_code":"62099.0",
    "gn:asciiname":"Vaux",
    "gn:country_code":"BE",
    "gn:dem":218,
    "gn:feature_class":"P",
    "gn:feature_code":"PPL",
    "gn:name":"Vaux",
    "gn:population":0,
    "gn:timezone":"Europe/Brussels",
    "iso:country":"BE",
    "wof:name":"Vaux",
    "wof:placetype":"locality"
},
  "geometry": {"coordinates":[5.74133,50.65749],"type":"Point"}
}