{
  "type": "Feature",
  "properties": {
    "gn:admin1_code":"WAL",
    "gn:admin2_code":"WLG",
    "gn:admin3_code":"62.0",
    "gn:admin4_code":"62099.0",
    "gn:asciiname":"Vaux",
    "gn:country_code":"BE",
    "gn:dem":218,
    "gn:feature_class":"P",
    "gn:feature_code":"PPL",
    "gn:name":"Vaux",
    "gn:population":0,
    "gn:timezone":"Europe/Brussels",
    "iso:country":"BE",
    "name:ceb_x_preferred":[
        "Vaux"
    ],
    "name:deu_x_preferred":[
        "Vaux"
    ],
    "name:epo_x_preferred":[
        "Vaux"
    ],
    "name:fra_x_preferred":[
        "Vaux"
    ],
    "name:hye_x_preferred":[
        "\u054e\u0578"
    ],
    "name:ita_x_preferred":[
        "Vaux"
    ],
    "name:jpn_x_preferred":[
        "\u30f4\u30a9\u30fc"
    ],
    "name:nds_x_preferred":[
        "Vaux"
    ],
    "name:nld_x_preferred":[
        "Vaux"
    ],
    "name:oci_x_preferred":[
        "Vaux"
    ],
    "name:pms_x_preferred":[
        "Vaux"
    ],
    "name:pol_x_preferred":[
        "Vaux"
    ],
    "name:por_x_preferred":[
        "Vaux"
    ],
    "name:slk_x_preferred":[
        "Vaux"
    ],
    "name:spa_x_preferred":[
        "Vaux"
    ],
    "name:swe_x_preferred":[
        "Vaux"
    ],
    "wof:name":"Vaux",
    "wof:placetype":"locality"
},
  "geometry": {"coordinates":[5.74133,50.65749],"type":"Point"}
}