{
  "type": "Feature",
  "properties": {
    "gn:admin1_code":"WAL",
    "gn:admin2_code":"WHT",
    "gn:admin3_code":"52.0",
    "gn:admin4_code":"52011.0",
    "gn:asciiname":"Try d'Haies",
    "gn:country_code":"BE",
    "gn:dem":188,
    "gn:feature_class":"P",
    "gn:feature_code":"PPL",
    "gn:name":"Try d'Haies",
    "gn:population":0,
    "gn:timezone":"Europe/Brussels",
    "iso:country":"BE",
    "wof:name":"Try d'Haies",
    "wof:placetype":"locality"
},
  "geometry": {"coordinates":[4.45,50.36667],"type":"Point"}
}