{
  "type": "Feature",
  "properties": {
    "gn:admin1_code":"WAL",
    "gn:admin2_code":"WLX",
    "gn:admin3_code":"84.0",
    "gn:admin4_code":"84033.0",
    "gn:asciiname":"Nobipre",
    "gn:country_code":"BE",
    "gn:dem":475,
    "gn:feature_class":"P",
    "gn:feature_code":"PPL",
    "gn:name":"Nobipr\u00e9",
    "gn:population":0,
    "gn:timezone":"Europe/Brussels",
    "iso:country":"BE",
    "wof:name":"Nobipre",
    "wof:placetype":"locality"
},
  "geometry": {"coordinates":[5.61667,49.81667],"type":"Point"}
}