{
  "type": "Feature",
  "properties": {
    "gn:admin1_code":"WAL",
    "gn:admin2_code":"WHT",
    "gn:asciiname":"Vlasselaar",
    "gn:country_code":"BE",
    "gn:dem":66,
    "gn:feature_class":"P",
    "gn:feature_code":"PPL",
    "gn:name":"Vlasselaar",
    "gn:population":0,
    "gn:timezone":"Europe/Brussels",
    "iso:country":"BE",
    "name:und_x_variant":[
        "Vlasselaer",
        "Vlasselaar"
    ],
    "wof:name":"Vlasselaar",
    "wof:placetype":"locality"
},
  "geometry": {"coordinates":[4.76667,50.95],"type":"Point"}
}