{
  "type": "Feature",
  "properties": {
    "gn:admin1_code":"WAL",
    "gn:admin2_code":"WLG",
    "gn:admin3_code":"61.0",
    "gn:admin4_code":"61068.0",
    "gn:asciiname":"Cabendes",
    "gn:country_code":"BE",
    "gn:dem":140,
    "gn:feature_class":"P",
    "gn:feature_code":"PPL",
    "gn:name":"Cabendes",
    "gn:population":0,
    "gn:timezone":"Europe/Brussels",
    "iso:country":"BE",
    "wof:name":"Cabendes",
    "wof:placetype":"locality"
},
  "geometry": {"coordinates":[5.28186,50.56262],"type":"Point"}
}