{
  "type": "Feature",
  "properties": {
    "gn:gn_country":"BE",
    "gn:gn_fcode":"PPL",
    "gn:gn_pop":0,
    "iso:country":"BE",
    "name:eng_x_preferred":[
        "Ch\u00e2telineau"
    ],
    "name:fra_x_preferred":[
        "Ch\u00e2telineau"
    ],
    "name:hun_x_preferred":[
        "Ch\u00e2telineau"
    ],
    "name:nld_x_preferred":[
        "Ch\u00e2telineau"
    ],
    "name:swe_x_preferred":[
        "Ch\u00e2telineau"
    ],
    "name:wln_x_preferred":[
        "Tcheslinea"
    ],
    "qs_pg:aaroncc":"BE",
    "qs_pg:gn_country":"BE",
    "qs_pg:gn_fcode":"PPL",
    "qs_pg:gn_pop":0,
    "qs_pg:name":"Ch\u00e2telineau",
    "qs_pg:name_adm0":"Belgique",
    "qs_pg:name_adm1":"Hainaut",
    "qs_pg:photos_9k":1,
    "qs_pg:photos_9r":1,
    "qs_pg:photos_all":1,
    "qs_pg:photos_sr":0,
    "qs_pg:pop_sr":0,
    "qs_pg:qs_pg_placetype":"locality",
    "qs_pg:qs_pg_placetype_gp":"Town",
    "qs_pg:woe_adm0":23424757,
    "woe:adm0_id":23424757,
    "woe:name_adm0":"Belgique",
    "woe:name_adm1":"Hainaut",
    "woe:placetype":"Town",
    "wof:name":"Ch\u00e2telineau",
    "wof:placetype":"locality"
},
  "geometry": {"coordinates":[4.52016,50.415],"type":"Point"}
}