{
  "type": "Feature",
  "properties": {
    "gn:admin1_code":"WAL",
    "gn:admin2_code":"WLG",
    "gn:admin3_code":"62.0",
    "gn:admin4_code":"62038.0",
    "gn:asciiname":"Chantraine",
    "gn:country_code":"BE",
    "gn:dem":258,
    "gn:feature_class":"P",
    "gn:feature_code":"PPL",
    "gn:name":"Chantraine",
    "gn:population":0,
    "gn:timezone":"Europe/Brussels",
    "iso:country":"BE",
    "name:bug_x_preferred":[
        "Chantraine"
    ],
    "name:cat_x_preferred":[
        "Chantraine"
    ],
    "name:ceb_x_preferred":[
        "Chantraine"
    ],
    "name:deu_x_preferred":[
        "Chantraine"
    ],
    "name:eus_x_preferred":[
        "Chantraine"
    ],
    "name:fra_x_preferred":[
        "Chantraine"
    ],
    "name:hun_x_preferred":[
        "Chantraine"
    ],
    "name:ind_x_preferred":[
        "Chantraine"
    ],
    "name:ita_x_preferred":[
        "Chantraine"
    ],
    "name:kaz_x_preferred":[
        "\u0428\u0430\u043d\u0442\u0440\u0435\u043d"
    ],
    "name:mlg_x_preferred":[
        "Chantraine"
    ],
    "name:msa_x_preferred":[
        "Chantraine"
    ],
    "name:nld_x_preferred":[
        "Chantraine"
    ],
    "name:oci_x_preferred":[
        "Chantraine"
    ],
    "name:pol_x_preferred":[
        "Chantraine"
    ],
    "name:slk_x_preferred":[
        "Chantraine"
    ],
    "name:spa_x_preferred":[
        "Chantraine"
    ],
    "name:srp_x_preferred":[
        "\u0428\u0430\u043d\u0442\u0440\u0435\u043d"
    ],
    "name:swe_x_preferred":[
        "Chantraine"
    ],
    "name:ukr_x_preferred":[
        "\u0428\u0430\u043d\u0442\u0440\u0435\u043d"
    ],
    "name:uzb_x_preferred":[
        "Chantraine"
    ],
    "name:vie_x_preferred":[
        "Chantraine"
    ],
    "name:vol_x_preferred":[
        "Chantraine"
    ],
    "name:war_x_preferred":[
        "Chantraine"
    ],
    "name:zho_x_preferred":[
        "\u5c1a\u7279\u5170"
    ],
    "wof:name":"Chantraine",
    "wof:placetype":"locality"
},
  "geometry": {"coordinates":[5.67418,50.60959],"type":"Point"}
}