{
  "type": "Feature",
  "properties": {
    "gn:admin1_code":"WAL",
    "gn:admin2_code":"WLG",
    "gn:admin3_code":"62.0",
    "gn:admin4_code":"62038.0",
    "gn:asciiname":"Chantraine",
    "gn:country_code":"BE",
    "gn:dem":258,
    "gn:feature_class":"P",
    "gn:feature_code":"PPL",
    "gn:name":"Chantraine",
    "gn:population":0,
    "gn:timezone":"Europe/Brussels",
    "iso:country":"BE",
    "wof:name":"Chantraine",
    "wof:placetype":"locality"
},
  "geometry": {"coordinates":[5.67418,50.60959],"type":"Point"}
}