{
  "type": "Feature",
  "properties": {
    "gn:admin1_code":"VLG",
    "gn:admin2_code":"VLI",
    "gn:admin3_code":"71.0",
    "gn:admin4_code":"71045.0",
    "gn:asciiname":"Tichelarij",
    "gn:country_code":"BE",
    "gn:dem":56,
    "gn:feature_class":"P",
    "gn:feature_code":"PPL",
    "gn:name":"Tichelarij",
    "gn:population":0,
    "gn:timezone":"Europe/Brussels",
    "iso:country":"BE",
    "name:und_x_variant":[
        "Tichelerij",
        "Tichelrij",
        "Trichelarij",
        "Tichelarij"
    ],
    "wof:name":"Tichelarij",
    "wof:placetype":"locality"
},
  "geometry": {"coordinates":[5.20299,50.88389],"type":"Point"}
}