{
  "type": "Feature",
  "properties": {
    "gn:admin1_code":"WAL",
    "gn:admin2_code":"WLG",
    "gn:admin3_code":"63.0",
    "gn:admin4_code":"63086.0",
    "gn:asciiname":"Wanneranval",
    "gn:country_code":"BE",
    "gn:dem":372,
    "gn:feature_class":"P",
    "gn:feature_code":"PPL",
    "gn:name":"Wanneranval",
    "gn:population":0,
    "gn:timezone":"Europe/Brussels",
    "iso:country":"BE",
    "name:und_x_variant":[
        "Vanneranval",
        "Wanneranval"
    ],
    "wof:name":"Wanneranval",
    "wof:placetype":"locality"
},
  "geometry": {"coordinates":[5.92097,50.3636],"type":"Point"}
}