{
  "type": "Feature",
  "properties": {
    "gn:admin1_code":"WAL",
    "gn:admin2_code":"WBR",
    "gn:admin3_code":"25.0",
    "gn:admin4_code":"25119.0",
    "gn:asciiname":"Lasne-Chapelle-Saint-Lambert",
    "gn:country_code":"BE",
    "gn:dem":104,
    "gn:feature_class":"P",
    "gn:feature_code":"PPL",
    "gn:name":"Lasne-Chapelle-Saint-Lambert",
    "gn:population":0,
    "gn:timezone":"Europe/Brussels",
    "iso:country":"BE",
    "name:und_x_variant":[
        "Lasne (Lasne-Chapelle-Saint-Lambert)"
    ],
    "wof:name":"Lasne-Chapelle-Saint-Lambert",
    "wof:placetype":"locality"
},
  "geometry": {"coordinates":[4.50105,50.69298],"type":"Point"}
}