{
  "type": "Feature",
  "properties": {
    "gn:admin1_code":"VLG",
    "gn:admin2_code":"VBR",
    "gn:admin3_code":"24.0",
    "gn:admin4_code":"24041.0",
    "gn:asciiname":"Meer",
    "gn:country_code":"BE",
    "gn:dem":89,
    "gn:feature_class":"P",
    "gn:feature_code":"PPL",
    "gn:name":"Meer",
    "gn:population":0,
    "gn:timezone":"Europe/Brussels",
    "iso:country":"BE",
    "name:ceb_x_preferred":[
        "Meer"
    ],
    "name:deu_x_preferred":[
        "Meer"
    ],
    "name:fin_x_preferred":[
        "Meer"
    ],
    "name:fra_x_preferred":[
        "Meer"
    ],
    "name:ita_x_preferred":[
        "Meer"
    ],
    "name:jpn_x_preferred":[
        "\u30df\u30fc\u30a2"
    ],
    "name:nds_x_preferred":[
        "Meer"
    ],
    "name:nld_x_preferred":[
        "Meer"
    ],
    "name:und_x_variant":[
        "De Meer",
        "Meer"
    ],
    "wof:name":"Meer",
    "wof:placetype":"locality"
},
  "geometry": {"coordinates":[4.81998,50.78697],"type":"Point"}
}