{
  "type": "Feature",
  "properties": {
    "gn:admin1_code":"WAL",
    "gn:admin2_code":"WNA",
    "gn:admin3_code":"93.0",
    "gn:admin4_code":"93090.0",
    "gn:asciiname":"Le Planiat",
    "gn:country_code":"BE",
    "gn:dem":316,
    "gn:feature_class":"P",
    "gn:feature_code":"PPL",
    "gn:name":"Le Planiat",
    "gn:population":0,
    "gn:timezone":"Europe/Brussels",
    "iso:country":"BE",
    "name:und_x_variant":[
        "Le Plamat",
        "Le Planiat"
    ],
    "wof:name":"Le Planiat",
    "wof:placetype":"locality"
},
  "geometry": {"coordinates":[4.65,50.05],"type":"Point"}
}