{
  "type": "Feature",
  "properties": {
    "gn:admin1_code":"VLG",
    "gn:admin2_code":"VWV",
    "gn:admin3_code":"33.0",
    "gn:admin4_code":"33021.0",
    "gn:asciiname":"Sint-Jan ter Biezen",
    "gn:country_code":"BE",
    "gn:dem":32,
    "gn:feature_class":"P",
    "gn:feature_code":"PPL",
    "gn:name":"Sint-Jan ter Biezen",
    "gn:population":0,
    "gn:timezone":"Europe/Brussels",
    "iso:country":"BE",
    "name:und_x_variant":[
        "Sint-Jans ter Biezen",
        "Sint-Jan ter Biezen"
    ],
    "wof:name":"Sint-Jan ter Biezen",
    "wof:placetype":"locality"
},
  "geometry": {"coordinates":[2.66635,50.85974],"type":"Point"}
}