{
  "type": "Feature",
  "properties": {
    "gn:admin1_code":"WAL",
    "gn:admin2_code":"WNA",
    "gn:admin3_code":"92.0",
    "gn:admin4_code":"92097.0",
    "gn:asciiname":"Hodoumont",
    "gn:country_code":"BE",
    "gn:dem":225,
    "gn:feature_class":"P",
    "gn:feature_code":"PPL",
    "gn:name":"Hodoumont",
    "gn:population":0,
    "gn:timezone":"Europe/Brussels",
    "iso:country":"BE",
    "name:und_x_variant":[
        "Houdoumont",
        "Hodoumont"
    ],
    "wof:name":"Hodoumont",
    "wof:placetype":"locality"
},
  "geometry": {"coordinates":[5.19929,50.43689000000001],"type":"Point"}
}