{
  "type": "Feature",
  "properties": {
    "gn:admin1_code":"WAL",
    "gn:admin2_code":"WLX",
    "gn:admin3_code":"83.0",
    "gn:admin4_code":"83012.0",
    "gn:asciiname":"Villers-Sainte-Gertrude",
    "gn:country_code":"BE",
    "gn:dem":267,
    "gn:feature_class":"P",
    "gn:feature_code":"PPL",
    "gn:name":"Villers-Sainte-Gertrude",
    "gn:population":0,
    "gn:timezone":"Europe/Brussels",
    "iso:country":"BE",
    "name:fra_x_preferred":[
        "Villers-Sainte-Gertrude"
    ],
    "name:nld_x_preferred":[
        "Villers-Sainte-Gertrude"
    ],
    "wof:name":"Villers-Sainte-Gertrude",
    "wof:placetype":"locality"
},
  "geometry": {"coordinates":[5.5799,50.36077],"type":"Point"}
}