{
  "type": "Feature",
  "properties": {
    "gn:admin1_code":"VLG",
    "gn:admin2_code":"VLI",
    "gn:admin3_code":"72.0",
    "gn:admin4_code":"72038.0",
    "gn:asciiname":"Vlasmer",
    "gn:country_code":"BE",
    "gn:dem":59,
    "gn:feature_class":"P",
    "gn:feature_code":"PPL",
    "gn:name":"Vlasmer",
    "gn:population":0,
    "gn:timezone":"Europe/Brussels",
    "iso:country":"BE",
    "name:und_x_variant":[
        "Vlasmeer",
        "Vlasmer"
    ],
    "wof:name":"Vlasmer",
    "wof:placetype":"locality"
},
  "geometry": {"coordinates":[5.36457,51.1639],"type":"Point"}
}