{
  "type": "Feature",
  "properties": {
    "gn:admin1_code":"VLG",
    "gn:admin2_code":"VBR",
    "gn:admin3_code":"24.0",
    "gn:admin4_code":"24134.0",
    "gn:asciiname":"Schutterveld",
    "gn:country_code":"BE",
    "gn:dem":23,
    "gn:feature_class":"P",
    "gn:feature_code":"PPL",
    "gn:name":"Schutterveld",
    "gn:population":0,
    "gn:timezone":"Europe/Brussels",
    "iso:country":"BE",
    "wof:name":"Schutterveld",
    "wof:placetype":"locality"
},
  "geometry": {"coordinates":[4.93535,50.982],"type":"Point"}
}