{
  "type": "Feature",
  "properties": {
    "gn:country":"BE",
    "gn:fcode":"PPL",
    "gn:population":0,
    "iso:country":"BE",
    "name:ara_x_preferred":[
        "\u0646\u0648\u0641\u064a\u0644"
    ],
    "name:cat_x_preferred":[
        "Noville"
    ],
    "name:ces_x_preferred":[
        "Noville"
    ],
    "name:deu_x_preferred":[
        "Noville"
    ],
    "name:eng_x_preferred":[
        "Noville"
    ],
    "name:fra_x_preferred":[
        "Noville"
    ],
    "name:gle_x_preferred":[
        "Noville"
    ],
    "name:hun_x_preferred":[
        "Noville"
    ],
    "name:jpn_x_preferred":[
        "\u30ce\u30fc\u30f4\u30a3\u30eb"
    ],
    "name:ltz_x_preferred":[
        "Noville-lez-Bastogne"
    ],
    "name:nld_x_preferred":[
        "Noville"
    ],
    "name:und_x_variant":[
        "Bastogne (Noville)"
    ],
    "name:wln_x_preferred":[
        "Noveye-dil\u00e9-Bastogne"
    ],
    "qs_pg:aaroncc":"BE",
    "qs_pg:gn_country":"BE",
    "qs_pg:gn_fcode":"PPL",
    "qs_pg:gn_pop":0,
    "qs_pg:name":"Noville",
    "qs_pg:name_adm0":"Belgique",
    "qs_pg:name_adm1":"Luxembourg",
    "qs_pg:photos_9k":1,
    "qs_pg:photos_9r":1,
    "qs_pg:photos_all":1,
    "qs_pg:photos_sr":0,
    "qs_pg:pop_sr":0,
    "qs_pg:qs_pg_placetype":"locality",
    "qs_pg:qs_pg_placetype_gp":"Town",
    "qs_pg:woe_adm0":23424757,
    "woe:adm0_id":23424757,
    "woe:name_adm0":"Belgique",
    "woe:name_adm1":"Luxembourg",
    "woe:placetype":"Town",
    "wof:name":"Noville",
    "wof:placetype":"locality"
},
  "geometry": {"coordinates":[5.76104,50.06386],"type":"Point"}
}