{
  "type": "Feature",
  "properties": {
    "gn:gn_country":"BE",
    "gn:gn_fcode":"PPL",
    "gn:gn_pop":0,
    "iso:country":"BE",
    "name:dut_x_preferred":[
        "Noville"
    ],
    "name:eng_x_preferred":[
        "Noville"
    ],
    "name:fre_x_preferred":[
        "Noville"
    ],
    "name:hun_x_preferred":[
        "Noville"
    ],
    "name:ltz_x_preferred":[
        "Noville-lez-Bastogne"
    ],
    "name:unk_x_variant":[
        "Bastogne (Noville)"
    ],
    "name:wln_x_preferred":[
        "Noveye-dil\u00e9-Bastogne"
    ],
    "qs_pg:aaroncc":"BE",
    "qs_pg:gn_country":"BE",
    "qs_pg:gn_fcode":"PPL",
    "qs_pg:gn_pop":0,
    "qs_pg:name":"Noville",
    "qs_pg:name_adm0":"Belgique",
    "qs_pg:name_adm1":"Luxembourg",
    "qs_pg:photos_9k":1,
    "qs_pg:photos_9r":1,
    "qs_pg:photos_all":1,
    "qs_pg:photos_sr":0,
    "qs_pg:pop_sr":0,
    "qs_pg:qs_pg_placetype":"locality",
    "qs_pg:qs_pg_placetype_gp":"Town",
    "qs_pg:woe_adm0":23424757,
    "woe:adm0_id":23424757,
    "woe:name_adm0":"Belgique",
    "woe:name_adm1":"Luxembourg",
    "woe:placetype":"Town",
    "wof:name":"Noville",
    "wof:placetype":"locality"
},
  "geometry": {"coordinates":[5.76104,50.06386],"type":"Point"}
}