{
  "type": "Feature",
  "properties": {
    "gn:admin1_code":"WAL",
    "gn:admin2_code":"WLG",
    "gn:admin3_code":"63.0",
    "gn:admin4_code":"63035.0",
    "gn:asciiname":"Houyeux",
    "gn:country_code":"BE",
    "gn:dem":176,
    "gn:feature_class":"P",
    "gn:feature_code":"PPL",
    "gn:name":"Houyeux",
    "gn:population":0,
    "gn:timezone":"Europe/Brussels",
    "iso:country":"BE",
    "wof:name":"Houyeux",
    "wof:placetype":"locality"
},
  "geometry": {"coordinates":[5.83333,50.68333],"type":"Point"}
}