{
  "type": "Feature",
  "properties": {
    "gn:country":"BE",
    "gn:fcode":"PPL",
    "gn:population":14521,
    "iso:country":"BE",
    "name:bre_x_preferred":[
        "Rumst"
    ],
    "name:bul_x_preferred":[
        "\u0420\u044c\u043e\u043c\u0441\u0442"
    ],
    "name:cat_x_preferred":[
        "Rumst"
    ],
    "name:ceb_x_preferred":[
        "Rumst"
    ],
    "name:dan_x_preferred":[
        "Rumst"
    ],
    "name:deu_x_preferred":[
        "Rumst"
    ],
    "name:ell_x_preferred":[
        "\u03a1\u03c5\u03bc\u03c3\u03c4"
    ],
    "name:eng_x_preferred":[
        "Rumst"
    ],
    "name:epo_x_preferred":[
        "Rumst"
    ],
    "name:eus_x_preferred":[
        "Rumst"
    ],
    "name:fao_x_preferred":[
        "Rumst"
    ],
    "name:fas_x_preferred":[
        "\u0631\u0645\u0633\u062a"
    ],
    "name:fra_x_preferred":[
        "Rumst"
    ],
    "name:hun_x_preferred":[
        "Rumst"
    ],
    "name:ita_x_preferred":[
        "Rumst"
    ],
    "name:kal_x_preferred":[
        "Rumst"
    ],
    "name:lit_x_preferred":[
        "Rumstas"
    ],
    "name:ltz_x_preferred":[
        "Rumst"
    ],
    "name:nld_x_preferred":[
        "Rumst"
    ],
    "name:nno_x_preferred":[
        "Rumst"
    ],
    "name:nob_x_preferred":[
        "Rumst"
    ],
    "name:oci_x_preferred":[
        "Rumst"
    ],
    "name:por_x_preferred":[
        "Rumst"
    ],
    "name:ron_x_preferred":[
        "Rumst"
    ],
    "name:rus_x_preferred":[
        "\u0420\u044e\u043c\u0441\u0442"
    ],
    "name:slk_x_preferred":[
        "Rumst"
    ],
    "name:spa_x_preferred":[
        "Rumst"
    ],
    "name:swe_x_preferred":[
        "Rumst"
    ],
    "name:und_x_variant":[
        "Rumpst"
    ],
    "name:vie_x_preferred":[
        "Rumst"
    ],
    "name:vol_x_preferred":[
        "Rumst"
    ],
    "name:war_x_preferred":[
        "Rumst"
    ],
    "name:zho_x_preferred":[
        "\u5415\u59c6\u65af\u7279"
    ],
    "qs_pg:aaroncc":"BE",
    "qs_pg:gn_country":"BE",
    "qs_pg:gn_fcode":"PPL",
    "qs_pg:gn_pop":14521,
    "qs_pg:name":"Rumst",
    "qs_pg:name_adm0":"Belgique",
    "qs_pg:name_adm1":"Antwerpen",
    "qs_pg:photos":282,
    "qs_pg:photos_1k":57,
    "qs_pg:photos_9k":1,
    "qs_pg:photos_9r":4,
    "qs_pg:photos_all":282,
    "qs_pg:photos_sr":5,
    "qs_pg:pop_sr":6,
    "qs_pg:qs_pg_placetype":"locality",
    "qs_pg:qs_pg_placetype_gp":"Town",
    "qs_pg:woe_adm0":23424757,
    "woe:adm0_id":23424757,
    "woe:name_adm0":"Belgique",
    "woe:name_adm1":"Antwerpen",
    "woe:placetype":"Town",
    "wof:name":"Rumst",
    "wof:placetype":"locality",
    "wof:population":14521
},
  "geometry": {"coordinates":[4.42217,51.08153],"type":"Point"}
}