{
  "type": "Feature",
  "properties": {
    "gn:admin1_code":"WAL",
    "gn:admin2_code":"WHT",
    "gn:admin3_code":"52.0",
    "gn:admin4_code":"52063.0",
    "gn:asciiname":"Bois de Nauwe",
    "gn:country_code":"BE",
    "gn:dem":156,
    "gn:feature_class":"P",
    "gn:feature_code":"PPL",
    "gn:name":"Bois de Nauwe",
    "gn:population":0,
    "gn:timezone":"Europe/Brussels",
    "iso:country":"BE",
    "wof:name":"Bois de Nauwe",
    "wof:placetype":"locality"
},
  "geometry": {"coordinates":[4.3059,50.52457],"type":"Point"}
}