{
  "type": "Feature",
  "properties": {
    "gn:admin1_code":"VLG",
    "gn:admin2_code":"VOV",
    "gn:admin3_code":"42.0",
    "gn:admin4_code":"42028.0",
    "gn:asciiname":"Wezepoel",
    "gn:country_code":"BE",
    "gn:dem":5,
    "gn:feature_class":"P",
    "gn:feature_code":"PPL",
    "gn:name":"Wezepoel",
    "gn:population":0,
    "gn:timezone":"Europe/Brussels",
    "iso:country":"BE",
    "wof:name":"Wezepoel",
    "wof:placetype":"locality"
},
  "geometry": {"coordinates":[4.02417,51.06698],"type":"Point"}
}