{
  "type": "Feature",
  "properties": {
    "gn:admin1_code":"VLG",
    "gn:admin2_code":"VAN",
    "gn:admin3_code":"11.0",
    "gn:admin4_code":"11016.0",
    "gn:asciiname":"Bredestraat",
    "gn:country_code":"BE",
    "gn:dem":13,
    "gn:feature_class":"P",
    "gn:feature_code":"PPL",
    "gn:name":"Bredestraat",
    "gn:population":0,
    "gn:timezone":"Europe/Brussels",
    "iso:country":"BE",
    "wof:name":"Bredestraat",
    "wof:placetype":"locality"
},
  "geometry": {"coordinates":[4.49348,51.4453],"type":"Point"}
}