{
  "type": "Feature",
  "properties": {
    "gn:admin1_code":"WAL",
    "gn:admin2_code":"WNA",
    "gn:admin3_code":"93.0",
    "gn:admin4_code":"93090.0",
    "gn:asciiname":"Najauge",
    "gn:country_code":"BE",
    "gn:dem":126,
    "gn:feature_class":"P",
    "gn:feature_code":"PPL",
    "gn:name":"Najauge",
    "gn:population":0,
    "gn:timezone":"Europe/Brussels",
    "iso:country":"BE",
    "wof:name":"Najauge",
    "wof:placetype":"locality"
},
  "geometry": {"coordinates":[4.69101,50.09421],"type":"Point"}
}