{
  "type": "Feature",
  "properties": {
    "gn:admin1_code":"WAL",
    "gn:admin2_code":"WHT",
    "gn:admin3_code":"52.0",
    "gn:admin4_code":"52063.0",
    "gn:asciiname":"Buisseret",
    "gn:country_code":"BE",
    "gn:dem":123,
    "gn:feature_class":"P",
    "gn:feature_code":"PPL",
    "gn:name":"Buisseret",
    "gn:population":0,
    "gn:timezone":"Europe/Brussels",
    "iso:country":"BE",
    "wof:name":"Buisseret",
    "wof:placetype":"locality"
},
  "geometry": {"coordinates":[4.21667,50.53333],"type":"Point"}
}