{
  "type": "Feature",
  "properties": {
    "gn:admin1_code":"WAL",
    "gn:admin2_code":"WHT",
    "gn:admin3_code":"56.0",
    "gn:admin4_code":"56051.0",
    "gn:asciiname":"La Mazure",
    "gn:country_code":"BE",
    "gn:dem":248,
    "gn:feature_class":"P",
    "gn:feature_code":"PPL",
    "gn:name":"La Mazure",
    "gn:population":0,
    "gn:timezone":"Europe/Brussels",
    "iso:country":"BE",
    "name:und_x_variant":[
        "La Masure",
        "La Mazure"
    ],
    "wof:name":"La Mazure",
    "wof:placetype":"locality"
},
  "geometry": {"coordinates":[4.15,49.98333],"type":"Point"}
}