{
  "type": "Feature",
  "properties": {
    "gn:admin1_code":"WAL",
    "gn:admin2_code":"WLX",
    "gn:admin3_code":"82.0",
    "gn:admin4_code":"82032.0",
    "gn:asciiname":"Ville-du-Bois",
    "gn:country_code":"BE",
    "gn:dem":395,
    "gn:feature_class":"P",
    "gn:feature_code":"PPL",
    "gn:name":"Ville-du-Bois",
    "gn:population":0,
    "gn:timezone":"Europe/Brussels",
    "iso:country":"BE",
    "wof:name":"Ville-du-Bois",
    "wof:placetype":"locality"
},
  "geometry": {"coordinates":[5.93667,50.2925],"type":"Point"}
}