{
  "type": "Feature",
  "properties": {
    "gn:admin1_code":"VLG",
    "gn:admin2_code":"VOV",
    "gn:admin3_code":"45.0",
    "gn:admin4_code":"45041.0",
    "gn:asciiname":"Kathoek",
    "gn:country_code":"BE",
    "gn:dem":81,
    "gn:feature_class":"P",
    "gn:feature_code":"PPL",
    "gn:name":"Kathoek",
    "gn:population":0,
    "gn:timezone":"Europe/Brussels",
    "iso:country":"BE",
    "wof:name":"Kathoek",
    "wof:placetype":"locality"
},
  "geometry": {"coordinates":[3.62499,50.76778],"type":"Point"}
}