{
  "type": "Feature",
  "properties": {
    "gn:admin1_code":"VLG",
    "gn:admin2_code":"VBR",
    "gn:admin3_code":"24.0",
    "gn:admin4_code":"24020.0",
    "gn:asciiname":"Dassenaarde",
    "gn:country_code":"BE",
    "gn:dem":21,
    "gn:feature_class":"P",
    "gn:feature_code":"PPL",
    "gn:name":"Dassenaarde",
    "gn:population":0,
    "gn:timezone":"Europe/Brussels",
    "iso:country":"BE",
    "name:und_x_variant":[
        "Dassen Aerde",
        "Dassenaarde"
    ],
    "wof:name":"Dassenaarde",
    "wof:placetype":"locality"
},
  "geometry": {"coordinates":[5.04691,51.01634],"type":"Point"}
}