{
  "type": "Feature",
  "properties": {
    "gn:admin1_code":"VLG",
    "gn:admin2_code":"VAN",
    "gn:admin3_code":"12.0",
    "gn:admin4_code":"12026.0",
    "gn:asciiname":"Bist",
    "gn:country_code":"BE",
    "gn:dem":7,
    "gn:feature_class":"P",
    "gn:feature_code":"PPL",
    "gn:name":"Bist",
    "gn:population":0,
    "gn:timezone":"Europe/Brussels",
    "iso:country":"BE",
    "name:ceb_x_preferred":[
        "Bist"
    ],
    "name:ita_x_preferred":[
        "Bist"
    ],
    "name:kat_x_preferred":[
        "\u10d1\u10d8\u10e1\u10d7\u10d8"
    ],
    "name:swe_x_preferred":[
        "Bist"
    ],
    "wof:name":"Bist",
    "wof:placetype":"locality"
},
  "geometry": {"coordinates":[4.60173,51.14635],"type":"Point"}
}