{
  "type": "Feature",
  "properties": {
    "gn:admin1_code":"VLG",
    "gn:admin2_code":"VAN",
    "gn:admin3_code":"13.0",
    "gn:admin4_code":"13017.0",
    "gn:asciiname":"Hoge Bergen",
    "gn:country_code":"BE",
    "gn:dem":30,
    "gn:feature_class":"P",
    "gn:feature_code":"PPL",
    "gn:name":"Hoge Bergen",
    "gn:population":0,
    "gn:timezone":"Europe/Brussels",
    "iso:country":"BE",
    "name:und_x_variant":[
        "Hooge Bergen",
        "Hoge Bergen"
    ],
    "wof:name":"Hoge Bergen",
    "wof:placetype":"locality"
},
  "geometry": {"coordinates":[4.96667,51.23333],"type":"Point"}
}