{
  "type": "Feature",
  "properties": {
    "gn:admin1_code":"WAL",
    "gn:admin2_code":"WLX",
    "gn:admin3_code":"84.0",
    "gn:admin4_code":"84033.0",
    "gn:asciiname":"Xaimont",
    "gn:country_code":"BE",
    "gn:dem":399,
    "gn:feature_class":"P",
    "gn:feature_code":"PPL",
    "gn:name":"Xaimont",
    "gn:population":0,
    "gn:timezone":"Europe/Brussels",
    "iso:country":"BE",
    "wof:name":"Xaimont",
    "wof:placetype":"locality"
},
  "geometry": {"coordinates":[5.54078,49.80563],"type":"Point"}
}