{
  "type": "Feature",
  "properties": {
    "gn:admin1_code":"VLG",
    "gn:admin2_code":"VAN",
    "gn:admin3_code":"11.0",
    "gn:admin4_code":"11009.0",
    "gn:asciiname":"Sternhoven",
    "gn:country_code":"BE",
    "gn:dem":21,
    "gn:feature_class":"P",
    "gn:feature_code":"PPL",
    "gn:name":"Sternhoven",
    "gn:population":0,
    "gn:timezone":"Europe/Brussels",
    "iso:country":"BE",
    "name:und_x_variant":[
        "Sterthoven",
        "Sternhoven"
    ],
    "wof:name":"Sternhoven",
    "wof:placetype":"locality"
},
  "geometry": {"coordinates":[4.61976,51.34099000000001],"type":"Point"}
}