{
  "type": "Feature",
  "properties": {
    "gn:admin1_code":"VLG",
    "gn:admin2_code":"VAN",
    "gn:admin3_code":"11.0",
    "gn:admin4_code":"11035.0",
    "gn:asciiname":"Schapenvondert",
    "gn:country_code":"BE",
    "gn:dem":11,
    "gn:feature_class":"P",
    "gn:feature_code":"PPL",
    "gn:name":"Schapenvondert",
    "gn:population":0,
    "gn:timezone":"Europe/Brussels",
    "iso:country":"BE",
    "name:und_x_variant":[
        "Schaepvonderd",
        "Schaepen-Vondert",
        "Schaapen-Vondert",
        "Schapenvondert"
    ],
    "wof:name":"Schapenvondert",
    "wof:placetype":"locality"
},
  "geometry": {"coordinates":[4.56435,51.18255],"type":"Point"}
}