{
  "type": "Feature",
  "properties": {
    "gn:admin1_code":"WAL",
    "gn:admin2_code":"WBR",
    "gn:admin3_code":"25.0",
    "gn:admin4_code":"25015.0",
    "gn:asciiname":"Bois du Foyau",
    "gn:country_code":"BE",
    "gn:dem":137,
    "gn:feature_class":"P",
    "gn:feature_code":"PPL",
    "gn:name":"Bois du Foyau",
    "gn:population":0,
    "gn:timezone":"Europe/Brussels",
    "iso:country":"BE",
    "wof:name":"Bois du Foyau",
    "wof:placetype":"locality"
},
  "geometry": {"coordinates":[4.28333,50.66667],"type":"Point"}
}