{
  "type": "Feature",
  "properties": {
    "gn:gn_country":"BE",
    "gn:gn_fcode":"PPL",
    "gn:gn_pop":0,
    "iso:country":"BE",
    "name:dut_x_preferred":[
        "Sint-Maria-Oudenhove"
    ],
    "name:eng_x_preferred":[
        "Sint-Maria-Oudenhove"
    ],
    "name:fre_x_preferred":[
        "Audenhove-Sainte-Marie"
    ],
    "name:hun_x_preferred":[
        "Sint-Maria-Oudenhove"
    ],
    "name:swe_x_preferred":[
        "Sint-Maria-Oudenhove"
    ],
    "name:unk_x_variant":[
        "Audenhove-Sainte-Marie"
    ],
    "qs_pg:aaroncc":"BE",
    "qs_pg:gn_country":"BE",
    "qs_pg:gn_fcode":"PPL",
    "qs_pg:gn_pop":0,
    "qs_pg:name":"St.-Maria-Oudenhove",
    "qs_pg:name_adm0":"Belgique",
    "qs_pg:name_adm1":"Oost-Vlaanderen",
    "qs_pg:photos_9r":0,
    "qs_pg:photos_sr":0,
    "qs_pg:pop_sr":0,
    "qs_pg:qs_pg_placetype":"locality",
    "qs_pg:qs_pg_placetype_gp":"Town",
    "qs_pg:woe_adm0":23424757,
    "woe:adm0_id":23424757,
    "woe:name_adm0":"Belgique",
    "woe:name_adm1":"Oost-Vlaanderen",
    "woe:placetype":"Town",
    "wof:name":"St.-Maria-Oudenhove",
    "wof:placetype":"locality"
},
  "geometry": {"coordinates":[3.79556,50.83364],"type":"Point"}
}