{
  "type": "Feature",
  "properties": {
    "gn:admin1_code":"VLG",
    "gn:admin2_code":"VLI",
    "gn:admin3_code":"71.0",
    "gn:admin4_code":"71037.0",
    "gn:asciiname":"Gestel",
    "gn:country_code":"BE",
    "gn:dem":28,
    "gn:feature_class":"P",
    "gn:feature_code":"PPL",
    "gn:name":"Gestel",
    "gn:population":0,
    "gn:timezone":"Europe/Brussels",
    "iso:country":"BE",
    "name:deu_x_preferred":[
        "Gestel"
    ],
    "name:epo_x_preferred":[
        "Gestel"
    ],
    "name:fra_x_preferred":[
        "Gestel"
    ],
    "name:nds_x_preferred":[
        "Gestel"
    ],
    "name:nld_x_preferred":[
        "Gestel"
    ],
    "name:rus_x_preferred":[
        "\u0413\u0435\u0441\u0442\u0435\u043b"
    ],
    "wof:name":"Gestel",
    "wof:placetype":"locality"
},
  "geometry": {"coordinates":[5.21361,51.03157],"type":"Point"}
}