{
  "type": "Feature",
  "properties": {
    "gn:admin1_code":"WAL",
    "gn:admin2_code":"WNA",
    "gn:admin3_code":"93.0",
    "gn:admin4_code":"93014.0",
    "gn:asciiname":"Aublain",
    "gn:country_code":"BE",
    "gn:dem":195,
    "gn:feature_class":"P",
    "gn:feature_code":"PPL",
    "gn:name":"Aublain",
    "gn:population":0,
    "gn:timezone":"Europe/Brussels",
    "iso:country":"BE",
    "wof:name":"Aublain",
    "wof:placetype":"locality"
},
  "geometry": {"coordinates":[4.4096,50.06644],"type":"Point"}
}