{
  "type": "Feature",
  "properties": {
    "gn:admin1_code":"WAL",
    "gn:admin2_code":"WHT",
    "gn:admin3_code":"53.0",
    "gn:admin4_code":"53014.0",
    "gn:asciiname":"Petit Hornu",
    "gn:country_code":"BE",
    "gn:dem":114,
    "gn:feature_class":"P",
    "gn:feature_code":"PPL",
    "gn:name":"Petit Hornu",
    "gn:population":0,
    "gn:timezone":"Europe/Brussels",
    "iso:country":"BE",
    "wof:name":"Petit Hornu",
    "wof:placetype":"locality"
},
  "geometry": {"coordinates":[3.81294,50.39703],"type":"Point"}
}