{
  "type": "Feature",
  "properties": {
    "gn:admin1_code":"WAL",
    "gn:admin2_code":"WLG",
    "gn:admin3_code":"62.0",
    "gn:admin4_code":"62119.0",
    "gn:asciiname":"Booze",
    "gn:country_code":"BE",
    "gn:dem":170,
    "gn:feature_class":"P",
    "gn:feature_code":"PPL",
    "gn:name":"Booze",
    "gn:population":0,
    "gn:timezone":"Europe/Brussels",
    "iso:country":"BE",
    "name:deu_x_preferred":[
        "Booze"
    ],
    "name:fra_x_preferred":[
        "Booze"
    ],
    "name:und_x_variant":[
        "Boose",
        "Booze"
    ],
    "wof:name":"Booze",
    "wof:placetype":"locality"
},
  "geometry": {"coordinates":[5.70813,50.67131],"type":"Point"}
}