{
  "type": "Feature",
  "properties": {
    "gn:admin1_code":"WAL",
    "gn:admin2_code":"WLG",
    "gn:admin3_code":"61.0",
    "gn:admin4_code":"61031.0",
    "gn:asciiname":"Statte",
    "gn:country_code":"BE",
    "gn:dem":81,
    "gn:feature_class":"P",
    "gn:feature_code":"PPL",
    "gn:name":"Statte",
    "gn:population":0,
    "gn:timezone":"Europe/Brussels",
    "iso:country":"BE",
    "name:ara_x_preferred":[
        "\u0633\u062a\u0627\u062a\u064a"
    ],
    "name:azb_x_preferred":[
        "\u0633\u062a\u0627\u062a\u0647"
    ],
    "name:bel_x_preferred":[
        "\u0421\u0442\u0430\u0442\u044d"
    ],
    "name:bul_x_preferred":[
        "\u0421\u0442\u0430\u0442\u0435"
    ],
    "name:ceb_x_preferred":[
        "Statte"
    ],
    "name:deu_x_preferred":[
        "Statte"
    ],
    "name:epo_x_preferred":[
        "Statte"
    ],
    "name:eus_x_preferred":[
        "Statte"
    ],
    "name:fas_x_preferred":[
        "\u0633\u062a\u0627\u062a\u0647"
    ],
    "name:fra_x_preferred":[
        "Statte"
    ],
    "name:hun_x_preferred":[
        "Statte"
    ],
    "name:hye_x_preferred":[
        "\u054d\u057f\u0561\u057f\u0565"
    ],
    "name:ina_x_preferred":[
        "Statte"
    ],
    "name:ita_x_preferred":[
        "Statte"
    ],
    "name:jpn_x_preferred":[
        "\u30b9\u30bf\u30c3\u30c6"
    ],
    "name:kaz_x_preferred":[
        "\u0421\u0442\u0430\u0442\u0442\u0435"
    ],
    "name:lat_x_preferred":[
        "Statiae"
    ],
    "name:lmo_x_preferred":[
        "Statte"
    ],
    "name:msa_x_preferred":[
        "Statte"
    ],
    "name:nap_x_preferred":[
        "Statte"
    ],
    "name:nld_x_preferred":[
        "Statte"
    ],
    "name:pms_x_preferred":[
        "Statte"
    ],
    "name:pol_x_preferred":[
        "Statte"
    ],
    "name:por_x_preferred":[
        "Statte"
    ],
    "name:ron_x_preferred":[
        "Statte"
    ],
    "name:rus_x_preferred":[
        "\u0421\u0442\u0430\u0442\u0442\u0435"
    ],
    "name:scn_x_preferred":[
        "Statti"
    ],
    "name:spa_x_preferred":[
        "Statte"
    ],
    "name:srp_x_preferred":[
        "\u0421\u0442\u0430\u0442\u0435"
    ],
    "name:ukr_x_preferred":[
        "\u0421\u0442\u0430\u0442\u0442\u0435"
    ],
    "name:und_x_variant":[
        "Huy-Statte"
    ],
    "name:uzb_x_preferred":[
        "Statte"
    ],
    "name:vol_x_preferred":[
        "Statte"
    ],
    "name:war_x_preferred":[
        "Statte"
    ],
    "name:zho_x_preferred":[
        "\u65af\u5854\u6cf0"
    ],
    "wof:name":"Statte",
    "wof:placetype":"locality"
},
  "geometry": {"coordinates":[5.21945,50.53100000000001],"type":"Point"}
}