{
  "type": "Feature",
  "properties": {
    "gn:admin1_code":"WAL",
    "gn:admin2_code":"WLG",
    "gn:admin3_code":"61.0",
    "gn:admin4_code":"61031.0",
    "gn:asciiname":"Statte",
    "gn:country_code":"BE",
    "gn:dem":81,
    "gn:feature_class":"P",
    "gn:feature_code":"PPL",
    "gn:name":"Statte",
    "gn:population":0,
    "gn:timezone":"Europe/Brussels",
    "iso:country":"BE",
    "name:und_x_variant":[
        "Huy-Statte",
        "Statte"
    ],
    "wof:name":"Statte",
    "wof:placetype":"locality"
},
  "geometry": {"coordinates":[5.21945,50.53100000000001],"type":"Point"}
}