{
  "type": "Feature",
  "properties": {
    "gn:admin1_code":"VLG",
    "gn:admin2_code":"VLI",
    "gn:admin3_code":"73.0",
    "gn:admin4_code":"73006.0",
    "gn:asciiname":"Laar",
    "gn:country_code":"BE",
    "gn:dem":48,
    "gn:feature_class":"P",
    "gn:feature_code":"PPL",
    "gn:name":"Laar",
    "gn:population":0,
    "gn:timezone":"Europe/Brussels",
    "iso:country":"BE",
    "wof:name":"Laar",
    "wof:placetype":"locality"
},
  "geometry": {"coordinates":[5.48269,50.88647],"type":"Point"}
}