{
  "type": "Feature",
  "properties": {
    "gn:admin1_code":"VLG",
    "gn:admin2_code":"VLI",
    "gn:admin3_code":"73.0",
    "gn:admin4_code":"73006.0",
    "gn:asciiname":"Laar",
    "gn:country_code":"BE",
    "gn:dem":48,
    "gn:feature_class":"P",
    "gn:feature_code":"PPL",
    "gn:name":"Laar",
    "gn:population":0,
    "gn:timezone":"Europe/Brussels",
    "iso:country":"BE",
    "name:ceb_x_preferred":[
        "Laar"
    ],
    "name:deu_x_preferred":[
        "Laar"
    ],
    "name:epo_x_preferred":[
        "Laar"
    ],
    "name:est_x_preferred":[
        "Laar"
    ],
    "name:eus_x_preferred":[
        "Laar"
    ],
    "name:fas_x_preferred":[
        "\u0644\u0627\u0631"
    ],
    "name:fra_x_preferred":[
        "Laar"
    ],
    "name:hun_x_preferred":[
        "Laar"
    ],
    "name:ita_x_preferred":[
        "Laar"
    ],
    "name:kaz_x_preferred":[
        "\u041b\u0430\u0440"
    ],
    "name:kir_x_preferred":[
        "\u041b\u0430\u0440"
    ],
    "name:lat_x_preferred":[
        "Laar"
    ],
    "name:msa_x_preferred":[
        "Laar"
    ],
    "name:nld_x_preferred":[
        "Laar"
    ],
    "name:pol_x_preferred":[
        "Laar"
    ],
    "name:por_x_preferred":[
        "Laar"
    ],
    "name:ron_x_preferred":[
        "Laar"
    ],
    "name:rus_x_preferred":[
        "\u041b\u0430\u0440"
    ],
    "name:spa_x_preferred":[
        "Laar"
    ],
    "name:srp_x_preferred":[
        "\u041b\u0430\u0440"
    ],
    "name:ukr_x_preferred":[
        "\u041b\u0430\u0430\u0440"
    ],
    "name:uzb_x_preferred":[
        "Laar"
    ],
    "name:vie_x_preferred":[
        "Laar"
    ],
    "name:vol_x_preferred":[
        "Laar"
    ],
    "name:war_x_preferred":[
        "Laar"
    ],
    "wof:name":"Laar",
    "wof:placetype":"locality"
},
  "geometry": {"coordinates":[5.48269,50.88647],"type":"Point"}
}