{
  "type": "Feature",
  "properties": {
    "gn:admin1_code":"WAL",
    "gn:admin2_code":"WNA",
    "gn:admin3_code":"91.0",
    "gn:admin4_code":"91030.0",
    "gn:asciiname":"Namorimont",
    "gn:country_code":"BE",
    "gn:dem":297,
    "gn:feature_class":"P",
    "gn:feature_code":"PPL",
    "gn:name":"Namorimont",
    "gn:population":0,
    "gn:timezone":"Europe/Brussels",
    "iso:country":"BE",
    "wof:name":"Namorimont",
    "wof:placetype":"locality"
},
  "geometry": {"coordinates":[5.11091,50.23628],"type":"Point"}
}