{
  "type": "Feature",
  "properties": {
    "gn:admin1_code":"VLG",
    "gn:admin2_code":"VWV",
    "gn:admin3_code":"32.0",
    "gn:admin4_code":"32011.0",
    "gn:asciiname":"Vla",
    "gn:country_code":"BE",
    "gn:dem":20,
    "gn:feature_class":"P",
    "gn:feature_code":"PPL",
    "gn:name":"Vla",
    "gn:population":0,
    "gn:timezone":"Europe/Brussels",
    "iso:country":"BE",
    "name:afr_x_preferred":[
        "Vla"
    ],
    "name:cat_x_preferred":[
        "Vla"
    ],
    "name:ces_x_preferred":[
        "Vla"
    ],
    "name:dan_x_preferred":[
        "Vla"
    ],
    "name:deu_x_preferred":[
        "Vla"
    ],
    "name:fra_x_preferred":[
        "Cr\u00e8me dessert"
    ],
    "name:hun_x_preferred":[
        "Vla"
    ],
    "name:hye_x_preferred":[
        "\u0556\u056c\u0561"
    ],
    "name:ind_x_preferred":[
        "Vla"
    ],
    "name:ita_x_preferred":[
        "Vla"
    ],
    "name:ksh_x_preferred":[
        "Vla"
    ],
    "name:nld_x_preferred":[
        "Vla"
    ],
    "name:pol_x_preferred":[
        "Vla"
    ],
    "name:spa_x_preferred":[
        "Vla"
    ],
    "name:tur_x_preferred":[
        "Vla"
    ],
    "name:ukr_x_preferred":[
        "\u0424\u043b\u0430"
    ],
    "name:und_x_variant":[
        "Vlaa",
        "Vlae"
    ],
    "wof:name":"Vla",
    "wof:placetype":"locality"
},
  "geometry": {"coordinates":[2.97495,50.99162000000001],"type":"Point"}
}