{
  "type": "Feature",
  "properties": {
    "gn:admin1_code":"WAL",
    "gn:admin2_code":"WHT",
    "gn:admin3_code":"56.0",
    "gn:admin4_code":"56088.0",
    "gn:asciiname":"Les Herimonts",
    "gn:country_code":"BE",
    "gn:dem":234,
    "gn:feature_class":"P",
    "gn:feature_code":"PPL",
    "gn:name":"Les H\u00e9rimonts",
    "gn:population":0,
    "gn:timezone":"Europe/Brussels",
    "iso:country":"BE",
    "wof:name":"Les Herimonts",
    "wof:placetype":"locality"
},
  "geometry": {"coordinates":[4.18878,50.18808],"type":"Point"}
}