{
  "type": "Feature",
  "properties": {
    "gn:admin1_code":"VLG",
    "gn:admin2_code":"VWV",
    "gn:admin3_code":"37.0",
    "gn:admin4_code":"37018.0",
    "gn:asciiname":"Meiboom",
    "gn:country_code":"BE",
    "gn:dem":33,
    "gn:feature_class":"P",
    "gn:feature_code":"PPL",
    "gn:name":"Meiboom",
    "gn:population":0,
    "gn:timezone":"Europe/Brussels",
    "iso:country":"BE",
    "name:und_x_variant":[
        "Meyboom",
        "Meiboom"
    ],
    "wof:name":"Meiboom",
    "wof:placetype":"locality"
},
  "geometry": {"coordinates":[3.18995,51.02722],"type":"Point"}
}