{
  "type": "Feature",
  "properties": {
    "gn:admin1_code":"WAL",
    "gn:admin2_code":"WLG",
    "gn:admin3_code":"61.0",
    "gn:admin4_code":"61081.0",
    "gn:asciiname":"Saint-Vitu",
    "gn:country_code":"BE",
    "gn:dem":232,
    "gn:feature_class":"P",
    "gn:feature_code":"PPL",
    "gn:name":"Saint-Vitu",
    "gn:population":0,
    "gn:timezone":"Europe/Brussels",
    "iso:country":"BE",
    "wof:name":"Saint-Vitu",
    "wof:placetype":"locality"
},
  "geometry": {"coordinates":[5.3513,50.48483],"type":"Point"}
}