{
  "type": "Feature",
  "properties": {
    "gn:admin1_code":"WAL",
    "gn:admin2_code":"WLX",
    "gn:admin3_code":"82.0",
    "gn:admin4_code":"82038.0",
    "gn:asciiname":"Rechimont",
    "gn:country_code":"BE",
    "gn:dem":418,
    "gn:feature_class":"P",
    "gn:feature_code":"PPL",
    "gn:name":"Rechimont",
    "gn:population":0,
    "gn:timezone":"Europe/Brussels",
    "iso:country":"BE",
    "wof:name":"Rechimont",
    "wof:placetype":"locality"
},
  "geometry": {"coordinates":[5.57211,50.01229],"type":"Point"}
}