{
  "type": "Feature",
  "properties": {
    "gn:admin1_code":"VLG",
    "gn:admin2_code":"VAN",
    "gn:admin3_code":"13.0",
    "gn:admin4_code":"13019.0",
    "gn:asciiname":"Hoeven",
    "gn:country_code":"BE",
    "gn:dem":12,
    "gn:feature_class":"P",
    "gn:feature_code":"PPL",
    "gn:name":"Hoeven",
    "gn:population":0,
    "gn:timezone":"Europe/Brussels",
    "iso:country":"BE",
    "name:cat_x_preferred":[
        "Hoeven"
    ],
    "name:ceb_x_preferred":[
        "Hoeven"
    ],
    "name:fas_x_preferred":[
        "\u0647\u0648\u0641\u0646"
    ],
    "name:fra_x_preferred":[
        "Hoeven"
    ],
    "name:ita_x_preferred":[
        "Hoeven"
    ],
    "name:nld_x_preferred":[
        "Hoeven"
    ],
    "wof:name":"Hoeven",
    "wof:placetype":"locality"
},
  "geometry": {"coordinates":[4.84033,51.21667],"type":"Point"}
}