{
  "type": "Feature",
  "properties": {
    "gn:admin1_code":"WAL",
    "gn:admin2_code":"WHT",
    "gn:admin3_code":"57.0",
    "gn:admin4_code":"57081.0",
    "gn:asciiname":"Maulde",
    "gn:country_code":"BE",
    "gn:dem":62,
    "gn:feature_class":"P",
    "gn:feature_code":"PPL",
    "gn:name":"Maulde",
    "gn:population":0,
    "gn:timezone":"Europe/Brussels",
    "iso:country":"BE",
    "name:bre_x_preferred":[
        "Maulde"
    ],
    "name:cat_x_preferred":[
        "Maulde"
    ],
    "name:ceb_x_preferred":[
        "Maulde"
    ],
    "name:deu_x_preferred":[
        "Maulde"
    ],
    "name:eus_x_preferred":[
        "Maulde"
    ],
    "name:fra_x_preferred":[
        "Maulde"
    ],
    "name:hun_x_preferred":[
        "Maulde"
    ],
    "name:ind_x_preferred":[
        "Maulde"
    ],
    "name:ita_x_preferred":[
        "Maulde"
    ],
    "name:kaz_x_preferred":[
        "\u041c\u043e\u043b\u044c\u0434"
    ],
    "name:lat_x_preferred":[
        "Maulde"
    ],
    "name:mlg_x_preferred":[
        "Maulde"
    ],
    "name:msa_x_preferred":[
        "Maulde"
    ],
    "name:nld_x_preferred":[
        "Maulde"
    ],
    "name:oci_x_preferred":[
        "Maulde"
    ],
    "name:pol_x_preferred":[
        "Maulde"
    ],
    "name:ron_x_preferred":[
        "Maulde"
    ],
    "name:slk_x_preferred":[
        "Maulde"
    ],
    "name:spa_x_preferred":[
        "Maulde"
    ],
    "name:swe_x_preferred":[
        "Maulde"
    ],
    "name:ukr_x_preferred":[
        "\u041c\u043e\u043b\u044c\u0434"
    ],
    "name:vie_x_preferred":[
        "Maulde"
    ],
    "name:vol_x_preferred":[
        "Maulde"
    ],
    "name:war_x_preferred":[
        "Maulde"
    ],
    "name:zho_x_preferred":[
        "\u83ab\u5c14\u5fb7"
    ],
    "wof:name":"Maulde",
    "wof:placetype":"locality"
},
  "geometry": {"coordinates":[3.5488,50.61676],"type":"Point"}
}