{
  "type": "Feature",
  "properties": {
    "gn:country":"BE",
    "gn:fcode":"PPL",
    "gn:population":0,
    "iso:country":"BE",
    "name:eng_x_preferred":[
        "Spalbeek"
    ],
    "name:fra_x_preferred":[
        "Spalbeek"
    ],
    "name:hun_x_preferred":[
        "Spalbeek"
    ],
    "name:lim_x_preferred":[
        "Spalbeek"
    ],
    "name:nld_x_preferred":[
        "Spalbeek"
    ],
    "name:und_x_variant":[
        "Hasselt (Spalbeek)"
    ],
    "qs_pg:aaroncc":"BE",
    "qs_pg:gn_country":"BE",
    "qs_pg:gn_fcode":"PPL",
    "qs_pg:gn_pop":0,
    "qs_pg:name":"Spalbeek",
    "qs_pg:name_adm0":"Belgique",
    "qs_pg:name_adm1":"Limburg",
    "qs_pg:photos":40,
    "qs_pg:photos_1k":8,
    "qs_pg:photos_9k":1,
    "qs_pg:photos_9r":2,
    "qs_pg:photos_all":40,
    "qs_pg:photos_sr":2,
    "qs_pg:pop_sr":0,
    "qs_pg:qs_pg_placetype":"locality",
    "qs_pg:qs_pg_placetype_gp":"Town",
    "qs_pg:woe_adm0":23424757,
    "woe:adm0_id":23424757,
    "woe:name_adm0":"Belgique",
    "woe:name_adm1":"Limburg",
    "woe:placetype":"Town",
    "wof:name":"Spalbeek",
    "wof:placetype":"locality"
},
  "geometry": {"coordinates":[5.22391,50.94918],"type":"Point"}
}