{
  "type": "Feature",
  "properties": {
    "gn:admin1_code":"WAL",
    "gn:admin2_code":"WNA",
    "gn:admin3_code":"93.0",
    "gn:admin4_code":"93056.0",
    "gn:asciiname":"Surice",
    "gn:country_code":"BE",
    "gn:dem":213,
    "gn:feature_class":"P",
    "gn:feature_code":"PPL",
    "gn:name":"Surice",
    "gn:population":0,
    "gn:timezone":"Europe/Brussels",
    "iso:country":"BE",
    "wof:name":"Surice",
    "wof:placetype":"locality"
},
  "geometry": {"coordinates":[4.69645,50.18161],"type":"Point"}
}