{
  "type": "Feature",
  "properties": {
    "gn:country":"BE",
    "gn:fcode":"PPL",
    "gn:population":0,
    "iso:country":"BE",
    "name:cat_x_preferred":[
        "Landelies"
    ],
    "name:eng_x_preferred":[
        "Landelies"
    ],
    "name:fra_x_preferred":[
        "Landelies"
    ],
    "name:hun_x_preferred":[
        "Landelies"
    ],
    "name:nld_x_preferred":[
        "Landelies"
    ],
    "name:und_x_variant":[
        "Montigny-le-Tilleul (Landelies)"
    ],
    "name:wln_x_preferred":[
        "Landliye"
    ],
    "qs_pg:aaroncc":"BE",
    "qs_pg:gn_country":"BE",
    "qs_pg:gn_fcode":"PPL",
    "qs_pg:gn_pop":0,
    "qs_pg:name":"Landelies",
    "qs_pg:name_adm0":"Belgique",
    "qs_pg:name_adm1":"Hainaut",
    "qs_pg:photos":802,
    "qs_pg:photos_1k":163,
    "qs_pg:photos_9k":4,
    "qs_pg:photos_9r":6,
    "qs_pg:photos_all":802,
    "qs_pg:photos_sr":9,
    "qs_pg:pop_sr":0,
    "qs_pg:qs_pg_placetype":"locality",
    "qs_pg:qs_pg_placetype_gp":"Town",
    "qs_pg:woe_adm0":23424757,
    "woe:adm0_id":23424757,
    "woe:name_adm0":"Belgique",
    "woe:name_adm1":"Hainaut",
    "woe:placetype":"Town",
    "wof:name":"Landelies",
    "wof:placetype":"locality"
},
  "geometry": {"coordinates":[4.35076,50.38001],"type":"Point"}
}