{
  "type": "Feature",
  "properties": {
    "gn:admin1_code":"VLG",
    "gn:admin2_code":"VLI",
    "gn:admin3_code":"72.0",
    "gn:admin4_code":"72038.0",
    "gn:asciiname":"Kamert",
    "gn:country_code":"BE",
    "gn:dem":60,
    "gn:feature_class":"P",
    "gn:feature_code":"PPL",
    "gn:name":"Kamert",
    "gn:population":0,
    "gn:timezone":"Europe/Brussels",
    "iso:country":"BE",
    "wof:name":"Kamert",
    "wof:placetype":"locality"
},
  "geometry": {"coordinates":[5.34891,51.13505],"type":"Point"}
}