{
  "type": "Feature",
  "properties": {
    "gn:admin1_code":"VLG",
    "gn:admin2_code":"VOV",
    "gn:admin3_code":"41.0",
    "gn:admin4_code":"41048.0",
    "gn:asciiname":"Walhoven",
    "gn:country_code":"BE",
    "gn:dem":41,
    "gn:feature_class":"P",
    "gn:feature_code":"PPL",
    "gn:name":"Walhoven",
    "gn:population":0,
    "gn:timezone":"Europe/Brussels",
    "iso:country":"BE",
    "name:und_x_variant":[
        "Waalhove",
        "Walhoven"
    ],
    "wof:name":"Walhoven",
    "wof:placetype":"locality"
},
  "geometry": {"coordinates":[3.95573,50.85016],"type":"Point"}
}