{
  "type": "Feature",
  "properties": {
    "gn:admin1_code":"VLG",
    "gn:admin2_code":"VWV",
    "gn:admin3_code":"38.0",
    "gn:admin4_code":"38002.0",
    "gn:asciiname":"Kruisabele",
    "gn:country_code":"BE",
    "gn:dem":0,
    "gn:feature_class":"P",
    "gn:feature_code":"PPL",
    "gn:name":"Kruisabele",
    "gn:population":0,
    "gn:timezone":"Europe/Brussels",
    "iso:country":"BE",
    "name:und_x_variant":[
        "Kruisse Abeele",
        "Kruisabele"
    ],
    "wof:name":"Kruisabele",
    "wof:placetype":"locality"
},
  "geometry": {"coordinates":[2.74006,51.04154000000001],"type":"Point"}
}