{
  "type": "Feature",
  "properties": {
    "gn:admin1_code":"VLG",
    "gn:admin2_code":"VAN",
    "gn:admin3_code":"11.0",
    "gn:admin4_code":"11038.0",
    "gn:asciiname":"Boerenhoek",
    "gn:country_code":"BE",
    "gn:dem":9,
    "gn:feature_class":"P",
    "gn:feature_code":"PPL",
    "gn:name":"Boerenhoek",
    "gn:population":0,
    "gn:timezone":"Europe/Brussels",
    "iso:country":"BE",
    "wof:name":"Boerenhoek",
    "wof:placetype":"locality"
},
  "geometry": {"coordinates":[4.35259,51.12422],"type":"Point"}
}