{
  "type": "Feature",
  "properties": {
    "gn:admin1_code":"VLG",
    "gn:admin2_code":"VWV",
    "gn:admin3_code":"33.0",
    "gn:admin4_code":"33040.0",
    "gn:asciiname":"Schaap Balir",
    "gn:country_code":"BE",
    "gn:dem":22,
    "gn:feature_class":"P",
    "gn:feature_code":"PPL",
    "gn:name":"Schaap Balir",
    "gn:population":0,
    "gn:timezone":"Europe/Brussels",
    "iso:country":"BE",
    "name:und_x_variant":[
        "Schaep Baillie",
        "Schaap-Balie",
        "Schaap Balir"
    ],
    "wof:name":"Schaap Balir",
    "wof:placetype":"locality"
},
  "geometry": {"coordinates":[2.97198,50.94537],"type":"Point"}
}