{
  "type": "Feature",
  "properties": {
    "gn:admin1_code":"WAL",
    "gn:admin2_code":"WLG",
    "gn:admin3_code":"62.0",
    "gn:admin4_code":"62096.0",
    "gn:asciiname":"Bas Laveu",
    "gn:country_code":"BE",
    "gn:dem":77,
    "gn:feature_class":"P",
    "gn:feature_code":"PPL",
    "gn:name":"Bas Laveu",
    "gn:population":0,
    "gn:timezone":"Europe/Brussels",
    "iso:country":"BE",
    "wof:name":"Bas Laveu",
    "wof:placetype":"locality"
},
  "geometry": {"coordinates":[5.48945,50.61269],"type":"Point"}
}