{
  "type": "Feature",
  "properties": {
    "gn:admin1_code":"VLG",
    "gn:admin2_code":"VLI",
    "gn:admin3_code":"71.0",
    "gn:admin4_code":"71020.0",
    "gn:asciiname":"Gennep",
    "gn:country_code":"BE",
    "gn:dem":26,
    "gn:feature_class":"P",
    "gn:feature_code":"PPL",
    "gn:name":"Gennep",
    "gn:population":0,
    "gn:timezone":"Europe/Brussels",
    "iso:country":"BE",
    "name:afr_x_preferred":[
        "Gennep"
    ],
    "name:ara_x_preferred":[
        "\u062e\u0646\u064a\u0628"
    ],
    "name:arg_x_preferred":[
        "Gennep"
    ],
    "name:cat_x_preferred":[
        "Gennep"
    ],
    "name:ceb_x_preferred":[
        "Gemeente Gennep"
    ],
    "name:dan_x_preferred":[
        "Gennep"
    ],
    "name:deu_x_preferred":[
        "Gennep"
    ],
    "name:epo_x_preferred":[
        "Gennep"
    ],
    "name:eus_x_preferred":[
        "Gennep"
    ],
    "name:fas_x_preferred":[
        "\u062e\u0646\u067e"
    ],
    "name:fra_x_preferred":[
        "Gennep"
    ],
    "name:hye_x_preferred":[
        "\u053d\u0565\u0576\u0565\u057a"
    ],
    "name:ind_x_preferred":[
        "Gennep"
    ],
    "name:ita_x_preferred":[
        "Gennep"
    ],
    "name:jav_x_preferred":[
        "Gennep"
    ],
    "name:jpn_x_preferred":[
        "\u30d8\u30cd\u30d7"
    ],
    "name:lat_x_preferred":[
        "Gennapium"
    ],
    "name:lim_x_preferred":[
        "Gennep"
    ],
    "name:msa_x_preferred":[
        "Gennep"
    ],
    "name:nld_x_preferred":[
        "Gennep"
    ],
    "name:nor_x_preferred":[
        "Gennep"
    ],
    "name:pol_x_preferred":[
        "Gennep"
    ],
    "name:ron_x_preferred":[
        "Gennep"
    ],
    "name:rus_x_preferred":[
        "\u0413\u0435\u043d\u043d\u0435\u043f"
    ],
    "name:spa_x_preferred":[
        "Gennep"
    ],
    "name:sqi_x_preferred":[
        "Gennep"
    ],
    "name:stq_x_preferred":[
        "Gennep"
    ],
    "name:swe_x_preferred":[
        "Gennep"
    ],
    "name:tur_x_preferred":[
        "Gennep"
    ],
    "name:ukr_x_preferred":[
        "\u0413\u0435\u043d\u043d\u0435\u043f"
    ],
    "name:vie_x_preferred":[
        "Gennep"
    ],
    "name:vol_x_preferred":[
        "Gennep"
    ],
    "name:war_x_preferred":[
        "Gennep"
    ],
    "name:zho_x_preferred":[
        "\u4ea8\u8a25\u666e"
    ],
    "wof:name":"Gennep",
    "wof:placetype":"locality"
},
  "geometry": {"coordinates":[5.08333,50.98333],"type":"Point"}
}