{
  "type": "Feature",
  "properties": {
    "gn:admin1_code":"VLG",
    "gn:admin2_code":"VLI",
    "gn:admin3_code":"72.0",
    "gn:admin4_code":"72030.0",
    "gn:asciiname":"Heihoek",
    "gn:country_code":"BE",
    "gn:dem":65,
    "gn:feature_class":"P",
    "gn:feature_code":"PPL",
    "gn:name":"Heihoek",
    "gn:population":0,
    "gn:timezone":"Europe/Brussels",
    "iso:country":"BE",
    "name:und_x_variant":[
        "De Hoek",
        "Het Hoek",
        "Heihoek"
    ],
    "wof:name":"Heihoek",
    "wof:placetype":"locality"
},
  "geometry": {"coordinates":[5.43426,51.11541],"type":"Point"}
}