{
  "type": "Feature",
  "properties": {
    "gn:admin1_code":"WAL",
    "gn:admin2_code":"WLX",
    "gn:admin3_code":"84.0",
    "gn:admin4_code":"84029.0",
    "gn:asciiname":"Gribomont",
    "gn:country_code":"BE",
    "gn:dem":374,
    "gn:feature_class":"P",
    "gn:feature_code":"PPL",
    "gn:name":"Gribomont",
    "gn:population":0,
    "gn:timezone":"Europe/Brussels",
    "iso:country":"BE",
    "wof:name":"Gribomont",
    "wof:placetype":"locality"
},
  "geometry": {"coordinates":[5.3243,49.82166],"type":"Point"}
}