{
  "type": "Feature",
  "properties": {
    "gn:admin1_code":"WAL",
    "gn:admin2_code":"WBR",
    "gn:admin3_code":"25.0",
    "gn:admin4_code":"25123.0",
    "gn:asciiname":"Pierreux",
    "gn:country_code":"BE",
    "gn:dem":74,
    "gn:feature_class":"P",
    "gn:feature_code":"PPL",
    "gn:name":"Pierreux",
    "gn:population":0,
    "gn:timezone":"Europe/Brussels",
    "iso:country":"BE",
    "wof:name":"Pierreux",
    "wof:placetype":"locality"
},
  "geometry": {"coordinates":[4.11966,50.66052],"type":"Point"}
}