{
  "type": "Feature",
  "properties": {
    "gn:admin1_code":"VLG",
    "gn:admin2_code":"VBR",
    "gn:admin3_code":"24.0",
    "gn:admin4_code":"24062.0",
    "gn:asciiname":"Beneden Kessel",
    "gn:country_code":"BE",
    "gn:dem":20,
    "gn:feature_class":"P",
    "gn:feature_code":"PPL",
    "gn:name":"Beneden Kessel",
    "gn:population":0,
    "gn:timezone":"Europe/Brussels",
    "iso:country":"BE",
    "name:und_x_variant":[
        "Kessel",
        "Beneden Kessel"
    ],
    "wof:name":"Beneden Kessel",
    "wof:placetype":"locality"
},
  "geometry": {"coordinates":[4.7279,50.89903],"type":"Point"}
}