{
  "type": "Feature",
  "properties": {
    "gn:admin1_code":"VLG",
    "gn:admin2_code":"VOV",
    "gn:admin3_code":"41.0",
    "gn:admin4_code":"41048.0",
    "gn:asciiname":"Stene Brug",
    "gn:country_code":"BE",
    "gn:dem":16,
    "gn:feature_class":"P",
    "gn:feature_code":"PPL",
    "gn:name":"Stene Brug",
    "gn:population":0,
    "gn:timezone":"Europe/Brussels",
    "iso:country":"BE",
    "name:und_x_variant":[
        "Steenebrug",
        "Stenen Brug",
        "Stene Brug"
    ],
    "wof:name":"Stene Brug",
    "wof:placetype":"locality"
},
  "geometry": {"coordinates":[4.04983,50.82283],"type":"Point"}
}