{
  "type": "Feature",
  "properties": {
    "gn:admin1_code":"VLG",
    "gn:admin2_code":"VLI",
    "gn:admin3_code":"71.0",
    "gn:admin4_code":"71069.0",
    "gn:asciiname":"Genenbemd",
    "gn:country_code":"BE",
    "gn:dem":29,
    "gn:feature_class":"P",
    "gn:feature_code":"PPL",
    "gn:name":"Genenbemd",
    "gn:population":0,
    "gn:timezone":"Europe/Brussels",
    "iso:country":"BE",
    "name:und_x_variant":[
        "Genebemde",
        "Geenenbemde",
        "Genenbemd"
    ],
    "wof:name":"Genenbemd",
    "wof:placetype":"locality"
},
  "geometry": {"coordinates":[5.14128,51.1037],"type":"Point"}
}