{
  "type": "Feature",
  "properties": {
    "gn:admin1_code":"VLG",
    "gn:admin2_code":"VAN",
    "gn:admin3_code":"11.0",
    "gn:admin4_code":"11053.0",
    "gn:asciiname":"Breikelen",
    "gn:country_code":"BE",
    "gn:dem":18,
    "gn:feature_class":"P",
    "gn:feature_code":"PPL",
    "gn:name":"Breikelen",
    "gn:population":0,
    "gn:timezone":"Europe/Brussels",
    "iso:country":"BE",
    "name:und_x_variant":[
        "Breikelken",
        "Breikelen"
    ],
    "wof:name":"Breikelen",
    "wof:placetype":"locality"
},
  "geometry": {"coordinates":[4.58456,51.38828],"type":"Point"}
}