{
  "type": "Feature",
  "properties": {
    "gn:admin1_code":"VLG",
    "gn:admin2_code":"VLI",
    "gn:admin3_code":"71.0",
    "gn:admin4_code":"71020.0",
    "gn:asciiname":"Halensbroek",
    "gn:country_code":"BE",
    "gn:dem":26,
    "gn:feature_class":"P",
    "gn:feature_code":"PPL",
    "gn:name":"Halensbroek",
    "gn:population":0,
    "gn:timezone":"Europe/Brussels",
    "iso:country":"BE",
    "name:und_x_variant":[
        "Haelens Broek",
        "Halensbroek"
    ],
    "wof:name":"Halensbroek",
    "wof:placetype":"locality"
},
  "geometry": {"coordinates":[5.10048,50.95766],"type":"Point"}
}