{
  "type": "Feature",
  "properties": {
    "gn:admin1_code":"VLG",
    "gn:admin2_code":"VOV",
    "gn:admin3_code":"44.0",
    "gn:admin4_code":"44021.0",
    "gn:asciiname":"Schootkouter",
    "gn:country_code":"BE",
    "gn:dem":10,
    "gn:feature_class":"P",
    "gn:feature_code":"PPL",
    "gn:name":"Schootkouter",
    "gn:population":0,
    "gn:timezone":"Europe/Brussels",
    "iso:country":"BE",
    "name:und_x_variant":[
        "Schootkauter",
        "Schootkouter"
    ],
    "wof:name":"Schootkouter",
    "wof:placetype":"locality"
},
  "geometry": {"coordinates":[3.75,51.08333],"type":"Point"}
}