{
  "type": "Feature",
  "properties": {
    "gn:admin1_code":"VLG",
    "gn:admin2_code":"VLI",
    "gn:asciiname":"Pierreux",
    "gn:country_code":"BE",
    "gn:dem":266,
    "gn:feature_class":"P",
    "gn:feature_code":"PPL",
    "gn:name":"Pierreux",
    "gn:population":0,
    "gn:timezone":"Europe/Brussels",
    "iso:country":"BE",
    "wof:name":"Pierreux",
    "wof:placetype":"locality"
},
  "geometry": {"coordinates":[5.63333,50.45],"type":"Point"}
}