{
  "type": "Feature",
  "properties": {
    "gn:admin1_code":"VLG",
    "gn:admin2_code":"VOV",
    "gn:admin3_code":"44.0",
    "gn:admin4_code":"44043.0",
    "gn:asciiname":"Kwenenbos",
    "gn:country_code":"BE",
    "gn:dem":13,
    "gn:feature_class":"P",
    "gn:feature_code":"PPL",
    "gn:name":"Kwenenbos",
    "gn:population":0,
    "gn:timezone":"Europe/Brussels",
    "iso:country":"BE",
    "name:und_x_variant":[
        "Quenenbosch",
        "Kwenenbos"
    ],
    "wof:name":"Kwenenbos",
    "wof:placetype":"locality"
},
  "geometry": {"coordinates":[3.73047,50.97645],"type":"Point"}
}