{
  "type": "Feature",
  "properties": {
    "gn:admin1_code":"WAL",
    "gn:admin2_code":"WNA",
    "gn:admin3_code":"92.0",
    "gn:admin4_code":"92097.0",
    "gn:asciiname":"Eve",
    "gn:country_code":"BE",
    "gn:dem":246,
    "gn:feature_class":"P",
    "gn:feature_code":"PPL",
    "gn:name":"\u00c9ve",
    "gn:population":0,
    "gn:timezone":"Europe/Brussels",
    "iso:country":"BE",
    "wof:name":"Eve",
    "wof:placetype":"locality"
},
  "geometry": {"coordinates":[5.16427,50.40561],"type":"Point"}
}