{
  "type": "Feature",
  "properties": {
    "gn:admin1_code":"VLG",
    "gn:admin2_code":"VAN",
    "gn:admin3_code":"13.0",
    "gn:admin4_code":"13017.0",
    "gn:asciiname":"Stenenstraat",
    "gn:country_code":"BE",
    "gn:dem":17,
    "gn:feature_class":"P",
    "gn:feature_code":"PPL",
    "gn:name":"Stenenstraat",
    "gn:population":0,
    "gn:timezone":"Europe/Brussels",
    "iso:country":"BE",
    "name:und_x_variant":[
        "Steenenstraat",
        "Stenenstraat"
    ],
    "wof:name":"Stenenstraat",
    "wof:placetype":"locality"
},
  "geometry": {"coordinates":[4.92192,51.21479],"type":"Point"}
}