{
  "type": "Feature",
  "properties": {
    "gn:gn_country":"BE",
    "gn:gn_fcode":"PPL",
    "gn:gn_pop":0,
    "iso:country":"BE",
    "name:bul_x_preferred":[
        "\u0421\u043e\u0441\u043e\u0439\u0435"
    ],
    "name:dut_x_preferred":[
        "Sosoye"
    ],
    "name:eng_x_preferred":[
        "Sosoye"
    ],
    "name:fre_x_preferred":[
        "Sosoye"
    ],
    "name:swe_x_preferred":[
        "Sosoye"
    ],
    "name:unk_x_variant":[
        "Anh\u00e9e (Sosoye)"
    ],
    "name:wln_x_preferred":[
        "S\u00f4zoye"
    ],
    "qs_pg:aaroncc":"BE",
    "qs_pg:gn_country":"BE",
    "qs_pg:gn_fcode":"PPL",
    "qs_pg:gn_pop":0,
    "qs_pg:name":"Sosoye",
    "qs_pg:name_adm0":"Belgique",
    "qs_pg:name_adm1":"Namur",
    "qs_pg:photos":130,
    "qs_pg:photos_1k":26,
    "qs_pg:photos_9k":1,
    "qs_pg:photos_9r":3,
    "qs_pg:photos_all":130,
    "qs_pg:photos_sr":3,
    "qs_pg:pop_sr":0,
    "qs_pg:qs_pg_placetype":"locality",
    "qs_pg:qs_pg_placetype_gp":"Town",
    "qs_pg:woe_adm0":23424757,
    "woe:adm0_id":23424757,
    "woe:name_adm0":"Belgique",
    "woe:name_adm1":"Namur",
    "woe:placetype":"Town",
    "wof:name":"Sosoye",
    "wof:placetype":"locality"
},
  "geometry": {"coordinates":[4.78214,50.29548],"type":"Point"}
}