{
  "type": "Feature",
  "properties": {
    "gn:admin1_code":"WAL",
    "gn:admin2_code":"WHT",
    "gn:admin3_code":"51.0",
    "gn:admin4_code":"51065.0",
    "gn:asciiname":"Baureux",
    "gn:country_code":"BE",
    "gn:dem":52,
    "gn:feature_class":"P",
    "gn:feature_code":"PPL",
    "gn:name":"Baureux",
    "gn:population":0,
    "gn:timezone":"Europe/Brussels",
    "iso:country":"BE",
    "wof:name":"Baureux",
    "wof:placetype":"locality"
},
  "geometry": {"coordinates":[3.52994,50.70683],"type":"Point"}
}