{
  "type": "Feature",
  "properties": {
    "gn:admin1_code":"VLG",
    "gn:admin2_code":"VBR",
    "gn:admin3_code":"23.0",
    "gn:admin4_code":"23081.0",
    "gn:asciiname":"Boekt",
    "gn:country_code":"BE",
    "gn:dem":9,
    "gn:feature_class":"P",
    "gn:feature_code":"PPL",
    "gn:name":"Boekt",
    "gn:population":0,
    "gn:timezone":"Europe/Brussels",
    "iso:country":"BE",
    "name:nld_x_preferred":[
        "Boekt"
    ],
    "name:und_x_variant":[
        "Bocht",
        "Bockt",
        "Boekt"
    ],
    "wof:name":"Boekt",
    "wof:placetype":"locality"
},
  "geometry": {"coordinates":[4.4995,50.9534],"type":"Point"}
}