{
  "type": "Feature",
  "properties": {
    "gn:admin1_code":"VLG",
    "gn:admin2_code":"VOV",
    "gn:admin3_code":"41.0",
    "gn:admin4_code":"41002.0",
    "gn:asciiname":"Dries",
    "gn:country_code":"BE",
    "gn:dem":19,
    "gn:feature_class":"P",
    "gn:feature_code":"PPL",
    "gn:name":"Dries",
    "gn:population":0,
    "gn:timezone":"Europe/Brussels",
    "iso:country":"BE",
    "name:und_x_variant":[
        "Driesch",
        "Dries"
    ],
    "wof:name":"Dries",
    "wof:placetype":"locality"
},
  "geometry": {"coordinates":[4.01907,50.91466],"type":"Point"}
}