{
  "type": "Feature",
  "properties": {
    "iso:country":"BE",
    "qs_pg:aaroncc":"BE",
    "qs_pg:name":"Hourlay",
    "qs_pg:name_adm0":"Belgique",
    "qs_pg:name_adm1":"Luxembourg",
    "qs_pg:photos":6,
    "qs_pg:photos_1k":1,
    "qs_pg:photos_9k":1,
    "qs_pg:photos_9r":1,
    "qs_pg:photos_all":6,
    "qs_pg:photos_sr":1,
    "qs_pg:pop_sr":0,
    "qs_pg:qs_pg_placetype":"locality",
    "qs_pg:qs_pg_placetype_gp":"Town",
    "qs_pg:woe_adm0":23424757,
    "woe:adm0_id":23424757,
    "woe:name_adm0":"Belgique",
    "woe:name_adm1":"Luxembourg",
    "woe:placetype":"Town",
    "wof:name":"Hourlay",
    "wof:placetype":"locality"
},
  "geometry": {"coordinates":[5.6042285,50.358686],"type":"Point"}
}