{
  "type": "Feature",
  "properties": {
    "gn:admin1_code":"WAL",
    "gn:admin2_code":"WLX",
    "gn:admin3_code":"82.0",
    "gn:admin4_code":"82009.0",
    "gn:asciiname":"Strainchamps",
    "gn:country_code":"BE",
    "gn:dem":438,
    "gn:feature_class":"P",
    "gn:feature_code":"PPL",
    "gn:name":"Strainchamps",
    "gn:population":0,
    "gn:timezone":"Europe/Brussels",
    "iso:country":"BE",
    "wof:name":"Strainchamps",
    "wof:placetype":"locality"
},
  "geometry": {"coordinates":[5.68541,49.8804],"type":"Point"}
}