{
  "type": "Feature",
  "properties": {
    "gn:admin1_code":"WAL",
    "gn:admin2_code":"WHT",
    "gn:admin3_code":"56.0",
    "gn:admin4_code":"56086.0",
    "gn:asciiname":"Grogeries",
    "gn:country_code":"BE",
    "gn:dem":213,
    "gn:feature_class":"P",
    "gn:feature_code":"PPL",
    "gn:name":"Grogeries",
    "gn:population":0,
    "gn:timezone":"Europe/Brussels",
    "iso:country":"BE",
    "wof:name":"Grogeries",
    "wof:placetype":"locality"
},
  "geometry": {"coordinates":[4.42601,50.3382],"type":"Point"}
}