{
  "type": "Feature",
  "properties": {
    "gn:admin1_code":"VLG",
    "gn:admin2_code":"VOV",
    "gn:admin3_code":"46.0",
    "gn:admin4_code":"46003.0",
    "gn:asciiname":"Leurshoek",
    "gn:country_code":"BE",
    "gn:dem":-1,
    "gn:feature_class":"P",
    "gn:feature_code":"PPL",
    "gn:name":"Leurshoek",
    "gn:population":0,
    "gn:timezone":"Europe/Brussels",
    "iso:country":"BE",
    "wof:name":"Leurshoek",
    "wof:placetype":"locality"
},
  "geometry": {"coordinates":[4.26667,51.23333],"type":"Point"}
}