{
  "type": "Feature",
  "properties": {
    "gn:admin1_code":"WAL",
    "gn:admin2_code":"WHT",
    "gn:admin3_code":"53.0",
    "gn:admin4_code":"53082.0",
    "gn:asciiname":"Petit Wasmes",
    "gn:country_code":"BE",
    "gn:dem":81,
    "gn:feature_class":"P",
    "gn:feature_code":"PPL",
    "gn:name":"Petit Wasmes",
    "gn:population":0,
    "gn:timezone":"Europe/Brussels",
    "iso:country":"BE",
    "name:tur_x_preferred":[
        "Petit Wasmes"
    ],
    "wof:name":"Petit Wasmes",
    "wof:placetype":"locality"
},
  "geometry": {"coordinates":[3.82891,50.40983],"type":"Point"}
}