{
  "type": "Feature",
  "properties": {
    "gn:admin1_code":"VLG",
    "gn:admin2_code":"VLI",
    "gn:admin3_code":"71.0",
    "gn:admin4_code":"71057.0",
    "gn:asciiname":"Baal",
    "gn:country_code":"BE",
    "gn:dem":21,
    "gn:feature_class":"P",
    "gn:feature_code":"PPL",
    "gn:name":"Baal",
    "gn:population":0,
    "gn:timezone":"Europe/Brussels",
    "iso:country":"BE",
    "name:afr_x_preferred":[
        "Ba\u00e4l"
    ],
    "name:ara_x_preferred":[
        "\u0628\u0639\u0644"
    ],
    "name:arz_x_preferred":[
        "\u0628\u0639\u0644"
    ],
    "name:azb_x_preferred":[
        "\u0628\u0639\u0644"
    ],
    "name:aze_x_preferred":[
        "Baal"
    ],
    "name:bel_x_preferred":[
        "\u0411\u0430\u0430\u043b"
    ],
    "name:ben_x_preferred":[
        "\u09ac\u09be\u0986\u09b2"
    ],
    "name:bul_x_preferred":[
        "\u0411\u0430\u0430\u043b"
    ],
    "name:cat_x_preferred":[
        "Baal"
    ],
    "name:ces_x_preferred":[
        "Baal"
    ],
    "name:cym_x_preferred":[
        "Ba\u02bfal"
    ],
    "name:dan_x_preferred":[
        "Baal"
    ],
    "name:deu_x_preferred":[
        "Baal"
    ],
    "name:ell_x_preferred":[
        "\u0392\u03ac\u03b1\u03bb"
    ],
    "name:epo_x_preferred":[
        "Baalo"
    ],
    "name:est_x_preferred":[
        "Baal"
    ],
    "name:eus_x_preferred":[
        "Baal"
    ],
    "name:fas_x_preferred":[
        "\u0628\u0639\u0644"
    ],
    "name:fin_x_preferred":[
        "Baal"
    ],
    "name:fra_x_preferred":[
        "Baal"
    ],
    "name:glg_x_preferred":[
        "Baal"
    ],
    "name:got_x_preferred":[
        "\ud800\udf31\ud800\udf30\ud800\udf30\ud800\udf3b"
    ],
    "name:heb_x_preferred":[
        "\u05d1\u05e2\u05dc"
    ],
    "name:hun_x_preferred":[
        "Ba\u00e1l"
    ],
    "name:ind_x_preferred":[
        "Ba'al"
    ],
    "name:ita_x_preferred":[
        "Baal"
    ],
    "name:jpn_x_preferred":[
        "\u30d0\u30a2\u30eb"
    ],
    "name:lad_x_preferred":[
        "Baal"
    ],
    "name:lit_x_preferred":[
        "Baalas"
    ],
    "name:ltz_x_preferred":[
        "Baal"
    ],
    "name:mal_x_preferred":[
        "\u0d2c\u0d3e\u0d7d \u0d26\u0d47\u0d35\u0d7b"
    ],
    "name:nds_x_preferred":[
        "Baal"
    ],
    "name:nld_x_preferred":[
        "Ba\u00e4l"
    ],
    "name:nor_x_preferred":[
        "Baal"
    ],
    "name:pol_x_preferred":[
        "Baal"
    ],
    "name:por_x_preferred":[
        "Baal"
    ],
    "name:pus_x_preferred":[
        "\u0628\u0639\u0644"
    ],
    "name:ron_x_preferred":[
        "Baal"
    ],
    "name:rus_x_preferred":[
        "\u0411\u0430\u0430\u043b"
    ],
    "name:sco_x_preferred":[
        "Baal"
    ],
    "name:slv_x_preferred":[
        "Baal"
    ],
    "name:spa_x_preferred":[
        "Baal"
    ],
    "name:srp_x_preferred":[
        "\u0411\u0430\u0430\u043b"
    ],
    "name:swe_x_preferred":[
        "Baal"
    ],
    "name:tgl_x_preferred":[
        "Ba\u02bfal"
    ],
    "name:tha_x_preferred":[
        "\u0e1a\u0e32\u0e2d\u0e31\u0e25"
    ],
    "name:tur_x_preferred":[
        "Baal"
    ],
    "name:ukr_x_preferred":[
        "\u0412\u0430\u0430\u043b"
    ],
    "name:und_x_variant":[
        "Bael"
    ],
    "name:urd_x_preferred":[
        "\u0628\u0639\u0644"
    ],
    "name:wol_x_preferred":[
        "Baal"
    ],
    "wof:name":"Baal",
    "wof:placetype":"locality"
},
  "geometry": {"coordinates":[5.08333,51.08333],"type":"Point"}
}