{
  "type": "Feature",
  "properties": {
    "gn:admin1_code":"VLG",
    "gn:admin2_code":"VLI",
    "gn:admin3_code":"72.0",
    "gn:admin4_code":"72037.0",
    "gn:asciiname":"Inkensven",
    "gn:country_code":"BE",
    "gn:dem":37,
    "gn:feature_class":"P",
    "gn:feature_code":"PPL",
    "gn:name":"Inkensven",
    "gn:population":0,
    "gn:timezone":"Europe/Brussels",
    "iso:country":"BE",
    "wof:name":"Inkensven",
    "wof:placetype":"locality"
},
  "geometry": {"coordinates":[5.55,51.23333],"type":"Point"}
}