{
  "type": "Feature",
  "properties": {
    "gn:admin1_code":"VLG",
    "gn:admin2_code":"VWV",
    "gn:asciiname":"Kortewilde",
    "gn:country_code":"BE",
    "gn:dem":20,
    "gn:feature_class":"P",
    "gn:feature_code":"PPL",
    "gn:name":"Kortewilde",
    "gn:population":0,
    "gn:timezone":"Europe/Brussels",
    "iso:country":"BE",
    "wof:name":"Kortewilde",
    "wof:placetype":"locality"
},
  "geometry": {"coordinates":[2.96114,50.79636],"type":"Point"}
}