{
  "type": "Feature",
  "properties": {
    "gn:admin1_code":"VLG",
    "gn:admin2_code":"VLI",
    "gn:admin3_code":"71.0",
    "gn:admin4_code":"71020.0",
    "gn:asciiname":"Rotem",
    "gn:country_code":"BE",
    "gn:dem":38,
    "gn:feature_class":"P",
    "gn:feature_code":"PPL",
    "gn:name":"Rotem",
    "gn:population":0,
    "gn:timezone":"Europe/Brussels",
    "iso:country":"BE",
    "name:und_x_variant":[
        "Rothem",
        "Rotem"
    ],
    "wof:name":"Rotem",
    "wof:placetype":"locality"
},
  "geometry": {"coordinates":[5.09106,50.92322],"type":"Point"}
}