{
  "type": "Feature",
  "properties": {
    "gn:admin1_code":"VLG",
    "gn:admin2_code":"VAN",
    "gn:admin3_code":"13.0",
    "gn:admin4_code":"13040.0",
    "gn:asciiname":"Zeverdonk",
    "gn:country_code":"BE",
    "gn:dem":19,
    "gn:feature_class":"P",
    "gn:feature_code":"PPL",
    "gn:name":"Zeverdonk",
    "gn:population":0,
    "gn:timezone":"Europe/Brussels",
    "iso:country":"BE",
    "name:und_x_variant":[
        "Severdonck",
        "Zeverdonk"
    ],
    "wof:name":"Zeverdonk",
    "wof:placetype":"locality"
},
  "geometry": {"coordinates":[4.94601,51.28939],"type":"Point"}
}