{
  "type": "Feature",
  "properties": {
    "gn:admin1_code":"WAL",
    "gn:admin2_code":"WLG",
    "gn:admin3_code":"62.0",
    "gn:admin4_code":"62100.0",
    "gn:asciiname":"Rouvreux",
    "gn:country_code":"BE",
    "gn:dem":259,
    "gn:feature_class":"P",
    "gn:feature_code":"PPL",
    "gn:name":"Rouvreux",
    "gn:population":0,
    "gn:timezone":"Europe/Brussels",
    "iso:country":"BE",
    "name:und_x_variant":[
        "Sprimont (Rouvreux)"
    ],
    "wof:name":"Rouvreux",
    "wof:placetype":"locality"
},
  "geometry": {"coordinates":[5.65006,50.48984],"type":"Point"}
}