{
  "type": "Feature",
  "properties": {
    "gn:admin1_code":"VLG",
    "gn:admin2_code":"VBR",
    "gn:admin3_code":"24.0",
    "gn:admin4_code":"24135.0",
    "gn:asciiname":"Houwaartseberg",
    "gn:country_code":"BE",
    "gn:dem":70,
    "gn:feature_class":"P",
    "gn:feature_code":"PPL",
    "gn:name":"Houwaartseberg",
    "gn:population":0,
    "gn:timezone":"Europe/Brussels",
    "iso:country":"BE",
    "name:und_x_variant":[
        "Hauwaertsche Berg",
        "Houwaartseberg"
    ],
    "wof:name":"Houwaartseberg",
    "wof:placetype":"locality"
},
  "geometry": {"coordinates":[4.85623,50.94225],"type":"Point"}
}