{
  "type": "Feature",
  "properties": {
    "gn:admin1_code":"VLG",
    "gn:admin2_code":"VOV",
    "gn:admin3_code":"44.0",
    "gn:admin4_code":"44049.0",
    "gn:asciiname":"Osse",
    "gn:country_code":"BE",
    "gn:dem":8,
    "gn:feature_class":"P",
    "gn:feature_code":"PPL",
    "gn:name":"Osse",
    "gn:population":0,
    "gn:timezone":"Europe/Brussels",
    "iso:country":"BE",
    "name:ceb_x_preferred":[
        "Osse"
    ],
    "name:deu_x_preferred":[
        "Osse"
    ],
    "name:fra_x_preferred":[
        "Osse"
    ],
    "name:ita_x_preferred":[
        "Osse"
    ],
    "name:nld_x_preferred":[
        "Osse"
    ],
    "name:pol_x_preferred":[
        "Osse"
    ],
    "name:por_x_preferred":[
        "Osse"
    ],
    "name:scn_x_preferred":[
        "Osse"
    ],
    "name:swe_x_preferred":[
        "Osse"
    ],
    "name:ukr_x_preferred":[
        "\u041e\u0441\u0441\u0435"
    ],
    "name:und_x_variant":[
        "Oossche"
    ],
    "wof:name":"Osse",
    "wof:placetype":"locality"
},
  "geometry": {"coordinates":[3.55,51.05],"type":"Point"}
}