{
  "type": "Feature",
  "properties": {
    "gn:admin1_code":"WAL",
    "gn:admin2_code":"WLX",
    "gn:admin3_code":"82.0",
    "gn:admin4_code":"82037.0",
    "gn:asciiname":"Le Rovreux",
    "gn:country_code":"BE",
    "gn:dem":512,
    "gn:feature_class":"P",
    "gn:feature_code":"PPL",
    "gn:name":"Le Rovreux",
    "gn:population":0,
    "gn:timezone":"Europe/Brussels",
    "iso:country":"BE",
    "wof:name":"Le Rovreux",
    "wof:placetype":"locality"
},
  "geometry": {"coordinates":[5.95,50.25],"type":"Point"}
}