{
  "type": "Feature",
  "properties": {
    "gn:admin1_code":"VLG",
    "gn:admin2_code":"VLI",
    "gn:admin3_code":"72.0",
    "gn:admin4_code":"72021.0",
    "gn:asciiname":"Op den Berg",
    "gn:country_code":"BE",
    "gn:dem":46,
    "gn:feature_class":"P",
    "gn:feature_code":"PPL",
    "gn:name":"Op den Berg",
    "gn:population":0,
    "gn:timezone":"Europe/Brussels",
    "iso:country":"BE",
    "wof:name":"Op den Berg",
    "wof:placetype":"locality"
},
  "geometry": {"coordinates":[5.68405,51.08013],"type":"Point"}
}