{
  "type": "Feature",
  "properties": {
    "gn:admin1_code":"WAL",
    "gn:admin2_code":"WLG",
    "gn:admin3_code":"64.0",
    "gn:admin4_code":"64056.0",
    "gn:asciiname":"Bergilers",
    "gn:country_code":"BE",
    "gn:dem":106,
    "gn:feature_class":"P",
    "gn:feature_code":"PPL",
    "gn:name":"Bergilers",
    "gn:population":0,
    "gn:timezone":"Europe/Brussels",
    "iso:country":"BE",
    "name:und_x_variant":[
        "Belliek",
        "Oreye (Bergilers)"
    ],
    "wof:name":"Bergilers",
    "wof:placetype":"locality"
},
  "geometry": {"coordinates":[5.32914,50.71586],"type":"Point"}
}