{
  "type": "Feature",
  "properties": {
    "gn:admin1_code":"WAL",
    "gn:admin2_code":"WHT",
    "gn:admin3_code":"55.0",
    "gn:admin4_code":"55004.0",
    "gn:asciiname":"Haute Houssiere",
    "gn:country_code":"BE",
    "gn:dem":102,
    "gn:feature_class":"P",
    "gn:feature_code":"PPL",
    "gn:name":"Haute Houssi\u00e8re",
    "gn:population":0,
    "gn:timezone":"Europe/Brussels",
    "iso:country":"BE",
    "wof:name":"Haute Houssiere",
    "wof:placetype":"locality"
},
  "geometry": {"coordinates":[4.14286,50.59624],"type":"Point"}
}