{
  "type": "Feature",
  "properties": {
    "gn:admin1_code":"VLG",
    "gn:admin2_code":"VOV",
    "gn:admin3_code":"45.0",
    "gn:admin4_code":"45035.0",
    "gn:asciiname":"Houwaart",
    "gn:country_code":"BE",
    "gn:dem":90,
    "gn:feature_class":"P",
    "gn:feature_code":"PPL",
    "gn:name":"Houwaart",
    "gn:population":0,
    "gn:timezone":"Europe/Brussels",
    "iso:country":"BE",
    "name:und_x_variant":[
        "Hauwaert",
        "Houwaart"
    ],
    "wof:name":"Houwaart",
    "wof:placetype":"locality"
},
  "geometry": {"coordinates":[3.65357,50.8314],"type":"Point"}
}