{
  "type": "Feature",
  "properties": {
    "gn:admin1_code":"WAL",
    "gn:admin2_code":"WLG",
    "gn:admin3_code":"63.0",
    "gn:admin4_code":"63046.0",
    "gn:asciiname":"Quatre Chemins",
    "gn:country_code":"BE",
    "gn:dem":278,
    "gn:feature_class":"P",
    "gn:feature_code":"PPL",
    "gn:name":"Quatre Chemins",
    "gn:population":0,
    "gn:timezone":"Europe/Brussels",
    "iso:country":"BE",
    "wof:name":"Quatre Chemins",
    "wof:placetype":"locality"
},
  "geometry": {"coordinates":[5.90527,50.63945],"type":"Point"}
}