{
  "type": "Feature",
  "properties": {
    "gn:admin1_code":"VLG",
    "gn:admin2_code":"VWV",
    "gn:admin3_code":"34.0",
    "gn:admin4_code":"34022.0",
    "gn:asciiname":"'t Molentje",
    "gn:country_code":"BE",
    "gn:dem":31,
    "gn:feature_class":"P",
    "gn:feature_code":"PPL",
    "gn:name":"'t Molentje",
    "gn:population":0,
    "gn:timezone":"Europe/Brussels",
    "iso:country":"BE",
    "wof:name":"'t Molentje",
    "wof:placetype":"locality"
},
  "geometry": {"coordinates":[3.3205,50.74697000000001],"type":"Point"}
}