{
  "type": "Feature",
  "properties": {
    "gn:gn_country":"BE",
    "gn:gn_fcode":"PPL",
    "gn:gn_pop":0,
    "iso:country":"BE",
    "name:unk_x_variant":[
        "Hockay"
    ],
    "qs_pg:aaroncc":"BE",
    "qs_pg:gn_country":"BE",
    "qs_pg:gn_fcode":"PPL",
    "qs_pg:gn_pop":0,
    "qs_pg:name":"Hockai",
    "qs_pg:name_adm0":"Belgique",
    "qs_pg:name_adm1":"Li\u00e8ge",
    "qs_pg:photos":68,
    "qs_pg:photos_1k":14,
    "qs_pg:photos_9k":1,
    "qs_pg:photos_9r":2,
    "qs_pg:photos_all":68,
    "qs_pg:photos_sr":2,
    "qs_pg:pop_sr":0,
    "qs_pg:qs_pg_placetype":"locality",
    "qs_pg:qs_pg_placetype_gp":"Town",
    "qs_pg:woe_adm0":23424757,
    "woe:adm0_id":23424757,
    "woe:name_adm0":"Belgique",
    "woe:name_adm1":"Li\u00e8ge",
    "woe:placetype":"Town",
    "wof:name":"Hockai",
    "wof:placetype":"locality"
},
  "geometry": {"coordinates":[5.98783,50.48183],"type":"Point"}
}