{
  "type": "Feature",
  "properties": {
    "gn:admin1_code":"WAL",
    "gn:admin2_code":"WHT",
    "gn:admin3_code":"52.0",
    "gn:admin4_code":"52015.0",
    "gn:asciiname":"Rianwelz",
    "gn:country_code":"BE",
    "gn:dem":165,
    "gn:feature_class":"P",
    "gn:feature_code":"PPL",
    "gn:name":"Rianwelz",
    "gn:population":0,
    "gn:timezone":"Europe/Brussels",
    "iso:country":"BE",
    "wof:name":"Rianwelz",
    "wof:placetype":"locality"
},
  "geometry": {"coordinates":[4.35,50.45],"type":"Point"}
}