{
  "type": "Feature",
  "properties": {
    "gn:admin1_code":"VLG",
    "gn:admin2_code":"VLI",
    "gn:admin3_code":"71.0",
    "gn:admin4_code":"71045.0",
    "gn:asciiname":"Borglever",
    "gn:country_code":"BE",
    "gn:dem":62,
    "gn:feature_class":"P",
    "gn:feature_code":"PPL",
    "gn:name":"Borglever",
    "gn:population":0,
    "gn:timezone":"Europe/Brussels",
    "iso:country":"BE",
    "name:und_x_variant":[
        "Berg-Lever",
        "Borglever"
    ],
    "wof:name":"Borglever",
    "wof:placetype":"locality"
},
  "geometry": {"coordinates":[5.23333,50.88333],"type":"Point"}
}