{
  "type": "Feature",
  "properties": {
    "gn:admin1_code":"VLG",
    "gn:admin2_code":"VBR",
    "gn:admin3_code":"24.0",
    "gn:admin4_code":"24007.0",
    "gn:asciiname":"Hulst",
    "gn:country_code":"BE",
    "gn:dem":22,
    "gn:feature_class":"P",
    "gn:feature_code":"PPL",
    "gn:name":"Hulst",
    "gn:population":0,
    "gn:timezone":"Europe/Brussels",
    "iso:country":"BE",
    "name:afr_x_preferred":[
        "Hulst"
    ],
    "name:ara_x_preferred":[
        "\u0647\u0648\u0644\u0633\u062a"
    ],
    "name:bre_x_preferred":[
        "Hulst"
    ],
    "name:cat_x_preferred":[
        "Hulst"
    ],
    "name:ceb_x_preferred":[
        "Gemeente Hulst"
    ],
    "name:dan_x_preferred":[
        "Hulst"
    ],
    "name:deu_x_preferred":[
        "Hulst"
    ],
    "name:eus_x_preferred":[
        "Hulst"
    ],
    "name:fas_x_preferred":[
        "\u0647\u0648\u0644\u0633\u062a"
    ],
    "name:fra_x_preferred":[
        "Hulst"
    ],
    "name:fry_x_preferred":[
        "Hulst"
    ],
    "name:gle_x_preferred":[
        "Hulst"
    ],
    "name:hye_x_preferred":[
        "\u0540\u0578\u0582\u056c\u057d\u057f"
    ],
    "name:ind_x_preferred":[
        "Hulst"
    ],
    "name:ita_x_preferred":[
        "Hulst"
    ],
    "name:lim_x_preferred":[
        "Hulst"
    ],
    "name:msa_x_preferred":[
        "Hulst"
    ],
    "name:nld_x_preferred":[
        "Hulst"
    ],
    "name:nor_x_preferred":[
        "Hulst"
    ],
    "name:pol_x_preferred":[
        "Hulst"
    ],
    "name:por_x_preferred":[
        "Hulst"
    ],
    "name:rus_x_preferred":[
        "\u0425\u044e\u043b\u0441\u0442"
    ],
    "name:spa_x_preferred":[
        "Hulst"
    ],
    "name:sqi_x_preferred":[
        "Hulst"
    ],
    "name:stq_x_preferred":[
        "Hulst"
    ],
    "name:swe_x_preferred":[
        "Hulst"
    ],
    "name:tur_x_preferred":[
        "Hulst"
    ],
    "name:vls_x_preferred":[
        "Hulst"
    ],
    "name:vol_x_preferred":[
        "Hulst"
    ],
    "name:zea_x_preferred":[
        "Ulst"
    ],
    "name:zho_x_preferred":[
        "\u8a31\u723e\u65af\u7279"
    ],
    "wof:name":"Hulst",
    "wof:placetype":"locality"
},
  "geometry": {"coordinates":[4.79635,50.99088],"type":"Point"}
}