{
  "type": "Feature",
  "properties": {
    "gn:admin1_code":"WAL",
    "gn:admin2_code":"WNA",
    "gn:admin3_code":"91.0",
    "gn:admin4_code":"91034.0",
    "gn:asciiname":"Plantis de Geauvelant",
    "gn:country_code":"BE",
    "gn:dem":251,
    "gn:feature_class":"P",
    "gn:feature_code":"PPL",
    "gn:name":"Plantis de Geauvelant",
    "gn:population":0,
    "gn:timezone":"Europe/Brussels",
    "iso:country":"BE",
    "name:und_x_variant":[
        "Planti de Geauvelant",
        "Plantis de Geauvelant"
    ],
    "wof:name":"Plantis de Geauvelant",
    "wof:placetype":"locality"
},
  "geometry": {"coordinates":[5.01667,50.26667],"type":"Point"}
}