{
  "type": "Feature",
  "properties": {
    "gn:admin1_code":"WAL",
    "gn:admin2_code":"WLG",
    "gn:admin3_code":"63.0",
    "gn:admin4_code":"63084.0",
    "gn:asciiname":"Vivier",
    "gn:country_code":"BE",
    "gn:dem":254,
    "gn:feature_class":"P",
    "gn:feature_code":"PPL",
    "gn:name":"Vivier",
    "gn:population":0,
    "gn:timezone":"Europe/Brussels",
    "iso:country":"BE",
    "wof:name":"Vivier",
    "wof:placetype":"locality"
},
  "geometry": {"coordinates":[5.94076,50.68551],"type":"Point"}
}