{
  "type": "Feature",
  "properties": {
    "gn:admin1_code":"VLG",
    "gn:admin2_code":"VOV",
    "gn:admin3_code":"41.0",
    "gn:admin4_code":"41048.0",
    "gn:asciiname":"Rattenberg",
    "gn:country_code":"BE",
    "gn:dem":29,
    "gn:feature_class":"P",
    "gn:feature_code":"PPL",
    "gn:name":"Rattenberg",
    "gn:population":0,
    "gn:timezone":"Europe/Brussels",
    "iso:country":"BE",
    "name:bar_x_preferred":[
        "R\u00e5ttnberg"
    ],
    "name:bul_x_preferred":[
        "\u0420\u0430\u0442\u0435\u043d\u0431\u0435\u0440\u0433"
    ],
    "name:ceb_x_preferred":[
        "Rattenberg"
    ],
    "name:deu_x_preferred":[
        "Rattenberg"
    ],
    "name:est_x_preferred":[
        "Rattenberg"
    ],
    "name:fas_x_preferred":[
        "\u0631\u0627\u062a\u0646\u0628\u0631\u06af"
    ],
    "name:fra_x_preferred":[
        "Rattenberg"
    ],
    "name:hun_x_preferred":[
        "Rattenberg"
    ],
    "name:ind_x_preferred":[
        "Rattenberg"
    ],
    "name:ita_x_preferred":[
        "Rattenberg"
    ],
    "name:kaz_x_preferred":[
        "\u0420\u0430\u0442\u0442\u0435\u043d\u0431\u0435\u0440\u0433"
    ],
    "name:kor_x_preferred":[
        "\ub77c\ud150\ubca0\ub974\ud06c"
    ],
    "name:nld_x_preferred":[
        "Rattenberg"
    ],
    "name:nor_x_preferred":[
        "Rattenberg"
    ],
    "name:pol_x_preferred":[
        "Rattenberg"
    ],
    "name:rus_x_preferred":[
        "\u0420\u0430\u0442\u0442\u0435\u043d\u0431\u0435\u0440\u0433"
    ],
    "name:slk_x_preferred":[
        "Rattenberg"
    ],
    "name:spa_x_preferred":[
        "Rattenberg"
    ],
    "name:swe_x_preferred":[
        "Rattenberg"
    ],
    "name:ukr_x_preferred":[
        "\u0420\u0430\u0442\u0442\u0435\u043d\u0431\u0435\u0440\u0433"
    ],
    "name:uzb_x_preferred":[
        "Rattenberg"
    ],
    "name:vol_x_preferred":[
        "Rattenberg"
    ],
    "name:war_x_preferred":[
        "Rattenberg"
    ],
    "name:zho_x_preferred":[
        "\u62c9\u6ed5\u5821"
    ],
    "wof:name":"Rattenberg",
    "wof:placetype":"locality"
},
  "geometry": {"coordinates":[4.05,50.86667],"type":"Point"}
}