{
  "type": "Feature",
  "properties": {
    "gn:admin1_code":"WAL",
    "gn:admin2_code":"WHT",
    "gn:admin3_code":"52.0",
    "gn:admin4_code":"52025.0",
    "gn:asciiname":"Trieu Gilson",
    "gn:country_code":"BE",
    "gn:dem":213,
    "gn:feature_class":"P",
    "gn:feature_code":"PPL",
    "gn:name":"Trieu Gilson",
    "gn:population":0,
    "gn:timezone":"Europe/Brussels",
    "iso:country":"BE",
    "wof:name":"Trieu Gilson",
    "wof:placetype":"locality"
},
  "geometry": {"coordinates":[4.49967,50.3541],"type":"Point"}
}