{
  "type": "Feature",
  "properties": {
    "gn:admin1_code":"VLG",
    "gn:admin2_code":"VLI",
    "gn:admin3_code":"72.0",
    "gn:admin4_code":"72030.0",
    "gn:asciiname":"Molhem",
    "gn:country_code":"BE",
    "gn:dem":58,
    "gn:feature_class":"P",
    "gn:feature_code":"PPL",
    "gn:name":"Molhem",
    "gn:population":0,
    "gn:timezone":"Europe/Brussels",
    "iso:country":"BE",
    "wof:name":"Molhem",
    "wof:placetype":"locality"
},
  "geometry": {"coordinates":[5.43291,51.14623],"type":"Point"}
}