{
  "type": "Feature",
  "properties": {
    "gn:admin1_code":"VLG",
    "gn:admin2_code":"VBR",
    "gn:admin3_code":"24.0",
    "gn:admin4_code":"24028.0",
    "gn:asciiname":"Bergen-Einde",
    "gn:country_code":"BE",
    "gn:dem":49,
    "gn:feature_class":"P",
    "gn:feature_code":"PPL",
    "gn:name":"Bergen-Einde",
    "gn:population":0,
    "gn:timezone":"Europe/Brussels",
    "iso:country":"BE",
    "wof:name":"Bergen-Einde",
    "wof:placetype":"locality"
},
  "geometry": {"coordinates":[5.17535,50.90574],"type":"Point"}
}