{
  "type": "Feature",
  "properties": {
    "gn:admin1_code":"WAL",
    "gn:admin2_code":"WLG",
    "gn:admin3_code":"63.0",
    "gn:admin4_code":"63080.0",
    "gn:asciiname":"Mont Rigi",
    "gn:cc2":"BE",
    "gn:country_code":"BE",
    "gn:dem":675,
    "gn:feature_class":"P",
    "gn:feature_code":"PPL",
    "gn:name":"Mont Rigi",
    "gn:population":0,
    "gn:timezone":"Europe/Brussels",
    "iso:country":"BE",
    "name:und_x_variant":[
        "Monte-Rigi"
    ],
    "wof:name":"Mont Rigi",
    "wof:placetype":"locality"
},
  "geometry": {"coordinates":[6.0745,50.51135],"type":"Point"}
}