{
  "type": "Feature",
  "properties": {
    "iso:country":"BE",
    "qs_pg:aaroncc":"BE",
    "qs_pg:name":"Zwaan",
    "qs_pg:name_adm0":"Belgique",
    "qs_pg:name_adm1":"Antwerpen",
    "qs_pg:photos":228,
    "qs_pg:photos_1k":46,
    "qs_pg:photos_9k":1,
    "qs_pg:photos_9r":4,
    "qs_pg:photos_all":228,
    "qs_pg:photos_sr":4,
    "qs_pg:pop_sr":0,
    "qs_pg:qs_pg_placetype":"locality",
    "qs_pg:qs_pg_placetype_gp":"Town",
    "qs_pg:woe_adm0":23424757,
    "woe:adm0_id":23424757,
    "woe:name_adm0":"Belgique",
    "woe:name_adm1":"Antwerpen",
    "woe:placetype":"Town",
    "wof:name":"Zwaan",
    "wof:placetype":"locality"
},
  "geometry": {"coordinates":[4.553639,51.312749],"type":"Point"}
}