{
  "type": "Feature",
  "properties": {
    "gn:admin1_code":"VLG",
    "gn:admin2_code":"VOV",
    "gn:admin3_code":"46.0",
    "gn:admin4_code":"46025.0",
    "gn:asciiname":"Vierstraat",
    "gn:country_code":"BE",
    "gn:dem":21,
    "gn:feature_class":"P",
    "gn:feature_code":"PPL",
    "gn:name":"Vierstraat",
    "gn:population":0,
    "gn:timezone":"Europe/Brussels",
    "iso:country":"BE",
    "wof:name":"Vierstraat",
    "wof:placetype":"locality"
},
  "geometry": {"coordinates":[4.22413,51.1472],"type":"Point"}
}