{
  "type": "Feature",
  "properties": {
    "gn:admin1_code":"WAL",
    "gn:admin2_code":"WHT",
    "gn:asciiname":"Wippendries",
    "gn:country_code":"BE",
    "gn:dem":8,
    "gn:feature_class":"P",
    "gn:feature_code":"PPL",
    "gn:name":"Wippendries",
    "gn:population":0,
    "gn:timezone":"Europe/Brussels",
    "iso:country":"BE",
    "name:und_x_variant":[
        "Ouden Wippendries",
        "Wippendries"
    ],
    "wof:name":"Wippendries",
    "wof:placetype":"locality"
},
  "geometry": {"coordinates":[4.508,50.96572000000001],"type":"Point"}
}