{
  "type": "Feature",
  "properties": {
    "gn:admin1_code":"WAL",
    "gn:admin2_code":"WLG",
    "gn:admin3_code":"63.0",
    "gn:admin4_code":"63084.0",
    "gn:asciiname":"Ruyff",
    "gn:country_code":"BE",
    "gn:dem":279,
    "gn:feature_class":"P",
    "gn:feature_code":"PPL",
    "gn:name":"Ruyff",
    "gn:population":0,
    "gn:timezone":"Europe/Brussels",
    "iso:country":"BE",
    "name:und_x_variant":[
        "Ruyft",
        "Ruyff"
    ],
    "wof:name":"Ruyff",
    "wof:placetype":"locality"
},
  "geometry": {"coordinates":[5.95203,50.67518],"type":"Point"}
}