{
  "type": "Feature",
  "properties": {
    "gn:admin1_code":"VLG",
    "gn:admin2_code":"VWV",
    "gn:admin3_code":"32.0",
    "gn:admin4_code":"32011.0",
    "gn:asciiname":"Groenenspriet",
    "gn:country_code":"BE",
    "gn:dem":9,
    "gn:feature_class":"P",
    "gn:feature_code":"PPL",
    "gn:name":"Groenenspriet",
    "gn:population":0,
    "gn:timezone":"Europe/Brussels",
    "iso:country":"BE",
    "name:und_x_variant":[
        "Groenespriet",
        "Groenenspriet"
    ],
    "wof:name":"Groenenspriet",
    "wof:placetype":"locality"
},
  "geometry": {"coordinates":[3.05,51.05],"type":"Point"}
}