{
  "type": "Feature",
  "properties": {
    "gn:admin1_code":"VLG",
    "gn:admin2_code":"VLI",
    "gn:admin3_code":"73.0",
    "gn:admin4_code":"73001.0",
    "gn:asciiname":"Hulzen",
    "gn:country_code":"BE",
    "gn:dem":56,
    "gn:feature_class":"P",
    "gn:feature_code":"PPL",
    "gn:name":"Hulzen",
    "gn:population":0,
    "gn:timezone":"Europe/Brussels",
    "iso:country":"BE",
    "name:und_x_variant":[
        "Hulsen",
        "Hulzen"
    ],
    "wof:name":"Hulzen",
    "wof:placetype":"locality"
},
  "geometry": {"coordinates":[5.26031,50.87796],"type":"Point"}
}