{
  "type": "Feature",
  "properties": {
    "gn:admin1_code":"WAL",
    "gn:admin2_code":"WLX",
    "gn:admin3_code":"83.0",
    "gn:admin4_code":"83040.0",
    "gn:asciiname":"Au dela de l'Eau",
    "gn:country_code":"BE",
    "gn:dem":318,
    "gn:feature_class":"P",
    "gn:feature_code":"PPL",
    "gn:name":"Au del\u00e0 de l'Eau",
    "gn:population":0,
    "gn:timezone":"Europe/Brussels",
    "iso:country":"BE",
    "wof:name":"Au dela de l'Eau",
    "wof:placetype":"locality"
},
  "geometry": {"coordinates":[5.41667,50.16667],"type":"Point"}
}