{
  "type": "Feature",
  "properties": {
    "gn:admin1_code":"WAL",
    "gn:admin2_code":"WLG",
    "gn:admin3_code":"62.0",
    "gn:admin4_code":"62026.0",
    "gn:asciiname":"Halleux",
    "gn:country_code":"BE",
    "gn:dem":189,
    "gn:feature_class":"P",
    "gn:feature_code":"PPL",
    "gn:name":"Halleux",
    "gn:population":0,
    "gn:timezone":"Europe/Brussels",
    "iso:country":"BE",
    "wof:name":"Halleux",
    "wof:placetype":"locality"
},
  "geometry": {"coordinates":[5.62668,50.48111],"type":"Point"}
}