{
  "type": "Feature",
  "properties": {
    "gn:admin1_code":"WAL",
    "gn:admin2_code":"WLX",
    "gn:admin3_code":"85.0",
    "gn:admin4_code":"85011.0",
    "gn:asciiname":"Les Forges Roussel",
    "gn:country_code":"BE",
    "gn:dem":315,
    "gn:feature_class":"P",
    "gn:feature_code":"PPL",
    "gn:name":"Les Forges Roussel",
    "gn:population":0,
    "gn:timezone":"Europe/Brussels",
    "iso:country":"BE",
    "name:und_x_variant":[
        "Forges Roussel",
        "Les Forges Roussel"
    ],
    "wof:name":"Les Forges Roussel",
    "wof:placetype":"locality"
},
  "geometry": {"coordinates":[5.30225,49.72969000000001],"type":"Point"}
}