{
  "type": "Feature",
  "properties": {
    "gn:admin1_code":"WAL",
    "gn:admin2_code":"WBR",
    "gn:admin3_code":"25.0",
    "gn:admin4_code":"25068.0",
    "gn:asciiname":"Bruyeres",
    "gn:country_code":"BE",
    "gn:dem":117,
    "gn:feature_class":"P",
    "gn:feature_code":"PPL",
    "gn:name":"Bruy\u00e8res",
    "gn:population":0,
    "gn:timezone":"Europe/Brussels",
    "iso:country":"BE",
    "wof:name":"Bruyeres",
    "wof:placetype":"locality"
},
  "geometry": {"coordinates":[4.60207,50.65561],"type":"Point"}
}