{
  "type": "Feature",
  "properties": {
    "gn:admin1_code":"WAL",
    "gn:admin2_code":"WLG",
    "gn:admin3_code":"63.0",
    "gn:admin4_code":"63038.0",
    "gn:asciiname":"Haut Beaumal",
    "gn:country_code":"BE",
    "gn:dem":509,
    "gn:feature_class":"P",
    "gn:feature_code":"PPL",
    "gn:name":"Haut Beaumal",
    "gn:population":0,
    "gn:timezone":"Europe/Brussels",
    "iso:country":"BE",
    "wof:name":"Haut Beaumal",
    "wof:placetype":"locality"
},
  "geometry": {"coordinates":[6.01667,50.55],"type":"Point"}
}