{
  "type": "Feature",
  "properties": {
    "gn:admin1_code":"VLG",
    "gn:admin2_code":"VOV",
    "gn:admin3_code":"45.0",
    "gn:admin4_code":"45035.0",
    "gn:asciiname":"Akselwal",
    "gn:country_code":"BE",
    "gn:dem":14,
    "gn:feature_class":"P",
    "gn:feature_code":"PPL",
    "gn:name":"Akselwal",
    "gn:population":0,
    "gn:timezone":"Europe/Brussels",
    "iso:country":"BE",
    "name:und_x_variant":[
        "Axelwalle",
        "Akselwalle",
        "Akselwal"
    ],
    "wof:name":"Akselwal",
    "wof:placetype":"locality"
},
  "geometry": {"coordinates":[3.63682,50.89658],"type":"Point"}
}