{
  "type": "Feature",
  "properties": {
    "gn:admin1_code":"WAL",
    "gn:admin2_code":"WHT",
    "gn:asciiname":"Walsbergen",
    "gn:country_code":"BE",
    "gn:dem":42,
    "gn:feature_class":"P",
    "gn:feature_code":"PPL",
    "gn:name":"Walsbergen",
    "gn:population":0,
    "gn:timezone":"Europe/Brussels",
    "iso:country":"BE",
    "wof:name":"Walsbergen",
    "wof:placetype":"locality"
},
  "geometry": {"coordinates":[5.03333,50.81667],"type":"Point"}
}