{
  "type": "Feature",
  "properties": {
    "gn:admin1_code":"VLG",
    "gn:admin2_code":"VBR",
    "gn:admin3_code":"23.0",
    "gn:admin4_code":"23038.0",
    "gn:asciiname":"Laar",
    "gn:country_code":"BE",
    "gn:dem":23,
    "gn:feature_class":"P",
    "gn:feature_code":"PPL",
    "gn:name":"Laar",
    "gn:population":0,
    "gn:timezone":"Europe/Brussels",
    "iso:country":"BE",
    "wof:name":"Laar",
    "wof:placetype":"locality"
},
  "geometry": {"coordinates":[4.54894,50.92203],"type":"Point"}
}