{
  "type": "Feature",
  "properties": {
    "gn:admin1_code":"WAL",
    "gn:admin2_code":"WHT",
    "gn:admin3_code":"57.0",
    "gn:admin4_code":"57081.0",
    "gn:asciiname":"La Louviere",
    "gn:country_code":"BE",
    "gn:dem":51,
    "gn:feature_class":"P",
    "gn:feature_code":"PPL",
    "gn:name":"La Louvi\u00e8re",
    "gn:population":0,
    "gn:timezone":"Europe/Brussels",
    "iso:country":"BE",
    "wof:name":"La Louviere",
    "wof:placetype":"locality"
},
  "geometry": {"coordinates":[3.49209,50.58727],"type":"Point"}
}