{
  "type": "Feature",
  "properties": {
    "gn:admin1_code":"WAL",
    "gn:admin2_code":"WHT",
    "gn:admin3_code":"55.0",
    "gn:admin4_code":"55010.0",
    "gn:asciiname":"Les Six Censes",
    "gn:country_code":"BE",
    "gn:dem":60,
    "gn:feature_class":"P",
    "gn:feature_code":"PPL",
    "gn:name":"Les Six Censes",
    "gn:population":0,
    "gn:timezone":"Europe/Brussels",
    "iso:country":"BE",
    "name:und_x_variant":[
        "Les Six Cences",
        "Les Six Censes"
    ],
    "wof:name":"Les Six Censes",
    "wof:placetype":"locality"
},
  "geometry": {"coordinates":[4.06779,50.66178],"type":"Point"}
}