{
  "type": "Feature",
  "properties": {
    "gn:admin1_code":"VLG",
    "gn:admin2_code":"VOV",
    "gn:admin3_code":"46.0",
    "gn:admin4_code":"46025.0",
    "gn:asciiname":"De Wallen",
    "gn:country_code":"BE",
    "gn:dem":23,
    "gn:feature_class":"P",
    "gn:feature_code":"PPL",
    "gn:name":"De Wallen",
    "gn:population":0,
    "gn:timezone":"Europe/Brussels",
    "iso:country":"BE",
    "name:ara_x_preferred":[
        "\u062f\u064a \u0641\u0627\u0644\u064a\u0646"
    ],
    "name:cat_x_preferred":[
        "Districte roig d'Amsterdam"
    ],
    "name:ces_x_preferred":[
        "De Wallen"
    ],
    "name:dan_x_preferred":[
        "De Wallen"
    ],
    "name:deu_x_preferred":[
        "De Wallen"
    ],
    "name:epo_x_preferred":[
        "De Wallen"
    ],
    "name:eus_x_preferred":[
        "Amsterdamgo auzo gorria"
    ],
    "name:fas_x_preferred":[
        "\u062f\u0648 \u0648\u0627\u0644\u0646"
    ],
    "name:fin_x_preferred":[
        "De Wallen"
    ],
    "name:fra_x_preferred":[
        "De Wallen"
    ],
    "name:glg_x_preferred":[
        "Barrio vermello"
    ],
    "name:heb_x_preferred":[
        "\u05d3\u05d4 \u05d5\u05d0\u05dc\u05df"
    ],
    "name:ita_x_preferred":[
        "De Wallen"
    ],
    "name:kor_x_preferred":[
        "\ub354 \ubc1c\ub7f0"
    ],
    "name:lit_x_preferred":[
        "Amsterdamo raudon\u0173j\u0173 \u017eibint\u0173 kvartalas"
    ],
    "name:nld_x_preferred":[
        "De Wallen"
    ],
    "name:nor_x_preferred":[
        "De Wallen"
    ],
    "name:pol_x_preferred":[
        "De Wallen"
    ],
    "name:por_x_preferred":[
        "De Wallen"
    ],
    "name:rus_x_preferred":[
        "\u0414\u0435 \u0412\u0430\u043b\u043b\u0435\u043d"
    ],
    "name:slk_x_preferred":[
        "De Wallen"
    ],
    "name:srp_x_preferred":[
        "\u0414\u0435 \u0412\u0430\u043b\u0435\u043d"
    ],
    "name:swe_x_preferred":[
        "De Wallen"
    ],
    "name:ukr_x_preferred":[
        "\u0414\u0435 \u0412\u0430\u043b\u043b\u0435\u043d"
    ],
    "name:und_x_variant":[
        "Den Wallen",
        "De Wallen"
    ],
    "name:vie_x_preferred":[
        "De Wallen"
    ],
    "name:zho_x_preferred":[
        "\u5fb7\u74e6\u4f26"
    ],
    "wof:name":"De Wallen",
    "wof:placetype":"locality"
},
  "geometry": {"coordinates":[4.25,51.13333],"type":"Point"}
}