{
  "type": "Feature",
  "properties": {
    "gn:admin1_code":"VLG",
    "gn:admin2_code":"VOV",
    "gn:admin3_code":"46.0",
    "gn:admin4_code":"46025.0",
    "gn:asciiname":"De Wallen",
    "gn:country_code":"BE",
    "gn:dem":23,
    "gn:feature_class":"P",
    "gn:feature_code":"PPL",
    "gn:name":"De Wallen",
    "gn:population":0,
    "gn:timezone":"Europe/Brussels",
    "iso:country":"BE",
    "name:und_x_variant":[
        "Den Wallen",
        "De Wallen"
    ],
    "wof:name":"De Wallen",
    "wof:placetype":"locality"
},
  "geometry": {"coordinates":[4.25,51.13333],"type":"Point"}
}