{
  "type": "Feature",
  "properties": {
    "gn:admin1_code":"VLG",
    "gn:admin2_code":"VOV",
    "gn:admin3_code":"46.0",
    "gn:admin4_code":"46003.0",
    "gn:asciiname":"Zillebeke",
    "gn:country_code":"BE",
    "gn:dem":5,
    "gn:feature_class":"P",
    "gn:feature_code":"PPL",
    "gn:name":"Zillebeke",
    "gn:population":0,
    "gn:timezone":"Europe/Brussels",
    "iso:country":"BE",
    "name:bre_x_preferred":[
        "Zillebeke"
    ],
    "name:ceb_x_preferred":[
        "Zillebeke"
    ],
    "name:deu_x_preferred":[
        "Zillebeke"
    ],
    "name:fra_x_preferred":[
        "Zillebeke"
    ],
    "name:ita_x_preferred":[
        "Zillebeke"
    ],
    "name:nld_x_preferred":[
        "Zillebeke"
    ],
    "name:swe_x_preferred":[
        "Zillebeke"
    ],
    "name:vls_x_preferred":[
        "Zillebeke"
    ],
    "wof:name":"Zillebeke",
    "wof:placetype":"locality"
},
  "geometry": {"coordinates":[4.22772,51.22235],"type":"Point"}
}