{
  "type": "Feature",
  "properties": {
    "gn:admin1_code":"VLG",
    "gn:admin2_code":"VAN",
    "gn:admin3_code":"13.0",
    "gn:admin4_code":"13046.0",
    "gn:asciiname":"Heieinde",
    "gn:country_code":"BE",
    "gn:dem":22,
    "gn:feature_class":"P",
    "gn:feature_code":"PPL",
    "gn:name":"Heieinde",
    "gn:population":0,
    "gn:timezone":"Europe/Brussels",
    "iso:country":"BE",
    "name:und_x_variant":[
        "Heiende",
        "Heieinde"
    ],
    "wof:name":"Heieinde",
    "wof:placetype":"locality"
},
  "geometry": {"coordinates":[4.88008,51.30164],"type":"Point"}
}