{
  "type": "Feature",
  "properties": {
    "gn:admin1_code":"VLG",
    "gn:admin2_code":"VAN",
    "gn:admin3_code":"12.0",
    "gn:admin4_code":"12035.0",
    "gn:asciiname":"Duivelshoek",
    "gn:country_code":"BE",
    "gn:dem":6,
    "gn:feature_class":"P",
    "gn:feature_code":"PPL",
    "gn:name":"Duivelshoek",
    "gn:population":0,
    "gn:timezone":"Europe/Brussels",
    "iso:country":"BE",
    "wof:name":"Duivelshoek",
    "wof:placetype":"locality"
},
  "geometry": {"coordinates":[4.5651,51.04648],"type":"Point"}
}