{
  "type": "Feature",
  "properties": {
    "gn:admin1_code":"WAL",
    "gn:admin2_code":"WNA",
    "gn:admin3_code":"91.0",
    "gn:admin4_code":"91072.0",
    "gn:asciiname":"Finnevaux",
    "gn:country_code":"BE",
    "gn:dem":265,
    "gn:feature_class":"P",
    "gn:feature_code":"PPL",
    "gn:name":"Finnevaux",
    "gn:population":0,
    "gn:timezone":"Europe/Brussels",
    "iso:country":"BE",
    "wof:name":"Finnevaux",
    "wof:placetype":"locality"
},
  "geometry": {"coordinates":[4.94286,50.15768],"type":"Point"}
}