{
  "type": "Feature",
  "properties": {
    "gn:admin1_code":"WAL",
    "gn:admin2_code":"WBR",
    "gn:admin3_code":"25.0",
    "gn:admin4_code":"25048.0",
    "gn:asciiname":"Bruyere",
    "gn:country_code":"BE",
    "gn:dem":84,
    "gn:feature_class":"P",
    "gn:feature_code":"PPL",
    "gn:name":"Bruy\u00e8re",
    "gn:population":0,
    "gn:timezone":"Europe/Brussels",
    "iso:country":"BE",
    "name:und_x_variant":[
        "La Bruy\u00e8re",
        "Bruy\u00e8re"
    ],
    "wof:name":"Bruyere",
    "wof:placetype":"locality"
},
  "geometry": {"coordinates":[4.83948,50.6998],"type":"Point"}
}