{
  "type": "Feature",
  "properties": {
    "gn:country":"BE",
    "gn:fcode":"PPL",
    "gn:population":0,
    "iso:country":"BE",
    "name:ceb_x_preferred":[
        "Couillet"
    ],
    "name:deu_x_preferred":[
        "Couillet"
    ],
    "name:eng_x_preferred":[
        "Couillet"
    ],
    "name:fas_x_preferred":[
        "\u06a9\u0648\u0626\u06cc\u0647"
    ],
    "name:fra_x_preferred":[
        "Couillet"
    ],
    "name:gle_x_preferred":[
        "Couillet"
    ],
    "name:hun_x_preferred":[
        "Couillet"
    ],
    "name:ita_x_preferred":[
        "Couillet"
    ],
    "name:nld_x_preferred":[
        "Couillet"
    ],
    "name:pcd_x_preferred":[
        "Couyet"
    ],
    "name:spa_x_preferred":[
        "Couillet"
    ],
    "name:swe_x_preferred":[
        "Couillet"
    ],
    "name:und_x_variant":[
        "Charleroi (Couillet)"
    ],
    "name:wln_x_preferred":[
        "Couyet"
    ],
    "qs_pg:aaroncc":"BE",
    "qs_pg:gn_country":"BE",
    "qs_pg:gn_fcode":"PPL",
    "qs_pg:gn_pop":0,
    "qs_pg:name":"Couillet",
    "qs_pg:name_adm0":"Belgique",
    "qs_pg:name_adm1":"Hainaut",
    "qs_pg:photos_9k":1,
    "qs_pg:photos_9r":1,
    "qs_pg:photos_all":1,
    "qs_pg:photos_sr":0,
    "qs_pg:pop_sr":0,
    "qs_pg:qs_pg_placetype":"locality",
    "qs_pg:qs_pg_placetype_gp":"Town",
    "qs_pg:woe_adm0":23424757,
    "woe:adm0_id":23424757,
    "woe:name_adm0":"Belgique",
    "woe:name_adm1":"Hainaut",
    "woe:placetype":"Town",
    "wof:name":"Couillet",
    "wof:placetype":"locality"
},
  "geometry": {"coordinates":[4.45908,50.39139],"type":"Point"}
}