{
  "type": "Feature",
  "properties": {
    "gn:admin1_code":"WAL",
    "gn:admin2_code":"WLG",
    "gn:admin3_code":"61.0",
    "gn:admin4_code":"61012.0",
    "gn:asciiname":"Hoyoux",
    "gn:country_code":"BE",
    "gn:dem":235,
    "gn:feature_class":"P",
    "gn:feature_code":"PPL",
    "gn:name":"Hoyoux",
    "gn:population":0,
    "gn:timezone":"Europe/Brussels",
    "iso:country":"BE",
    "name:cat_x_preferred":[
        "Hoyoux"
    ],
    "name:ceb_x_preferred":[
        "Hoyoux"
    ],
    "name:fra_x_preferred":[
        "Hoyoux"
    ],
    "name:nld_x_preferred":[
        "Hoyoux"
    ],
    "name:swe_x_preferred":[
        "Hoyoux"
    ],
    "name:wln_x_preferred":[
        "Hoyou"
    ],
    "wof:name":"Hoyoux",
    "wof:placetype":"locality"
},
  "geometry": {"coordinates":[5.29335,50.39559000000001],"type":"Point"}
}