{
  "type": "Feature",
  "properties": {
    "gn:admin1_code":"WAL",
    "gn:admin2_code":"WNA",
    "gn:admin3_code":"92.0",
    "gn:admin4_code":"92006.0",
    "gn:asciiname":"Miere",
    "gn:country_code":"BE",
    "gn:dem":236,
    "gn:feature_class":"P",
    "gn:feature_code":"PPL",
    "gn:name":"Mi\u00e8re",
    "gn:population":0,
    "gn:timezone":"Europe/Brussels",
    "iso:country":"BE",
    "wof:name":"Miere",
    "wof:placetype":"locality"
},
  "geometry": {"coordinates":[5.00185,50.36501],"type":"Point"}
}