{
  "type": "Feature",
  "properties": {
    "gn:admin1_code":"WAL",
    "gn:admin2_code":"WLG",
    "gn:admin3_code":"62.0",
    "gn:admin4_code":"62009.0",
    "gn:asciiname":"Sedoz",
    "gn:country_code":"BE",
    "gn:dem":158,
    "gn:feature_class":"P",
    "gn:feature_code":"PPL",
    "gn:name":"Sedoz",
    "gn:population":0,
    "gn:timezone":"Europe/Brussels",
    "iso:country":"BE",
    "wof:name":"Sedoz",
    "wof:placetype":"locality"
},
  "geometry": {"coordinates":[5.74187,50.46564],"type":"Point"}
}