{
  "type": "Feature",
  "properties": {
    "gn:country":"BE",
    "gn:fcode":"PPL",
    "gn:population":0,
    "iso:country":"BE",
    "name:cat_x_preferred":[
        "Dochamps"
    ],
    "name:eng_x_preferred":[
        "Dochamps"
    ],
    "name:fra_x_preferred":[
        "Dochamps"
    ],
    "name:gle_x_preferred":[
        "Dochamps"
    ],
    "name:nld_x_preferred":[
        "Dochamps"
    ],
    "name:wln_x_preferred":[
        "D\u00f4tchamp"
    ],
    "qs_pg:aaroncc":"BE",
    "qs_pg:gn_country":"BE",
    "qs_pg:gn_fcode":"PPL",
    "qs_pg:gn_pop":0,
    "qs_pg:name":"Dochamps",
    "qs_pg:name_adm0":"Belgique",
    "qs_pg:name_adm1":"Luxembourg",
    "qs_pg:photos":115,
    "qs_pg:photos_1k":23,
    "qs_pg:photos_9k":1,
    "qs_pg:photos_9r":3,
    "qs_pg:photos_all":115,
    "qs_pg:photos_sr":3,
    "qs_pg:pop_sr":0,
    "qs_pg:qs_pg_placetype":"locality",
    "qs_pg:qs_pg_placetype_gp":"Town",
    "qs_pg:woe_adm0":23424757,
    "woe:adm0_id":23424757,
    "woe:name_adm0":"Belgique",
    "woe:name_adm1":"Luxembourg",
    "woe:placetype":"Town",
    "wof:name":"Dochamps",
    "wof:placetype":"locality"
},
  "geometry": {"coordinates":[5.53333,50.23333],"type":"Point"}
}