{
  "type": "Feature",
  "properties": {
    "gn:admin1_code":"VLG",
    "gn:admin2_code":"VAN",
    "gn:admin3_code":"13.0",
    "gn:admin4_code":"13017.0",
    "gn:asciiname":"Groot Kluis",
    "gn:country_code":"BE",
    "gn:dem":20,
    "gn:feature_class":"P",
    "gn:feature_code":"PPL",
    "gn:name":"Groot Kluis",
    "gn:population":0,
    "gn:timezone":"Europe/Brussels",
    "iso:country":"BE",
    "name:und_x_variant":[
        "Cluys",
        "Groote-Cluis",
        "Groote-Kluis",
        "Grote Kluis",
        "Groot Kluis"
    ],
    "wof:name":"Groot Kluis",
    "wof:placetype":"locality"
},
  "geometry": {"coordinates":[4.98947,51.25995],"type":"Point"}
}