{
  "type": "Feature",
  "properties": {
    "gn:admin1_code":"WAL",
    "gn:admin2_code":"WBR",
    "gn:admin3_code":"25.0",
    "gn:admin4_code":"25124.0",
    "gn:asciiname":"Nil Pierreux",
    "gn:country_code":"BE",
    "gn:dem":131,
    "gn:feature_class":"P",
    "gn:feature_code":"PPL",
    "gn:name":"Nil Pierreux",
    "gn:population":0,
    "gn:timezone":"Europe/Brussels",
    "iso:country":"BE",
    "wof:name":"Nil Pierreux",
    "wof:placetype":"locality"
},
  "geometry": {"coordinates":[4.65065,50.63166],"type":"Point"}
}