{
  "type": "Feature",
  "properties": {
    "gn:admin1_code":"VLG",
    "gn:admin2_code":"VLI",
    "gn:admin3_code":"72.0",
    "gn:admin4_code":"72025.0",
    "gn:asciiname":"Broeseind",
    "gn:country_code":"BE",
    "gn:dem":36,
    "gn:feature_class":"P",
    "gn:feature_code":"PPL",
    "gn:name":"Broeseind",
    "gn:population":0,
    "gn:timezone":"Europe/Brussels",
    "iso:country":"BE",
    "wof:name":"Broeseind",
    "wof:placetype":"locality"
},
  "geometry": {"coordinates":[5.42804,51.23878],"type":"Point"}
}