{
  "type": "Feature",
  "properties": {
    "gn:admin1_code":"WAL",
    "gn:admin2_code":"WLX",
    "gn:admin3_code":"85.0",
    "gn:admin4_code":"85045.0",
    "gn:asciiname":"Saint-Mard",
    "gn:country_code":"BE",
    "gn:dem":206,
    "gn:feature_class":"P",
    "gn:feature_code":"PPL",
    "gn:name":"Saint-Mard",
    "gn:population":0,
    "gn:timezone":"Europe/Brussels",
    "iso:country":"BE",
    "wof:name":"Saint-Mard",
    "wof:placetype":"locality"
},
  "geometry": {"coordinates":[5.53427,49.55403],"type":"Point"}
}