{
  "type": "Feature",
  "properties": {
    "gn:admin1_code":"WAL",
    "gn:admin2_code":"WLX",
    "gn:admin3_code":"85.0",
    "gn:admin4_code":"85045.0",
    "gn:asciiname":"Saint-Mard",
    "gn:country_code":"BE",
    "gn:dem":206,
    "gn:feature_class":"P",
    "gn:feature_code":"PPL",
    "gn:name":"Saint-Mard",
    "gn:population":0,
    "gn:timezone":"Europe/Brussels",
    "iso:country":"BE",
    "name:ceb_x_preferred":[
        "Saint-Mard"
    ],
    "name:deu_x_preferred":[
        "Saint-Mard"
    ],
    "name:epo_x_preferred":[
        "Saint-Mard"
    ],
    "name:fra_x_preferred":[
        "Saint-Mard"
    ],
    "name:ita_x_preferred":[
        "Saint-Mard"
    ],
    "name:ltz_x_preferred":[
        "Saint-Mard"
    ],
    "name:nds_x_preferred":[
        "Saint-Mard"
    ],
    "name:nld_x_preferred":[
        "Saint-Mard"
    ],
    "name:oci_x_preferred":[
        "Saint-Mard"
    ],
    "name:pms_x_preferred":[
        "Saint-Mard"
    ],
    "name:pol_x_preferred":[
        "Saint-Mard"
    ],
    "name:por_x_preferred":[
        "Saint-Mard"
    ],
    "name:rus_x_preferred":[
        "\u0421\u0435\u043d-\u041c\u0430\u0440"
    ],
    "name:slk_x_preferred":[
        "Saint-Mard"
    ],
    "name:spa_x_preferred":[
        "Saint-Mard"
    ],
    "name:swe_x_preferred":[
        "Saint-Mard"
    ],
    "name:ukr_x_preferred":[
        "\u0421\u0435\u043d-\u041c\u0430\u0440"
    ],
    "wof:name":"Saint-Mard",
    "wof:placetype":"locality"
},
  "geometry": {"coordinates":[5.53427,49.55403],"type":"Point"}
}