{
  "type": "Feature",
  "properties": {
    "gn:admin1_code":"VLG",
    "gn:admin2_code":"VWV",
    "gn:admin3_code":"37.0",
    "gn:admin4_code":"37007.0",
    "gn:asciiname":"Het Veld",
    "gn:country_code":"BE",
    "gn:dem":23,
    "gn:feature_class":"P",
    "gn:feature_code":"PPL",
    "gn:name":"Het Veld",
    "gn:population":0,
    "gn:timezone":"Europe/Brussels",
    "iso:country":"BE",
    "wof:name":"Het Veld",
    "wof:placetype":"locality"
},
  "geometry": {"coordinates":[3.25,50.95],"type":"Point"}
}