{
  "type": "Feature",
  "properties": {
    "gn:admin1_code":"WAL",
    "gn:admin2_code":"WLG",
    "gn:admin3_code":"61.0",
    "gn:admin4_code":"61072.0",
    "gn:asciiname":"Mont Falize",
    "gn:country_code":"BE",
    "gn:dem":69,
    "gn:feature_class":"P",
    "gn:feature_code":"PPL",
    "gn:name":"Mont Falize",
    "gn:population":0,
    "gn:timezone":"Europe/Brussels",
    "iso:country":"BE",
    "wof:name":"Mont Falize",
    "wof:placetype":"locality"
},
  "geometry": {"coordinates":[5.21667,50.53333],"type":"Point"}
}