{
  "type": "Feature",
  "properties": {
    "gn:admin1_code":"VLG",
    "gn:admin2_code":"VOV",
    "gn:admin3_code":"44.0",
    "gn:admin4_code":"44011.0",
    "gn:asciiname":"Duine",
    "gn:country_code":"BE",
    "gn:dem":9,
    "gn:feature_class":"P",
    "gn:feature_code":"PPL",
    "gn:name":"Duine",
    "gn:population":0,
    "gn:timezone":"Europe/Brussels",
    "iso:country":"BE",
    "name:und_x_variant":[
        "Den Duine",
        "Duine"
    ],
    "wof:name":"Duine",
    "wof:placetype":"locality"
},
  "geometry": {"coordinates":[3.45,51.01667],"type":"Point"}
}