{
  "type": "Feature",
  "properties": {
    "gn:admin1_code":"VLG",
    "gn:admin2_code":"VOV",
    "gn:admin3_code":"41.0",
    "gn:admin4_code":"41027.0",
    "gn:asciiname":"Helle",
    "gn:country_code":"BE",
    "gn:dem":59,
    "gn:feature_class":"P",
    "gn:feature_code":"PPL",
    "gn:name":"Helle",
    "gn:population":0,
    "gn:timezone":"Europe/Brussels",
    "iso:country":"BE",
    "name:bre_x_preferred":[
        "Helle"
    ],
    "name:ceb_x_preferred":[
        "Helle"
    ],
    "name:dan_x_preferred":[
        "Helle"
    ],
    "name:deu_x_preferred":[
        "Helle"
    ],
    "name:ell_x_preferred":[
        "\u0388\u03bb\u03bb\u03b7"
    ],
    "name:fin_x_preferred":[
        "Helle"
    ],
    "name:ita_x_preferred":[
        "Helle"
    ],
    "name:lim_x_preferred":[
        "Helle"
    ],
    "name:nld_x_preferred":[
        "Helle"
    ],
    "name:nor_x_preferred":[
        "Helle"
    ],
    "name:rus_x_preferred":[
        "\u0425\u0435\u043b\u043b\u0435"
    ],
    "name:swe_x_preferred":[
        "Helle"
    ],
    "wof:name":"Helle",
    "wof:placetype":"locality"
},
  "geometry": {"coordinates":[3.93333,50.86667],"type":"Point"}
}