{
  "type": "Feature",
  "properties": {
    "gn:admin1_code":"WAL",
    "gn:admin2_code":"WNA",
    "gn:admin3_code":"92.0",
    "gn:admin4_code":"92035.0",
    "gn:asciiname":"Francqnee",
    "gn:country_code":"BE",
    "gn:dem":138,
    "gn:feature_class":"P",
    "gn:feature_code":"PPL",
    "gn:name":"Francqn\u00e9e",
    "gn:population":0,
    "gn:timezone":"Europe/Brussels",
    "iso:country":"BE",
    "name:und_x_variant":[
        "Franquen\u00e9e",
        "Francqn\u00e9e"
    ],
    "wof:name":"Francqnee",
    "wof:placetype":"locality"
},
  "geometry": {"coordinates":[4.94251,50.62101],"type":"Point"}
}