{
  "type": "Feature",
  "properties": {
    "gn:admin1_code":"WAL",
    "gn:admin2_code":"WNA",
    "gn:admin3_code":"91.0",
    "gn:admin4_code":"91120.0",
    "gn:asciiname":"Haie Curie",
    "gn:country_code":"BE",
    "gn:dem":246,
    "gn:feature_class":"P",
    "gn:feature_code":"PPL",
    "gn:name":"Haie Curie",
    "gn:population":0,
    "gn:timezone":"Europe/Brussels",
    "iso:country":"BE",
    "wof:name":"Haie Curie",
    "wof:placetype":"locality"
},
  "geometry": {"coordinates":[5.30672,50.2673],"type":"Point"}
}