{
  "type": "Feature",
  "properties": {
    "gn:admin1_code":"VLG",
    "gn:admin2_code":"VBR",
    "gn:admin3_code":"23.0",
    "gn:admin4_code":"23105.0",
    "gn:asciiname":"Mazits",
    "gn:country_code":"BE",
    "gn:dem":38,
    "gn:feature_class":"P",
    "gn:feature_code":"PPL",
    "gn:name":"Mazits",
    "gn:population":0,
    "gn:timezone":"Europe/Brussels",
    "iso:country":"BE",
    "wof:name":"Mazits",
    "wof:placetype":"locality"
},
  "geometry": {"coordinates":[4.09588,50.92154],"type":"Point"}
}