{
  "type": "Feature",
  "properties": {
    "gn:admin1_code":"VLG",
    "gn:admin2_code":"VAN",
    "gn:admin3_code":"13.0",
    "gn:admin4_code":"13019.0",
    "gn:asciiname":"Heerle",
    "gn:country_code":"BE",
    "gn:dem":12,
    "gn:feature_class":"P",
    "gn:feature_code":"PPL",
    "gn:name":"Heerle",
    "gn:population":0,
    "gn:timezone":"Europe/Brussels",
    "iso:country":"BE",
    "name:ceb_x_preferred":[
        "Heerle"
    ],
    "name:fra_x_preferred":[
        "Heerle"
    ],
    "name:nld_x_preferred":[
        "Heerle"
    ],
    "name:spa_x_preferred":[
        "Heerle"
    ],
    "wof:name":"Heerle",
    "wof:placetype":"locality"
},
  "geometry": {"coordinates":[4.86594,51.22079],"type":"Point"}
}