{
  "type": "Feature",
  "properties": {
    "gn:admin1_code":"VLG",
    "gn:admin2_code":"VOV",
    "gn:admin3_code":"45.0",
    "gn:admin4_code":"45035.0",
    "gn:asciiname":"Meerse",
    "gn:country_code":"BE",
    "gn:dem":11,
    "gn:feature_class":"P",
    "gn:feature_code":"PPL",
    "gn:name":"Meerse",
    "gn:population":0,
    "gn:timezone":"Europe/Brussels",
    "iso:country":"BE",
    "name:und_x_variant":[
        "Meersche",
        "Meerse"
    ],
    "wof:name":"Meerse",
    "wof:placetype":"locality"
},
  "geometry": {"coordinates":[3.54562,50.80812],"type":"Point"}
}