{
  "type": "Feature",
  "properties": {
    "gn:admin1_code":"VLG",
    "gn:admin2_code":"VLI",
    "gn:admin3_code":"73.0",
    "gn:admin4_code":"73006.0",
    "gn:asciiname":"Haag",
    "gn:country_code":"BE",
    "gn:dem":44,
    "gn:feature_class":"P",
    "gn:feature_code":"PPL",
    "gn:name":"Haag",
    "gn:population":0,
    "gn:timezone":"Europe/Brussels",
    "iso:country":"BE",
    "wof:name":"Haag",
    "wof:placetype":"locality"
},
  "geometry": {"coordinates":[5.52355,50.89708],"type":"Point"}
}