{
  "type": "Feature",
  "properties": {
    "gn:admin1_code":"WAL",
    "gn:admin2_code":"WLG",
    "gn:admin3_code":"61.0",
    "gn:admin4_code":"61012.0",
    "gn:asciiname":"Ochain",
    "gn:country_code":"BE",
    "gn:dem":262,
    "gn:feature_class":"P",
    "gn:feature_code":"PPL",
    "gn:name":"Ochain",
    "gn:population":0,
    "gn:timezone":"Europe/Brussels",
    "iso:country":"BE",
    "wof:name":"Ochain",
    "wof:placetype":"locality"
},
  "geometry": {"coordinates":[5.36314,50.43131],"type":"Point"}
}