{
  "type": "Feature",
  "properties": {
    "gn:admin1_code":"VLG",
    "gn:admin2_code":"VOV",
    "gn:admin3_code":"45.0",
    "gn:admin4_code":"45062.0",
    "gn:asciiname":"Stene",
    "gn:country_code":"BE",
    "gn:dem":55,
    "gn:feature_class":"P",
    "gn:feature_code":"PPL",
    "gn:name":"Stene",
    "gn:population":0,
    "gn:timezone":"Europe/Brussels",
    "iso:country":"BE",
    "name:nor_x_preferred":[
        "Stene"
    ],
    "name:und_x_variant":[
        "Steene"
    ],
    "wof:name":"Stene",
    "wof:placetype":"locality"
},
  "geometry": {"coordinates":[3.68333,50.81667],"type":"Point"}
}