{
  "type": "Feature",
  "properties": {
    "gn:admin1_code":"WAL",
    "gn:admin2_code":"WNA",
    "gn:admin3_code":"91.0",
    "gn:admin4_code":"91034.0",
    "gn:asciiname":"Fin Fourneau",
    "gn:country_code":"BE",
    "gn:dem":260,
    "gn:feature_class":"P",
    "gn:feature_code":"PPL",
    "gn:name":"Fin Fourneau",
    "gn:population":0,
    "gn:timezone":"Europe/Brussels",
    "iso:country":"BE",
    "wof:name":"Fin Fourneau",
    "wof:placetype":"locality"
},
  "geometry": {"coordinates":[4.95,50.23333],"type":"Point"}
}