{
  "type": "Feature",
  "properties": {
    "gn:admin1_code":"VLG",
    "gn:admin2_code":"VOV",
    "gn:admin3_code":"41.0",
    "gn:admin4_code":"41027.0",
    "gn:asciiname":"Terhagen",
    "gn:country_code":"BE",
    "gn:dem":51,
    "gn:feature_class":"P",
    "gn:feature_code":"PPL",
    "gn:name":"Terhagen",
    "gn:population":0,
    "gn:timezone":"Europe/Brussels",
    "iso:country":"BE",
    "wof:name":"Terhagen",
    "wof:placetype":"locality"
},
  "geometry": {"coordinates":[3.89899,50.89915],"type":"Point"}
}