{
  "type": "Feature",
  "properties": {
    "gn:admin1_code":"VLG",
    "gn:admin2_code":"VBR",
    "gn:admin3_code":"23.0",
    "gn:admin4_code":"23032.0",
    "gn:asciiname":"Druimeren",
    "gn:country_code":"BE",
    "gn:dem":45,
    "gn:feature_class":"P",
    "gn:feature_code":"PPL",
    "gn:name":"Druimeren",
    "gn:population":0,
    "gn:timezone":"Europe/Brussels",
    "iso:country":"BE",
    "name:und_x_variant":[
        "Druimieren",
        "Druimeeren",
        "Druimeren"
    ],
    "wof:name":"Druimeren",
    "wof:placetype":"locality"
},
  "geometry": {"coordinates":[4.06863,50.74371],"type":"Point"}
}