{
  "type": "Feature",
  "properties": {
    "gn:admin1_code":"WAL",
    "gn:admin2_code":"WHT",
    "gn:admin3_code":"57.0",
    "gn:admin4_code":"57094.0",
    "gn:asciiname":"Grand Marais",
    "gn:country_code":"BE",
    "gn:dem":57,
    "gn:feature_class":"P",
    "gn:feature_code":"PPL",
    "gn:name":"Grand Marais",
    "gn:population":0,
    "gn:timezone":"Europe/Brussels",
    "iso:country":"BE",
    "name:ceb_x_preferred":[
        "Grand Marais"
    ],
    "name:deu_x_preferred":[
        "Grand Marais"
    ],
    "name:fin_x_preferred":[
        "Grand Marais"
    ],
    "name:fra_x_preferred":[
        "Grand Marais"
    ],
    "name:swe_x_preferred":[
        "Grand Marais"
    ],
    "name:vol_x_preferred":[
        "Grand Marais"
    ],
    "wof:name":"Grand Marais",
    "wof:placetype":"locality"
},
  "geometry": {"coordinates":[3.66667,50.63333],"type":"Point"}
}