{
  "type": "Feature",
  "properties": {
    "gn:gn_country":"BE",
    "gn:gn_fcode":"PPL",
    "gn:gn_pop":0,
    "iso:country":"BE",
    "name:eng_x_preferred":[
        "Ragnies"
    ],
    "name:fra_x_preferred":[
        "Ragnies"
    ],
    "name:hun_x_preferred":[
        "Ragnies"
    ],
    "name:nld_x_preferred":[
        "Ragnies"
    ],
    "name:unk_x_variant":[
        "Thuin (Ragnies)"
    ],
    "name:wln_x_preferred":[
        "Ragniye"
    ],
    "qs_pg:aaroncc":"BE",
    "qs_pg:gn_country":"BE",
    "qs_pg:gn_fcode":"PPL",
    "qs_pg:gn_pop":0,
    "qs_pg:name":"Ragnies",
    "qs_pg:name_adm0":"Belgique",
    "qs_pg:name_adm1":"Hainaut",
    "qs_pg:photos":81,
    "qs_pg:photos_1k":16,
    "qs_pg:photos_9k":1,
    "qs_pg:photos_9r":3,
    "qs_pg:photos_all":81,
    "qs_pg:photos_sr":3,
    "qs_pg:pop_sr":0,
    "qs_pg:qs_pg_placetype":"locality",
    "qs_pg:qs_pg_placetype_gp":"Town",
    "qs_pg:woe_adm0":23424757,
    "woe:adm0_id":23424757,
    "woe:name_adm0":"Belgique",
    "woe:name_adm1":"Hainaut",
    "woe:placetype":"Town",
    "wof:name":"Ragnies",
    "wof:placetype":"locality"
},
  "geometry": {"coordinates":[4.2845,50.30804],"type":"Point"}
}