{
  "type": "Feature",
  "properties": {
    "gn:admin1_code":"WAL",
    "gn:admin2_code":"WLX",
    "gn:admin3_code":"83.0",
    "gn:admin4_code":"83031.0",
    "gn:asciiname":"Taillet",
    "gn:country_code":"BE",
    "gn:dem":358,
    "gn:feature_class":"P",
    "gn:feature_code":"PPL",
    "gn:name":"Taillet",
    "gn:population":0,
    "gn:timezone":"Europe/Brussels",
    "iso:country":"BE",
    "name:arg_x_preferred":[
        "Tellet"
    ],
    "name:cat_x_preferred":[
        "Tellet"
    ],
    "name:ceb_x_preferred":[
        "Taillet"
    ],
    "name:dan_x_preferred":[
        "Taillet"
    ],
    "name:deu_x_preferred":[
        "Taillet"
    ],
    "name:eus_x_preferred":[
        "Taillet"
    ],
    "name:fas_x_preferred":[
        "\u062a\u0627\u06cc\u0647"
    ],
    "name:fra_x_preferred":[
        "Taillet"
    ],
    "name:hun_x_preferred":[
        "Taillet"
    ],
    "name:ita_x_preferred":[
        "Taillet"
    ],
    "name:kaz_x_preferred":[
        "\u0422\u0430\u0435"
    ],
    "name:lat_x_preferred":[
        "Taillet"
    ],
    "name:lmo_x_preferred":[
        "Taillet"
    ],
    "name:msa_x_preferred":[
        "Taillet"
    ],
    "name:nld_x_preferred":[
        "Taillet"
    ],
    "name:oci_x_preferred":[
        "Tellet"
    ],
    "name:pol_x_preferred":[
        "Taillet"
    ],
    "name:ron_x_preferred":[
        "Taillet"
    ],
    "name:slk_x_preferred":[
        "Taillet"
    ],
    "name:spa_x_preferred":[
        "Taillet"
    ],
    "name:swe_x_preferred":[
        "Taillet"
    ],
    "name:ukr_x_preferred":[
        "\u0422\u0430\u0454"
    ],
    "name:urd_x_preferred":[
        "\u062a\u0627\u0626\u06d2"
    ],
    "name:vie_x_preferred":[
        "Taillet"
    ],
    "name:vol_x_preferred":[
        "Taillet"
    ],
    "name:war_x_preferred":[
        "Taillet"
    ],
    "name:zho_x_preferred":[
        "\u5854\u8036"
    ],
    "wof:name":"Taillet",
    "wof:placetype":"locality"
},
  "geometry": {"coordinates":[5.55,50.16667],"type":"Point"}
}