{
  "type": "Feature",
  "properties": {
    "gn:admin1_code":"VLG",
    "gn:admin2_code":"VAN",
    "gn:admin3_code":"12.0",
    "gn:admin4_code":"12034.0",
    "gn:asciiname":"Wipheide",
    "gn:country_code":"BE",
    "gn:dem":5,
    "gn:feature_class":"P",
    "gn:feature_code":"PPL",
    "gn:name":"Wipheide",
    "gn:population":0,
    "gn:timezone":"Europe/Brussels",
    "iso:country":"BE",
    "name:und_x_variant":[
        "Wipheyde",
        "Wipheide"
    ],
    "wof:name":"Wipheide",
    "wof:placetype":"locality"
},
  "geometry": {"coordinates":[4.25518,51.04813],"type":"Point"}
}