{
  "type": "Feature",
  "properties": {
    "gn:admin1_code":"WAL",
    "gn:admin2_code":"WBR",
    "gn:admin3_code":"25.0",
    "gn:admin4_code":"25107.0",
    "gn:asciiname":"Marbisoux",
    "gn:country_code":"BE",
    "gn:dem":140,
    "gn:feature_class":"P",
    "gn:feature_code":"PPL",
    "gn:name":"Marbisoux",
    "gn:population":0,
    "gn:timezone":"Europe/Brussels",
    "iso:country":"BE",
    "wof:name":"Marbisoux",
    "wof:placetype":"locality"
},
  "geometry": {"coordinates":[4.55443,50.55025],"type":"Point"}
}