{
  "type": "Feature",
  "properties": {
    "gn:admin1_code":"VLG",
    "gn:admin2_code":"VWV",
    "gn:admin3_code":"31.0",
    "gn:admin4_code":"31033.0",
    "gn:asciiname":"Hoge",
    "gn:country_code":"BE",
    "gn:dem":37,
    "gn:feature_class":"P",
    "gn:feature_code":"PPL",
    "gn:name":"Hoge",
    "gn:population":0,
    "gn:timezone":"Europe/Brussels",
    "iso:country":"BE",
    "name:ceb_x_preferred":[
        "Hoge"
    ],
    "name:deu_x_preferred":[
        "Hoge"
    ],
    "name:und_x_variant":[
        "Hooghe"
    ],
    "wof:name":"Hoge",
    "wof:placetype":"locality"
},
  "geometry": {"coordinates":[3.08815,51.0771],"type":"Point"}
}