{
  "type": "Feature",
  "properties": {
    "gn:admin1_code":"VLG",
    "gn:admin2_code":"VBR",
    "gn:admin3_code":"24.0",
    "gn:admin4_code":"24011.0",
    "gn:asciiname":"Culo",
    "gn:country_code":"BE",
    "gn:dem":79,
    "gn:feature_class":"P",
    "gn:feature_code":"PPL",
    "gn:name":"Culo",
    "gn:population":0,
    "gn:timezone":"Europe/Brussels",
    "iso:country":"BE",
    "name:ceb_x_preferred":[
        "Culo"
    ],
    "name:fas_x_preferred":[
        "\u06a9\u0648\u0644\u0648"
    ],
    "name:spa_x_preferred":[
        "Culo"
    ],
    "name:swe_x_preferred":[
        "Culo"
    ],
    "name:und_x_variant":[
        "Culot"
    ],
    "wof:name":"Culo",
    "wof:placetype":"locality"
},
  "geometry": {"coordinates":[4.78575,50.80528],"type":"Point"}
}