{
  "type": "Feature",
  "properties": {
    "gn:country":"BE",
    "gn:fcode":"PPL",
    "gn:population":0,
    "iso:country":"BE",
    "name:eng_x_preferred":[
        "Ollignies"
    ],
    "name:fra_x_preferred":[
        "Ollignies"
    ],
    "name:gle_x_preferred":[
        "Ollignies"
    ],
    "name:hun_x_preferred":[
        "Ollignies"
    ],
    "name:ita_x_preferred":[
        "Ollignies"
    ],
    "name:nld_x_preferred":[
        "Woelingen"
    ],
    "name:pcd_x_preferred":[
        "Ollignies"
    ],
    "qs_pg:aaroncc":"BE",
    "qs_pg:gn_country":"BE",
    "qs_pg:gn_fcode":"PPL",
    "qs_pg:gn_pop":0,
    "qs_pg:name":"Ollignies",
    "qs_pg:name_adm0":"Belgique",
    "qs_pg:name_adm1":"Hainaut",
    "qs_pg:photos":50,
    "qs_pg:photos_1k":10,
    "qs_pg:photos_9k":1,
    "qs_pg:photos_9r":2,
    "qs_pg:photos_all":50,
    "qs_pg:photos_sr":2,
    "qs_pg:pop_sr":0,
    "qs_pg:qs_pg_placetype":"locality",
    "qs_pg:qs_pg_placetype_gp":"Town",
    "qs_pg:woe_adm0":23424757,
    "woe:adm0_id":23424757,
    "woe:name_adm0":"Belgique",
    "woe:name_adm1":"Hainaut",
    "woe:placetype":"Town",
    "wof:name":"Ollignies",
    "wof:placetype":"locality"
},
  "geometry": {"coordinates":[3.86229,50.68794],"type":"Point"}
}