{
  "type": "Feature",
  "properties": {
    "gn:country":"BE",
    "gn:fcode":"PPL",
    "gn:population":0,
    "iso:country":"BE",
    "name:bul_x_preferred":[
        "\u041c\u0435\u043b\u0434\u0435\u043d"
    ],
    "name:ceb_x_preferred":[
        "Melden"
    ],
    "name:eng_x_preferred":[
        "Melden"
    ],
    "name:fra_x_preferred":[
        "Melden"
    ],
    "name:hun_x_preferred":[
        "Melden"
    ],
    "name:nld_x_preferred":[
        "Melden"
    ],
    "name:swe_x_preferred":[
        "Melden"
    ],
    "qs_pg:aaroncc":"BE",
    "qs_pg:gn_country":"BE",
    "qs_pg:gn_fcode":"PPL",
    "qs_pg:gn_pop":0,
    "qs_pg:name":"Melden",
    "qs_pg:name_adm0":"Belgique",
    "qs_pg:name_adm1":"Oost-Vlaanderen",
    "qs_pg:photos":72,
    "qs_pg:photos_1k":15,
    "qs_pg:photos_9k":1,
    "qs_pg:photos_9r":2,
    "qs_pg:photos_all":72,
    "qs_pg:photos_sr":2,
    "qs_pg:pop_sr":0,
    "qs_pg:qs_pg_placetype":"locality",
    "qs_pg:qs_pg_placetype_gp":"Town",
    "qs_pg:woe_adm0":23424757,
    "woe:adm0_id":23424757,
    "woe:name_adm0":"Belgique",
    "woe:name_adm1":"Oost-Vlaanderen",
    "woe:placetype":"Town",
    "wof:name":"Melden",
    "wof:placetype":"locality"
},
  "geometry": {"coordinates":[3.56538,50.81449],"type":"Point"}
}