{
  "type": "Feature",
  "properties": {
    "gn:admin1_code":"WAL",
    "gn:admin2_code":"WHT",
    "gn:admin3_code":"56.0",
    "gn:admin4_code":"56088.0",
    "gn:asciiname":"Plagneau",
    "gn:country_code":"BE",
    "gn:dem":223,
    "gn:feature_class":"P",
    "gn:feature_code":"PPL",
    "gn:name":"Plagneau",
    "gn:population":0,
    "gn:timezone":"Europe/Brussels",
    "iso:country":"BE",
    "wof:name":"Plagneau",
    "wof:placetype":"locality"
},
  "geometry": {"coordinates":[4.27188,50.13753],"type":"Point"}
}