{
  "type": "Feature",
  "properties": {
    "gn:admin1_code":"WAL",
    "gn:admin2_code":"WNA",
    "gn:admin3_code":"91.0",
    "gn:admin4_code":"91034.0",
    "gn:asciiname":"Freche Try",
    "gn:country_code":"BE",
    "gn:dem":279,
    "gn:feature_class":"P",
    "gn:feature_code":"PPL",
    "gn:name":"Fr\u00eache Try",
    "gn:population":0,
    "gn:timezone":"Europe/Brussels",
    "iso:country":"BE",
    "wof:name":"Freche Try",
    "wof:placetype":"locality"
},
  "geometry": {"coordinates":[4.95814,50.29216],"type":"Point"}
}