{
  "type": "Feature",
  "properties": {
    "gn:admin1_code":"VLG",
    "gn:admin2_code":"VOV",
    "gn:admin3_code":"45.0",
    "gn:admin4_code":"45063.0",
    "gn:asciiname":"Eekhoutdries",
    "gn:country_code":"BE",
    "gn:dem":33,
    "gn:feature_class":"P",
    "gn:feature_code":"PPL",
    "gn:name":"Eekhoutdries",
    "gn:population":0,
    "gn:timezone":"Europe/Brussels",
    "iso:country":"BE",
    "wof:name":"Eekhoutdries",
    "wof:placetype":"locality"
},
  "geometry": {"coordinates":[3.85,50.81667],"type":"Point"}
}