{
  "type": "Feature",
  "properties": {
    "gn:admin1_code":"VLG",
    "gn:admin2_code":"VOV",
    "gn:admin3_code":"44.0",
    "gn:admin4_code":"44034.0",
    "gn:asciiname":"Kuistershoek",
    "gn:country_code":"BE",
    "gn:dem":4,
    "gn:feature_class":"P",
    "gn:feature_code":"PPL",
    "gn:name":"Kuistershoek",
    "gn:population":0,
    "gn:timezone":"Europe/Brussels",
    "iso:country":"BE",
    "name:und_x_variant":[
        "Kuisterhoek",
        "Kuystershoek",
        "Kuistershoek"
    ],
    "wof:name":"Kuistershoek",
    "wof:placetype":"locality"
},
  "geometry": {"coordinates":[3.85,51.13333],"type":"Point"}
}