{
  "type": "Feature",
  "properties": {
    "gn:admin1_code":"WAL",
    "gn:admin2_code":"WNA",
    "gn:admin3_code":"91.0",
    "gn:admin4_code":"91030.0",
    "gn:asciiname":"Jannee",
    "gn:country_code":"BE",
    "gn:dem":308,
    "gn:feature_class":"P",
    "gn:feature_code":"PPL",
    "gn:name":"Jann\u00e9e",
    "gn:population":0,
    "gn:timezone":"Europe/Brussels",
    "iso:country":"BE",
    "wof:name":"Jannee",
    "wof:placetype":"locality"
},
  "geometry": {"coordinates":[5.19921,50.28452],"type":"Point"}
}