{
  "type": "Feature",
  "properties": {
    "gn:admin1_code":"VLG",
    "gn:admin2_code":"VOV",
    "gn:admin3_code":"41.0",
    "gn:admin4_code":"41002.0",
    "gn:asciiname":"Molenhoek",
    "gn:country_code":"BE",
    "gn:dem":6,
    "gn:feature_class":"P",
    "gn:feature_code":"PPL",
    "gn:name":"Molenhoek",
    "gn:population":0,
    "gn:timezone":"Europe/Brussels",
    "iso:country":"BE",
    "name:afr_x_preferred":[
        "Molenhoek"
    ],
    "name:ceb_x_preferred":[
        "Molenhoek"
    ],
    "name:fas_x_preferred":[
        "\u0645\u0648\u0644\u0646\u200c\u0647\u0648\u06a9"
    ],
    "name:fra_x_preferred":[
        "Molenhoek"
    ],
    "name:lim_x_preferred":[
        "De Meulenhoek"
    ],
    "name:nld_x_preferred":[
        "Molenhoek"
    ],
    "name:pol_x_preferred":[
        "Molenhoek"
    ],
    "wof:name":"Molenhoek",
    "wof:placetype":"locality"
},
  "geometry": {"coordinates":[4.04443,50.98736],"type":"Point"}
}