{
  "type": "Feature",
  "properties": {
    "gn:admin1_code":"VLG",
    "gn:admin2_code":"VOV",
    "gn:admin3_code":"41.0",
    "gn:admin4_code":"41002.0",
    "gn:asciiname":"Molenhoek",
    "gn:country_code":"BE",
    "gn:dem":6,
    "gn:feature_class":"P",
    "gn:feature_code":"PPL",
    "gn:name":"Molenhoek",
    "gn:population":0,
    "gn:timezone":"Europe/Brussels",
    "iso:country":"BE",
    "wof:name":"Molenhoek",
    "wof:placetype":"locality"
},
  "geometry": {"coordinates":[4.04443,50.98736],"type":"Point"}
}