{
  "type": "Feature",
  "properties": {
    "gn:admin1_code":"WAL",
    "gn:admin2_code":"WLG",
    "gn:admin3_code":"63.0",
    "gn:admin4_code":"63012.0",
    "gn:asciiname":"Holzheim",
    "gn:country_code":"BE",
    "gn:dem":580,
    "gn:feature_class":"P",
    "gn:feature_code":"PPL",
    "gn:name":"Holzheim",
    "gn:population":0,
    "gn:timezone":"Europe/Brussels",
    "iso:country":"BE",
    "wof:name":"Holzheim",
    "wof:placetype":"locality"
},
  "geometry": {"coordinates":[6.29444,50.35056],"type":"Point"}
}