{
  "type": "Feature",
  "properties": {
    "gn:country":"BE",
    "gn:fcode":"PPL",
    "gn:population":0,
    "iso:country":"BE",
    "name:ara_x_preferred":[
        "\u0628\u064a\u064a\u0643"
    ],
    "name:ceb_x_preferred":[
        "Beek"
    ],
    "name:epo_x_preferred":[
        "Beek"
    ],
    "name:fas_x_preferred":[
        "\u0628\u06cc\u06a9"
    ],
    "name:lim_x_preferred":[
        "Baek"
    ],
    "name:nld_x_preferred":[
        "Beek"
    ],
    "name:rus_x_preferred":[
        "\u0411\u0435\u043a"
    ],
    "qs_pg:aaroncc":"BE",
    "qs_pg:gn_country":"BE",
    "qs_pg:gn_fcode":"PPL",
    "qs_pg:gn_pop":0,
    "qs_pg:name":"Beek",
    "qs_pg:name_adm0":"Belgique",
    "qs_pg:name_adm1":"Limburg",
    "qs_pg:photos":80,
    "qs_pg:photos_1k":16,
    "qs_pg:photos_9k":1,
    "qs_pg:photos_9r":3,
    "qs_pg:photos_all":80,
    "qs_pg:photos_sr":3,
    "qs_pg:pop_sr":0,
    "qs_pg:qs_pg_placetype":"locality",
    "qs_pg:qs_pg_placetype_gp":"Town",
    "qs_pg:woe_adm0":23424757,
    "woe:adm0_id":23424757,
    "woe:name_adm0":"Belgique",
    "woe:name_adm1":"Limburg",
    "woe:placetype":"Town",
    "wof:name":"Beek",
    "wof:placetype":"locality"
},
  "geometry": {"coordinates":[5.60302,51.15517],"type":"Point"}
}