{
  "type": "Feature",
  "properties": {
    "gn:admin1_code":"WAL",
    "gn:admin2_code":"WLX",
    "gn:admin3_code":"83.0",
    "gn:admin4_code":"83044.0",
    "gn:asciiname":"Rendeux Bas",
    "gn:country_code":"BE",
    "gn:dem":187,
    "gn:feature_class":"P",
    "gn:feature_code":"PPL",
    "gn:name":"Rendeux Bas",
    "gn:population":0,
    "gn:timezone":"Europe/Brussels",
    "iso:country":"BE",
    "wof:name":"Rendeux Bas",
    "wof:placetype":"locality"
},
  "geometry": {"coordinates":[5.49902,50.24244],"type":"Point"}
}