{
  "type": "Feature",
  "properties": {
    "gn:admin1_code":"WAL",
    "gn:admin2_code":"WHT",
    "gn:admin3_code":"54.0",
    "gn:admin4_code":"54010.0",
    "gn:asciiname":"Le Gheer",
    "gn:country_code":"BE",
    "gn:dem":18,
    "gn:elevation":"18.0",
    "gn:feature_class":"P",
    "gn:feature_code":"PPL",
    "gn:name":"Le Gheer",
    "gn:population":0,
    "gn:timezone":"Europe/Brussels",
    "iso:country":"BE",
    "wof:name":"Le Gheer",
    "wof:placetype":"locality"
},
  "geometry": {"coordinates":[2.91172,50.73276],"type":"Point"}
}