{
  "type": "Feature",
  "properties": {
    "gn:admin1_code":"WAL",
    "gn:admin2_code":"WLX",
    "gn:admin3_code":"82.0",
    "gn:admin4_code":"82038.0",
    "gn:asciiname":"Laval",
    "gn:country_code":"BE",
    "gn:dem":446,
    "gn:feature_class":"P",
    "gn:feature_code":"PPL",
    "gn:name":"Laval",
    "gn:population":0,
    "gn:timezone":"Europe/Brussels",
    "iso:country":"BE",
    "name:fra_x_preferred":[
        "Laval"
    ],
    "wof:name":"Laval",
    "wof:placetype":"locality"
},
  "geometry": {"coordinates":[5.58333,50.01667],"type":"Point"}
}