{
  "type": "Feature",
  "properties": {
    "gn:admin1_code":"VLG",
    "gn:admin2_code":"VLI",
    "gn:admin3_code":"72.0",
    "gn:admin4_code":"72018.0",
    "gn:asciiname":"Geistingen",
    "gn:country_code":"BE",
    "gn:dem":29,
    "gn:feature_class":"P",
    "gn:feature_code":"PPL",
    "gn:name":"Geistingen",
    "gn:population":0,
    "gn:timezone":"Europe/Brussels",
    "iso:country":"BE",
    "name:fra_x_preferred":[
        "Geistingen"
    ],
    "name:lim_x_preferred":[
        "Geistinge"
    ],
    "name:nld_x_preferred":[
        "Geistingen"
    ],
    "name:und_x_variant":[
        "Geystingen"
    ],
    "wof:name":"Geistingen",
    "wof:placetype":"locality"
},
  "geometry": {"coordinates":[5.8084,51.13316],"type":"Point"}
}