{
  "type": "Feature",
  "properties": {
    "gn:gn_country":"BE",
    "gn:gn_fcode":"PPL",
    "gn:gn_pop":0,
    "iso:country":"BE",
    "name:ceb_x_preferred":[
        "Werken"
    ],
    "name:eng_x_preferred":[
        "Werken"
    ],
    "name:fra_x_preferred":[
        "Werken"
    ],
    "name:hun_x_preferred":[
        "Werken"
    ],
    "name:nld_x_preferred":[
        "Werken"
    ],
    "name:por_x_preferred":[
        "Werken"
    ],
    "name:swe_x_preferred":[
        "Werken"
    ],
    "name:unk_x_variant":[
        "Wercken"
    ],
    "name:vls_x_preferred":[
        "Werkn"
    ],
    "qs_pg:aaroncc":"BE",
    "qs_pg:gn_country":"BE",
    "qs_pg:gn_fcode":"PPL",
    "qs_pg:gn_pop":0,
    "qs_pg:name":"Werken",
    "qs_pg:name_adm0":"Belgique",
    "qs_pg:name_adm1":"West-Vlaanderen",
    "qs_pg:photos":159,
    "qs_pg:photos_1k":32,
    "qs_pg:photos_9k":1,
    "qs_pg:photos_9r":4,
    "qs_pg:photos_all":159,
    "qs_pg:photos_sr":4,
    "qs_pg:pop_sr":0,
    "qs_pg:qs_pg_placetype":"locality",
    "qs_pg:qs_pg_placetype_gp":"Town",
    "qs_pg:woe_adm0":23424757,
    "woe:adm0_id":23424757,
    "woe:name_adm0":"Belgique",
    "woe:name_adm1":"West-Vlaanderen",
    "woe:placetype":"Town",
    "wof:name":"Werken",
    "wof:placetype":"locality"
},
  "geometry": {"coordinates":[2.96448,51.0294],"type":"Point"}
}