{
  "type": "Feature",
  "properties": {
    "gn:admin1_code":"WAL",
    "gn:admin2_code":"WLX",
    "gn:asciiname":"Le Beau Ban",
    "gn:country_code":"BE",
    "gn:dem":339,
    "gn:feature_class":"P",
    "gn:feature_code":"PPL",
    "gn:name":"Le Beau Ban",
    "gn:population":0,
    "gn:timezone":"Europe/Brussels",
    "iso:country":"BE",
    "wof:name":"Le Beau Ban",
    "wof:placetype":"locality"
},
  "geometry": {"coordinates":[5.28333,49.68333],"type":"Point"}
}