{
  "type": "Feature",
  "properties": {
    "gn:admin1_code":"VLG",
    "gn:admin2_code":"VAN",
    "gn:admin3_code":"13.0",
    "gn:admin4_code":"13025.0",
    "gn:asciiname":"Molsveld",
    "gn:country_code":"BE",
    "gn:dem":28,
    "gn:feature_class":"P",
    "gn:feature_code":"PPL",
    "gn:name":"Molsveld",
    "gn:population":0,
    "gn:timezone":"Europe/Brussels",
    "iso:country":"BE",
    "name:und_x_variant":[
        "Het Mollschveld",
        "Molsveld"
    ],
    "wof:name":"Molsveld",
    "wof:placetype":"locality"
},
  "geometry": {"coordinates":[5.10066,51.18575],"type":"Point"}
}