{
  "type": "Feature",
  "properties": {
    "gn:admin1_code":"WAL",
    "gn:admin2_code":"WHT",
    "gn:admin3_code":"56.0",
    "gn:admin4_code":"56088.0",
    "gn:asciiname":"Louviere",
    "gn:country_code":"BE",
    "gn:dem":237,
    "gn:feature_class":"P",
    "gn:feature_code":"PPL",
    "gn:name":"Louvi\u00e8re",
    "gn:population":0,
    "gn:timezone":"Europe/Brussels",
    "iso:country":"BE",
    "wof:name":"Louviere",
    "wof:placetype":"locality"
},
  "geometry": {"coordinates":[4.17938,50.16011],"type":"Point"}
}