{
  "type": "Feature",
  "properties": {
    "gn:admin1_code":"WAL",
    "gn:admin2_code":"WBR",
    "gn:admin3_code":"25.0",
    "gn:admin4_code":"25118.0",
    "gn:asciiname":"Opheylissem",
    "gn:country_code":"BE",
    "gn:dem":62,
    "gn:feature_class":"P",
    "gn:feature_code":"PPL",
    "gn:name":"Opheylissem",
    "gn:population":0,
    "gn:timezone":"Europe/Brussels",
    "iso:country":"BE",
    "name:bul_x_preferred":[
        "\u0410\u0431\u0430\u0442\u0441\u0442\u0432\u043e \u0415\u043b\u0438\u0441\u0435\u043c"
    ],
    "name:fra_x_preferred":[
        "Abbaye d'Heylissem"
    ],
    "name:und_x_variant":[
        "H\u00e9l\u00e9cine (Opheylissem)"
    ],
    "wof:name":"Opheylissem",
    "wof:placetype":"locality"
},
  "geometry": {"coordinates":[4.97689,50.7471],"type":"Point"}
}