{
  "type": "Feature",
  "properties": {
    "gn:admin1_code":"VLG",
    "gn:admin2_code":"VOV",
    "gn:admin3_code":"41.0",
    "gn:admin4_code":"41027.0",
    "gn:asciiname":"Winkel",
    "gn:country_code":"BE",
    "gn:dem":34,
    "gn:feature_class":"P",
    "gn:feature_code":"PPL",
    "gn:name":"Winkel",
    "gn:population":0,
    "gn:timezone":"Europe/Brussels",
    "iso:country":"BE",
    "name:und_x_variant":[
        "Winket",
        "Winkel"
    ],
    "wof:name":"Winkel",
    "wof:placetype":"locality"
},
  "geometry": {"coordinates":[3.91667,50.83333],"type":"Point"}
}