{
  "type": "Feature",
  "properties": {
    "gn:admin1_code":"WAL",
    "gn:admin2_code":"WLG",
    "gn:admin3_code":"63.0",
    "gn:admin4_code":"63004.0",
    "gn:asciiname":"Brandehaag",
    "gn:country_code":"BE",
    "gn:dem":564,
    "gn:feature_class":"P",
    "gn:feature_code":"PPL",
    "gn:name":"Brandehaag",
    "gn:population":0,
    "gn:timezone":"Europe/Brussels",
    "iso:country":"BE",
    "wof:name":"Brandehaag",
    "wof:placetype":"locality"
},
  "geometry": {"coordinates":[6.1288,50.55957],"type":"Point"}
}