{
  "type": "Feature",
  "properties": {
    "gn:admin1_code":"VLG",
    "gn:admin2_code":"VOV",
    "gn:admin3_code":"45.0",
    "gn:admin4_code":"45065.0",
    "gn:asciiname":"Eesstraat",
    "gn:country_code":"BE",
    "gn:dem":46,
    "gn:feature_class":"P",
    "gn:feature_code":"PPL",
    "gn:name":"Eesstraat",
    "gn:population":0,
    "gn:timezone":"Europe/Brussels",
    "iso:country":"BE",
    "name:und_x_variant":[
        "Heesstraat",
        "Eesstraat"
    ],
    "wof:name":"Eesstraat",
    "wof:placetype":"locality"
},
  "geometry": {"coordinates":[3.71667,50.85],"type":"Point"}
}