{
  "type": "Feature",
  "properties": {
    "gn:admin1_code":"WAL",
    "gn:admin2_code":"WHT",
    "gn:admin3_code":"57.0",
    "gn:admin4_code":"57081.0",
    "gn:asciiname":"Pic-au-Vent",
    "gn:country_code":"BE",
    "gn:dem":61,
    "gn:feature_class":"P",
    "gn:feature_code":"PPL",
    "gn:name":"Pic-au-Vent",
    "gn:population":0,
    "gn:timezone":"Europe/Brussels",
    "iso:country":"BE",
    "wof:name":"Pic-au-Vent",
    "wof:placetype":"locality"
},
  "geometry": {"coordinates":[3.34982,50.58566],"type":"Point"}
}