{
  "type": "Feature",
  "properties": {
    "gn:admin1_code":"WAL",
    "gn:admin2_code":"WNA",
    "gn:admin3_code":"92.0",
    "gn:admin4_code":"92097.0",
    "gn:asciiname":"Baya",
    "gn:country_code":"BE",
    "gn:dem":251,
    "gn:feature_class":"P",
    "gn:feature_code":"PPL",
    "gn:name":"Baya",
    "gn:population":0,
    "gn:timezone":"Europe/Brussels",
    "iso:country":"BE",
    "wof:name":"Baya",
    "wof:placetype":"locality"
},
  "geometry": {"coordinates":[5.19499,50.4635],"type":"Point"}
}