{
  "type": "Feature",
  "properties": {
    "gn:admin1_code":"WAL",
    "gn:admin2_code":"WHT",
    "gn:admin3_code":"55.0",
    "gn:admin4_code":"55004.0",
    "gn:asciiname":"Planoit",
    "gn:country_code":"BE",
    "gn:dem":117,
    "gn:feature_class":"P",
    "gn:feature_code":"PPL",
    "gn:name":"Planoit",
    "gn:population":0,
    "gn:timezone":"Europe/Brussels",
    "iso:country":"BE",
    "wof:name":"Planoit",
    "wof:placetype":"locality"
},
  "geometry": {"coordinates":[4.18802,50.63249],"type":"Point"}
}