{
  "type": "Feature",
  "properties": {
    "gn:country":"BE",
    "gn:fcode":"PPL",
    "gn:population":0,
    "iso:country":"BE",
    "name:deu_x_preferred":[
        "Kotem"
    ],
    "name:eng_x_preferred":[
        "Kotem"
    ],
    "name:fra_x_preferred":[
        "Kotem"
    ],
    "name:gle_x_preferred":[
        "Kotem"
    ],
    "name:lim_x_preferred":[
        "Kote"
    ],
    "name:nld_x_preferred":[
        "Kotem"
    ],
    "name:und_x_variant":[
        "Cothem"
    ],
    "qs_pg:aaroncc":"BE",
    "qs_pg:gn_country":"BE",
    "qs_pg:gn_fcode":"PPL",
    "qs_pg:gn_pop":0,
    "qs_pg:name":"Kotem",
    "qs_pg:name_adm0":"Belgique",
    "qs_pg:name_adm1":"Limburg",
    "qs_pg:photos":356,
    "qs_pg:photos_1k":72,
    "qs_pg:photos_9k":2,
    "qs_pg:photos_9r":5,
    "qs_pg:photos_all":356,
    "qs_pg:photos_sr":6,
    "qs_pg:pop_sr":0,
    "qs_pg:qs_pg_placetype":"locality",
    "qs_pg:qs_pg_placetype_gp":"Town",
    "qs_pg:woe_adm0":23424757,
    "woe:adm0_id":23424757,
    "woe:name_adm0":"Belgique",
    "woe:name_adm1":"Limburg",
    "woe:placetype":"Town",
    "wof:name":"Kotem",
    "wof:placetype":"locality"
},
  "geometry": {"coordinates":[5.7425,50.94914],"type":"Point"}
}