{
  "type": "Feature",
  "properties": {
    "gn:admin1_code":"WAL",
    "gn:admin2_code":"WLG",
    "gn:admin3_code":"62.0",
    "gn:admin4_code":"62119.0",
    "gn:asciiname":"Haute Saive",
    "gn:country_code":"BE",
    "gn:dem":185,
    "gn:feature_class":"P",
    "gn:feature_code":"PPL",
    "gn:name":"Haute Saive",
    "gn:population":0,
    "gn:timezone":"Europe/Brussels",
    "iso:country":"BE",
    "wof:name":"Haute Saive",
    "wof:placetype":"locality"
},
  "geometry": {"coordinates":[5.67628,50.65846],"type":"Point"}
}