{
  "type": "Feature",
  "properties": {
    "gn:admin1_code":"VLG",
    "gn:admin2_code":"VOV",
    "gn:admin3_code":"45.0",
    "gn:admin4_code":"45064.0",
    "gn:asciiname":"Oudenhove",
    "gn:country_code":"BE",
    "gn:dem":115,
    "gn:feature_class":"P",
    "gn:feature_code":"PPL",
    "gn:name":"Oudenhove",
    "gn:population":0,
    "gn:timezone":"Europe/Brussels",
    "iso:country":"BE",
    "name:und_x_variant":[
        "Audenhove",
        "Oudenhove"
    ],
    "wof:name":"Oudenhove",
    "wof:placetype":"locality"
},
  "geometry": {"coordinates":[3.67042,50.77355],"type":"Point"}
}