{
  "type": "Feature",
  "properties": {
    "gn:country":"BE",
    "gn:fcode":"PPL",
    "gn:population":0,
    "iso:country":"BE",
    "name:cat_x_preferred":[
        "Sint-Martens-Voeren"
    ],
    "name:eng_x_preferred":[
        "Sint-Martens-Voeren"
    ],
    "name:fra_x_preferred":[
        "Fouron-Saint-Martin"
    ],
    "name:fra_x_variant":[
        "Fourons (Fouron-Saint-Martin)"
    ],
    "name:hun_x_preferred":[
        "Sint-Martens-Voeren"
    ],
    "name:lim_x_preferred":[
        "S'n Mae\u00ebte"
    ],
    "name:nld_x_preferred":[
        "Voeren (Sint-Martens-Voeren)"
    ],
    "name:nld_x_variant":[
        "Sint-Martens-Voeren"
    ],
    "qs_pg:aaroncc":"BE",
    "qs_pg:gn_country":"BE",
    "qs_pg:gn_fcode":"PPL",
    "qs_pg:gn_pop":0,
    "qs_pg:name":"St.-Martens-Voeren",
    "qs_pg:name_adm0":"Belgique",
    "qs_pg:name_adm1":"Limburg",
    "qs_pg:photos":109,
    "qs_pg:photos_1k":22,
    "qs_pg:photos_9k":1,
    "qs_pg:photos_9r":3,
    "qs_pg:photos_all":109,
    "qs_pg:photos_sr":3,
    "qs_pg:pop_sr":0,
    "qs_pg:qs_pg_placetype":"locality",
    "qs_pg:qs_pg_placetype_gp":"Town",
    "qs_pg:woe_adm0":23424757,
    "woe:adm0_id":23424757,
    "woe:name_adm0":"Belgique",
    "woe:name_adm1":"Limburg",
    "woe:placetype":"Town",
    "wof:name":"St.-Martens-Voeren",
    "wof:placetype":"locality"
},
  "geometry": {"coordinates":[5.81288,50.74846],"type":"Point"}
}