{
  "type": "Feature",
  "properties": {
    "gn:admin1_code":"VLG",
    "gn:admin2_code":"VAN",
    "gn:admin3_code":"11.0",
    "gn:admin4_code":"11053.0",
    "gn:asciiname":"Ouderseel",
    "gn:country_code":"BE",
    "gn:dem":22,
    "gn:feature_class":"P",
    "gn:feature_code":"PPL",
    "gn:name":"Ouderseel",
    "gn:population":0,
    "gn:timezone":"Europe/Brussels",
    "iso:country":"BE",
    "name:und_x_variant":[
        "Ouderzeel",
        "Ouderseel"
    ],
    "wof:name":"Ouderseel",
    "wof:placetype":"locality"
},
  "geometry": {"coordinates":[4.51717,51.37463],"type":"Point"}
}