{
  "type": "Feature",
  "properties": {
    "gn:admin1_code":"WAL",
    "gn:admin2_code":"WBR",
    "gn:admin3_code":"25.0",
    "gn:admin4_code":"25121.0",
    "gn:asciiname":"Rofessart",
    "gn:country_code":"BE",
    "gn:dem":88,
    "gn:feature_class":"P",
    "gn:feature_code":"PPL",
    "gn:name":"Rofessart",
    "gn:population":0,
    "gn:timezone":"Europe/Brussels",
    "iso:country":"BE",
    "wof:name":"Rofessart",
    "wof:placetype":"locality"
},
  "geometry": {"coordinates":[4.54628,50.68901],"type":"Point"}
}