{
  "type": "Feature",
  "properties": {
    "gn:admin1_code":"WAL",
    "gn:admin2_code":"WLG",
    "gn:admin3_code":"63.0",
    "gn:admin4_code":"63045.0",
    "gn:asciiname":"Villettes",
    "gn:country_code":"BE",
    "gn:dem":380,
    "gn:feature_class":"P",
    "gn:feature_code":"PPL",
    "gn:name":"Villettes",
    "gn:population":0,
    "gn:timezone":"Europe/Brussels",
    "iso:country":"BE",
    "name:bug_x_preferred":[
        "Villettes"
    ],
    "name:cat_x_preferred":[
        "Villettes"
    ],
    "name:ceb_x_preferred":[
        "Villettes"
    ],
    "name:deu_x_preferred":[
        "Villettes"
    ],
    "name:eus_x_preferred":[
        "Villettes"
    ],
    "name:fra_x_preferred":[
        "Villettes"
    ],
    "name:hun_x_preferred":[
        "Villettes"
    ],
    "name:ind_x_preferred":[
        "Villettes"
    ],
    "name:ita_x_preferred":[
        "Villettes"
    ],
    "name:kaz_x_preferred":[
        "\u0412\u0438\u043b\u043b\u0435\u0442\u0442"
    ],
    "name:lat_x_preferred":[
        "Villettes"
    ],
    "name:mlg_x_preferred":[
        "Villettes"
    ],
    "name:msa_x_preferred":[
        "Villettes"
    ],
    "name:nld_x_preferred":[
        "Villettes"
    ],
    "name:oci_x_preferred":[
        "Villettes"
    ],
    "name:pms_x_preferred":[
        "Villettes"
    ],
    "name:pol_x_preferred":[
        "Villettes"
    ],
    "name:por_x_preferred":[
        "Villettes"
    ],
    "name:ron_x_preferred":[
        "Villettes"
    ],
    "name:slk_x_preferred":[
        "Villettes"
    ],
    "name:spa_x_preferred":[
        "Villettes"
    ],
    "name:swe_x_preferred":[
        "Villettes"
    ],
    "name:ukr_x_preferred":[
        "\u0412\u0456\u043b\u043b\u0435\u0442\u0442"
    ],
    "name:vie_x_preferred":[
        "Villettes"
    ],
    "name:vol_x_preferred":[
        "Villettes"
    ],
    "name:war_x_preferred":[
        "Villettes"
    ],
    "name:zho_x_preferred":[
        "\u7ef4\u96f7\u7279"
    ],
    "wof:name":"Villettes",
    "wof:placetype":"locality"
},
  "geometry": {"coordinates":[5.76471,50.32857],"type":"Point"}
}