{
  "type": "Feature",
  "properties": {
    "gn:admin1_code":"VLG",
    "gn:admin2_code":"VBR",
    "gn:admin3_code":"23.0",
    "gn:admin4_code":"23016.0",
    "gn:asciiname":"Oosthoek",
    "gn:country_code":"BE",
    "gn:dem":34,
    "gn:feature_class":"P",
    "gn:feature_code":"PPL",
    "gn:name":"Oosthoek",
    "gn:population":0,
    "gn:timezone":"Europe/Brussels",
    "iso:country":"BE",
    "wof:name":"Oosthoek",
    "wof:placetype":"locality"
},
  "geometry": {"coordinates":[4.20914,50.8712],"type":"Point"}
}