{
  "type": "Feature",
  "properties": {
    "gn:admin1_code":"WAL",
    "gn:admin2_code":"WNA",
    "gn:admin3_code":"92.0",
    "gn:admin4_code":"92048.0",
    "gn:asciiname":"Aisemont",
    "gn:country_code":"BE",
    "gn:dem":199,
    "gn:feature_class":"P",
    "gn:feature_code":"PPL",
    "gn:name":"Aisemont",
    "gn:population":0,
    "gn:timezone":"Europe/Brussels",
    "iso:country":"BE",
    "name:und_x_variant":[
        "Fosses-la-Ville (Aisemont)"
    ],
    "wof:name":"Aisemont",
    "wof:placetype":"locality"
},
  "geometry": {"coordinates":[4.65185,50.40491],"type":"Point"}
}