{
  "type": "Feature",
  "properties": {
    "gn:admin1_code":"VLG",
    "gn:admin2_code":"VOV",
    "gn:admin3_code":"46.0",
    "gn:admin4_code":"46020.0",
    "gn:asciiname":"Hol",
    "gn:country_code":"BE",
    "gn:dem":5,
    "gn:feature_class":"P",
    "gn:feature_code":"PPL",
    "gn:name":"Hol",
    "gn:population":0,
    "gn:timezone":"Europe/Brussels",
    "iso:country":"BE",
    "name:und_x_variant":[
        "Meuleken Hol"
    ],
    "wof:name":"Hol",
    "wof:placetype":"locality"
},
  "geometry": {"coordinates":[4.09164,51.22328],"type":"Point"}
}