{
  "type": "Feature",
  "properties": {
    "iso:country":"BE",
    "name:bre_x_preferred":[
        "Ruisbroek"
    ],
    "name:bul_x_preferred":[
        "\u0420\u0443\u0438\u0441\u0431\u0440\u043e\u0435\u043a"
    ],
    "name:cat_x_preferred":[
        "Ruisbroek"
    ],
    "name:ceb_x_preferred":[
        "Ruisbroek"
    ],
    "name:deu_x_preferred":[
        "Ruisbroek"
    ],
    "name:eng_x_preferred":[
        "Ruisbroek"
    ],
    "name:fra_x_preferred":[
        "Ruisbroek"
    ],
    "name:hun_x_preferred":[
        "Ruisbroek"
    ],
    "name:nld_x_preferred":[
        "Ruisbroek"
    ],
    "name:nno_x_preferred":[
        "Ruisbroek"
    ],
    "name:nob_x_preferred":[
        "Ruisbroek"
    ],
    "name:rus_x_preferred":[
        "\u0420\u0451\u0439\u0441\u0431\u0440\u0443\u043a"
    ],
    "name:sme_x_preferred":[
        "Ruisbroek"
    ],
    "name:swe_x_preferred":[
        "Ruisbroek"
    ],
    "name:und_x_variant":[
        "Sint-Pieters-Leeuw (Ruisbroek)"
    ],
    "qs:gn_fcode":"PPL",
    "qs:gn_local":0,
    "qs:gn_namadm1":"VLG",
    "qs:gn_name":"Ruisbroek",
    "qs:local_max":172,
    "qs:local_sum":397,
    "qs:localhoods":4,
    "qs:name":"Ruisbroek",
    "qs:name_adm0":"Belgique",
    "qs:name_adm1":"Vlaams Brabant",
    "qs:name_adm2":"Halle-Vilvoorde",
    "qs:name_lau":"St.-Pieters-Leeuw",
    "qs:name_local":"St.-Pieters-Leeuw",
    "qs:photo_max":26,
    "qs:photo_sum":172,
    "qs:placetype":"Suburb",
    "qs:quad_count":19,
    "qs:woe_adm0":23424757,
    "qs:woe_adm1":22525998,
    "qs:woe_adm2":12591768,
    "qs:woe_lau":20074659,
    "qs:woe_local":20074659,
    "qs:woe_ver":"7.10.0",
    "wd:wordcount":158,
    "wof:lang":[
        "dut"
    ],
    "wof:name":"Ruisbroek",
    "wof:placetype":"neighbourhood"
},
  "geometry": {"coordinates":[4.294607,50.788575],"type":"Point"}
}