{
  "type": "Feature",
  "properties": {
    "gn:admin1_code":"VLG",
    "gn:admin2_code":"VOV",
    "gn:admin3_code":"45.0",
    "gn:admin4_code":"45060.0",
    "gn:asciiname":"Pensemont",
    "gn:country_code":"BE",
    "gn:dem":70,
    "gn:feature_class":"P",
    "gn:feature_code":"PPL",
    "gn:name":"Pensemont",
    "gn:population":0,
    "gn:timezone":"Europe/Brussels",
    "iso:country":"BE",
    "wof:name":"Pensemont",
    "wof:placetype":"locality"
},
  "geometry": {"coordinates":[3.5103,50.76994000000001],"type":"Point"}
}