{
  "type": "Feature",
  "properties": {
    "gn:admin1_code":"VLG",
    "gn:admin2_code":"VOV",
    "gn:admin3_code":"44.0",
    "gn:admin4_code":"44021.0",
    "gn:asciiname":"Terdonk",
    "gn:country_code":"BE",
    "gn:dem":5,
    "gn:feature_class":"P",
    "gn:feature_code":"PPL",
    "gn:name":"Terdonk",
    "gn:population":0,
    "gn:timezone":"Europe/Brussels",
    "iso:country":"BE",
    "name:und_x_variant":[
        "Terdonck",
        "Terdonk"
    ],
    "wof:name":"Terdonk",
    "wof:placetype":"locality"
},
  "geometry": {"coordinates":[3.79499,51.14917],"type":"Point"}
}