{
  "type": "Feature",
  "properties": {
    "gn:admin1_code":"VLG",
    "gn:admin2_code":"VLI",
    "gn:admin3_code":"71.0",
    "gn:admin4_code":"71047.0",
    "gn:asciiname":"Het Laar",
    "gn:country_code":"BE",
    "gn:dem":81,
    "gn:feature_class":"P",
    "gn:feature_code":"PPL",
    "gn:name":"Het Laar",
    "gn:population":0,
    "gn:timezone":"Europe/Brussels",
    "iso:country":"BE",
    "name:und_x_variant":[
        "Laar",
        "Het Laer",
        "Het Laar"
    ],
    "wof:name":"Het Laar",
    "wof:placetype":"locality"
},
  "geometry": {"coordinates":[5.58743,51.05438],"type":"Point"}
}