{
  "type": "Feature",
  "properties": {
    "gn:admin1_code":"VLG",
    "gn:admin2_code":"VOV",
    "gn:admin3_code":"44.0",
    "gn:admin4_code":"44019.0",
    "gn:asciiname":"Hulleken",
    "gn:country_code":"BE",
    "gn:dem":7,
    "gn:feature_class":"P",
    "gn:feature_code":"PPL",
    "gn:name":"Hulleken",
    "gn:population":0,
    "gn:timezone":"Europe/Brussels",
    "iso:country":"BE",
    "wof:name":"Hulleken",
    "wof:placetype":"locality"
},
  "geometry": {"coordinates":[3.68266,51.11994],"type":"Point"}
}