{
  "type": "Feature",
  "properties": {
    "gn:admin1_code":"WAL",
    "gn:admin2_code":"WLX",
    "gn:admin3_code":"83.0",
    "gn:admin4_code":"83055.0",
    "gn:asciiname":"Lamormenil",
    "gn:country_code":"BE",
    "gn:dem":444,
    "gn:feature_class":"P",
    "gn:feature_code":"PPL",
    "gn:name":"Lamormenil",
    "gn:population":0,
    "gn:timezone":"Europe/Brussels",
    "iso:country":"BE",
    "wof:name":"Lamormenil",
    "wof:placetype":"locality"
},
  "geometry": {"coordinates":[5.63684,50.25505],"type":"Point"}
}