{
  "type": "Feature",
  "properties": {
    "gn:admin1_code":"WAL",
    "gn:admin2_code":"WNA",
    "gn:admin3_code":"92.0",
    "gn:admin4_code":"92141.0",
    "gn:asciiname":"Alveaux",
    "gn:country_code":"BE",
    "gn:dem":166,
    "gn:feature_class":"P",
    "gn:feature_code":"PPL",
    "gn:name":"Alveaux",
    "gn:population":0,
    "gn:timezone":"Europe/Brussels",
    "iso:country":"BE",
    "name:und_x_variant":[
        "Alvaux",
        "Alveaux"
    ],
    "wof:name":"Alveaux",
    "wof:placetype":"locality"
},
  "geometry": {"coordinates":[4.80853,50.55497],"type":"Point"}
}