{
  "type": "Feature",
  "properties": {
    "gn:admin1_code":"WAL",
    "gn:admin2_code":"WLX",
    "gn:admin3_code":"83.0",
    "gn:admin4_code":"83013.0",
    "gn:asciiname":"Les Aunais",
    "gn:country_code":"BE",
    "gn:dem":204,
    "gn:feature_class":"P",
    "gn:feature_code":"PPL",
    "gn:name":"Les Aunais",
    "gn:population":0,
    "gn:timezone":"Europe/Brussels",
    "iso:country":"BE",
    "wof:name":"Les Aunais",
    "wof:placetype":"locality"
},
  "geometry": {"coordinates":[5.59211,50.33598],"type":"Point"}
}