{
  "type": "Feature",
  "properties": {
    "gn:admin1_code":"VLG",
    "gn:admin2_code":"VAN",
    "gn:admin3_code":"11.0",
    "gn:admin4_code":"11002.0",
    "gn:asciiname":"Gallifort",
    "gn:country_code":"BE",
    "gn:dem":5,
    "gn:feature_class":"P",
    "gn:feature_code":"PPL",
    "gn:name":"Gallifort",
    "gn:population":0,
    "gn:timezone":"Europe/Brussels",
    "iso:country":"BE",
    "name:und_x_variant":[
        "Galifort",
        "Gallifort"
    ],
    "wof:name":"Gallifort",
    "wof:placetype":"locality"
},
  "geometry": {"coordinates":[4.45991,51.22398],"type":"Point"}
}