{
  "type": "Feature",
  "properties": {
    "gn:gn_country":"BE",
    "gn:gn_fcode":"PPL",
    "gn:gn_pop":0,
    "iso:country":"BE",
    "name:eng_x_preferred":[
        "Bovesse"
    ],
    "name:fra_x_preferred":[
        "Bovesse"
    ],
    "name:nld_x_preferred":[
        "Bovesse"
    ],
    "name:unk_x_variant":[
        "La Bruy\u00e8re (Bovesse)"
    ],
    "name:wln_x_preferred":[
        "Bovesse"
    ],
    "qs_pg:aaroncc":"BE",
    "qs_pg:gn_country":"BE",
    "qs_pg:gn_fcode":"PPL",
    "qs_pg:gn_pop":0,
    "qs_pg:name":"Bovesse",
    "qs_pg:name_adm0":"Belgique",
    "qs_pg:name_adm1":"Namur",
    "qs_pg:photos_9r":0,
    "qs_pg:photos_sr":0,
    "qs_pg:pop_sr":0,
    "qs_pg:qs_pg_placetype":"locality",
    "qs_pg:qs_pg_placetype_gp":"Town",
    "qs_pg:woe_adm0":23424757,
    "woe:adm0_id":23424757,
    "woe:name_adm0":"Belgique",
    "woe:name_adm1":"Namur",
    "woe:placetype":"Town",
    "wof:name":"Bovesse",
    "wof:placetype":"locality"
},
  "geometry": {"coordinates":[4.78086,50.51938],"type":"Point"}
}