{
  "type": "Feature",
  "properties": {
    "gn:admin1_code":"WAL",
    "gn:admin2_code":"WLG",
    "gn:admin3_code":"63.0",
    "gn:admin4_code":"63067.0",
    "gn:asciiname":"Mackenbach",
    "gn:country_code":"BE",
    "gn:dem":428,
    "gn:feature_class":"P",
    "gn:feature_code":"PPL",
    "gn:name":"Mackenbach",
    "gn:population":0,
    "gn:timezone":"Europe/Brussels",
    "iso:country":"BE",
    "name:ceb_x_preferred":[
        "Mackenbach"
    ],
    "name:deu_x_preferred":[
        "Mackenbach"
    ],
    "name:epo_x_preferred":[
        "Mackenbach"
    ],
    "name:eus_x_preferred":[
        "Mackenbach"
    ],
    "name:fas_x_preferred":[
        "\u0645\u0627\u06a9\u0646\u0628\u0627\u062e"
    ],
    "name:fra_x_preferred":[
        "Mackenbach"
    ],
    "name:hun_x_preferred":[
        "Mackenbach"
    ],
    "name:ita_x_preferred":[
        "Mackenbach"
    ],
    "name:kaz_x_preferred":[
        "\u041c\u0430\u043a\u043a\u0435\u043d\u0431\u0430\u0445"
    ],
    "name:kir_x_preferred":[
        "\u041c\u0430\u043a\u043a\u0435\u043d\u0431\u0430\u0445"
    ],
    "name:msa_x_preferred":[
        "Mackenbach"
    ],
    "name:nld_x_preferred":[
        "Mackenbach"
    ],
    "name:pol_x_preferred":[
        "Mackenbach"
    ],
    "name:por_x_preferred":[
        "Mackenbach"
    ],
    "name:ron_x_preferred":[
        "Mackenbach"
    ],
    "name:rus_x_preferred":[
        "\u041c\u0430\u043a\u043a\u0435\u043d\u0431\u0430\u0445"
    ],
    "name:spa_x_preferred":[
        "Mackenbach"
    ],
    "name:srp_x_preferred":[
        "\u041c\u0430\u043a\u0435\u043d\u0431\u0430\u0445"
    ],
    "name:ukr_x_preferred":[
        "\u041c\u0430\u043a\u043a\u0435\u043d\u0431\u0430\u0445"
    ],
    "name:uzb_x_preferred":[
        "Mackenbach"
    ],
    "name:vie_x_preferred":[
        "Mackenbach"
    ],
    "name:vol_x_preferred":[
        "Mackenbach"
    ],
    "name:war_x_preferred":[
        "Mackenbach"
    ],
    "name:zho_x_preferred":[
        "\u9a6c\u80af\u5df4\u8d6b"
    ],
    "wof:name":"Mackenbach",
    "wof:placetype":"locality"
},
  "geometry": {"coordinates":[6.23263,50.28417],"type":"Point"}
}