{
  "type": "Feature",
  "properties": {
    "gn:admin1_code":"WAL",
    "gn:admin2_code":"WNA",
    "gn:admin3_code":"92.0",
    "gn:admin4_code":"92114.0",
    "gn:asciiname":"La Chaussee",
    "gn:country_code":"BE",
    "gn:dem":151,
    "gn:feature_class":"P",
    "gn:feature_code":"PPL",
    "gn:name":"La Chauss\u00e9e",
    "gn:population":0,
    "gn:timezone":"Europe/Brussels",
    "iso:country":"BE",
    "name:und_x_variant":[
        "La Chaus\u00e9e",
        "La Chauss\u00e9e"
    ],
    "wof:name":"La Chaussee",
    "wof:placetype":"locality"
},
  "geometry": {"coordinates":[4.59443,50.55124],"type":"Point"}
}