{
  "type": "Feature",
  "properties": {
    "gn:admin1_code":"VLG",
    "gn:admin2_code":"VBR",
    "gn:admin3_code":"23.0",
    "gn:admin4_code":"23045.0",
    "gn:asciiname":"De Plas",
    "gn:country_code":"BE",
    "gn:dem":9,
    "gn:feature_class":"P",
    "gn:feature_code":"PPL",
    "gn:name":"De Plas",
    "gn:population":0,
    "gn:timezone":"Europe/Brussels",
    "iso:country":"BE",
    "wof:name":"De Plas",
    "wof:placetype":"locality"
},
  "geometry": {"coordinates":[4.26333,51.00069000000001],"type":"Point"}
}