{
  "type": "Feature",
  "properties": {
    "gn:admin1_code":"WAL",
    "gn:admin2_code":"WLX",
    "gn:admin3_code":"84.0",
    "gn:admin4_code":"84043.0",
    "gn:asciiname":"Hochit Champ",
    "gn:country_code":"BE",
    "gn:dem":451,
    "gn:feature_class":"P",
    "gn:feature_code":"PPL",
    "gn:name":"Hochit Champ",
    "gn:population":0,
    "gn:timezone":"Europe/Brussels",
    "iso:country":"BE",
    "name:und_x_variant":[
        "Hoch\u00eechamp",
        "Hochuchamp",
        "Hochit Champ"
    ],
    "wof:name":"Hochit Champ",
    "wof:placetype":"locality"
},
  "geometry": {"coordinates":[5.48333,49.85],"type":"Point"}
}