{
  "type": "Feature",
  "properties": {
    "gn:admin1_code":"WAL",
    "gn:admin2_code":"WNA",
    "gn:admin3_code":"92.0",
    "gn:admin4_code":"92054.0",
    "gn:asciiname":"Maizeroulle",
    "gn:country_code":"BE",
    "gn:dem":132,
    "gn:feature_class":"P",
    "gn:feature_code":"PPL",
    "gn:name":"Maizeroulle",
    "gn:population":0,
    "gn:timezone":"Europe/Brussels",
    "iso:country":"BE",
    "wof:name":"Maizeroulle",
    "wof:placetype":"locality"
},
  "geometry": {"coordinates":[5.01238,50.44247],"type":"Point"}
}