{
  "type": "Feature",
  "properties": {
    "gn:admin1_code":"WAL",
    "gn:admin2_code":"WNA",
    "gn:admin3_code":"92.0",
    "gn:admin4_code":"92003.0",
    "gn:asciiname":"Groynne",
    "gn:country_code":"BE",
    "gn:dem":201,
    "gn:feature_class":"P",
    "gn:feature_code":"PPL",
    "gn:name":"Groynne",
    "gn:population":0,
    "gn:timezone":"Europe/Brussels",
    "iso:country":"BE",
    "wof:name":"Groynne",
    "wof:placetype":"locality"
},
  "geometry": {"coordinates":[5.07826,50.46947],"type":"Point"}
}