{
  "type": "Feature",
  "properties": {
    "gn:gn_country":"BE",
    "gn:gn_fcode":"PPL",
    "gn:gn_pop":0,
    "iso:country":"BE",
    "name:bre_x_preferred":[
        "Woesten"
    ],
    "name:ceb_x_preferred":[
        "Woesten"
    ],
    "name:eng_x_preferred":[
        "Woesten"
    ],
    "name:fas_x_preferred":[
        "\u0648\u0648\u0627\u0633\u062a\u0646"
    ],
    "name:fra_x_preferred":[
        "Woesten"
    ],
    "name:hun_x_preferred":[
        "Woesten"
    ],
    "name:nld_x_preferred":[
        "Woesten"
    ],
    "name:swe_x_preferred":[
        "Woesten"
    ],
    "name:vls_x_preferred":[
        "Woestn"
    ],
    "qs_pg:aaroncc":"BE",
    "qs_pg:gn_country":"BE",
    "qs_pg:gn_fcode":"PPL",
    "qs_pg:gn_pop":0,
    "qs_pg:name":"Woesten",
    "qs_pg:name_adm0":"Belgique",
    "qs_pg:name_adm1":"West-Vlaanderen",
    "qs_pg:photos_9k":1,
    "qs_pg:photos_9r":1,
    "qs_pg:photos_all":1,
    "qs_pg:photos_sr":0,
    "qs_pg:pop_sr":0,
    "qs_pg:qs_pg_placetype":"locality",
    "qs_pg:qs_pg_placetype_gp":"Town",
    "qs_pg:woe_adm0":23424757,
    "woe:adm0_id":23424757,
    "woe:name_adm0":"Belgique",
    "woe:name_adm1":"West-Vlaanderen",
    "woe:placetype":"Town",
    "wof:name":"Woesten",
    "wof:placetype":"locality"
},
  "geometry": {"coordinates":[2.78959,50.89971],"type":"Point"}
}