{
  "type": "Feature",
  "properties": {
    "gn:admin1_code":"WAL",
    "gn:admin2_code":"WHT",
    "gn:admin3_code":"56.0",
    "gn:admin4_code":"56078.0",
    "gn:asciiname":"La Houzee",
    "gn:country_code":"BE",
    "gn:dem":164,
    "gn:feature_class":"P",
    "gn:feature_code":"PPL",
    "gn:name":"La Houz\u00e9e",
    "gn:population":0,
    "gn:timezone":"Europe/Brussels",
    "iso:country":"BE",
    "name:und_x_variant":[
        "Houz\u00e9e",
        "La Houz\u00e9e"
    ],
    "wof:name":"La Houzee",
    "wof:placetype":"locality"
},
  "geometry": {"coordinates":[4.33698,50.3115],"type":"Point"}
}