{
  "type": "Feature",
  "properties": {
    "gn:admin1_code":"VLG",
    "gn:admin2_code":"VWV",
    "gn:admin3_code":"38.0",
    "gn:admin4_code":"38025.0",
    "gn:asciiname":"Zoutenaaie",
    "gn:country_code":"BE",
    "gn:dem":0,
    "gn:feature_class":"P",
    "gn:feature_code":"PPL",
    "gn:name":"Zoutenaaie",
    "gn:population":0,
    "gn:timezone":"Europe/Brussels",
    "iso:country":"BE",
    "name:und_x_variant":[
        "Zoetenaey",
        "Zoutenaaie"
    ],
    "wof:name":"Zoutenaaie",
    "wof:placetype":"locality"
},
  "geometry": {"coordinates":[2.75451,51.04818],"type":"Point"}
}