{
  "type": "Feature",
  "properties": {
    "gn:admin1_code":"VLG",
    "gn:admin2_code":"VAN",
    "gn:admin3_code":"13.0",
    "gn:admin4_code":"13037.0",
    "gn:asciiname":"De Parre",
    "gn:country_code":"BE",
    "gn:dem":22,
    "gn:feature_class":"P",
    "gn:feature_code":"PPL",
    "gn:name":"De Parre",
    "gn:population":0,
    "gn:timezone":"Europe/Brussels",
    "iso:country":"BE",
    "name:und_x_variant":[
        "Parre",
        "De Parre"
    ],
    "wof:name":"De Parre",
    "wof:placetype":"locality"
},
  "geometry": {"coordinates":[4.76575,51.33635],"type":"Point"}
}