{
  "type": "Feature",
  "properties": {
    "gn:admin1_code":"WAL",
    "gn:admin2_code":"WHT",
    "gn:admin3_code":"56.0",
    "gn:admin4_code":"56016.0",
    "gn:asciiname":"Riezes",
    "gn:country_code":"BE",
    "gn:dem":340,
    "gn:feature_class":"P",
    "gn:feature_code":"PPL",
    "gn:name":"Ri\u00e8zes",
    "gn:population":0,
    "gn:timezone":"Europe/Brussels",
    "iso:country":"BE",
    "name:und_x_variant":[
        "Chimay (Ri\u00e8zes)"
    ],
    "wof:name":"Riezes",
    "wof:placetype":"locality"
},
  "geometry": {"coordinates":[4.36874,49.95948],"type":"Point"}
}