{
  "type": "Feature",
  "properties": {
    "gn:admin1_code":"VLG",
    "gn:admin2_code":"VWV",
    "gn:admin3_code":"37.0",
    "gn:admin4_code":"37018.0",
    "gn:asciiname":"Riek",
    "gn:country_code":"BE",
    "gn:dem":22,
    "gn:feature_class":"P",
    "gn:feature_code":"PPL",
    "gn:name":"Riek",
    "gn:population":0,
    "gn:timezone":"Europe/Brussels",
    "iso:country":"BE",
    "name:und_x_variant":[
        "Rick",
        "Riek"
    ],
    "wof:name":"Riek",
    "wof:placetype":"locality"
},
  "geometry": {"coordinates":[3.19668,51.05193],"type":"Point"}
}