{
  "type": "Feature",
  "properties": {
    "gn:admin1_code":"WAL",
    "gn:admin2_code":"WLX",
    "gn:admin3_code":"84.0",
    "gn:admin4_code":"84075.0",
    "gn:asciiname":"Barzin",
    "gn:country_code":"BE",
    "gn:dem":285,
    "gn:feature_class":"P",
    "gn:feature_code":"PPL",
    "gn:name":"Barzin",
    "gn:population":0,
    "gn:timezone":"Europe/Brussels",
    "iso:country":"BE",
    "name:ara_x_preferred":[
        "\u0628\u0627\u0631\u0632\u064a\u0646"
    ],
    "wof:name":"Barzin",
    "wof:placetype":"locality"
},
  "geometry": {"coordinates":[5.08019,50.0716],"type":"Point"}
}