{
  "type": "Feature",
  "properties": {
    "gn:admin1_code":"WAL",
    "gn:admin2_code":"WHT",
    "gn:admin3_code":"55.0",
    "gn:admin4_code":"55023.0",
    "gn:asciiname":"Longpont",
    "gn:country_code":"BE",
    "gn:dem":49,
    "gn:feature_class":"P",
    "gn:feature_code":"PPL",
    "gn:name":"Longpont",
    "gn:population":0,
    "gn:timezone":"Europe/Brussels",
    "iso:country":"BE",
    "name:bug_x_preferred":[
        "Longpont"
    ],
    "name:cat_x_preferred":[
        "Longpont"
    ],
    "name:ceb_x_preferred":[
        "Longpont"
    ],
    "name:deu_x_preferred":[
        "Longpont"
    ],
    "name:eus_x_preferred":[
        "Longpont"
    ],
    "name:fra_x_preferred":[
        "Longpont"
    ],
    "name:hun_x_preferred":[
        "Longpont"
    ],
    "name:hye_x_preferred":[
        "\u053c\u0578\u0576\u057a\u0578\u0576"
    ],
    "name:ind_x_preferred":[
        "Longpont"
    ],
    "name:ita_x_preferred":[
        "Longpont"
    ],
    "name:lat_x_preferred":[
        "Longpont"
    ],
    "name:mlg_x_preferred":[
        "Longpont"
    ],
    "name:msa_x_preferred":[
        "Longpont"
    ],
    "name:nld_x_preferred":[
        "Longpont"
    ],
    "name:oci_x_preferred":[
        "Longpont"
    ],
    "name:pms_x_preferred":[
        "Longpont"
    ],
    "name:pol_x_preferred":[
        "Longpont"
    ],
    "name:por_x_preferred":[
        "Longpont"
    ],
    "name:rus_x_preferred":[
        "\u041b\u043e\u043d\u043f\u043e\u043d"
    ],
    "name:slk_x_preferred":[
        "Longpont"
    ],
    "name:spa_x_preferred":[
        "Longpont"
    ],
    "name:sqi_x_preferred":[
        "Longpont"
    ],
    "name:swe_x_preferred":[
        "Longpont"
    ],
    "name:ukr_x_preferred":[
        "\u041b\u043e\u043d\u043f\u043e\u043d"
    ],
    "name:uzb_x_preferred":[
        "Longpont"
    ],
    "name:vie_x_preferred":[
        "Longpont"
    ],
    "name:vol_x_preferred":[
        "Longpont"
    ],
    "name:war_x_preferred":[
        "Longpont"
    ],
    "name:zea_x_preferred":[
        "Longpont"
    ],
    "wof:name":"Longpont",
    "wof:placetype":"locality"
},
  "geometry": {"coordinates":[3.81667,50.73333],"type":"Point"}
}