{
  "type": "Feature",
  "properties": {
    "gn:admin1_code":"WAL",
    "gn:admin2_code":"WLX",
    "gn:admin3_code":"83.0",
    "gn:admin4_code":"83049.0",
    "gn:asciiname":"Basseilles",
    "gn:country_code":"BE",
    "gn:dem":455,
    "gn:feature_class":"P",
    "gn:feature_code":"PPL",
    "gn:name":"Basseilles",
    "gn:population":0,
    "gn:timezone":"Europe/Brussels",
    "iso:country":"BE",
    "wof:name":"Basseilles",
    "wof:placetype":"locality"
},
  "geometry": {"coordinates":[5.46667,50.08333],"type":"Point"}
}