{
  "type": "Feature",
  "properties": {
    "gn:admin1_code":"WAL",
    "gn:admin2_code":"WHT",
    "gn:admin3_code":"56.0",
    "gn:admin4_code":"56016.0",
    "gn:asciiname":"L'Escaillere",
    "gn:country_code":"BE",
    "gn:dem":326,
    "gn:feature_class":"P",
    "gn:feature_code":"PPL",
    "gn:name":"L'Escaill\u00e8re",
    "gn:population":0,
    "gn:timezone":"Europe/Brussels",
    "iso:country":"BE",
    "name:und_x_variant":[
        "Chimay (L'Escaill\u00e8re)"
    ],
    "wof:name":"L'Escaillere",
    "wof:placetype":"locality"
},
  "geometry": {"coordinates":[4.43067,49.94503],"type":"Point"}
}