{
  "type": "Feature",
  "properties": {
    "gn:admin1_code":"VLG",
    "gn:admin2_code":"VLI",
    "gn:admin3_code":"72.0",
    "gn:admin4_code":"72037.0",
    "gn:asciiname":"Dijk",
    "gn:country_code":"BE",
    "gn:dem":36,
    "gn:feature_class":"P",
    "gn:feature_code":"PPL",
    "gn:name":"Dijk",
    "gn:population":0,
    "gn:timezone":"Europe/Brussels",
    "iso:country":"BE",
    "name:und_x_variant":[
        "Dyk",
        "Dijk"
    ],
    "wof:name":"Dijk",
    "wof:placetype":"locality"
},
  "geometry": {"coordinates":[5.51667,51.25],"type":"Point"}
}