{
  "type": "Feature",
  "properties": {
    "gn:admin1_code":"WAL",
    "gn:admin2_code":"WLG",
    "gn:admin3_code":"62.0",
    "gn:admin4_code":"62079.0",
    "gn:asciiname":"Hallembaye",
    "gn:country_code":"BE",
    "gn:dem":66,
    "gn:feature_class":"P",
    "gn:feature_code":"PPL",
    "gn:name":"Hallembaye",
    "gn:population":0,
    "gn:timezone":"Europe/Brussels",
    "iso:country":"BE",
    "wof:name":"Hallembaye",
    "wof:placetype":"locality"
},
  "geometry": {"coordinates":[5.6611,50.74015],"type":"Point"}
}