{
  "type": "Feature",
  "properties": {
    "gn:admin1_code":"VLG",
    "gn:admin2_code":"VBR",
    "gn:admin3_code":"23.0",
    "gn:admin4_code":"23097.0",
    "gn:asciiname":"Meersen",
    "gn:country_code":"BE",
    "gn:dem":17,
    "gn:feature_class":"P",
    "gn:feature_code":"PPL",
    "gn:name":"Meersen",
    "gn:population":0,
    "gn:timezone":"Europe/Brussels",
    "iso:country":"BE",
    "name:und_x_variant":[
        "Meerschen",
        "Meersen"
    ],
    "wof:name":"Meersen",
    "wof:placetype":"locality"
},
  "geometry": {"coordinates":[4.06667,50.85],"type":"Point"}
}