{
  "type": "Feature",
  "properties": {
    "gn:admin1_code":"VLG",
    "gn:admin2_code":"VWV",
    "gn:admin3_code":"36.0",
    "gn:admin4_code":"36015.0",
    "gn:asciiname":"Tasse",
    "gn:country_code":"BE",
    "gn:dem":20,
    "gn:feature_class":"P",
    "gn:feature_code":"PPL",
    "gn:name":"Tasse",
    "gn:population":0,
    "gn:timezone":"Europe/Brussels",
    "iso:country":"BE",
    "name:nld_x_preferred":[
        "Tasse"
    ],
    "name:und_x_variant":[
        "Fassche",
        "Tassch\u00e9"
    ],
    "wof:name":"Tasse",
    "wof:placetype":"locality"
},
  "geometry": {"coordinates":[3.16667,50.95],"type":"Point"}
}