{
  "type": "Feature",
  "properties": {
    "iso:country":"BE",
    "name:eng_x_preferred":[
        "Grimbergen Airfield"
    ],
    "name:fas_x_preferred":[
        "\u0641\u0631\u0648\u062f\u06af\u0627\u0647 \u0635\u062d\u0631\u0627\u06cc\u06cc \u06af\u0631\u06cc\u0645\u0628\u0631\u06af\u0646"
    ],
    "name:jpn_x_preferred":[
        "\u30b0\u30ea\u30e0\u30d9\u30eb\u30b2\u30f3\u98db\u884c\u5834"
    ],
    "name:msa_x_preferred":[
        "Lapangan Terbang Lint"
    ],
    "name:nld_x_preferred":[
        "Vliegveld van Grimbergen"
    ],
    "name:pol_x_preferred":[
        "Port lotniczy Grimbergen"
    ],
    "name:tgk_x_preferred":[
        "\u0424\u0443\u0440\u0443\u0434\u0433\u043e\u04b3\u0438 \u0441\u0430\u04b3\u0440\u043e \u0433\u0440\u0438\u043c\u0431\u0440\u0433\u043d"
    ],
    "oa:elevation_ft":"70",
    "oa:type":"small_airport",
    "woe:hierarchy":{
        "country_id":23424757,
        "county_id":12591768,
        "localadmin_id":12602583,
        "planet_id":1,
        "state_id":22525998
    },
    "wof:name":"Luchthaven Grimbergen",
    "wof:placetype":"campus"
},
  "geometry": {"coordinates":[4.3933333333333,50.949444444444],"type":"Point"}
}