{
  "type": "Feature",
  "properties": {
    "iso:country":"BE",
    "oa:elevation_ft":"70",
    "oa:type":"small_airport",
    "woe:hierarchy":{
        "country_id":23424757,
        "county_id":12591768,
        "localadmin_id":12602583,
        "planet_id":1,
        "state_id":22525998
    },
    "wof:name":"Luchthaven Grimbergen",
    "wof:placetype":"campus"
},
  "geometry": {"coordinates":[4.3933333333333,50.949444444444],"type":"Point"}
}