{
  "type": "Feature",
  "properties": {
    "gn:admin1_code":"VLG",
    "gn:admin2_code":"VOV",
    "gn:admin3_code":"45.0",
    "gn:admin4_code":"45057.0",
    "gn:asciiname":"Rooigem",
    "gn:country_code":"BE",
    "gn:dem":27,
    "gn:feature_class":"P",
    "gn:feature_code":"PPL",
    "gn:name":"Rooigem",
    "gn:population":0,
    "gn:timezone":"Europe/Brussels",
    "iso:country":"BE",
    "name:und_x_variant":[
        "Roijgem",
        "Roygem",
        "Rooigem"
    ],
    "wof:name":"Rooigem",
    "wof:placetype":"locality"
},
  "geometry": {"coordinates":[3.59136,50.88947],"type":"Point"}
}