{
  "type": "Feature",
  "properties": {
    "gn:admin1_code":"VLG",
    "gn:admin2_code":"VLI",
    "gn:admin3_code":"71.0",
    "gn:admin4_code":"71066.0",
    "gn:asciiname":"Berkenen",
    "gn:country_code":"BE",
    "gn:dem":50,
    "gn:feature_class":"P",
    "gn:feature_code":"PPL",
    "gn:name":"Berkenen",
    "gn:population":0,
    "gn:timezone":"Europe/Brussels",
    "iso:country":"BE",
    "wof:name":"Berkenen",
    "wof:placetype":"locality"
},
  "geometry": {"coordinates":[5.37849,51.00349],"type":"Point"}
}