{
  "type": "Feature",
  "properties": {
    "gn:admin1_code":"WAL",
    "gn:admin2_code":"WHT",
    "gn:admin3_code":"55.0",
    "gn:admin4_code":"55004.0",
    "gn:asciiname":"Le Marouset",
    "gn:cc2":"BE",
    "gn:country_code":"BE",
    "gn:dem":149,
    "gn:feature_class":"P",
    "gn:feature_code":"PPL",
    "gn:name":"Le Marouset",
    "gn:population":0,
    "gn:timezone":"Europe/Brussels",
    "iso:country":"BE",
    "name:und_x_variant":[
        "Marouset"
    ],
    "wof:name":"Le Marouset",
    "wof:placetype":"locality"
},
  "geometry": {"coordinates":[4.17455,50.60716],"type":"Point"}
}