{
  "type": "Feature",
  "properties": {
    "gn:admin1_code":"VLG",
    "gn:admin2_code":"VOV",
    "gn:admin3_code":"44.0",
    "gn:admin4_code":"44080.0",
    "gn:asciiname":"Nekke",
    "gn:country_code":"BE",
    "gn:dem":9,
    "gn:feature_class":"P",
    "gn:feature_code":"PPL",
    "gn:name":"Nekke",
    "gn:population":0,
    "gn:timezone":"Europe/Brussels",
    "iso:country":"BE",
    "name:und_x_variant":[
        "Necke",
        "Nekke"
    ],
    "wof:name":"Nekke",
    "wof:placetype":"locality"
},
  "geometry": {"coordinates":[3.54294,51.11538],"type":"Point"}
}