{
  "type": "Feature",
  "properties": {
    "gn:admin1_code":"WAL",
    "gn:admin2_code":"WLX",
    "gn:admin3_code":"83.0",
    "gn:admin4_code":"83031.0",
    "gn:asciiname":"La Penne",
    "gn:country_code":"BE",
    "gn:dem":390,
    "gn:feature_class":"P",
    "gn:feature_code":"PPL",
    "gn:name":"La Penne",
    "gn:population":0,
    "gn:timezone":"Europe/Brussels",
    "iso:country":"BE",
    "name:ara_x_preferred":[
        "\u0644\u0627 \u0628\u064a\u0646"
    ],
    "name:bug_x_preferred":[
        "La Penne"
    ],
    "name:cat_x_preferred":[
        "La Pena"
    ],
    "name:ceb_x_preferred":[
        "La Penne"
    ],
    "name:deu_x_preferred":[
        "La Penne"
    ],
    "name:eus_x_preferred":[
        "La Penne"
    ],
    "name:fas_x_preferred":[
        "\u0644\u0627 \u067e\u0646\u0647"
    ],
    "name:fin_x_preferred":[
        "La Penne"
    ],
    "name:fra_x_preferred":[
        "La Penne"
    ],
    "name:hun_x_preferred":[
        "La Penne"
    ],
    "name:hye_x_preferred":[
        "\u053c\u0561 \u054a\u0565\u0576"
    ],
    "name:ind_x_preferred":[
        "La Penne"
    ],
    "name:ita_x_preferred":[
        "La Penne"
    ],
    "name:lat_x_preferred":[
        "Pinna"
    ],
    "name:lmo_x_preferred":[
        "La Penne"
    ],
    "name:msa_x_preferred":[
        "La Penne"
    ],
    "name:nld_x_preferred":[
        "La Penne"
    ],
    "name:oci_x_preferred":[
        "La Pena"
    ],
    "name:pol_x_preferred":[
        "La Penne"
    ],
    "name:por_x_preferred":[
        "La Penne"
    ],
    "name:ron_x_preferred":[
        "La Penne"
    ],
    "name:rus_x_preferred":[
        "\u041b\u0430-\u041f\u0435\u043d"
    ],
    "name:slk_x_preferred":[
        "La Penne"
    ],
    "name:spa_x_preferred":[
        "La Penne"
    ],
    "name:sqi_x_preferred":[
        "La Penne"
    ],
    "name:swe_x_preferred":[
        "La Penne"
    ],
    "name:ukr_x_preferred":[
        "\u041b\u0430-\u041f\u0435\u043d\u043d"
    ],
    "name:urd_x_preferred":[
        "\u0644\u0627 \u067e\u06cc\u0646\u06cc"
    ],
    "name:vie_x_preferred":[
        "La Penne"
    ],
    "name:vol_x_preferred":[
        "La Penne"
    ],
    "name:war_x_preferred":[
        "La Penne"
    ],
    "name:zho_x_preferred":[
        "\u62c9\u5e9e"
    ],
    "wof:name":"La Penne",
    "wof:placetype":"locality"
},
  "geometry": {"coordinates":[5.66667,50.11667],"type":"Point"}
}