{
  "type": "Feature",
  "properties": {
    "gn:admin1_code":"VLG",
    "gn:admin2_code":"VAN",
    "gn:admin3_code":"11.0",
    "gn:admin4_code":"11056.0",
    "gn:asciiname":"Slijkhoek",
    "gn:country_code":"BE",
    "gn:dem":7,
    "gn:feature_class":"P",
    "gn:feature_code":"PPL",
    "gn:name":"Slijkhoek",
    "gn:population":0,
    "gn:timezone":"Europe/Brussels",
    "iso:country":"BE",
    "wof:name":"Slijkhoek",
    "wof:placetype":"locality"
},
  "geometry": {"coordinates":[4.33668,51.20382],"type":"Point"}
}