{
  "type": "Feature",
  "properties": {
    "gn:admin1_code":"WAL",
    "gn:admin2_code":"WBR",
    "gn:admin3_code":"25.0",
    "gn:admin4_code":"25119.0",
    "gn:asciiname":"La Brire",
    "gn:country_code":"BE",
    "gn:dem":92,
    "gn:feature_class":"P",
    "gn:feature_code":"PPL",
    "gn:name":"La Brire",
    "gn:population":0,
    "gn:timezone":"Europe/Brussels",
    "iso:country":"BE",
    "name:und_x_variant":[
        "Brire",
        "La Brire"
    ],
    "wof:name":"La Brire",
    "wof:placetype":"locality"
},
  "geometry": {"coordinates":[4.49204,50.69857],"type":"Point"}
}