{
  "type": "Feature",
  "properties": {
    "gn:admin1_code":"WAL",
    "gn:admin2_code":"WNA",
    "gn:admin3_code":"91.0",
    "gn:admin4_code":"91103.0",
    "gn:asciiname":"Foy",
    "gn:country_code":"BE",
    "gn:dem":180,
    "gn:feature_class":"P",
    "gn:feature_code":"PPL",
    "gn:name":"Foy",
    "gn:population":0,
    "gn:timezone":"Europe/Brussels",
    "iso:country":"BE",
    "wof:name":"Foy",
    "wof:placetype":"locality"
},
  "geometry": {"coordinates":[4.80946,50.29404],"type":"Point"}
}