{
  "type": "Feature",
  "properties": {
    "gn:admin1_code":"VLG",
    "gn:admin2_code":"VBR",
    "gn:admin3_code":"24.0",
    "gn:admin4_code":"24007.0",
    "gn:asciiname":"Molenberg",
    "gn:country_code":"BE",
    "gn:dem":39,
    "gn:feature_class":"P",
    "gn:feature_code":"PPL",
    "gn:name":"Molenberg",
    "gn:population":0,
    "gn:timezone":"Europe/Brussels",
    "iso:country":"BE",
    "wof:name":"Molenberg",
    "wof:placetype":"locality"
},
  "geometry": {"coordinates":[4.78273,50.99331],"type":"Point"}
}