{
  "type": "Feature",
  "properties": {
    "gn:admin1_code":"WAL",
    "gn:admin2_code":"WNA",
    "gn:admin3_code":"91.0",
    "gn:admin4_code":"91064.0",
    "gn:asciiname":"Verlee",
    "gn:country_code":"BE",
    "gn:dem":266,
    "gn:feature_class":"P",
    "gn:feature_code":"PPL",
    "gn:name":"Verl\u00e9e",
    "gn:population":0,
    "gn:timezone":"Europe/Brussels",
    "iso:country":"BE",
    "name:und_x_variant":[
        "Havelange (Verl\u00e9e)"
    ],
    "wof:name":"Verlee",
    "wof:placetype":"locality"
},
  "geometry": {"coordinates":[5.27893,50.36802],"type":"Point"}
}