{
  "type": "Feature",
  "properties": {
    "gn:admin1_code":"VLG",
    "gn:admin2_code":"VLI",
    "gn:admin3_code":"73.0",
    "gn:admin4_code":"73006.0",
    "gn:asciiname":"Spurk",
    "gn:country_code":"BE",
    "gn:dem":45,
    "gn:feature_class":"P",
    "gn:feature_code":"PPL",
    "gn:name":"Spurk",
    "gn:population":0,
    "gn:timezone":"Europe/Brussels",
    "iso:country":"BE",
    "name:aze_x_preferred":[
        "Sp\u00fcrk"
    ],
    "name:kaz_x_preferred":[
        "\u0421\u043f\u044e\u0440\u043a"
    ],
    "name:rus_x_preferred":[
        "\u0421\u043f\u044e\u0440\u043a"
    ],
    "wof:name":"Spurk",
    "wof:placetype":"locality"
},
  "geometry": {"coordinates":[5.50394,50.8871],"type":"Point"}
}