{
  "type": "Feature",
  "properties": {
    "gn:admin1_code":"VLG",
    "gn:admin2_code":"VAN",
    "gn:admin3_code":"13.0",
    "gn:admin4_code":"13053.0",
    "gn:asciiname":"Peren",
    "gn:country_code":"BE",
    "gn:dem":14,
    "gn:feature_class":"P",
    "gn:feature_code":"PPL",
    "gn:name":"Peren",
    "gn:population":0,
    "gn:timezone":"Europe/Brussels",
    "iso:country":"BE",
    "name:ceb_x_preferred":[
        "Peren"
    ],
    "name:hin_x_preferred":[
        "\u092a\u0947\u0930\u0947\u0928"
    ],
    "name:ita_x_preferred":[
        "Peren"
    ],
    "name:swe_x_preferred":[
        "Peren"
    ],
    "name:und_x_variant":[
        "Peyeren",
        "Peren"
    ],
    "name:urd_x_preferred":[
        "\u067e\u06cc\u0631\u06cc\u0646"
    ],
    "wof:name":"Peren",
    "wof:placetype":"locality"
},
  "geometry": {"coordinates":[4.95,51.06667],"type":"Point"}
}