{
  "type": "Feature",
  "properties": {
    "gn:gn_country":"BE",
    "gn:gn_fcode":"PPL",
    "gn:gn_pop":0,
    "iso:country":"BE",
    "name:bre_x_preferred":[
        "Zillebeke"
    ],
    "name:bul_x_preferred":[
        "\u0417\u0438\u043b\u0435\u0431\u0435\u043a\u0435"
    ],
    "name:eng_x_preferred":[
        "Zillebeke"
    ],
    "name:fra_x_preferred":[
        "Zillebeke"
    ],
    "name:hun_x_preferred":[
        "Zillebeke"
    ],
    "name:ita_x_preferred":[
        "Zillebeke"
    ],
    "name:nld_x_preferred":[
        "Zillebeke"
    ],
    "name:swe_x_preferred":[
        "Zillebeke"
    ],
    "name:vls_x_preferred":[
        "Zillebeke"
    ],
    "qs_pg:aaroncc":"BE",
    "qs_pg:gn_country":"BE",
    "qs_pg:gn_fcode":"PPL",
    "qs_pg:gn_pop":0,
    "qs_pg:name":"Zillebeke",
    "qs_pg:name_adm0":"Belgique",
    "qs_pg:name_adm1":"West-Vlaanderen",
    "qs_pg:photos":311,
    "qs_pg:photos_1k":63,
    "qs_pg:photos_9k":1,
    "qs_pg:photos_9r":5,
    "qs_pg:photos_all":311,
    "qs_pg:photos_sr":5,
    "qs_pg:pop_sr":0,
    "qs_pg:qs_pg_placetype":"locality",
    "qs_pg:qs_pg_placetype_gp":"Town",
    "qs_pg:woe_adm0":23424757,
    "woe:adm0_id":23424757,
    "woe:name_adm0":"Belgique",
    "woe:name_adm1":"West-Vlaanderen",
    "woe:placetype":"Town",
    "wof:name":"Zillebeke",
    "wof:placetype":"locality"
},
  "geometry": {"coordinates":[2.92249,50.83464],"type":"Point"}
}