{
  "type": "Feature",
  "properties": {
    "gn:gn_country":"BE",
    "gn:gn_fcode":"PPL",
    "gn:gn_pop":0,
    "iso:country":"BE",
    "name:bre_x_preferred":[
        "Stalhille"
    ],
    "name:eng_x_preferred":[
        "Stalhille"
    ],
    "name:fra_x_preferred":[
        "Stalhille"
    ],
    "name:hun_x_preferred":[
        "Stalhille"
    ],
    "name:nld_x_preferred":[
        "Stalhille"
    ],
    "name:por_x_preferred":[
        "Stalhille"
    ],
    "name:vls_x_preferred":[
        "Stalhille"
    ],
    "qs_pg:aaroncc":"BE",
    "qs_pg:gn_country":"BE",
    "qs_pg:gn_fcode":"PPL",
    "qs_pg:gn_pop":0,
    "qs_pg:name":"Stalhille",
    "qs_pg:name_adm0":"Belgique",
    "qs_pg:name_adm1":"West-Vlaanderen",
    "qs_pg:photos":161,
    "qs_pg:photos_1k":33,
    "qs_pg:photos_9k":1,
    "qs_pg:photos_9r":4,
    "qs_pg:photos_all":161,
    "qs_pg:photos_sr":4,
    "qs_pg:pop_sr":0,
    "qs_pg:qs_pg_placetype":"locality",
    "qs_pg:qs_pg_placetype_gp":"Town",
    "qs_pg:woe_adm0":23424757,
    "woe:adm0_id":23424757,
    "woe:name_adm0":"Belgique",
    "woe:name_adm1":"West-Vlaanderen",
    "woe:placetype":"Town",
    "wof:name":"Stalhille",
    "wof:placetype":"locality"
},
  "geometry": {"coordinates":[3.07198,51.21412],"type":"Point"}
}