{
  "type": "Feature",
  "properties": {
    "gn:admin1_code":"WAL",
    "gn:admin2_code":"WLX",
    "gn:admin3_code":"81.0",
    "gn:admin4_code":"81013.0",
    "gn:asciiname":"La Folie",
    "gn:country_code":"BE",
    "gn:dem":464,
    "gn:feature_class":"P",
    "gn:feature_code":"PPL",
    "gn:name":"La Folie",
    "gn:population":0,
    "gn:timezone":"Europe/Brussels",
    "iso:country":"BE",
    "name:bre_x_preferred":[
        "La Folie"
    ],
    "name:cat_x_preferred":[
        "La Folie"
    ],
    "name:ceb_x_preferred":[
        "La Folie"
    ],
    "name:deu_x_preferred":[
        "La Folie"
    ],
    "name:eus_x_preferred":[
        "La Folie"
    ],
    "name:fra_x_preferred":[
        "La Folie"
    ],
    "name:hun_x_preferred":[
        "La Folie"
    ],
    "name:hye_x_preferred":[
        "\u053c\u0561 \u0556\u0578\u056c\u056b"
    ],
    "name:ita_x_preferred":[
        "La Folie"
    ],
    "name:jav_x_preferred":[
        "La Folie"
    ],
    "name:kaz_x_preferred":[
        "\u041b\u0430-\u0424\u043e\u043b\u0438"
    ],
    "name:lat_x_preferred":[
        "La Folie"
    ],
    "name:msa_x_preferred":[
        "La Folie"
    ],
    "name:nld_x_preferred":[
        "La Folie"
    ],
    "name:oci_x_preferred":[
        "La Folie"
    ],
    "name:pms_x_preferred":[
        "La Folie"
    ],
    "name:pol_x_preferred":[
        "Folie"
    ],
    "name:por_x_preferred":[
        "La Folie"
    ],
    "name:ron_x_preferred":[
        "La Folie"
    ],
    "name:rus_x_preferred":[
        "\u041b\u0430-\u0424\u043e\u043b\u0438"
    ],
    "name:slk_x_preferred":[
        "La Folie"
    ],
    "name:spa_x_preferred":[
        "La Folie"
    ],
    "name:swe_x_preferred":[
        "La Folie"
    ],
    "name:ukr_x_preferred":[
        "\u041b\u0430-\u0424\u043e\u043b\u0456"
    ],
    "name:urd_x_preferred":[
        "\u0644\u0627 \u0641\u0648\u0644\u06cc"
    ],
    "name:uzb_x_preferred":[
        "La Folie"
    ],
    "name:vie_x_preferred":[
        "La Folie"
    ],
    "name:vol_x_preferred":[
        "La Folie"
    ],
    "name:war_x_preferred":[
        "La Folie"
    ],
    "name:zho_x_preferred":[
        "\u62c9\u798f\u5229\u8036"
    ],
    "wof:name":"La Folie",
    "wof:placetype":"locality"
},
  "geometry": {"coordinates":[5.74165,49.79497],"type":"Point"}
}