{
  "type": "Feature",
  "properties": {
    "gn:admin1_code":"WAL",
    "gn:admin2_code":"WLX",
    "gn:admin3_code":"81.0",
    "gn:admin4_code":"81013.0",
    "gn:asciiname":"La Folie",
    "gn:country_code":"BE",
    "gn:dem":464,
    "gn:feature_class":"P",
    "gn:feature_code":"PPL",
    "gn:name":"La Folie",
    "gn:population":0,
    "gn:timezone":"Europe/Brussels",
    "iso:country":"BE",
    "wof:name":"La Folie",
    "wof:placetype":"locality"
},
  "geometry": {"coordinates":[5.74165,49.79497],"type":"Point"}
}