{
  "type": "Feature",
  "properties": {
    "gn:admin1_code":"VLG",
    "gn:admin2_code":"VLI",
    "gn:admin3_code":"71.0",
    "gn:admin4_code":"71037.0",
    "gn:asciiname":"Mellar",
    "gn:country_code":"BE",
    "gn:dem":25,
    "gn:feature_class":"P",
    "gn:feature_code":"PPL",
    "gn:name":"Mellar",
    "gn:population":0,
    "gn:timezone":"Europe/Brussels",
    "iso:country":"BE",
    "name:und_x_variant":[
        "Mellaer",
        "Mellar"
    ],
    "wof:name":"Mellar",
    "wof:placetype":"locality"
},
  "geometry": {"coordinates":[5.15293,50.99507],"type":"Point"}
}