{
  "type": "Feature",
  "properties": {
    "gn:admin1_code":"WAL",
    "gn:admin2_code":"WLG",
    "gn:asciiname":"Hagelstein",
    "gn:country_code":"BE",
    "gn:dem":276,
    "gn:feature_class":"P",
    "gn:feature_code":"PPL",
    "gn:name":"Hagelstein",
    "gn:population":0,
    "gn:timezone":"Europe/Brussels",
    "iso:country":"BE",
    "wof:name":"Hagelstein",
    "wof:placetype":"locality"
},
  "geometry": {"coordinates":[5.86601,50.71663],"type":"Point"}
}