{
  "type": "Feature",
  "properties": {
    "gn:admin1_code":"WAL",
    "gn:admin2_code":"WHT",
    "gn:admin3_code":"56.0",
    "gn:admin4_code":"56049.0",
    "gn:asciiname":"Boustaine",
    "gn:country_code":"BE",
    "gn:dem":139,
    "gn:feature_class":"P",
    "gn:feature_code":"PPL",
    "gn:name":"Boustaine",
    "gn:population":0,
    "gn:timezone":"Europe/Brussels",
    "iso:country":"BE",
    "wof:name":"Boustaine",
    "wof:placetype":"locality"
},
  "geometry": {"coordinates":[4.16146,50.32984],"type":"Point"}
}