{
  "type": "Feature",
  "properties": {
    "gn:admin1_code":"WAL",
    "gn:admin2_code":"WLG",
    "gn:admin3_code":"62.0",
    "gn:admin4_code":"62060.0",
    "gn:asciiname":"Paifve",
    "gn:country_code":"BE",
    "gn:dem":147,
    "gn:feature_class":"P",
    "gn:feature_code":"PPL",
    "gn:name":"Paifve",
    "gn:population":0,
    "gn:timezone":"Europe/Brussels",
    "iso:country":"BE",
    "wof:name":"Paifve",
    "wof:placetype":"locality"
},
  "geometry": {"coordinates":[5.5234,50.7282],"type":"Point"}
}