{
  "type": "Feature",
  "properties": {
    "gn:admin1_code":"VLG",
    "gn:admin2_code":"VAN",
    "gn:admin3_code":"13.0",
    "gn:admin4_code":"13035.0",
    "gn:asciiname":"Klotkuilheide",
    "gn:country_code":"BE",
    "gn:dem":26,
    "gn:feature_class":"P",
    "gn:feature_code":"PPL",
    "gn:name":"Klotkuilheide",
    "gn:population":0,
    "gn:timezone":"Europe/Brussels",
    "iso:country":"BE",
    "name:und_x_variant":[
        "Klotkuil",
        "Klotkuilheide"
    ],
    "wof:name":"Klotkuilheide",
    "wof:placetype":"locality"
},
  "geometry": {"coordinates":[5.01667,51.45],"type":"Point"}
}