{
  "type": "Feature",
  "properties": {
    "gn:admin1_code":"VLG",
    "gn:admin2_code":"VLI",
    "gn:admin3_code":"72.0",
    "gn:admin4_code":"72038.0",
    "gn:asciiname":"Hooghoksent",
    "gn:country_code":"BE",
    "gn:dem":61,
    "gn:feature_class":"P",
    "gn:feature_code":"PPL",
    "gn:name":"Hooghoksent",
    "gn:population":0,
    "gn:timezone":"Europe/Brussels",
    "iso:country":"BE",
    "name:und_x_variant":[
        "Hoog-Hoxent",
        "Hooghoksent"
    ],
    "wof:name":"Hooghoksent",
    "wof:placetype":"locality"
},
  "geometry": {"coordinates":[5.40268,51.15369000000001],"type":"Point"}
}