{
  "type": "Feature",
  "properties": {
    "gn:admin1_code":"VLG",
    "gn:admin2_code":"VOV",
    "gn:admin3_code":"42.0",
    "gn:admin4_code":"42011.0",
    "gn:asciiname":"Dries",
    "gn:country_code":"BE",
    "gn:dem":4,
    "gn:feature_class":"P",
    "gn:feature_code":"PPL",
    "gn:name":"Dries",
    "gn:population":0,
    "gn:timezone":"Europe/Brussels",
    "iso:country":"BE",
    "wof:name":"Dries",
    "wof:placetype":"locality"
},
  "geometry": {"coordinates":[4.10278,51.00371],"type":"Point"}
}