{
  "type": "Feature",
  "properties": {
    "gn:admin1_code":"WAL",
    "gn:admin2_code":"WLX",
    "gn:admin3_code":"82.0",
    "gn:admin4_code":"82014.0",
    "gn:asciiname":"Sur les Vas",
    "gn:country_code":"BE",
    "gn:dem":442,
    "gn:feature_class":"P",
    "gn:feature_code":"PPL",
    "gn:name":"Sur les Vas",
    "gn:population":0,
    "gn:timezone":"Europe/Brussels",
    "iso:country":"BE",
    "wof:name":"Sur les Vas",
    "wof:placetype":"locality"
},
  "geometry": {"coordinates":[5.79153,50.1717],"type":"Point"}
}