{
  "type": "Feature",
  "properties": {
    "gn:admin1_code":"WAL",
    "gn:admin2_code":"WLX",
    "gn:admin3_code":"84.0",
    "gn:admin4_code":"84077.0",
    "gn:asciiname":"Bougnimont",
    "gn:country_code":"BE",
    "gn:dem":477,
    "gn:feature_class":"P",
    "gn:feature_code":"PPL",
    "gn:name":"Bougnimont",
    "gn:population":0,
    "gn:timezone":"Europe/Brussels",
    "iso:country":"BE",
    "wof:name":"Bougnimont",
    "wof:placetype":"locality"
},
  "geometry": {"coordinates":[5.4669,49.94448],"type":"Point"}
}