{
  "type": "Feature",
  "properties": {
    "gn:gn_country":"BE",
    "gn:gn_fcode":"PPL",
    "gn:gn_pop":200,
    "gn:population":200,
    "iso:country":"BE",
    "name:bul_x_preferred":[
        "\u041c\u0430\u0440\u0435\u0434\u0441\u043e\u0443\u0441"
    ],
    "name:cat_x_preferred":[
        "Maredsous"
    ],
    "name:dut_x_preferred":[
        "Maredsous"
    ],
    "name:eng_x_preferred":[
        "Maredsous"
    ],
    "name:fre_x_preferred":[
        "Maredsous"
    ],
    "name:ger_x_preferred":[
        "Maredsous"
    ],
    "name:rus_x_preferred":[
        "\u041c\u0430\u0440\u0435\u0434\u0441\u0443"
    ],
    "name:spa_x_preferred":[
        "Maredsous"
    ],
    "name:swe_x_preferred":[
        "Maredsous"
    ],
    "name:wln_x_preferred":[
        "Maredsou#Li bire di Maredsou"
    ],
    "qs_pg:aaroncc":"BE",
    "qs_pg:gn_country":"BE",
    "qs_pg:gn_fcode":"PPL",
    "qs_pg:gn_pop":200,
    "qs_pg:name":"Maredsous",
    "qs_pg:photos_9r":0,
    "qs_pg:photos_sr":0,
    "qs_pg:pop_sr":1,
    "qs_pg:qs_pg_placetype":"locality",
    "wof:name":"Maredsous",
    "wof:placetype":"locality",
    "wof:population":200
},
  "geometry": {"coordinates":[4.765,50.30776],"type":"Point"}
}