{
  "type": "Feature",
  "properties": {
    "gn:admin1_code":"VLG",
    "gn:admin2_code":"VBR",
    "gn:admin3_code":"23.0",
    "gn:admin4_code":"23077.0",
    "gn:asciiname":"Beisberg",
    "gn:country_code":"BE",
    "gn:dem":29,
    "gn:feature_class":"P",
    "gn:feature_code":"PPL",
    "gn:name":"Beisberg",
    "gn:population":0,
    "gn:timezone":"Europe/Brussels",
    "iso:country":"BE",
    "name:und_x_variant":[
        "Beysberg",
        "Beisberg"
    ],
    "wof:name":"Beisberg",
    "wof:placetype":"locality"
},
  "geometry": {"coordinates":[4.20941,50.78345],"type":"Point"}
}