{
  "type": "Feature",
  "properties": {
    "gn:gn_country":"BE",
    "gn:gn_fcode":"PPL",
    "gn:gn_pop":0,
    "iso:country":"BE",
    "name:deu_x_preferred":[
        "Eizeringen"
    ],
    "name:eng_x_preferred":[
        "Eizeringen"
    ],
    "name:fra_x_preferred":[
        "Eizeringen"
    ],
    "name:gle_x_preferred":[
        "Eizeringen"
    ],
    "name:nld_x_preferred":[
        "Eizeringen"
    ],
    "name:spa_x_preferred":[
        "Eizeringen"
    ],
    "name:unk_x_variant":[
        "Eyseringhen"
    ],
    "qs_pg:aaroncc":"BE",
    "qs_pg:gn_country":"BE",
    "qs_pg:gn_fcode":"PPL",
    "qs_pg:gn_pop":0,
    "qs_pg:name":"Eizeringen",
    "qs_pg:name_adm0":"Belgique",
    "qs_pg:name_adm1":"Vlaams Brabant",
    "qs_pg:photos_9r":0,
    "qs_pg:photos_sr":0,
    "qs_pg:pop_sr":0,
    "qs_pg:qs_pg_placetype":"locality",
    "qs_pg:qs_pg_placetype_gp":"Town",
    "qs_pg:woe_adm0":23424757,
    "woe:adm0_id":23424757,
    "woe:name_adm0":"Belgique",
    "woe:name_adm1":"Vlaams Brabant",
    "woe:placetype":"Town",
    "wof:name":"Eizeringen",
    "wof:placetype":"locality"
},
  "geometry": {"coordinates":[4.13695,50.83326],"type":"Point"}
}