{
  "type": "Feature",
  "properties": {
    "gn:admin1_code":"VLG",
    "gn:admin2_code":"VOV",
    "gn:admin3_code":"45.0",
    "gn:admin4_code":"45065.0",
    "gn:asciiname":"Zwartenbroek",
    "gn:country_code":"BE",
    "gn:dem":42,
    "gn:feature_class":"P",
    "gn:feature_code":"PPL",
    "gn:name":"Zwartenbroek",
    "gn:population":0,
    "gn:timezone":"Europe/Brussels",
    "iso:country":"BE",
    "wof:name":"Zwartenbroek",
    "wof:placetype":"locality"
},
  "geometry": {"coordinates":[3.73333,50.88333],"type":"Point"}
}