{
  "type": "Feature",
  "properties": {
    "gn:gn_country":"BE",
    "gn:gn_fcode":"PPL",
    "gn:gn_pop":0,
    "iso:country":"BE",
    "name:bre_x_preferred":[
        "Marche-les-Dames"
    ],
    "name:dut_x_preferred":[
        "Marche-les-Dames"
    ],
    "name:eng_x_preferred":[
        "Marche-les-Dames"
    ],
    "name:fre_x_preferred":[
        "Marche-les-Dames"
    ],
    "name:jpn_x_preferred":[
        "\u30de\u30eb\u30b7\u30e5\uff1d\u30ec\uff1d\u30c0\u30fc\u30e0"
    ],
    "name:ltz_x_preferred":[
        "Marche-les-Dames"
    ],
    "name:rum_x_preferred":[
        "Marche-les-Dames"
    ],
    "name:wln_x_preferred":[
        "M\u00e5tche-les-Dames"
    ],
    "qs_pg:aaroncc":"BE",
    "qs_pg:gn_country":"BE",
    "qs_pg:gn_fcode":"PPL",
    "qs_pg:gn_pop":0,
    "qs_pg:name":"Marche-les-Dames",
    "qs_pg:name_adm0":"Belgique",
    "qs_pg:name_adm1":"Namur",
    "qs_pg:photos":118,
    "qs_pg:photos_1k":24,
    "qs_pg:photos_9k":1,
    "qs_pg:photos_9r":3,
    "qs_pg:photos_all":118,
    "qs_pg:photos_sr":3,
    "qs_pg:pop_sr":0,
    "qs_pg:qs_pg_placetype":"locality",
    "qs_pg:qs_pg_placetype_gp":"Town",
    "qs_pg:woe_adm0":23424757,
    "woe:adm0_id":23424757,
    "woe:name_adm0":"Belgique",
    "woe:name_adm1":"Namur",
    "woe:placetype":"Town",
    "wof:name":"Marche-les-Dames",
    "wof:placetype":"locality"
},
  "geometry": {"coordinates":[4.95967,50.48585],"type":"Point"}
}