{
  "type": "Feature",
  "properties": {
    "gn:admin1_code":"VLG",
    "gn:admin2_code":"VWV",
    "gn:admin3_code":"32.0",
    "gn:admin4_code":"32003.0",
    "gn:asciiname":"Kalishoek",
    "gn:country_code":"BE",
    "gn:dem":6,
    "gn:feature_class":"P",
    "gn:feature_code":"PPL",
    "gn:name":"Kalishoek",
    "gn:population":0,
    "gn:timezone":"Europe/Brussels",
    "iso:country":"BE",
    "name:und_x_variant":[
        "Kaleshoek",
        "Kalishoek"
    ],
    "wof:name":"Kalishoek",
    "wof:placetype":"locality"
},
  "geometry": {"coordinates":[2.89008,51.06831],"type":"Point"}
}