{
  "type": "Feature",
  "properties": {
    "gn:admin1_code":"VLG",
    "gn:admin2_code":"VBR",
    "gn:admin3_code":"24.0",
    "gn:admin4_code":"24086.0",
    "gn:asciiname":"Prage",
    "gn:country_code":"BE",
    "gn:dem":51,
    "gn:feature_class":"P",
    "gn:feature_code":"PPL",
    "gn:name":"Prage",
    "gn:population":0,
    "gn:timezone":"Europe/Brussels",
    "iso:country":"BE",
    "name:und_x_variant":[
        "Praeghe",
        "Prage"
    ],
    "wof:name":"Prage",
    "wof:placetype":"locality"
},
  "geometry": {"coordinates":[4.67417,50.82361],"type":"Point"}
}