{
  "type": "Feature",
  "properties": {
    "gn:admin1_code":"VLG",
    "gn:admin2_code":"VBR",
    "gn:admin3_code":"24.0",
    "gn:admin4_code":"24014.0",
    "gn:asciiname":"Meerbeeksehoek",
    "gn:country_code":"BE",
    "gn:dem":8,
    "gn:feature_class":"P",
    "gn:feature_code":"PPL",
    "gn:name":"Meerbeeksehoek",
    "gn:population":0,
    "gn:timezone":"Europe/Brussels",
    "iso:country":"BE",
    "name:und_x_variant":[
        "Meerbeeksche Hoek",
        "Meerbeeksehoek"
    ],
    "wof:name":"Meerbeeksehoek",
    "wof:placetype":"locality"
},
  "geometry": {"coordinates":[4.55958,50.96767],"type":"Point"}
}