{
  "type": "Feature",
  "properties": {
    "gn:admin1_code":"WAL",
    "gn:admin2_code":"WHT",
    "gn:admin3_code":"53.0",
    "gn:admin4_code":"53014.0",
    "gn:asciiname":"Boussu Bois",
    "gn:cc2":"BE",
    "gn:country_code":"BE",
    "gn:dem":61,
    "gn:feature_class":"P",
    "gn:feature_code":"PPL",
    "gn:name":"Boussu Bois",
    "gn:population":0,
    "gn:timezone":"Europe/Brussels",
    "iso:country":"BE",
    "name:und_x_variant":[
        "Bois-de-Boussu"
    ],
    "wof:name":"Boussu Bois",
    "wof:placetype":"locality"
},
  "geometry": {"coordinates":[3.78822,50.41224],"type":"Point"}
}