{
  "type": "Feature",
  "properties": {
    "gn:admin1_code":"WAL",
    "gn:admin2_code":"WHT",
    "gn:admin3_code":"57.0",
    "gn:admin4_code":"57064.0",
    "gn:asciiname":"La Garenne",
    "gn:country_code":"BE",
    "gn:dem":48,
    "gn:feature_class":"P",
    "gn:feature_code":"PPL",
    "gn:name":"La Garenne",
    "gn:population":0,
    "gn:timezone":"Europe/Brussels",
    "iso:country":"BE",
    "name:fra_x_preferred":[
        "La Garenne"
    ],
    "name:swe_x_preferred":[
        "La Garenne"
    ],
    "wof:name":"La Garenne",
    "wof:placetype":"locality"
},
  "geometry": {"coordinates":[3.54206,50.51976],"type":"Point"}
}