{
  "type": "Feature",
  "properties": {
    "gn:admin1_code":"WAL",
    "gn:admin2_code":"WHT",
    "gn:admin3_code":"52.0",
    "gn:admin4_code":"52075.0",
    "gn:asciiname":"Wattimez",
    "gn:country_code":"BE",
    "gn:dem":157,
    "gn:feature_class":"P",
    "gn:feature_code":"PPL",
    "gn:name":"Wattimez",
    "gn:population":0,
    "gn:timezone":"Europe/Brussels",
    "iso:country":"BE",
    "wof:name":"Wattimez",
    "wof:placetype":"locality"
},
  "geometry": {"coordinates":[4.41808,50.55119000000001],"type":"Point"}
}