{
  "type": "Feature",
  "properties": {
    "gn:country":"BE",
    "gn:fcode":"PPL",
    "gn:population":0,
    "iso:country":"BE",
    "name:bre_x_preferred":[
        "Waardamme"
    ],
    "name:cat_x_preferred":[
        "Waardamme"
    ],
    "name:eng_x_preferred":[
        "Waardamme"
    ],
    "name:fra_x_preferred":[
        "Waardamme"
    ],
    "name:gle_x_preferred":[
        "Waardamme"
    ],
    "name:hun_x_preferred":[
        "Waardamme"
    ],
    "name:nld_x_preferred":[
        "Waardamme"
    ],
    "name:por_x_preferred":[
        "Waardamme"
    ],
    "name:und_x_variant":[
        "Waerdamme"
    ],
    "name:vls_x_preferred":[
        "Woardamme"
    ],
    "qs_pg:aaroncc":"BE",
    "qs_pg:gn_country":"BE",
    "qs_pg:gn_fcode":"PPL",
    "qs_pg:gn_pop":0,
    "qs_pg:name":"Waardamme",
    "qs_pg:name_adm0":"Belgique",
    "qs_pg:name_adm1":"West-Vlaanderen",
    "qs_pg:photos_9r":0,
    "qs_pg:photos_sr":0,
    "qs_pg:pop_sr":0,
    "qs_pg:qs_pg_placetype":"locality",
    "qs_pg:qs_pg_placetype_gp":"Town",
    "qs_pg:woe_adm0":23424757,
    "woe:adm0_id":23424757,
    "woe:name_adm0":"Belgique",
    "woe:name_adm1":"West-Vlaanderen",
    "woe:placetype":"Town",
    "wof:name":"Waardamme",
    "wof:placetype":"locality"
},
  "geometry": {"coordinates":[3.22288,51.11136],"type":"Point"}
}