{
  "type": "Feature",
  "properties": {
    "gn:admin1_code":"VLG",
    "gn:admin2_code":"VLI",
    "gn:admin3_code":"73.0",
    "gn:admin4_code":"73083.0",
    "gn:asciiname":"Kolmont",
    "gn:country_code":"BE",
    "gn:dem":104,
    "gn:feature_class":"P",
    "gn:feature_code":"PPL",
    "gn:name":"Kolmont",
    "gn:population":0,
    "gn:timezone":"Europe/Brussels",
    "iso:country":"BE",
    "name:und_x_variant":[
        "Tongeren (Kolmont)"
    ],
    "wof:name":"Kolmont",
    "wof:placetype":"locality"
},
  "geometry": {"coordinates":[5.42447,50.8042],"type":"Point"}
}