{
  "type": "Feature",
  "properties": {
    "iso:country":"BE",
    "name:bre_x_preferred":[
        "Jupille"
    ],
    "name:ceb_x_preferred":[
        "Jupille-sur-Meuse"
    ],
    "name:dan_x_preferred":[
        "Jupille-sur-Meuse"
    ],
    "name:deu_x_preferred":[
        "Jupille"
    ],
    "name:eng_x_preferred":[
        "Jupille-sur-Meuse"
    ],
    "name:epo_x_preferred":[
        "Jupille-sur-Meuse"
    ],
    "name:fra_x_preferred":[
        "Jupille"
    ],
    "name:fra_x_variant":[
        "Jupille-sur-Meuse"
    ],
    "name:hun_x_preferred":[
        "Jupille-sur-Meuse"
    ],
    "name:ita_x_preferred":[
        "Jupille-sur-Meuse"
    ],
    "name:jpn_x_preferred":[
        "\u30b8\u30e5\u30d4\u30e6\uff1d\u30b7\u30e5\u30eb\uff1d\u30e0\u30fc\u30ba"
    ],
    "name:lim_x_preferred":[
        "Jupille"
    ],
    "name:ltz_x_preferred":[
        "Jupille-sur-Meuse"
    ],
    "name:nld_x_preferred":[
        "Jupille-sur-Meuse"
    ],
    "name:slv_x_preferred":[
        "Jupille-sur-Meuse"
    ],
    "name:swe_x_preferred":[
        "Jupille-sur-Meuse"
    ],
    "name:und_x_variant":[
        "Li\u00e8ge (Jupille-sur-Meuse)"
    ],
    "name:vls_x_preferred":[
        "Hoogboom"
    ],
    "name:wln_x_preferred":[
        "Djoupeye"
    ],
    "qs:gn_adm0_cc":"BE",
    "qs:gn_fcode":"PPL",
    "qs:gn_local":2792413,
    "qs:gn_nam_loc":"Li\u00e8ge, Li\u00e8ge, Li\u00e8ge, BE",
    "qs:gn_namadm1":"WAL",
    "qs:gn_name":"Jupille-sur-Meuse",
    "qs:local_max":5890,
    "qs:local_sum":27074,
    "qs:localhoods":35,
    "qs:name":"Jupille",
    "qs:name_adm0":"Belgique",
    "qs:name_adm1":"Li\u00e8ge",
    "qs:name_adm2":"Li\u00e8ge",
    "qs:name_en":"Jupille-sur-Meuse",
    "qs:name_lau":"Li\u00e8ge",
    "qs:name_local":"Li\u00e8ge",
    "qs:photo_max":7,
    "qs:photo_sum":24,
    "qs:placetype":"Suburb",
    "qs:quad_count":7,
    "qs:woe_adm0":23424757,
    "qs:woe_adm1":7153300,
    "qs:woe_adm2":12591793,
    "qs:woe_lau":12602393,
    "qs:woe_local":973540,
    "qs:woe_ver":"7.10.0",
    "wof:lang":[
        "fre"
    ],
    "wof:name":"Jupille",
    "wof:placetype":"neighbourhood"
},
  "geometry": {"coordinates":[5.631914,50.650964],"type":"Point"}
}