{
  "type": "Feature",
  "properties": {
    "gn:admin1_code":"WAL",
    "gn:admin2_code":"WLX",
    "gn:admin3_code":"84.0",
    "gn:admin4_code":"84043.0",
    "gn:asciiname":"Hosseuse",
    "gn:country_code":"BE",
    "gn:dem":449,
    "gn:feature_class":"P",
    "gn:feature_code":"PPL",
    "gn:name":"Hosseuse",
    "gn:population":0,
    "gn:timezone":"Europe/Brussels",
    "iso:country":"BE",
    "wof:name":"Hosseuse",
    "wof:placetype":"locality"
},
  "geometry": {"coordinates":[5.41561,49.81667],"type":"Point"}
}