{
  "type": "Feature",
  "properties": {
    "gn:admin1_code":"VLG",
    "gn:admin2_code":"VOV",
    "gn:admin3_code":"43.0",
    "gn:admin4_code":"43002.0",
    "gn:asciiname":"Kapelle",
    "gn:country_code":"BE",
    "gn:dem":1,
    "gn:feature_class":"P",
    "gn:feature_code":"PPL",
    "gn:name":"Kapelle",
    "gn:population":0,
    "gn:timezone":"Europe/Brussels",
    "iso:country":"BE",
    "name:ara_x_preferred":[
        "\u0643\u0627\u0628\u064a\u0644\u0647"
    ],
    "name:bre_x_preferred":[
        "Kapelle"
    ],
    "name:deu_x_preferred":[
        "Kapelle"
    ],
    "name:eus_x_preferred":[
        "Kapelle"
    ],
    "name:fao_x_preferred":[
        "Kapelle"
    ],
    "name:fas_x_preferred":[
        "\u06a9\u0627\u067e\u0644\u0647"
    ],
    "name:fra_x_preferred":[
        "Kapelle"
    ],
    "name:fry_x_preferred":[
        "Kapelle"
    ],
    "name:gle_x_preferred":[
        "Kapelle"
    ],
    "name:glg_x_preferred":[
        "Kapelle"
    ],
    "name:ita_x_preferred":[
        "Kapelle"
    ],
    "name:lim_x_preferred":[
        "Kapelle"
    ],
    "name:nld_x_preferred":[
        "Kapelle"
    ],
    "name:pol_x_preferred":[
        "Kapelle"
    ],
    "name:ron_x_preferred":[
        "Kapelle"
    ],
    "name:rus_x_preferred":[
        "\u041a\u0430\u043f\u0435\u043b\u043b\u0435"
    ],
    "name:spa_x_preferred":[
        "Kapelle"
    ],
    "name:tur_x_preferred":[
        "Kapelle"
    ],
    "name:war_x_preferred":[
        "Kapelle"
    ],
    "name:zea_x_preferred":[
        "Kapelle"
    ],
    "name:zho_x_preferred":[
        "\u5361\u4f69\u52d2"
    ],
    "wof:name":"Kapelle",
    "wof:placetype":"locality"
},
  "geometry": {"coordinates":[3.73302,51.24667],"type":"Point"}
}