{
  "type": "Feature",
  "properties": {
    "gn:admin1_code":"VLG",
    "gn:admin2_code":"VOV",
    "gn:admin3_code":"42.0",
    "gn:admin4_code":"42025.0",
    "gn:asciiname":"Boskant",
    "gn:country_code":"BE",
    "gn:dem":11,
    "gn:feature_class":"P",
    "gn:feature_code":"PPL",
    "gn:name":"Boskant",
    "gn:population":0,
    "gn:timezone":"Europe/Brussels",
    "iso:country":"BE",
    "name:und_x_variant":[
        "Boschkant",
        "Boskant"
    ],
    "wof:name":"Boskant",
    "wof:placetype":"locality"
},
  "geometry": {"coordinates":[3.90619,50.99035],"type":"Point"}
}