{
  "type": "Feature",
  "properties": {
    "gn:admin1_code":"WAL",
    "gn:admin2_code":"WBR",
    "gn:admin3_code":"25.0",
    "gn:admin4_code":"25084.0",
    "gn:asciiname":"Warichet",
    "gn:country_code":"BE",
    "gn:dem":144,
    "gn:feature_class":"P",
    "gn:feature_code":"PPL",
    "gn:name":"Warichet",
    "gn:population":0,
    "gn:timezone":"Europe/Brussels",
    "iso:country":"BE",
    "name:und_x_variant":[
        "Le Warichet",
        "Warichet"
    ],
    "wof:name":"Warichet",
    "wof:placetype":"locality"
},
  "geometry": {"coordinates":[4.82614,50.62655],"type":"Point"}
}