{
  "type": "Feature",
  "properties": {
    "gn:admin1_code":"VLG",
    "gn:admin2_code":"VBR",
    "gn:admin3_code":"24.0",
    "gn:admin4_code":"24041.0",
    "gn:asciiname":"Elst",
    "gn:country_code":"BE",
    "gn:dem":66,
    "gn:feature_class":"P",
    "gn:feature_code":"PPL",
    "gn:name":"Elst",
    "gn:population":0,
    "gn:timezone":"Europe/Brussels",
    "iso:country":"BE",
    "wof:name":"Elst",
    "wof:placetype":"locality"
},
  "geometry": {"coordinates":[4.88849,50.76974000000001],"type":"Point"}
}