{
  "type": "Feature",
  "properties": {
    "gn:admin1_code":"WAL",
    "gn:admin2_code":"WHT",
    "gn:asciiname":"Geleitsbeek",
    "gn:country_code":"BE",
    "gn:dem":59,
    "gn:feature_class":"P",
    "gn:feature_code":"PPL",
    "gn:name":"Geleitsbeek",
    "gn:population":0,
    "gn:timezone":"Europe/Brussels",
    "iso:country":"BE",
    "name:und_x_variant":[
        "Geleijtsbeek",
        "Geleitsbeek"
    ],
    "wof:name":"Geleitsbeek",
    "wof:placetype":"locality"
},
  "geometry": {"coordinates":[4.33333,50.78333],"type":"Point"}
}