{
  "type": "Feature",
  "properties": {
    "gn:admin1_code":"WAL",
    "gn:admin2_code":"WHT",
    "gn:admin3_code":"52.0",
    "gn:admin4_code":"52015.0",
    "gn:asciiname":"Flechere",
    "gn:country_code":"BE",
    "gn:dem":151,
    "gn:feature_class":"P",
    "gn:feature_code":"PPL",
    "gn:name":"Fl\u00e9ch\u00e8re",
    "gn:population":0,
    "gn:timezone":"Europe/Brussels",
    "iso:country":"BE",
    "wof:name":"Flechere",
    "wof:placetype":"locality"
},
  "geometry": {"coordinates":[4.31018,50.49511],"type":"Point"}
}