{
  "type": "Feature",
  "properties": {
    "gn:admin1_code":"VLG",
    "gn:admin2_code":"VAN",
    "gn:admin3_code":"13.0",
    "gn:admin4_code":"13040.0",
    "gn:asciiname":"Winkel",
    "gn:country_code":"BE",
    "gn:dem":19,
    "gn:feature_class":"P",
    "gn:feature_code":"PPL",
    "gn:name":"Winkel",
    "gn:population":0,
    "gn:timezone":"Europe/Brussels",
    "iso:country":"BE",
    "name:als_x_preferred":[
        "Winkel"
    ],
    "name:bre_x_preferred":[
        "Winkel"
    ],
    "name:ceb_x_preferred":[
        "Winkel"
    ],
    "name:deu_x_preferred":[
        "Winkel"
    ],
    "name:epo_x_preferred":[
        "Winkel"
    ],
    "name:eus_x_preferred":[
        "Winkel"
    ],
    "name:fra_x_preferred":[
        "Winkel"
    ],
    "name:fry_x_preferred":[
        "Winkel"
    ],
    "name:ita_x_preferred":[
        "Winkel"
    ],
    "name:nds_x_preferred":[
        "Winkel"
    ],
    "name:nld_x_preferred":[
        "Winkel"
    ],
    "name:pol_x_preferred":[
        "Winkel"
    ],
    "name:por_x_preferred":[
        "Winkel"
    ],
    "name:rus_x_preferred":[
        "\u0412\u0438\u043d\u043a\u0435\u043b\u044c"
    ],
    "name:swe_x_preferred":[
        "Winkel"
    ],
    "name:vol_x_preferred":[
        "Winkel"
    ],
    "wof:name":"Winkel",
    "wof:placetype":"locality"
},
  "geometry": {"coordinates":[4.94766,51.27021],"type":"Point"}
}