{
  "type": "Feature",
  "properties": {
    "gn:admin1_code":"VLG",
    "gn:admin2_code":"VAN",
    "gn:admin3_code":"13.0",
    "gn:admin4_code":"13017.0",
    "gn:asciiname":"Ossen Goor",
    "gn:country_code":"BE",
    "gn:dem":16,
    "gn:feature_class":"P",
    "gn:feature_code":"PPL",
    "gn:name":"Ossen Goor",
    "gn:population":0,
    "gn:timezone":"Europe/Brussels",
    "iso:country":"BE",
    "wof:name":"Ossen Goor",
    "wof:placetype":"locality"
},
  "geometry": {"coordinates":[4.95026,51.22452],"type":"Point"}
}