{
  "type": "Feature",
  "properties": {
    "gn:admin1_code":"WAL",
    "gn:admin2_code":"WLG",
    "gn:admin3_code":"63.0",
    "gn:admin4_code":"63073.0",
    "gn:asciiname":"Beaumont",
    "gn:country_code":"BE",
    "gn:dem":390,
    "gn:feature_class":"P",
    "gn:feature_code":"PPL",
    "gn:name":"Beaumont",
    "gn:population":0,
    "gn:timezone":"Europe/Brussels",
    "iso:country":"BE",
    "wof:name":"Beaumont",
    "wof:placetype":"locality"
},
  "geometry": {"coordinates":[5.99538,50.37997],"type":"Point"}
}