{
  "type": "Feature",
  "properties": {
    "gn:admin1_code":"WAL",
    "gn:admin2_code":"WLG",
    "gn:admin3_code":"63.0",
    "gn:admin4_code":"63073.0",
    "gn:asciiname":"Beaumont",
    "gn:country_code":"BE",
    "gn:dem":390,
    "gn:feature_class":"P",
    "gn:feature_code":"PPL",
    "gn:name":"Beaumont",
    "gn:population":0,
    "gn:timezone":"Europe/Brussels",
    "iso:country":"BE",
    "name:bre_x_preferred":[
        "Beaumont"
    ],
    "name:cat_x_preferred":[
        "Beaumont"
    ],
    "name:ceb_x_preferred":[
        "Beaumont"
    ],
    "name:ces_x_preferred":[
        "Beaumont"
    ],
    "name:dan_x_preferred":[
        "Beaumont"
    ],
    "name:deu_x_preferred":[
        "Beaumont"
    ],
    "name:epo_x_preferred":[
        "Beaumont"
    ],
    "name:est_x_preferred":[
        "Beaumont"
    ],
    "name:fas_x_preferred":[
        "\u0628\u0648\u0645\u0648\u0646\u062a"
    ],
    "name:fin_x_preferred":[
        "Beaumont"
    ],
    "name:fra_x_preferred":[
        "Beaumont"
    ],
    "name:glg_x_preferred":[
        "Beaumont"
    ],
    "name:hun_x_preferred":[
        "Beaumont"
    ],
    "name:ita_x_preferred":[
        "Beaumont"
    ],
    "name:jpn_x_preferred":[
        "\u30dc\u30fc\u30e2\u30f3\u30c8"
    ],
    "name:kor_x_preferred":[
        "\ubcf4\ubaac\ud2b8"
    ],
    "name:lmo_x_preferred":[
        "Beaumont"
    ],
    "name:ltz_x_preferred":[
        "Beaumont"
    ],
    "name:nds_x_preferred":[
        "Beaumont"
    ],
    "name:nld_x_preferred":[
        "Beaumont"
    ],
    "name:nor_x_preferred":[
        "Beaumont"
    ],
    "name:oci_x_preferred":[
        "Beaumont"
    ],
    "name:pms_x_preferred":[
        "Beaumont"
    ],
    "name:pol_x_preferred":[
        "Beaumont"
    ],
    "name:por_x_preferred":[
        "Beaumont"
    ],
    "name:ron_x_preferred":[
        "Beaumont"
    ],
    "name:rus_x_preferred":[
        "\u0411\u043e\u043c\u043e\u043d\u0442"
    ],
    "name:slk_x_preferred":[
        "Beaumont"
    ],
    "name:slv_x_preferred":[
        "Beaumont"
    ],
    "name:spa_x_preferred":[
        "Beaumont"
    ],
    "name:srp_x_preferred":[
        "\u0411\u043e\u043c\u043e\u043d\u0442"
    ],
    "name:swe_x_preferred":[
        "Beaumont"
    ],
    "name:ukr_x_preferred":[
        "\u0411\u043e\u043c\u043e\u043d\u0442"
    ],
    "name:vol_x_preferred":[
        "Beaumont"
    ],
    "name:war_x_preferred":[
        "Beaumont"
    ],
    "name:zho_x_preferred":[
        "\u535a\u8499\u7279"
    ],
    "wof:name":"Beaumont",
    "wof:placetype":"locality"
},
  "geometry": {"coordinates":[5.99538,50.37997],"type":"Point"}
}