{
  "type": "Feature",
  "properties": {
    "gn:country":"BE",
    "gn:fcode":"PPL",
    "gn:population":0,
    "iso:country":"BE",
    "name:bre_x_preferred":[
        "Esen"
    ],
    "name:ceb_x_preferred":[
        "Esen"
    ],
    "name:eng_x_preferred":[
        "Esen"
    ],
    "name:epo_x_preferred":[
        "Esen"
    ],
    "name:fas_x_preferred":[
        "\u0627\u0633\u0646"
    ],
    "name:fra_x_preferred":[
        "Esen"
    ],
    "name:hun_x_preferred":[
        "Esen"
    ],
    "name:nld_x_preferred":[
        "Esen"
    ],
    "name:por_x_preferred":[
        "Esen"
    ],
    "name:swe_x_preferred":[
        "Esen"
    ],
    "name:und_x_variant":[
        "Eesen"
    ],
    "name:vls_x_preferred":[
        "\u00caesn"
    ],
    "qs_pg:aaroncc":"BE",
    "qs_pg:gn_country":"BE",
    "qs_pg:gn_fcode":"PPL",
    "qs_pg:gn_pop":0,
    "qs_pg:name":"Esen",
    "qs_pg:name_adm0":"Belgique",
    "qs_pg:name_adm1":"West-Vlaanderen",
    "qs_pg:photos_9k":1,
    "qs_pg:photos_9r":2,
    "qs_pg:photos_all":41,
    "qs_pg:photos_sr":0,
    "qs_pg:pop_sr":0,
    "qs_pg:qs_pg_placetype":"locality",
    "qs_pg:qs_pg_placetype_gp":"Town",
    "qs_pg:woe_adm0":23424757,
    "woe:adm0_id":23424757,
    "woe:name_adm0":"Belgique",
    "woe:name_adm1":"West-Vlaanderen",
    "woe:placetype":"Town",
    "wof:name":"Esen",
    "wof:placetype":"locality"
},
  "geometry": {"coordinates":[2.90189,51.0294],"type":"Point"}
}