{
  "type": "Feature",
  "properties": {
    "gn:admin1_code":"VLG",
    "gn:admin2_code":"VWV",
    "gn:admin3_code":"32.0",
    "gn:admin4_code":"32006.0",
    "gn:asciiname":"Luigem",
    "gn:country_code":"BE",
    "gn:dem":5,
    "gn:feature_class":"P",
    "gn:feature_code":"PPL",
    "gn:name":"Luigem",
    "gn:population":0,
    "gn:timezone":"Europe/Brussels",
    "iso:country":"BE",
    "name:und_x_variant":[
        "Luighem",
        "Luyghem",
        "Luigem"
    ],
    "wof:name":"Luigem",
    "wof:placetype":"locality"
},
  "geometry": {"coordinates":[2.83772,50.96306],"type":"Point"}
}