{
  "type": "Feature",
  "properties": {
    "gn:country":"BE",
    "gn:fcode":"PPL",
    "gn:population":3000,
    "iso:country":"BE",
    "qs_pg:aaroncc":"BE",
    "qs_pg:gn_country":"BE",
    "qs_pg:gn_fcode":"PPL",
    "qs_pg:gn_pop":3000,
    "qs_pg:name":"Perre",
    "qs_pg:photos_9r":0,
    "qs_pg:photos_sr":0,
    "qs_pg:pop_sr":4,
    "qs_pg:qs_pg_placetype":"locality",
    "wof:name":"Perre",
    "wof:placetype":"locality",
    "wof:population":3000
},
  "geometry": {"coordinates":[3.86098,50.88914],"type":"Point"}
}