{
  "type": "Feature",
  "properties": {
    "gn:admin1_code":"VLG",
    "gn:admin2_code":"VOV",
    "gn:admin3_code":"42.0",
    "gn:admin4_code":"42006.0",
    "gn:asciiname":"Hoeksken",
    "gn:country_code":"BE",
    "gn:dem":3,
    "gn:feature_class":"P",
    "gn:feature_code":"PPL",
    "gn:name":"Hoeksken",
    "gn:population":0,
    "gn:timezone":"Europe/Brussels",
    "iso:country":"BE",
    "wof:name":"Hoeksken",
    "wof:placetype":"locality"
},
  "geometry": {"coordinates":[4.06249,50.99559],"type":"Point"}
}