{
  "type": "Feature",
  "properties": {
    "gn:admin1_code":"WAL",
    "gn:admin2_code":"WHT",
    "gn:admin3_code":"51.0",
    "gn:admin4_code":"51009.0",
    "gn:asciiname":"Le Petit Crepin",
    "gn:country_code":"BE",
    "gn:dem":25,
    "gn:feature_class":"P",
    "gn:feature_code":"PPL",
    "gn:name":"Le Petit Cr\u00e9pin",
    "gn:population":0,
    "gn:timezone":"Europe/Brussels",
    "iso:country":"BE",
    "wof:name":"Le Petit Crepin",
    "wof:placetype":"locality"
},
  "geometry": {"coordinates":[3.71667,50.45],"type":"Point"}
}