{
  "type": "Feature",
  "properties": {
    "gn:admin1_code":"WAL",
    "gn:admin2_code":"WLX",
    "gn:admin3_code":"83.0",
    "gn:admin4_code":"83034.0",
    "gn:asciiname":"Hollogne",
    "gn:country_code":"BE",
    "gn:dem":306,
    "gn:feature_class":"P",
    "gn:feature_code":"PPL",
    "gn:name":"Hollogne",
    "gn:population":0,
    "gn:timezone":"Europe/Brussels",
    "iso:country":"BE",
    "name:und_x_variant":[
        "Hologne",
        "Hollogne"
    ],
    "wof:name":"Hollogne",
    "wof:placetype":"locality"
},
  "geometry": {"coordinates":[5.35793,50.21428],"type":"Point"}
}