{
  "type": "Feature",
  "properties": {
    "gn:admin1_code":"WAL",
    "gn:admin2_code":"WLX",
    "gn:admin3_code":"85.0",
    "gn:admin4_code":"85039.0",
    "gn:asciiname":"Lahage",
    "gn:country_code":"BE",
    "gn:dem":329,
    "gn:feature_class":"P",
    "gn:feature_code":"PPL",
    "gn:name":"Lahage",
    "gn:population":0,
    "gn:timezone":"Europe/Brussels",
    "iso:country":"BE",
    "name:arg_x_preferred":[
        "La Haja"
    ],
    "name:bug_x_preferred":[
        "Lahage"
    ],
    "name:cat_x_preferred":[
        "La Haja"
    ],
    "name:ceb_x_preferred":[
        "Lahage"
    ],
    "name:deu_x_preferred":[
        "Lahage"
    ],
    "name:eus_x_preferred":[
        "Lahage"
    ],
    "name:fra_x_preferred":[
        "Lahage"
    ],
    "name:hun_x_preferred":[
        "Lahage"
    ],
    "name:ita_x_preferred":[
        "Lahage"
    ],
    "name:lat_x_preferred":[
        "Lahage"
    ],
    "name:msa_x_preferred":[
        "Lahage"
    ],
    "name:nld_x_preferred":[
        "Lahage"
    ],
    "name:oci_x_preferred":[
        "La Haja"
    ],
    "name:pol_x_preferred":[
        "Lahage"
    ],
    "name:ron_x_preferred":[
        "Lahage"
    ],
    "name:rus_x_preferred":[
        "\u041b\u0430\u0430\u0436"
    ],
    "name:slk_x_preferred":[
        "Lahage"
    ],
    "name:spa_x_preferred":[
        "Lahage"
    ],
    "name:swe_x_preferred":[
        "Lahage"
    ],
    "name:ukr_x_preferred":[
        "\u041b\u0430\u0430\u0436"
    ],
    "name:urd_x_preferred":[
        "\u0644\u0627\u06c1\u0627\u06af\u06cc"
    ],
    "name:vie_x_preferred":[
        "Lahage"
    ],
    "name:vol_x_preferred":[
        "Lahage"
    ],
    "name:war_x_preferred":[
        "Lahage"
    ],
    "name:zho_x_preferred":[
        "\u62c9\u963f\u65e5"
    ],
    "wof:name":"Lahage",
    "wof:placetype":"locality"
},
  "geometry": {"coordinates":[5.50068,49.64557],"type":"Point"}
}