{
  "type": "Feature",
  "properties": {
    "gn:admin1_code":"WAL",
    "gn:admin2_code":"WLX",
    "gn:admin3_code":"85.0",
    "gn:admin4_code":"85039.0",
    "gn:asciiname":"Lahage",
    "gn:country_code":"BE",
    "gn:dem":329,
    "gn:feature_class":"P",
    "gn:feature_code":"PPL",
    "gn:name":"Lahage",
    "gn:population":0,
    "gn:timezone":"Europe/Brussels",
    "iso:country":"BE",
    "wof:name":"Lahage",
    "wof:placetype":"locality"
},
  "geometry": {"coordinates":[5.50068,49.64557],"type":"Point"}
}