{
  "type": "Feature",
  "properties": {
    "gn:country":"BE",
    "gn:fcode":"PPL",
    "gn:population":0,
    "iso:country":"BE",
    "name:bre_x_preferred":[
        "Temploux"
    ],
    "name:cat_x_preferred":[
        "Temploux"
    ],
    "name:ces_x_preferred":[
        "Temploux"
    ],
    "name:cos_x_preferred":[
        "Temploux"
    ],
    "name:cym_x_preferred":[
        "Temploux"
    ],
    "name:dan_x_preferred":[
        "Temploux"
    ],
    "name:deu_x_preferred":[
        "Temploux"
    ],
    "name:eng_x_preferred":[
        "Temploux"
    ],
    "name:est_x_preferred":[
        "Temploux"
    ],
    "name:fin_x_preferred":[
        "Temploux"
    ],
    "name:fra_x_preferred":[
        "Temploux"
    ],
    "name:gle_x_preferred":[
        "Temploux"
    ],
    "name:glg_x_preferred":[
        "Temploux"
    ],
    "name:hrv_x_preferred":[
        "Temploux"
    ],
    "name:hun_x_preferred":[
        "Temploux"
    ],
    "name:ind_x_preferred":[
        "Temploux"
    ],
    "name:ita_x_preferred":[
        "Temploux"
    ],
    "name:lav_x_preferred":[
        "Temploux"
    ],
    "name:lit_x_preferred":[
        "Temploux"
    ],
    "name:ltz_x_preferred":[
        "Temploux"
    ],
    "name:nld_x_preferred":[
        "Temploux"
    ],
    "name:nrm_x_preferred":[
        "Temploux"
    ],
    "name:oci_x_preferred":[
        "Temploux"
    ],
    "name:pol_x_preferred":[
        "Temploux"
    ],
    "name:por_x_preferred":[
        "Temploux"
    ],
    "name:ron_x_preferred":[
        "Temploux"
    ],
    "name:slk_x_preferred":[
        "Temploux"
    ],
    "name:slv_x_preferred":[
        "Temploux"
    ],
    "name:spa_x_preferred":[
        "Temploux"
    ],
    "name:swe_x_preferred":[
        "Temploux"
    ],
    "name:tah_x_preferred":[
        "Temploux"
    ],
    "name:tur_x_preferred":[
        "Temploux"
    ],
    "name:und_x_variant":[
        "Namur (Temploux)"
    ],
    "name:wln_x_preferred":[
        "Timplou"
    ],
    "qs_pg:aaroncc":"BE",
    "qs_pg:gn_country":"BE",
    "qs_pg:gn_fcode":"PPL",
    "qs_pg:gn_pop":0,
    "qs_pg:name":"Temploux",
    "qs_pg:name_adm0":"Belgique",
    "qs_pg:name_adm1":"Namur",
    "qs_pg:photos":153,
    "qs_pg:photos_1k":31,
    "qs_pg:photos_9k":1,
    "qs_pg:photos_9r":4,
    "qs_pg:photos_all":153,
    "qs_pg:photos_sr":4,
    "qs_pg:pop_sr":0,
    "qs_pg:qs_pg_placetype":"locality",
    "qs_pg:qs_pg_placetype_gp":"Town",
    "qs_pg:woe_adm0":23424757,
    "woe:adm0_id":23424757,
    "woe:name_adm0":"Belgique",
    "woe:name_adm1":"Namur",
    "woe:placetype":"Town",
    "wof:name":"Temploux",
    "wof:placetype":"locality"
},
  "geometry": {"coordinates":[4.75468,50.48558],"type":"Point"}
}