{
  "type": "Feature",
  "properties": {
    "gn:admin1_code":"VLG",
    "gn:admin2_code":"VOV",
    "gn:admin3_code":"41.0",
    "gn:admin4_code":"41048.0",
    "gn:asciiname":"Zevenhoek",
    "gn:country_code":"BE",
    "gn:dem":28,
    "gn:feature_class":"P",
    "gn:feature_code":"PPL",
    "gn:name":"Zevenhoek",
    "gn:population":0,
    "gn:timezone":"Europe/Brussels",
    "iso:country":"BE",
    "wof:name":"Zevenhoek",
    "wof:placetype":"locality"
},
  "geometry": {"coordinates":[3.95,50.81667],"type":"Point"}
}