{
  "type": "Feature",
  "properties": {
    "gn:admin1_code":"VLG",
    "gn:admin2_code":"VAN",
    "gn:admin3_code":"13.0",
    "gn:admin4_code":"13019.0",
    "gn:asciiname":"Zandhoven Heide",
    "gn:country_code":"BE",
    "gn:dem":17,
    "gn:feature_class":"P",
    "gn:feature_code":"PPL",
    "gn:name":"Zandhoven Heide",
    "gn:population":0,
    "gn:timezone":"Europe/Brussels",
    "iso:country":"BE",
    "name:und_x_variant":[
        "Sandhoeven-heiden",
        "Zandhoeven",
        "Zandhoven Heide"
    ],
    "wof:name":"Zandhoven Heide",
    "wof:placetype":"locality"
},
  "geometry": {"coordinates":[4.86442,51.25443],"type":"Point"}
}