{
  "type": "Feature",
  "properties": {
    "gn:admin1_code":"VLG",
    "gn:admin2_code":"VAN",
    "gn:admin3_code":"13.0",
    "gn:admin4_code":"13053.0",
    "gn:asciiname":"Heikant",
    "gn:country_code":"BE",
    "gn:dem":16,
    "gn:feature_class":"P",
    "gn:feature_code":"PPL",
    "gn:name":"Heikant",
    "gn:population":0,
    "gn:timezone":"Europe/Brussels",
    "iso:country":"BE",
    "name:fra_x_preferred":[
        "Heikant"
    ],
    "name:nld_x_preferred":[
        "Heikant"
    ],
    "name:por_x_preferred":[
        "Heikant"
    ],
    "name:spa_x_preferred":[
        "Heikant"
    ],
    "wof:name":"Heikant",
    "wof:placetype":"locality"
},
  "geometry": {"coordinates":[5.00119,51.10959],"type":"Point"}
}