{
  "type": "Feature",
  "properties": {
    "gn:admin1_code":"VLG",
    "gn:admin2_code":"VWV",
    "gn:admin3_code":"34.0",
    "gn:admin4_code":"34042.0",
    "gn:asciiname":"Klijte",
    "gn:country_code":"BE",
    "gn:dem":27,
    "gn:feature_class":"P",
    "gn:feature_code":"PPL",
    "gn:name":"Klijte",
    "gn:population":0,
    "gn:timezone":"Europe/Brussels",
    "iso:country":"BE",
    "name:und_x_variant":[
        "Klyte",
        "Klijtte",
        "Klytte",
        "Klijte"
    ],
    "wof:name":"Klijte",
    "wof:placetype":"locality"
},
  "geometry": {"coordinates":[3.38611,50.77947],"type":"Point"}
}