{
  "type": "Feature",
  "properties": {
    "gn:admin1_code":"VLG",
    "gn:admin2_code":"VOV",
    "gn:admin3_code":"44.0",
    "gn:admin4_code":"44011.0",
    "gn:asciiname":"Muizenhol",
    "gn:country_code":"BE",
    "gn:dem":8,
    "gn:feature_class":"P",
    "gn:feature_code":"PPL",
    "gn:name":"Muizenhol",
    "gn:population":0,
    "gn:timezone":"Europe/Brussels",
    "iso:country":"BE",
    "wof:name":"Muizenhol",
    "wof:placetype":"locality"
},
  "geometry": {"coordinates":[3.58841,50.98383],"type":"Point"}
}