{
  "type": "Feature",
  "properties": {
    "gn:admin1_code":"VLG",
    "gn:admin2_code":"VAN",
    "gn:admin3_code":"13.0",
    "gn:admin4_code":"13035.0",
    "gn:asciiname":"Kleine Vond",
    "gn:country_code":"BE",
    "gn:dem":30,
    "gn:feature_class":"P",
    "gn:feature_code":"PPL",
    "gn:name":"Kleine Vond",
    "gn:population":0,
    "gn:timezone":"Europe/Brussels",
    "iso:country":"BE",
    "wof:name":"Kleine Vond",
    "wof:placetype":"locality"
},
  "geometry": {"coordinates":[5.03333,51.43333],"type":"Point"}
}