{
  "type": "Feature",
  "properties": {
    "gn:admin1_code":"VLG",
    "gn:admin2_code":"VWV",
    "gn:admin3_code":"32.0",
    "gn:admin4_code":"32030.0",
    "gn:asciiname":"Gapaardhoek",
    "gn:country_code":"BE",
    "gn:dem":7,
    "gn:feature_class":"P",
    "gn:feature_code":"PPL",
    "gn:name":"Gapaardhoek",
    "gn:population":0,
    "gn:timezone":"Europe/Brussels",
    "iso:country":"BE",
    "name:und_x_variant":[
        "Capaardhoek",
        "Gapaardhoek"
    ],
    "wof:name":"Gapaardhoek",
    "wof:placetype":"locality"
},
  "geometry": {"coordinates":[2.69907,50.97052],"type":"Point"}
}