{
  "type": "Feature",
  "properties": {
    "gn:admin1_code":"VLG",
    "gn:admin2_code":"VBR",
    "gn:admin3_code":"23.0",
    "gn:admin4_code":"23050.0",
    "gn:asciiname":"Nerom",
    "gn:country_code":"BE",
    "gn:dem":14,
    "gn:feature_class":"P",
    "gn:feature_code":"PPL",
    "gn:name":"Nerom",
    "gn:population":0,
    "gn:timezone":"Europe/Brussels",
    "iso:country":"BE",
    "wof:name":"Nerom",
    "wof:placetype":"locality"
},
  "geometry": {"coordinates":[4.33342,50.97826],"type":"Point"}
}