{
  "type": "Feature",
  "properties": {
    "gn:admin1_code":"WAL",
    "gn:admin2_code":"WHT",
    "gn:admin3_code":"52.0",
    "gn:admin4_code":"52022.0",
    "gn:asciiname":"Trieux",
    "gn:country_code":"BE",
    "gn:dem":175,
    "gn:feature_class":"P",
    "gn:feature_code":"PPL",
    "gn:name":"Trieux",
    "gn:population":0,
    "gn:timezone":"Europe/Brussels",
    "iso:country":"BE",
    "wof:name":"Trieux",
    "wof:placetype":"locality"
},
  "geometry": {"coordinates":[4.3267,50.42639000000001],"type":"Point"}
}