{
  "type": "Feature",
  "properties": {
    "gn:admin1_code":"VLG",
    "gn:admin2_code":"VLI",
    "gn:admin3_code":"72.0",
    "gn:admin4_code":"72021.0",
    "gn:asciiname":"Roesterberg",
    "gn:country_code":"BE",
    "gn:dem":53,
    "gn:feature_class":"P",
    "gn:feature_code":"PPL",
    "gn:name":"Roesterberg",
    "gn:population":0,
    "gn:timezone":"Europe/Brussels",
    "iso:country":"BE",
    "name:und_x_variant":[
        "Roosterberg",
        "Roesterberg"
    ],
    "wof:name":"Roesterberg",
    "wof:placetype":"locality"
},
  "geometry": {"coordinates":[5.66167,51.08066],"type":"Point"}
}