{
  "type": "Feature",
  "properties": {
    "gn:admin1_code":"WAL",
    "gn:admin2_code":"WHT",
    "gn:admin3_code":"52.0",
    "gn:admin4_code":"52011.0",
    "gn:asciiname":"Fontery",
    "gn:country_code":"BE",
    "gn:dem":181,
    "gn:feature_class":"P",
    "gn:feature_code":"PPL",
    "gn:name":"Fontery",
    "gn:population":0,
    "gn:timezone":"Europe/Brussels",
    "iso:country":"BE",
    "wof:name":"Fontery",
    "wof:placetype":"locality"
},
  "geometry": {"coordinates":[4.47228,50.46055],"type":"Point"}
}