{
  "type": "Feature",
  "properties": {
    "gn:admin1_code":"WAL",
    "gn:admin2_code":"WNA",
    "gn:admin3_code":"91.0",
    "gn:admin4_code":"91005.0",
    "gn:asciiname":"Warnant",
    "gn:country_code":"BE",
    "gn:dem":116,
    "gn:feature_class":"P",
    "gn:feature_code":"PPL",
    "gn:name":"Warnant",
    "gn:population":0,
    "gn:timezone":"Europe/Brussels",
    "iso:country":"BE",
    "name:ceb_x_preferred":[
        "Warnant"
    ],
    "name:fra_x_preferred":[
        "Warnant"
    ],
    "name:nld_x_preferred":[
        "Warnant"
    ],
    "name:und_x_variant":[
        "Anh\u00e9e (Warnant)"
    ],
    "name:wln_x_preferred":[
        "Warnin"
    ],
    "wof:name":"Warnant",
    "wof:placetype":"locality"
},
  "geometry": {"coordinates":[4.84274,50.32327],"type":"Point"}
}