{
  "type": "Feature",
  "properties": {
    "gn:gn_country":"BE",
    "gn:gn_fcode":"PPL",
    "gn:gn_pop":0,
    "iso:country":"BE",
    "name:dut_x_preferred":[
        "Hever"
    ],
    "name:eng_x_preferred":[
        "Hever"
    ],
    "name:fre_x_preferred":[
        "Hever"
    ],
    "name:hun_x_preferred":[
        "Hever"
    ],
    "name:rus_x_preferred":[
        "\u0425\u0438\u0432\u0435\u0440"
    ],
    "name:swe_x_preferred":[
        "Hever"
    ],
    "name:unk_x_variant":[
        "Boortmeerbeek (Hever)"
    ],
    "qs_pg:aaroncc":"BE",
    "qs_pg:gn_country":"BE",
    "qs_pg:gn_fcode":"PPL",
    "qs_pg:gn_pop":0,
    "qs_pg:name":"Hever",
    "qs_pg:name_adm0":"Belgique",
    "qs_pg:name_adm1":"Vlaams Brabant",
    "qs_pg:photos":88,
    "qs_pg:photos_1k":18,
    "qs_pg:photos_9k":1,
    "qs_pg:photos_9r":3,
    "qs_pg:photos_all":88,
    "qs_pg:photos_sr":3,
    "qs_pg:pop_sr":0,
    "qs_pg:qs_pg_placetype":"locality",
    "qs_pg:qs_pg_placetype_gp":"Town",
    "qs_pg:woe_adm0":23424757,
    "woe:adm0_id":23424757,
    "woe:name_adm0":"Belgique",
    "woe:name_adm1":"Vlaams Brabant",
    "woe:placetype":"Town",
    "wof:name":"Hever",
    "wof:placetype":"locality"
},
  "geometry": {"coordinates":[4.55126,50.99545],"type":"Point"}
}