{
  "type": "Feature",
  "properties": {
    "gn:admin1_code":"WAL",
    "gn:admin2_code":"WHT",
    "gn:asciiname":"Romont",
    "gn:country_code":"BE",
    "gn:dem":65,
    "gn:feature_class":"P",
    "gn:feature_code":"PPL",
    "gn:name":"Romont",
    "gn:population":0,
    "gn:timezone":"Europe/Brussels",
    "iso:country":"BE",
    "name:als_x_preferred":[
        "Romont"
    ],
    "name:cat_x_preferred":[
        "Romont"
    ],
    "name:deu_x_preferred":[
        "Romont"
    ],
    "name:epo_x_preferred":[
        "Romont"
    ],
    "name:eus_x_preferred":[
        "Romont"
    ],
    "name:fas_x_preferred":[
        "\u0631\u0648\u0645\u0648\u0646"
    ],
    "name:fra_x_preferred":[
        "Romont"
    ],
    "name:ita_x_preferred":[
        "Romont"
    ],
    "name:lat_x_preferred":[
        "Rotundus Mons"
    ],
    "name:lmo_x_preferred":[
        "Romont"
    ],
    "name:msa_x_preferred":[
        "Romont"
    ],
    "name:nld_x_preferred":[
        "Romont"
    ],
    "name:pol_x_preferred":[
        "Romont"
    ],
    "name:por_x_preferred":[
        "Romont"
    ],
    "name:roh_x_preferred":[
        "Romont"
    ],
    "name:spa_x_preferred":[
        "Romont"
    ],
    "name:sqi_x_preferred":[
        "Romont"
    ],
    "name:swe_x_preferred":[
        "Romont"
    ],
    "name:vol_x_preferred":[
        "Romont"
    ],
    "name:war_x_preferred":[
        "Romont"
    ],
    "name:zho_x_preferred":[
        "\u7f85\u8499"
    ],
    "wof:name":"Romont",
    "wof:placetype":"locality"
},
  "geometry": {"coordinates":[3.93825,50.69409],"type":"Point"}
}