{
  "type": "Feature",
  "properties": {
    "gn:admin1_code":"WAL",
    "gn:admin2_code":"WLX",
    "gn:admin3_code":"83.0",
    "gn:admin4_code":"83049.0",
    "gn:asciiname":"Grinchamps",
    "gn:country_code":"BE",
    "gn:dem":380,
    "gn:feature_class":"P",
    "gn:feature_code":"PPL",
    "gn:name":"Grinchamps",
    "gn:population":0,
    "gn:timezone":"Europe/Brussels",
    "iso:country":"BE",
    "wof:name":"Grinchamps",
    "wof:placetype":"locality"
},
  "geometry": {"coordinates":[5.52195,50.12836],"type":"Point"}
}