{
  "type": "Feature",
  "properties": {
    "gn:admin1_code":"WAL",
    "gn:admin2_code":"WLG",
    "gn:admin3_code":"62.0",
    "gn:admin4_code":"62026.0",
    "gn:asciiname":"Hoyemont",
    "gn:country_code":"BE",
    "gn:dem":292,
    "gn:feature_class":"P",
    "gn:feature_code":"PPL",
    "gn:name":"Hoyemont",
    "gn:population":0,
    "gn:timezone":"Europe/Brussels",
    "iso:country":"BE",
    "wof:name":"Hoyemont",
    "wof:placetype":"locality"
},
  "geometry": {"coordinates":[5.61728,50.46783],"type":"Point"}
}