{
  "type": "Feature",
  "properties": {
    "gn:admin1_code":"WAL",
    "gn:admin2_code":"WLX",
    "gn:admin3_code":"84.0",
    "gn:admin4_code":"84010.0",
    "gn:asciiname":"Merleux Han",
    "gn:country_code":"BE",
    "gn:dem":276,
    "gn:feature_class":"P",
    "gn:feature_code":"PPL",
    "gn:name":"Merleux Han",
    "gn:population":0,
    "gn:timezone":"Europe/Brussels",
    "iso:country":"BE",
    "wof:name":"Merleux Han",
    "wof:placetype":"locality"
},
  "geometry": {"coordinates":[5.01667,49.83333],"type":"Point"}
}