{
  "type": "Feature",
  "properties": {
    "gn:admin1_code":"WAL",
    "gn:admin2_code":"WLX",
    "gn:asciiname":"Bellain",
    "gn:country_code":"BE",
    "gn:dem":499,
    "gn:feature_class":"P",
    "gn:feature_code":"PPL",
    "gn:name":"Bellain",
    "gn:population":0,
    "gn:timezone":"Europe/Brussels",
    "iso:country":"BE",
    "wof:name":"Bellain",
    "wof:placetype":"locality"
},
  "geometry": {"coordinates":[5.96667,50.16667],"type":"Point"}
}