{
  "type": "Feature",
  "properties": {
    "gn:admin1_code":"VLG",
    "gn:admin2_code":"VOV",
    "gn:admin3_code":"41.0",
    "gn:admin4_code":"41063.0",
    "gn:asciiname":"Leeg Kouter",
    "gn:country_code":"BE",
    "gn:dem":36,
    "gn:feature_class":"P",
    "gn:feature_code":"PPL",
    "gn:name":"Leeg Kouter",
    "gn:population":0,
    "gn:timezone":"Europe/Brussels",
    "iso:country":"BE",
    "name:und_x_variant":[
        "Leeg-Kauter",
        "Leeg Kouter"
    ],
    "wof:name":"Leeg Kouter",
    "wof:placetype":"locality"
},
  "geometry": {"coordinates":[3.88333,50.93333],"type":"Point"}
}