{
  "type": "Feature",
  "properties": {
    "gn:admin1_code":"WAL",
    "gn:admin2_code":"WHT",
    "gn:asciiname":"Zibbeek",
    "gn:country_code":"BE",
    "gn:dem":40,
    "gn:feature_class":"P",
    "gn:feature_code":"PPL",
    "gn:name":"Zibbeek",
    "gn:population":0,
    "gn:timezone":"Europe/Brussels",
    "iso:country":"BE",
    "wof:name":"Zibbeek",
    "wof:placetype":"locality"
},
  "geometry": {"coordinates":[4.21667,50.85],"type":"Point"}
}