{
  "type": "Feature",
  "properties": {
    "gn:admin1_code":"WAL",
    "gn:admin2_code":"WLX",
    "gn:admin3_code":"85.0",
    "gn:admin4_code":"85045.0",
    "gn:asciiname":"Latour",
    "gn:country_code":"BE",
    "gn:dem":217,
    "gn:feature_class":"P",
    "gn:feature_code":"PPL",
    "gn:name":"Latour",
    "gn:population":0,
    "gn:timezone":"Europe/Brussels",
    "iso:country":"BE",
    "name:deu_x_preferred":[
        "Latour"
    ],
    "name:epo_x_preferred":[
        "Latour"
    ],
    "name:fra_x_preferred":[
        "Latour"
    ],
    "name:ltz_x_preferred":[
        "Latour"
    ],
    "name:nld_x_preferred":[
        "Latour"
    ],
    "name:slk_x_preferred":[
        "Latour"
    ],
    "name:swe_x_preferred":[
        "Latour"
    ],
    "wof:name":"Latour",
    "wof:placetype":"locality"
},
  "geometry": {"coordinates":[5.57065,49.55736],"type":"Point"}
}