{
  "type": "Feature",
  "properties": {
    "iso:country":"BE",
    "name:dut_x_preferred":[
        "Ekkergem"
    ],
    "name:eng_x_preferred":[
        "Ekkergem"
    ],
    "qs:local_max":6077,
    "qs:local_sum":36126,
    "qs:localhoods":17,
    "qs:name":"Ekkergem",
    "qs:name_adm0":"Belgique",
    "qs:name_adm1":"Oost-Vlaanderen",
    "qs:name_adm2":"Gent",
    "qs:name_lau":"Gent",
    "qs:name_local":"Gent",
    "qs:photo_max":640,
    "qs:photo_sum":2965,
    "qs:placetype":"Suburb",
    "qs:quad_count":64,
    "qs:woe_adm0":23424757,
    "qs:woe_adm1":7153304,
    "qs:woe_adm2":12591774,
    "qs:woe_lau":12602289,
    "qs:woe_local":970013,
    "qs:woe_ver":"7.10.0",
    "wof:lang":[
        "dut"
    ],
    "wof:name":"Ekkergem",
    "wof:placetype":"neighbourhood"
},
  "geometry": {"coordinates":[3.716889,51.047003],"type":"Point"}
}