{
  "type": "Feature",
  "properties": {
    "gn:admin1_code":"WAL",
    "gn:admin2_code":"WLG",
    "gn:admin3_code":"62.0",
    "gn:admin4_code":"62060.0",
    "gn:asciiname":"Dalle",
    "gn:country_code":"BE",
    "gn:dem":135,
    "gn:feature_class":"P",
    "gn:feature_code":"PPL",
    "gn:name":"Dalle",
    "gn:population":0,
    "gn:timezone":"Europe/Brussels",
    "iso:country":"BE",
    "wof:name":"Dalle",
    "wof:placetype":"locality"
},
  "geometry": {"coordinates":[5.55007,50.74031],"type":"Point"}
}