{
  "type": "Feature",
  "properties": {
    "gn:admin1_code":"VLG",
    "gn:admin2_code":"VLI",
    "gn:admin3_code":"71.0",
    "gn:admin4_code":"71067.0",
    "gn:asciiname":"Besmer",
    "gn:country_code":"BE",
    "gn:dem":96,
    "gn:feature_class":"P",
    "gn:feature_code":"PPL",
    "gn:name":"Besmer",
    "gn:population":0,
    "gn:timezone":"Europe/Brussels",
    "iso:country":"BE",
    "name:und_x_variant":[
        "Bessemer",
        "Besmer"
    ],
    "wof:name":"Besmer",
    "wof:placetype":"locality"
},
  "geometry": {"coordinates":[5.6038,50.92441],"type":"Point"}
}