{
  "type": "Feature",
  "properties": {
    "gn:admin1_code":"VLG",
    "gn:admin2_code":"VAN",
    "gn:admin3_code":"11.0",
    "gn:admin4_code":"11018.0",
    "gn:asciiname":"Kallebeek",
    "gn:country_code":"BE",
    "gn:dem":18,
    "gn:feature_class":"P",
    "gn:feature_code":"PPL",
    "gn:name":"Kallebeek",
    "gn:population":0,
    "gn:timezone":"Europe/Brussels",
    "iso:country":"BE",
    "name:und_x_variant":[
        "Callebeek",
        "Kallebeek"
    ],
    "wof:name":"Kallebeek",
    "wof:placetype":"locality"
},
  "geometry": {"coordinates":[4.33837,51.14232],"type":"Point"}
}