{
  "type": "Feature",
  "properties": {
    "iso:country":"BE",
    "name:eng_x_preferred":[
        "Mutsaard"
    ],
    "name:fra_x_preferred":[
        "Mutsaard"
    ],
    "name:fre_x_variant":[
        "quartier De Wand",
        "quartier de la tour japonaise",
        "quartier des Pagodes"
    ],
    "name:nld_x_preferred":[
        "Mutsaard"
    ],
    "name:nld_x_variant":[
        "De Wand"
    ],
    "wof:name":"Mutsaard",
    "wof:placetype":"neighbourhood"
},
  "geometry": {"coordinates":[4.36124734252363,50.89848273864309],"type":"Point"}
}