{
  "type": "Feature",
  "properties": {
    "iso:country":"BE",
    "name:deu_x_preferred":[
        "Mutsaard"
    ],
    "name:eng_x_preferred":[
        "Mutsaard"
    ],
    "name:fra_x_preferred":[
        "Mutsaard"
    ],
    "name:fre_x_variant":[
        "quartier De Wand",
        "quartier de la tour japonaise",
        "quartier des Pagodes"
    ],
    "name:lat_x_preferred":[
        "Mutsaard"
    ],
    "name:lim_x_preferred":[
        "Mutsaard"
    ],
    "name:nld_x_preferred":[
        "Mutsaard"
    ],
    "name:nld_x_variant":[
        "De Wand"
    ],
    "name:pcd_x_preferred":[
        "Mutsaard"
    ],
    "name:vls_x_preferred":[
        "Mutsaard"
    ],
    "name:wln_x_preferred":[
        "Mutsaard"
    ],
    "wof:name":"Mutsaard",
    "wof:placetype":"neighbourhood"
},
  "geometry": {"coordinates":[4.361247,50.898483],"type":"Point"}
}