{
  "type": "Feature",
  "properties": {
    "gn:admin1_code":"VLG",
    "gn:admin2_code":"VWV",
    "gn:admin3_code":"31.0",
    "gn:admin4_code":"31022.0",
    "gn:asciiname":"Sijslo",
    "gn:country_code":"BE",
    "gn:dem":20,
    "gn:feature_class":"P",
    "gn:feature_code":"PPL",
    "gn:name":"Sijslo",
    "gn:population":0,
    "gn:timezone":"Europe/Brussels",
    "iso:country":"BE",
    "name:und_x_variant":[
        "Sysloo",
        "Sijsloo",
        "Sijslo"
    ],
    "wof:name":"Sijslo",
    "wof:placetype":"locality"
},
  "geometry": {"coordinates":[3.18808,51.10057000000001],"type":"Point"}
}