{
  "type": "Feature",
  "properties": {
    "gn:admin1_code":"WAL",
    "gn:admin2_code":"WHT",
    "gn:admin3_code":"55.0",
    "gn:admin4_code":"55040.0",
    "gn:asciiname":"Williaupont",
    "gn:country_code":"BE",
    "gn:dem":69,
    "gn:feature_class":"P",
    "gn:feature_code":"PPL",
    "gn:name":"Williaupont",
    "gn:population":0,
    "gn:timezone":"Europe/Brussels",
    "iso:country":"BE",
    "wof:name":"Williaupont",
    "wof:placetype":"locality"
},
  "geometry": {"coordinates":[4.03671,50.602],"type":"Point"}
}