{
  "type": "Feature",
  "properties": {
    "gn:admin1_code":"WAL",
    "gn:admin2_code":"WLG",
    "gn:admin3_code":"63.0",
    "gn:admin4_code":"63013.0",
    "gn:asciiname":"Gringertz",
    "gn:country_code":"BE",
    "gn:dem":538,
    "gn:feature_class":"P",
    "gn:feature_code":"PPL",
    "gn:name":"Gringertz",
    "gn:population":0,
    "gn:timezone":"Europe/Brussels",
    "iso:country":"BE",
    "wof:name":"Gringertz",
    "wof:placetype":"locality"
},
  "geometry": {"coordinates":[6.15,50.43333],"type":"Point"}
}