{
  "type": "Feature",
  "properties": {
    "gn:admin1_code":"WAL",
    "gn:admin2_code":"WNA",
    "gn:admin3_code":"92.0",
    "gn:admin4_code":"92035.0",
    "gn:asciiname":"Renise",
    "gn:country_code":"BE",
    "gn:dem":142,
    "gn:feature_class":"P",
    "gn:feature_code":"PPL",
    "gn:name":"Renise",
    "gn:population":0,
    "gn:timezone":"Europe/Brussels",
    "iso:country":"BE",
    "wof:name":"Renise",
    "wof:placetype":"locality"
},
  "geometry": {"coordinates":[4.87183,50.59531],"type":"Point"}
}