{
  "type": "Feature",
  "properties": {
    "gn:admin1_code":"WAL",
    "gn:admin2_code":"WNA",
    "gn:admin3_code":"92.0",
    "gn:admin4_code":"92140.0",
    "gn:asciiname":"Villeret",
    "gn:country_code":"BE",
    "gn:dem":116,
    "gn:feature_class":"P",
    "gn:feature_code":"PPL",
    "gn:name":"Villeret",
    "gn:population":0,
    "gn:timezone":"Europe/Brussels",
    "iso:country":"BE",
    "name:ceb_x_preferred":[
        "Villeret"
    ],
    "name:deu_x_preferred":[
        "Villeret"
    ],
    "name:epo_x_preferred":[
        "Villeret"
    ],
    "name:eus_x_preferred":[
        "Villeret"
    ],
    "name:fra_x_preferred":[
        "Villeret"
    ],
    "name:hun_x_preferred":[
        "Villeret"
    ],
    "name:ita_x_preferred":[
        "Villeret"
    ],
    "name:nds_x_preferred":[
        "Villeret"
    ],
    "name:nld_x_preferred":[
        "Villeret"
    ],
    "name:oci_x_preferred":[
        "Villeret"
    ],
    "name:pms_x_preferred":[
        "Villeret"
    ],
    "name:pol_x_preferred":[
        "Villeret"
    ],
    "name:por_x_preferred":[
        "Villeret"
    ],
    "name:rus_x_preferred":[
        "\u0412\u0438\u043b\u044c\u0440\u0435"
    ],
    "name:slk_x_preferred":[
        "Villeret"
    ],
    "name:spa_x_preferred":[
        "Villeret"
    ],
    "name:swe_x_preferred":[
        "Villeret"
    ],
    "name:ukr_x_preferred":[
        "\u0412\u0456\u043b\u044c\u0440\u0435"
    ],
    "wof:name":"Villeret",
    "wof:placetype":"locality"
},
  "geometry": {"coordinates":[4.65355,50.50719],"type":"Point"}
}