{
  "type": "Feature",
  "properties": {
    "gn:admin1_code":"WAL",
    "gn:admin2_code":"WNA",
    "gn:admin3_code":"92.0",
    "gn:admin4_code":"92140.0",
    "gn:asciiname":"Villeret",
    "gn:country_code":"BE",
    "gn:dem":116,
    "gn:feature_class":"P",
    "gn:feature_code":"PPL",
    "gn:name":"Villeret",
    "gn:population":0,
    "gn:timezone":"Europe/Brussels",
    "iso:country":"BE",
    "wof:name":"Villeret",
    "wof:placetype":"locality"
},
  "geometry": {"coordinates":[4.65355,50.50719],"type":"Point"}
}