{
  "type": "Feature",
  "properties": {
    "gn:admin1_code":"WAL",
    "gn:admin2_code":"WLX",
    "gn:admin3_code":"85.0",
    "gn:admin4_code":"85046.0",
    "gn:asciiname":"Coeuvins",
    "gn:country_code":"BE",
    "gn:dem":362,
    "gn:feature_class":"P",
    "gn:feature_code":"PPL",
    "gn:name":"Coeuvins",
    "gn:population":0,
    "gn:timezone":"Europe/Brussels",
    "iso:country":"BE",
    "wof:name":"Coeuvins",
    "wof:placetype":"locality"
},
  "geometry": {"coordinates":[5.63797,49.69832],"type":"Point"}
}