{
  "type": "Feature",
  "properties": {
    "gn:gn_country":"BE",
    "gn:gn_fcode":"PPL",
    "gn:gn_pop":0,
    "iso:country":"BE",
    "name:dut_x_preferred":[
        "Ooike"
    ],
    "name:eng_x_preferred":[
        "Ooike"
    ],
    "name:fre_x_preferred":[
        "Ooike"
    ],
    "name:hun_x_preferred":[
        "Ooike"
    ],
    "name:unk_x_variant":[
        "Oycke"
    ],
    "qs_pg:aaroncc":"BE",
    "qs_pg:gn_country":"BE",
    "qs_pg:gn_fcode":"PPL",
    "qs_pg:gn_pop":0,
    "qs_pg:name":"Ooike",
    "qs_pg:name_adm0":"Belgique",
    "qs_pg:name_adm1":"Oost-Vlaanderen",
    "qs_pg:photos_9k":1,
    "qs_pg:photos_9r":1,
    "qs_pg:photos_all":3,
    "qs_pg:photos_sr":0,
    "qs_pg:pop_sr":0,
    "qs_pg:qs_pg_placetype":"locality",
    "qs_pg:qs_pg_placetype_gp":"Town",
    "qs_pg:woe_adm0":23424757,
    "woe:adm0_id":23424757,
    "woe:name_adm0":"Belgique",
    "woe:name_adm1":"Oost-Vlaanderen",
    "woe:placetype":"Town",
    "wof:name":"Ooike",
    "wof:placetype":"locality"
},
  "geometry": {"coordinates":[3.55238,50.87112],"type":"Point"}
}