{
  "type": "Feature",
  "properties": {
    "gn:admin1_code":"WAL",
    "gn:admin2_code":"WLX",
    "gn:admin3_code":"83.0",
    "gn:admin4_code":"83013.0",
    "gn:asciiname":"Plome Mochon",
    "gn:country_code":"BE",
    "gn:dem":197,
    "gn:feature_class":"P",
    "gn:feature_code":"PPL",
    "gn:name":"Plome Mochon",
    "gn:population":0,
    "gn:timezone":"Europe/Brussels",
    "iso:country":"BE",
    "name:und_x_variant":[
        "Plume Mohon",
        "Plome Mochon"
    ],
    "wof:name":"Plome Mochon",
    "wof:placetype":"locality"
},
  "geometry": {"coordinates":[5.45808,50.29512],"type":"Point"}
}