{
  "type": "Feature",
  "properties": {
    "gn:admin1_code":"VLG",
    "gn:admin2_code":"VBR",
    "gn:admin3_code":"24.0",
    "gn:admin4_code":"24066.0",
    "gn:asciiname":"Lo",
    "gn:country_code":"BE",
    "gn:dem":92,
    "gn:feature_class":"P",
    "gn:feature_code":"PPL",
    "gn:name":"Lo",
    "gn:population":0,
    "gn:timezone":"Europe/Brussels",
    "iso:country":"BE",
    "name:und_x_variant":[
        "Loo",
        "Loo Bergen",
        "Lo"
    ],
    "wof:name":"Lo",
    "wof:placetype":"locality"
},
  "geometry": {"coordinates":[4.76223,50.87585],"type":"Point"}
}