{
  "type": "Feature",
  "properties": {
    "gn:admin1_code":"VLG",
    "gn:admin2_code":"VWV",
    "gn:admin3_code":"31.0",
    "gn:admin4_code":"31033.0",
    "gn:asciiname":"Slarrin",
    "gn:country_code":"BE",
    "gn:dem":10,
    "gn:feature_class":"P",
    "gn:feature_code":"PPL",
    "gn:name":"Slarrin",
    "gn:population":0,
    "gn:timezone":"Europe/Brussels",
    "iso:country":"BE",
    "wof:name":"Slarrin",
    "wof:placetype":"locality"
},
  "geometry": {"coordinates":[3.06667,51.05],"type":"Point"}
}