{
  "type": "Feature",
  "properties": {
    "iso:country":"BE",
    "name:fra_x_preferred":[
        "Cornillon"
    ],
    "name:unk_x_variant":[
        "Cornillon"
    ],
    "qs:gn_adm0_cc":"BE",
    "qs:gn_local":2792413,
    "qs:gn_nam_loc":"Li\u00e8ge, Li\u00e8ge, Li\u00e8ge, BE",
    "qs:gn_namadm1":"WAL",
    "qs:local_max":5890,
    "qs:local_sum":27074,
    "qs:localhoods":35,
    "qs:name":"Cornillon",
    "qs:name_adm0":"Belgique",
    "qs:name_adm1":"Li\u00e8ge",
    "qs:name_adm2":"Li\u00e8ge",
    "qs:name_lau":"Li\u00e8ge",
    "qs:name_local":"Li\u00e8ge",
    "qs:photo_max":191,
    "qs:photo_sum":1334,
    "qs:placetype":"Suburb",
    "qs:quad_count":48,
    "qs:woe_adm0":23424757,
    "qs:woe_adm1":7153300,
    "qs:woe_adm2":12591793,
    "qs:woe_lau":12602393,
    "qs:woe_local":973540,
    "qs:woe_ver":"7.10.0",
    "wof:lang":[
        "fre"
    ],
    "wof:name":"Cornillon",
    "wof:placetype":"neighbourhood"
},
  "geometry": {"coordinates":[5.582538,50.639622],"type":"Point"}
}