{
  "type": "Feature",
  "properties": {
    "iso:country":"BE",
    "name:bug_x_preferred":[
        "Cornillon"
    ],
    "name:cat_x_preferred":[
        "Cornilhon"
    ],
    "name:ceb_x_preferred":[
        "Cornillon"
    ],
    "name:deu_x_preferred":[
        "Cornillon"
    ],
    "name:eus_x_preferred":[
        "Cornillon"
    ],
    "name:fra_x_preferred":[
        "Cornillon"
    ],
    "name:hun_x_preferred":[
        "Cornillon"
    ],
    "name:ita_x_preferred":[
        "Cornillon"
    ],
    "name:kaz_x_preferred":[
        "\u041a\u043e\u0440\u043d\u0438\u0439\u043e\u043d"
    ],
    "name:lat_x_preferred":[
        "Cornillon"
    ],
    "name:lmo_x_preferred":[
        "Cornillon"
    ],
    "name:mlg_x_preferred":[
        "Cornillon"
    ],
    "name:msa_x_preferred":[
        "Cornillon"
    ],
    "name:nld_x_preferred":[
        "Cornillon"
    ],
    "name:oci_x_preferred":[
        "Cornilhon"
    ],
    "name:pol_x_preferred":[
        "Cornillon"
    ],
    "name:por_x_preferred":[
        "Cornillon"
    ],
    "name:ron_x_preferred":[
        "Cornillon"
    ],
    "name:slk_x_preferred":[
        "Cornillon"
    ],
    "name:spa_x_preferred":[
        "Cornillon"
    ],
    "name:srp_x_preferred":[
        "\u041a\u043e\u0440\u043d\u0438\u0458\u043e\u043d"
    ],
    "name:swe_x_preferred":[
        "Cornillon"
    ],
    "name:ukr_x_preferred":[
        "\u041a\u043e\u0440\u043d\u0456\u0439\u043e\u043d"
    ],
    "name:vie_x_preferred":[
        "Cornillon"
    ],
    "name:vol_x_preferred":[
        "Cornillon"
    ],
    "name:war_x_preferred":[
        "Cornillon"
    ],
    "name:zho_x_preferred":[
        "\u79d1\u5c14\u5c3c\u9686"
    ],
    "qs:gn_adm0_cc":"BE",
    "qs:gn_local":2792413,
    "qs:gn_nam_loc":"Li\u00e8ge, Li\u00e8ge, Li\u00e8ge, BE",
    "qs:gn_namadm1":"WAL",
    "qs:local_max":5890,
    "qs:local_sum":27074,
    "qs:localhoods":35,
    "qs:name":"Cornillon",
    "qs:name_adm0":"Belgique",
    "qs:name_adm1":"Li\u00e8ge",
    "qs:name_adm2":"Li\u00e8ge",
    "qs:name_lau":"Li\u00e8ge",
    "qs:name_local":"Li\u00e8ge",
    "qs:photo_max":191,
    "qs:photo_sum":1334,
    "qs:placetype":"Suburb",
    "qs:quad_count":48,
    "qs:woe_adm0":23424757,
    "qs:woe_adm1":7153300,
    "qs:woe_adm2":12591793,
    "qs:woe_lau":12602393,
    "qs:woe_local":973540,
    "qs:woe_ver":"7.10.0",
    "wof:lang":[
        "fre"
    ],
    "wof:name":"Cornillon",
    "wof:placetype":"neighbourhood"
},
  "geometry": {"coordinates":[5.582538,50.639622],"type":"Point"}
}