{
  "type": "Feature",
  "properties": {
    "gn:gn_country":"BE",
    "gn:gn_fcode":"PPL",
    "gn:gn_pop":0,
    "iso:country":"BE",
    "name:bug_x_preferred":[
        "Bruy\u00e8res"
    ],
    "name:cat_x_preferred":[
        "Bruy\u00e8res"
    ],
    "name:ceb_x_preferred":[
        "Bruy\u00e8res"
    ],
    "name:cym_x_preferred":[
        "Bruy\u00e8res"
    ],
    "name:deu_x_preferred":[
        "Bruy\u00e8res"
    ],
    "name:epo_x_preferred":[
        "Bruy\u00e8res"
    ],
    "name:eus_x_preferred":[
        "Bruy\u00e8res"
    ],
    "name:fra_x_preferred":[
        "Bruy\u00e8res"
    ],
    "name:hun_x_preferred":[
        "Bruy\u00e8res"
    ],
    "name:ind_x_preferred":[
        "Bruy\u00e8res"
    ],
    "name:ita_x_preferred":[
        "Bruy\u00e8res"
    ],
    "name:jpn_x_preferred":[
        "\u30d6\u30ea\u30e5\u30a4\u30a8\u30fc\u30eb"
    ],
    "name:kaz_x_preferred":[
        "\u0411\u0440\u044e\u0435\u0440"
    ],
    "name:lat_x_preferred":[
        "Bruerium"
    ],
    "name:ltz_x_preferred":[
        "Bruy\u00e8res"
    ],
    "name:mlg_x_preferred":[
        "Bruy\u00e8res"
    ],
    "name:msa_x_preferred":[
        "Bruy\u00e8res"
    ],
    "name:nld_x_preferred":[
        "Bruy\u00e8res"
    ],
    "name:oci_x_preferred":[
        "Bruy\u00e8res"
    ],
    "name:pms_x_preferred":[
        "Bruy\u00e8res"
    ],
    "name:pol_x_preferred":[
        "Bruy\u00e8res"
    ],
    "name:por_x_preferred":[
        "Bruy\u00e8res"
    ],
    "name:slk_x_preferred":[
        "Bruy\u00e8res"
    ],
    "name:spa_x_preferred":[
        "Bruy\u00e8res"
    ],
    "name:srp_x_preferred":[
        "\u0411\u0440\u0438\u0458\u0435\u0440"
    ],
    "name:swe_x_preferred":[
        "Bruy\u00e8res"
    ],
    "name:ukr_x_preferred":[
        "\u0411\u0440\u044e\u0454\u0440"
    ],
    "name:unk_x_variant":[
        "Les Bruy\u00e8res"
    ],
    "name:uzb_x_preferred":[
        "Bruy\u00e8res"
    ],
    "name:vie_x_preferred":[
        "Bruy\u00e8res"
    ],
    "name:vol_x_preferred":[
        "Bruy\u00e8res"
    ],
    "name:war_x_preferred":[
        "Bruy\u00e8res"
    ],
    "name:zho_x_preferred":[
        "\u5e03\u5415\u8036\u5c14"
    ],
    "qs_pg:aaroncc":"BE",
    "qs_pg:gn_country":"BE",
    "qs_pg:gn_fcode":"PPL",
    "qs_pg:gn_pop":0,
    "qs_pg:name":"Bruy\u00e8res",
    "qs_pg:name_adm0":"Belgique",
    "qs_pg:name_adm1":"Li\u00e8ge",
    "qs_pg:photos_9r":0,
    "qs_pg:photos_sr":0,
    "qs_pg:pop_sr":0,
    "qs_pg:qs_pg_placetype":"locality",
    "qs_pg:qs_pg_placetype_gp":"Town",
    "qs_pg:woe_adm0":23424757,
    "woe:adm0_id":23424757,
    "woe:name_adm0":"Belgique",
    "woe:name_adm1":"Li\u00e8ge",
    "woe:placetype":"Town",
    "wof:name":"Bruy\u00e8res",
    "wof:placetype":"locality"
},
  "geometry": {"coordinates":[5.79881,50.62148],"type":"Point"}
}