{
  "type": "Feature",
  "properties": {
    "gn:gn_country":"BE",
    "gn:gn_fcode":"PPL",
    "gn:gn_pop":0,
    "iso:country":"BE",
    "name:unk_x_variant":[
        "Les Bruy\u00e8res"
    ],
    "qs_pg:aaroncc":"BE",
    "qs_pg:gn_country":"BE",
    "qs_pg:gn_fcode":"PPL",
    "qs_pg:gn_pop":0,
    "qs_pg:name":"Bruy\u00e8res",
    "qs_pg:name_adm0":"Belgique",
    "qs_pg:name_adm1":"Li\u00e8ge",
    "qs_pg:photos_9r":0,
    "qs_pg:photos_sr":0,
    "qs_pg:pop_sr":0,
    "qs_pg:qs_pg_placetype":"locality",
    "qs_pg:qs_pg_placetype_gp":"Town",
    "qs_pg:woe_adm0":23424757,
    "woe:adm0_id":23424757,
    "woe:name_adm0":"Belgique",
    "woe:name_adm1":"Li\u00e8ge",
    "woe:placetype":"Town",
    "wof:name":"Bruy\u00e8res",
    "wof:placetype":"locality"
},
  "geometry": {"coordinates":[5.79881,50.62148],"type":"Point"}
}