{
  "type": "Feature",
  "properties": {
    "gn:admin1_code":"WAL",
    "gn:admin2_code":"WLX",
    "gn:admin3_code":"82.0",
    "gn:admin4_code":"82009.0",
    "gn:asciiname":"Vieille Eglise",
    "gn:country_code":"BE",
    "gn:dem":444,
    "gn:feature_class":"P",
    "gn:feature_code":"PPL",
    "gn:name":"Vieille \u00c9glise",
    "gn:population":0,
    "gn:timezone":"Europe/Brussels",
    "iso:country":"BE",
    "wof:name":"Vieille Eglise",
    "wof:placetype":"locality"
},
  "geometry": {"coordinates":[5.63333,49.83333],"type":"Point"}
}