{
  "type": "Feature",
  "properties": {
    "gn:admin1_code":"VLG",
    "gn:admin2_code":"VOV",
    "gn:admin3_code":"44.0",
    "gn:admin4_code":"44021.0",
    "gn:asciiname":"Kalsijde",
    "gn:country_code":"BE",
    "gn:dem":11,
    "gn:feature_class":"P",
    "gn:feature_code":"PPL",
    "gn:name":"Kalsijde",
    "gn:population":0,
    "gn:timezone":"Europe/Brussels",
    "iso:country":"BE",
    "wof:name":"Kalsijde",
    "wof:placetype":"locality"
},
  "geometry": {"coordinates":[3.66667,51.01667],"type":"Point"}
}