{
  "type": "Feature",
  "properties": {
    "gn:admin1_code":"VLG",
    "gn:admin2_code":"VBR",
    "gn:admin3_code":"23.0",
    "gn:admin4_code":"23023.0",
    "gn:asciiname":"Hazendries",
    "gn:country_code":"BE",
    "gn:dem":32,
    "gn:feature_class":"P",
    "gn:feature_code":"PPL",
    "gn:name":"Hazendries",
    "gn:population":0,
    "gn:timezone":"Europe/Brussels",
    "iso:country":"BE",
    "name:und_x_variant":[
        "Haesendries",
        "Hazendries"
    ],
    "wof:name":"Hazendries",
    "wof:placetype":"locality"
},
  "geometry": {"coordinates":[3.97657,50.74247],"type":"Point"}
}