{
  "type": "Feature",
  "properties": {
    "gn:admin1_code":"WAL",
    "gn:admin2_code":"WLG",
    "gn:admin3_code":"63.0",
    "gn:admin4_code":"63049.0",
    "gn:asciiname":"Winbomont",
    "gn:country_code":"BE",
    "gn:dem":416,
    "gn:feature_class":"P",
    "gn:feature_code":"PPL",
    "gn:name":"Winbomont",
    "gn:population":0,
    "gn:timezone":"Europe/Brussels",
    "iso:country":"BE",
    "wof:name":"Winbomont",
    "wof:placetype":"locality"
},
  "geometry": {"coordinates":[6.04849,50.42327],"type":"Point"}
}