{
  "type": "Feature",
  "properties": {
    "gn:admin1_code":"WAL",
    "gn:admin2_code":"WNA",
    "gn:admin3_code":"91.0",
    "gn:admin4_code":"91064.0",
    "gn:asciiname":"Baimont",
    "gn:country_code":"BE",
    "gn:dem":286,
    "gn:feature_class":"P",
    "gn:feature_code":"PPL",
    "gn:name":"Baimont",
    "gn:population":0,
    "gn:timezone":"Europe/Brussels",
    "iso:country":"BE",
    "wof:name":"Baimont",
    "wof:placetype":"locality"
},
  "geometry": {"coordinates":[5.2751,50.32697],"type":"Point"}
}