{
  "type": "Feature",
  "properties": {
    "gn:admin1_code":"WAL",
    "gn:admin2_code":"WHT",
    "gn:admin3_code":"52.0",
    "gn:admin4_code":"52025.0",
    "gn:asciiname":"Gougnies",
    "gn:country_code":"BE",
    "gn:dem":217,
    "gn:feature_class":"P",
    "gn:feature_code":"PPL",
    "gn:name":"Gougnies",
    "gn:population":0,
    "gn:timezone":"Europe/Brussels",
    "iso:country":"BE",
    "name:und_x_variant":[
        "Gerpinnes (Gougnies)"
    ],
    "wof:name":"Gougnies",
    "wof:placetype":"locality"
},
  "geometry": {"coordinates":[4.57615,50.35543],"type":"Point"}
}