{
  "type": "Feature",
  "properties": {
    "gn:admin1_code":"WAL",
    "gn:admin2_code":"WLG",
    "gn:admin3_code":"63.0",
    "gn:admin4_code":"63088.0",
    "gn:asciiname":"Chevemont",
    "gn:country_code":"BE",
    "gn:dem":246,
    "gn:feature_class":"P",
    "gn:feature_code":"PPL",
    "gn:name":"Chevemont",
    "gn:population":0,
    "gn:timezone":"Europe/Brussels",
    "iso:country":"BE",
    "wof:name":"Chevemont",
    "wof:placetype":"locality"
},
  "geometry": {"coordinates":[5.90634,50.71285],"type":"Point"}
}