{
  "type": "Feature",
  "properties": {
    "gn:admin1_code":"WAL",
    "gn:admin2_code":"WBR",
    "gn:admin3_code":"25.0",
    "gn:admin4_code":"25023.0",
    "gn:asciiname":"Bruyere du Sart",
    "gn:country_code":"BE",
    "gn:dem":78,
    "gn:feature_class":"P",
    "gn:feature_code":"PPL",
    "gn:name":"Bruy\u00e8re du Sart",
    "gn:population":0,
    "gn:timezone":"Europe/Brussels",
    "iso:country":"BE",
    "wof:name":"Bruyere du Sart",
    "wof:placetype":"locality"
},
  "geometry": {"coordinates":[4.5452,50.61433],"type":"Point"}
}