{
  "type": "Feature",
  "properties": {
    "gn:admin1_code":"WAL",
    "gn:admin2_code":"WLG",
    "gn:admin3_code":"63.0",
    "gn:admin4_code":"63003.0",
    "gn:asciiname":"Gorhez",
    "gn:country_code":"BE",
    "gn:dem":211,
    "gn:feature_class":"P",
    "gn:feature_code":"PPL",
    "gn:name":"Gorhez",
    "gn:population":0,
    "gn:timezone":"Europe/Brussels",
    "iso:country":"BE",
    "wof:name":"Gorhez",
    "wof:placetype":"locality"
},
  "geometry": {"coordinates":[5.83058,50.69861],"type":"Point"}
}