{
  "type": "Feature",
  "properties": {
    "gn:admin1_code":"WAL",
    "gn:admin2_code":"WLG",
    "gn:admin3_code":"62.0",
    "gn:admin4_code":"62121.0",
    "gn:asciiname":"Grandzee",
    "gn:country_code":"BE",
    "gn:dem":193,
    "gn:feature_class":"P",
    "gn:feature_code":"PPL",
    "gn:name":"Grandz\u00e9e",
    "gn:population":0,
    "gn:timezone":"Europe/Brussels",
    "iso:country":"BE",
    "wof:name":"Grandzee",
    "wof:placetype":"locality"
},
  "geometry": {"coordinates":[5.5358,50.53393],"type":"Point"}
}