{
  "type": "Feature",
  "properties": {
    "gn:admin1_code":"WAL",
    "gn:admin2_code":"WNA",
    "gn:admin3_code":"91.0",
    "gn:admin4_code":"91072.0",
    "gn:asciiname":"Grande-Trissogne",
    "gn:country_code":"BE",
    "gn:dem":255,
    "gn:feature_class":"P",
    "gn:feature_code":"PPL",
    "gn:name":"Grande-Trissogne",
    "gn:population":0,
    "gn:timezone":"Europe/Brussels",
    "iso:country":"BE",
    "wof:name":"Grande-Trissogne",
    "wof:placetype":"locality"
},
  "geometry": {"coordinates":[5.03003,50.22178],"type":"Point"}
}