{
  "type": "Feature",
  "properties": {
    "gn:admin1_code":"WAL",
    "gn:admin2_code":"WLX",
    "gn:admin3_code":"84.0",
    "gn:admin4_code":"84059.0",
    "gn:asciiname":"Cul du Four",
    "gn:country_code":"BE",
    "gn:dem":551,
    "gn:feature_class":"P",
    "gn:feature_code":"PPL",
    "gn:name":"Cul du Four",
    "gn:population":0,
    "gn:timezone":"Europe/Brussels",
    "iso:country":"BE",
    "wof:name":"Cul du Four",
    "wof:placetype":"locality"
},
  "geometry": {"coordinates":[5.3952,50.0482],"type":"Point"}
}