{
  "type": "Feature",
  "properties": {
    "gn:gn_country":"BE",
    "gn:gn_fcode":"PPL",
    "gn:gn_pop":0,
    "iso:country":"BE",
    "name:cat_x_preferred":[
        "Neufch\u00e2teau"
    ],
    "name:dut_x_preferred":[
        "Neufch\u00e2teau"
    ],
    "name:eng_x_preferred":[
        "Neufch\u00e2teau"
    ],
    "name:fre_x_preferred":[
        "Neufch\u00e2teau"
    ],
    "name:hun_x_preferred":[
        "Neufch\u00e2teau"
    ],
    "name:ltz_x_preferred":[
        "Neufch\u00e2teau"
    ],
    "name:unk_x_variant":[
        "Dalhem (Neufch\u00e2teau)"
    ],
    "qs_pg:aaroncc":"BE",
    "qs_pg:gn_country":"BE",
    "qs_pg:gn_fcode":"PPL",
    "qs_pg:gn_pop":0,
    "qs_pg:name":"Neufch\u00e2teau",
    "qs_pg:name_adm0":"Belgique",
    "qs_pg:name_adm1":"Li\u00e8ge",
    "qs_pg:photos":38,
    "qs_pg:photos_1k":8,
    "qs_pg:photos_9k":1,
    "qs_pg:photos_9r":2,
    "qs_pg:photos_all":38,
    "qs_pg:photos_sr":2,
    "qs_pg:pop_sr":0,
    "qs_pg:qs_pg_placetype":"locality",
    "qs_pg:qs_pg_placetype_gp":"Town",
    "qs_pg:woe_adm0":23424757,
    "woe:adm0_id":23424757,
    "woe:name_adm0":"Belgique",
    "woe:name_adm1":"Li\u00e8ge",
    "woe:placetype":"Town",
    "wof:name":"Neufch\u00e2teau",
    "wof:placetype":"locality"
},
  "geometry": {"coordinates":[5.77555,50.71961],"type":"Point"}
}