{
  "type": "Feature",
  "properties": {
    "gn:admin1_code":"WAL",
    "gn:admin2_code":"WNA",
    "gn:admin3_code":"92.0",
    "gn:admin4_code":"92141.0",
    "gn:asciiname":"Saint-Denis-Bovesse",
    "gn:country_code":"BE",
    "gn:dem":186,
    "gn:feature_class":"P",
    "gn:feature_code":"PPL",
    "gn:name":"Saint-Denis-Bovesse",
    "gn:population":0,
    "gn:timezone":"Europe/Brussels",
    "iso:country":"BE",
    "name:und_x_variant":[
        "La Bruy\u00e8re (Saint-Denis-Bovesse)"
    ],
    "wof:name":"Saint-Denis-Bovesse",
    "wof:placetype":"locality"
},
  "geometry": {"coordinates":[4.78278,50.53567],"type":"Point"}
}