{
  "type": "Feature",
  "properties": {
    "gn:admin1_code":"VLG",
    "gn:admin2_code":"VWV",
    "gn:admin3_code":"37.0",
    "gn:admin4_code":"37017.0",
    "gn:asciiname":"Abele",
    "gn:country_code":"BE",
    "gn:dem":13,
    "gn:feature_class":"P",
    "gn:feature_code":"PPL",
    "gn:name":"Abele",
    "gn:population":0,
    "gn:timezone":"Europe/Brussels",
    "iso:country":"BE",
    "name:bre_x_preferred":[
        "Abele"
    ],
    "name:nld_x_preferred":[
        "Abele"
    ],
    "name:und_x_variant":[
        "Abeele"
    ],
    "name:vls_x_preferred":[
        "Ab\u00eale"
    ],
    "wof:name":"Abele",
    "wof:placetype":"locality"
},
  "geometry": {"coordinates":[3.37571,50.92211],"type":"Point"}
}