{
  "type": "Feature",
  "properties": {
    "gn:admin1_code":"VLG",
    "gn:admin2_code":"VOV",
    "gn:admin3_code":"41.0",
    "gn:admin4_code":"41063.0",
    "gn:asciiname":"Strijmeers",
    "gn:country_code":"BE",
    "gn:dem":37,
    "gn:feature_class":"P",
    "gn:feature_code":"PPL",
    "gn:name":"Strijmeers",
    "gn:population":0,
    "gn:timezone":"Europe/Brussels",
    "iso:country":"BE",
    "name:und_x_variant":[
        "Strymeersch",
        "Strijmeersch",
        "Strijmeers"
    ],
    "wof:name":"Strijmeers",
    "wof:placetype":"locality"
},
  "geometry": {"coordinates":[3.91744,50.94752],"type":"Point"}
}