{
  "type": "Feature",
  "properties": {
    "gn:admin1_code":"VLG",
    "gn:admin2_code":"VAN",
    "gn:admin3_code":"12.0",
    "gn:admin4_code":"12021.0",
    "gn:asciiname":"Loverijk",
    "gn:country_code":"BE",
    "gn:dem":5,
    "gn:feature_class":"P",
    "gn:feature_code":"PPL",
    "gn:name":"Loverijk",
    "gn:population":0,
    "gn:timezone":"Europe/Brussels",
    "iso:country":"BE",
    "name:und_x_variant":[
        "Looverijck",
        "Louwerijk",
        "Loverijk"
    ],
    "wof:name":"Loverijk",
    "wof:placetype":"locality"
},
  "geometry": {"coordinates":[4.51667,51.11667],"type":"Point"}
}