{
  "type": "Feature",
  "properties": {
    "gn:admin1_code":"WAL",
    "gn:admin2_code":"WHT",
    "gn:admin3_code":"52.0",
    "gn:admin4_code":"52055.0",
    "gn:asciiname":"Mailmont",
    "gn:country_code":"BE",
    "gn:dem":134,
    "gn:feature_class":"P",
    "gn:feature_code":"PPL",
    "gn:name":"Mailmont",
    "gn:population":0,
    "gn:timezone":"Europe/Brussels",
    "iso:country":"BE",
    "wof:name":"Mailmont",
    "wof:placetype":"locality"
},
  "geometry": {"coordinates":[4.36039,50.52639],"type":"Point"}
}