{
  "type": "Feature",
  "properties": {
    "gn:admin1_code":"WAL",
    "gn:admin2_code":"WLG",
    "gn:admin3_code":"62.0",
    "gn:admin4_code":"62120.0",
    "gn:asciiname":"Le Trokay",
    "gn:country_code":"BE",
    "gn:dem":80,
    "gn:feature_class":"P",
    "gn:feature_code":"PPL",
    "gn:name":"Le Trokay",
    "gn:population":0,
    "gn:timezone":"Europe/Brussels",
    "iso:country":"BE",
    "wof:name":"Le Trokay",
    "wof:placetype":"locality"
},
  "geometry": {"coordinates":[5.43333,50.58333],"type":"Point"}
}