{
  "type": "Feature",
  "properties": {
    "gn:admin1_code":"WAL",
    "gn:admin2_code":"WHT",
    "gn:admin3_code":"51.0",
    "gn:admin4_code":"51012.0",
    "gn:asciiname":"Herimetz",
    "gn:country_code":"BE",
    "gn:dem":56,
    "gn:feature_class":"P",
    "gn:feature_code":"PPL",
    "gn:name":"Herimetz",
    "gn:population":0,
    "gn:timezone":"Europe/Brussels",
    "iso:country":"BE",
    "wof:name":"Herimetz",
    "wof:placetype":"locality"
},
  "geometry": {"coordinates":[3.86667,50.61667],"type":"Point"}
}