{
  "type": "Feature",
  "properties": {
    "gn:admin1_code":"WAL",
    "gn:admin2_code":"WHT",
    "gn:admin3_code":"57.0",
    "gn:admin4_code":"57094.0",
    "gn:asciiname":"La Caluyere",
    "gn:country_code":"BE",
    "gn:dem":69,
    "gn:feature_class":"P",
    "gn:feature_code":"PPL",
    "gn:name":"La Caluy\u00e8re",
    "gn:population":0,
    "gn:timezone":"Europe/Brussels",
    "iso:country":"BE",
    "wof:name":"La Caluyere",
    "wof:placetype":"locality"
},
  "geometry": {"coordinates":[3.59147,50.61278],"type":"Point"}
}