{
  "type": "Feature",
  "properties": {
    "gn:country":"BE",
    "gn:fcode":"PPL",
    "gn:population":0,
    "iso:country":"BE",
    "name:eng_x_preferred":[
        "Emptinne"
    ],
    "name:fra_x_preferred":[
        "Emptinne"
    ],
    "name:nld_x_preferred":[
        "Emptinne"
    ],
    "name:und_x_variant":[
        "Hamois (Emptinne)"
    ],
    "name:wln_x_preferred":[
        "Emtene-dil\u00e9-Hamw\u00e8"
    ],
    "qs_pg:aaroncc":"BE",
    "qs_pg:gn_country":"BE",
    "qs_pg:gn_fcode":"PPL",
    "qs_pg:gn_pop":0,
    "qs_pg:name":"Emptinne",
    "qs_pg:name_adm0":"Belgique",
    "qs_pg:name_adm1":"Namur",
    "qs_pg:photos_9k":1,
    "qs_pg:photos_9r":1,
    "qs_pg:photos_all":1,
    "qs_pg:photos_sr":0,
    "qs_pg:pop_sr":0,
    "qs_pg:qs_pg_placetype":"locality",
    "qs_pg:qs_pg_placetype_gp":"Town",
    "qs_pg:woe_adm0":23424757,
    "woe:adm0_id":23424757,
    "woe:name_adm0":"Belgique",
    "woe:name_adm1":"Namur",
    "woe:placetype":"Town",
    "wof:name":"Emptinne",
    "wof:placetype":"locality"
},
  "geometry": {"coordinates":[5.12135,50.32519],"type":"Point"}
}