{
  "type": "Feature",
  "properties": {
    "gn:admin1_code":"WAL",
    "gn:admin2_code":"WLX",
    "gn:admin3_code":"83.0",
    "gn:admin4_code":"83031.0",
    "gn:asciiname":"Foy",
    "gn:country_code":"BE",
    "gn:dem":244,
    "gn:feature_class":"P",
    "gn:feature_code":"PPL",
    "gn:name":"Foy",
    "gn:population":0,
    "gn:timezone":"Europe/Brussels",
    "iso:country":"BE",
    "wof:name":"Foy",
    "wof:placetype":"locality"
},
  "geometry": {"coordinates":[5.5163,50.18554],"type":"Point"}
}