{
  "type": "Feature",
  "properties": {
    "gn:admin1_code":"WAL",
    "gn:admin2_code":"WNA",
    "gn:admin3_code":"92.0",
    "gn:admin4_code":"92048.0",
    "gn:asciiname":"La Gilotrie",
    "gn:country_code":"BE",
    "gn:dem":200,
    "gn:feature_class":"P",
    "gn:feature_code":"PPL",
    "gn:name":"La Gilotrie",
    "gn:population":0,
    "gn:timezone":"Europe/Brussels",
    "iso:country":"BE",
    "name:und_x_variant":[
        "Giloterie",
        "Le Gilotrie",
        "La Giletrie",
        "La Gilotrie"
    ],
    "wof:name":"La Gilotrie",
    "wof:placetype":"locality"
},
  "geometry": {"coordinates":[4.6386,50.392],"type":"Point"}
}