{
  "type": "Feature",
  "properties": {
    "gn:admin1_code":"VLG",
    "gn:admin2_code":"VAN",
    "gn:admin3_code":"12.0",
    "gn:admin4_code":"12007.0",
    "gn:asciiname":"Klein Mechelen",
    "gn:country_code":"BE",
    "gn:dem":3,
    "gn:feature_class":"P",
    "gn:feature_code":"PPL",
    "gn:name":"Klein Mechelen",
    "gn:population":0,
    "gn:timezone":"Europe/Brussels",
    "iso:country":"BE",
    "wof:name":"Klein Mechelen",
    "wof:placetype":"locality"
},
  "geometry": {"coordinates":[4.27264,51.08614],"type":"Point"}
}