{
  "type": "Feature",
  "properties": {
    "gn:admin1_code":"VLG",
    "gn:admin2_code":"VWV",
    "gn:admin3_code":"31.0",
    "gn:admin4_code":"31006.0",
    "gn:asciiname":"Eibei",
    "gn:country_code":"BE",
    "gn:dem":2,
    "gn:feature_class":"P",
    "gn:feature_code":"PPL",
    "gn:name":"Eibei",
    "gn:population":0,
    "gn:timezone":"Europe/Brussels",
    "iso:country":"BE",
    "wof:name":"Eibei",
    "wof:placetype":"locality"
},
  "geometry": {"coordinates":[3.38333,51.23333],"type":"Point"}
}