{
  "type": "Feature",
  "properties": {
    "gn:admin1_code":"WAL",
    "gn:admin2_code":"WLX",
    "gn:admin3_code":"83.0",
    "gn:admin4_code":"83013.0",
    "gn:asciiname":"Champagne",
    "gn:country_code":"BE",
    "gn:dem":184,
    "gn:feature_class":"P",
    "gn:feature_code":"PPL",
    "gn:name":"Champagne",
    "gn:population":0,
    "gn:timezone":"Europe/Brussels",
    "iso:country":"BE",
    "wof:name":"Champagne",
    "wof:placetype":"locality"
},
  "geometry": {"coordinates":[5.4469,50.30292],"type":"Point"}
}