{
  "type": "Feature",
  "properties": {
    "gn:country":"BE",
    "gn:fcode":"PPL",
    "gn:population":0,
    "iso:country":"BE",
    "name:cat_x_preferred":[
        "Vieuxville"
    ],
    "name:eng_x_preferred":[
        "Vieuxville"
    ],
    "name:fra_x_preferred":[
        "Vieuxville"
    ],
    "name:gle_x_preferred":[
        "Vieuxville"
    ],
    "name:nld_x_preferred":[
        "Vieuxville"
    ],
    "name:wln_x_preferred":[
        "Li Viveye"
    ],
    "qs_pg:aaroncc":"BE",
    "qs_pg:gn_country":"BE",
    "qs_pg:gn_fcode":"PPL",
    "qs_pg:gn_pop":0,
    "qs_pg:name":"Vieuxville",
    "qs_pg:name_adm0":"Belgique",
    "qs_pg:name_adm1":"Li\u00e8ge",
    "qs_pg:photos_9k":1,
    "qs_pg:photos_9r":1,
    "qs_pg:photos_all":1,
    "qs_pg:photos_sr":0,
    "qs_pg:pop_sr":0,
    "qs_pg:qs_pg_placetype":"locality",
    "qs_pg:qs_pg_placetype_gp":"Town",
    "qs_pg:woe_adm0":23424757,
    "woe:adm0_id":23424757,
    "woe:name_adm0":"Belgique",
    "woe:name_adm1":"Li\u00e8ge",
    "woe:placetype":"Town",
    "wof:name":"Vieuxville",
    "wof:placetype":"locality"
},
  "geometry": {"coordinates":[5.54938,50.39484],"type":"Point"}
}