{
  "type": "Feature",
  "properties": {
    "gn:country":"BE",
    "gn:fcode":"PPL",
    "gn:population":0,
    "iso:country":"BE",
    "name:eng_x_preferred":[
        "Bothey"
    ],
    "name:est_x_preferred":[
        "Bothey"
    ],
    "name:fas_x_preferred":[
        "\u0628\u0648\u062a\u0627\u06cc"
    ],
    "name:fra_x_preferred":[
        "Bothey"
    ],
    "name:nld_x_preferred":[
        "Bothey"
    ],
    "name:und_x_variant":[
        "Gembloux (Bothey)"
    ],
    "name:wln_x_preferred":[
        "B\u00f4t\u00e8"
    ],
    "qs_pg:aaroncc":"BE",
    "qs_pg:gn_country":"BE",
    "qs_pg:gn_fcode":"PPL",
    "qs_pg:gn_pop":0,
    "qs_pg:name":"Bothey",
    "qs_pg:name_adm0":"Belgique",
    "qs_pg:name_adm1":"Namur",
    "qs_pg:photos":64,
    "qs_pg:photos_1k":13,
    "qs_pg:photos_9k":1,
    "qs_pg:photos_9r":2,
    "qs_pg:photos_all":64,
    "qs_pg:photos_sr":2,
    "qs_pg:pop_sr":0,
    "qs_pg:qs_pg_placetype":"locality",
    "qs_pg:qs_pg_placetype_gp":"Town",
    "qs_pg:woe_adm0":23424757,
    "woe:adm0_id":23424757,
    "woe:name_adm0":"Belgique",
    "woe:name_adm1":"Namur",
    "woe:placetype":"Town",
    "wof:name":"Bothey",
    "wof:placetype":"locality"
},
  "geometry": {"coordinates":[4.65014,50.52085],"type":"Point"}
}