{
  "type": "Feature",
  "properties": {
    "gn:admin1_code":"WAL",
    "gn:admin2_code":"WNA",
    "gn:asciiname":"Les Differents",
    "gn:country_code":"BE",
    "gn:dem":359,
    "gn:feature_class":"P",
    "gn:feature_code":"PPL",
    "gn:name":"Les Diff\u00e9rents",
    "gn:population":0,
    "gn:timezone":"Europe/Brussels",
    "iso:country":"BE",
    "wof:name":"Les Differents",
    "wof:placetype":"locality"
},
  "geometry": {"coordinates":[4.46705,49.94222],"type":"Point"}
}