{
  "type": "Feature",
  "properties": {
    "gn:admin1_code":"WAL",
    "gn:admin2_code":"WLG",
    "gn:admin3_code":"63.0",
    "gn:admin4_code":"63089.0",
    "gn:asciiname":"Stockis",
    "gn:country_code":"BE",
    "gn:dem":299,
    "gn:feature_class":"P",
    "gn:feature_code":"PPL",
    "gn:name":"Stockis",
    "gn:population":0,
    "gn:timezone":"Europe/Brussels",
    "iso:country":"BE",
    "wof:name":"Stockis",
    "wof:placetype":"locality"
},
  "geometry": {"coordinates":[5.8377,50.65231],"type":"Point"}
}