{
  "type": "Feature",
  "properties": {
    "gn:admin1_code":"WAL",
    "gn:admin2_code":"WLX",
    "gn:admin3_code":"83.0",
    "gn:admin4_code":"83012.0",
    "gn:asciiname":"Lohere",
    "gn:country_code":"BE",
    "gn:dem":218,
    "gn:feature_class":"P",
    "gn:feature_code":"PPL",
    "gn:name":"Loher\u00e9",
    "gn:population":0,
    "gn:timezone":"Europe/Brussels",
    "iso:country":"BE",
    "name:und_x_variant":[
        "Lohery",
        "Loher\u00e9"
    ],
    "wof:name":"Lohere",
    "wof:placetype":"locality"
},
  "geometry": {"coordinates":[5.53601,50.35],"type":"Point"}
}