{
  "type": "Feature",
  "properties": {
    "gn:admin1_code":"WAL",
    "gn:admin2_code":"WNA",
    "gn:admin3_code":"91.0",
    "gn:admin4_code":"91030.0",
    "gn:asciiname":"Enhet",
    "gn:country_code":"BE",
    "gn:dem":265,
    "gn:feature_class":"P",
    "gn:feature_code":"PPL",
    "gn:name":"Enhet",
    "gn:population":0,
    "gn:timezone":"Europe/Brussels",
    "iso:country":"BE",
    "name:dan_x_preferred":[
        "Enhed"
    ],
    "name:deu_x_preferred":[
        "Einheit"
    ],
    "name:jpn_x_preferred":[
        "\u5358\u4e00\u6027"
    ],
    "name:ltz_x_preferred":[
        "Eenheet"
    ],
    "name:nld_x_preferred":[
        "Eenheid"
    ],
    "name:slv_x_preferred":[
        "Enota"
    ],
    "name:swe_x_preferred":[
        "Enhet"
    ],
    "wof:name":"Enhet",
    "wof:placetype":"locality"
},
  "geometry": {"coordinates":[5.1037,50.22422],"type":"Point"}
}