{
  "type": "Feature",
  "properties": {
    "gn:admin1_code":"VLG",
    "gn:admin2_code":"VLI",
    "gn:admin3_code":"73.0",
    "gn:admin4_code":"73032.0",
    "gn:asciiname":"Nederstraat",
    "gn:country_code":"BE",
    "gn:dem":72,
    "gn:feature_class":"P",
    "gn:feature_code":"PPL",
    "gn:name":"Nederstraat",
    "gn:population":0,
    "gn:timezone":"Europe/Brussels",
    "iso:country":"BE",
    "wof:name":"Nederstraat",
    "wof:placetype":"locality"
},
  "geometry": {"coordinates":[5.48166,50.8713],"type":"Point"}
}