{
  "type": "Feature",
  "properties": {
    "gn:admin1_code":"WAL",
    "gn:admin2_code":"WHT",
    "gn:asciiname":"Vogelzang",
    "gn:country_code":"BE",
    "gn:dem":57,
    "gn:feature_class":"P",
    "gn:feature_code":"PPL",
    "gn:name":"Vogelzang",
    "gn:population":0,
    "gn:timezone":"Europe/Brussels",
    "iso:country":"BE",
    "wof:name":"Vogelzang",
    "wof:placetype":"locality"
},
  "geometry": {"coordinates":[4.16667,50.91667],"type":"Point"}
}