{
  "type": "Feature",
  "properties": {
    "gn:admin1_code":"VLG",
    "gn:admin2_code":"VAN",
    "gn:admin3_code":"12.0",
    "gn:admin4_code":"12025.0",
    "gn:asciiname":"Hooiendonk",
    "gn:country_code":"BE",
    "gn:dem":4,
    "gn:feature_class":"P",
    "gn:feature_code":"PPL",
    "gn:name":"Hooiendonk",
    "gn:population":0,
    "gn:timezone":"Europe/Brussels",
    "iso:country":"BE",
    "wof:name":"Hooiendonk",
    "wof:placetype":"locality"
},
  "geometry": {"coordinates":[4.41242,51.05367],"type":"Point"}
}